Workbook

Sheet PN
B1: NNRoad – Employer of Record, Payroll Worldwide
B2: 333 W San Carlos St., Suite 600, San Jose, CA 95113, USA
B3: USA: +1 (669) 377-5080 | www.NNRoad.com
A5: INVOICE
A7: Bill to:
A8: Company name: | B8: Omal Spa SB | D8: Currency | F8: USD
A9: Client ID: | B9: CNUS2025001 | D9: Invoice number | F9: PN-CNUS2025001-060920261
A10: Address: | B10: Ponte Nuovo 11/1, Rodengo Saiano (BS) Italy | D10: Invoice date | F10: =DATE(2026,7,31)
D11: Due date | F11: 46190
A12: VAT number | B12: IT00645720988
A14: Description | E14: ="Amount "&UAE!C6 | F14: Approx. In USD*
A15: EOR/PEO Cost | E15: =SUM(E16:E17) | F15: =SUM(F16:F17)
A16: ="- Labor cost for "&UAE!B9&" - "&MONTH(UAE!B2) &"-"& YEAR(UAE!B2) | E16: =UAE!I9+UAE!S9 | F16: =E16/$B$28
A17: ="- Expense claim for "&UAE!B9 | E17: =UAE!AE9 | F17: =E17/$B$28
A20: Service Fee | E20: =SUM(E21:E22) | F20: =SUM(F21:F22)
A21: ="- Management Fee - "&MONTH(UAE!B2) &"-"& YEAR(UAE!B2) | E21: =UAE!H9 | F21: =E21/$B$28
A25: EOR/PEO Service Cost | E25: =E15+E20 | F25: =F15+F20
A28: ="*FX rate USD: "&UAE!C6 | B28: =3.6725*0.97 | D28: EOR/PEO Service Cost | F28: =F25
D29: Outstanding payment | F29: =UAE!E22
D30: FX difference | F30: =UAE!E23
D31: Interests of delay | F31: =UAE!E24
D32: Bank Charges | F32: =UAE!E25
D33: Sub Total (Excluding Tax) | F33: =SUM(F28:F32)
D34: Tax | F34: =UAE!F6/'PN'!B28
D35: Total | F35: =SUM(F33:F34)
A39: Please pay the Invoice in FULL AMOUNT
A40: Beneficiary: NNROAD, INC. Bank Name: Chase Bank Bank Account: 132827913 Bank Add.: 690 River Oaks Parkway Ste A, San Jose, CA 95134, USA | D40: SWIFT BIC (international transfer): CHASUS33XXX Routing Number (domestic wire transfer): 021000021 Routing Number (domestic ACH and direct deposit): 322271627
A41: Notes:
A42: 1. Please ensure that you include the Invoice Number when making your payment. This will help us accurately process and allocate your payment .
A43: 2. This document becomes a Tax Invoice/Receipt upon payment. Please retain a copy for your records.
A44: 3. This is a computer generated document. No Signature required.

Sheet UAE
A1: UAE
A2: Pay Period | B2: ='UAE-L'!F3 | C2: ='UAE-L'!G3 | E2: ER
E3: Sum | F3: Business Tax | G3: Management Fee | I3: Gross Salary | S3: Mandatory Contribution | AE3: Expense Claim
G4: Subtotal | H4: Recurring Fee | I4: Subtotal | J4: EC - Basic Salary | K4: EC - Housing Allowance | L4: EC - Transport Allowance | M4: EC - School Allowance | N4: EC - Other allowance | O4: EC - Mobile Allowance | P4: EC - Food Allowance | Q4: EC - OT1 | R4: EC - OT2 | S4: Subtotal | T4: ='UAE-L'!AS2 | U4: ='UAE-L'!AT2 | V4: ='UAE-L'!AU2 | W4: ='UAE-L'!AV2 | X4: ='UAE-L'!AX2 | Y4: ='UAE-L'!AY2 | Z4: ='UAE-L'!AZ2 | AA4: ='UAE-L'!BA2 | AB4: ='UAE-L'!BB2 | AC4: ='UAE-L'!BC2 | AD4: ='UAE-L'!BD2 | AE4: Subtotal | AF4: Expense Claim
B6: Sum | C6: AED | E6: =SUM(E9:E17) | F6: =SUM(F9:F17) | G6: =SUM(G9:G17) | H6: =SUM(H9:H17) | I6: =SUM(I9:I17) | J6: =SUM(J9:J17) | K6: =SUM(K9:K17) | L6: =SUM(L9:L17) | ... AF6: =SUM(AF9:AF17)
E7: Prev VAT
E8: Curr VAT
B9: ='UAE-L'!B3 | C9: ='UAE EE'!D10 | E9: =F9+G9+I9+S9+AE9 | G9: =SUM(H9:H9) | H9: =1968 | I9: =SUM(J9:R9) | J9: ='UAE-L'!I3 | K9: ='UAE-L'!J3 | L9: ='UAE-L'!K3 | M9: ='UAE-L'!L3 | N9: ='UAE-L'!M3 | O9: ='UAE-L'!N3 | P9: ='UAE-L'!O3 | Q9: ='UAE-L'!R3 | R9: ='UAE-L'!S3 | S9: =SUM(T9:AD9) | T9: ='UAE-L'!AS3 | U9: ='UAE-L'!AT3 | V9: ='UAE-L'!AU3 | W9: ='UAE-L'!AV3 | X9: ='UAE-L'!AX3 | Y9: ='UAE-L'!AY3 | Z9: ='UAE-L'!AZ3*1.5 | AA9: ='UAE-L'!BA3 | AB9: ='UAE-L'!BB3 | AC9: ='UAE-L'!BC3 | AD9: ='UAE-L'!BD3 | AE9: =SUM(AF9:AF9) | AF9: ='UAE-L'!AM3
A21: Other Fee | E21: =SUM(E22:E26) | F21: 0
B22: Outstanding payment | E22: 0
B23: FX difference | E23: 0
B24: Interests of delay | E24: 0
B25: Bank Charges | E25: 10
B26: Invoice adjustment | E26: 0

Sheet UAE EE
A1: UAE EE
H2: EE
B3: Client Code | C3: Client Name | D3: EE Code | E3: EE Name | F3: Pay Period | H3: Net Income | I3: Gross Salary | T3: Expense Claim | V3: Mandatory Contribution | X3: Deduction
F4: From | G4: To | I4: Subtotal | J4: Basic Salary | K4: Housing Allowance | L4: Transport Allowance | M4: School Allowance | N4: Mobile Allowance | O4: Food Allowance | P4: Other Allowance | Q4: OT1 | R4: OT2 | S4: Other Adjustments | T4: Subtotal | U4: Expense Claim | V4: Subtotal | W4: Other
A6: EOR/PEO(AED)
B10: =PN!$B$9 | C10: =PN!B8 | E10: ='UAE-L'!B3 | F10: ='UAE-L'!F3 | G10: ='UAE-L'!G3 | H10: =I10+T10-V10-X10 | I10: =SUM(J10:S10) | J10: ='UAE-L'!AD3 | K10: ='UAE-L'!AE3 | L10: ='UAE-L'!AF3 | M10: ='UAE-L'!AG3 | N10: ='UAE-L'!AH3 | O10: ='UAE-L'!AI3 | P10: ='UAE-L'!AJ3 | Q10: ='UAE-L'!AK3 | R10: ='UAE-L'!AL3 | S10: 0 | T10: =SUM(U10:U10) | U10: ='UAE-L'!AM3 | V10: =SUM(W10:W10) | W10: 0 | X10: ='UAE-L'!AN3

Sheet UAE-L
A1: c | I1: Standard Salary Rates | Z1: HOURS AND DAYS WORKING | AD1: SALARIES | AP1: Installments | AS1: Accruals | AX1: Government Fees | BF1: INVOICE VALUES | BM1: OVERTIME 1
A2: Emp ID | B2: Employee Name | C2: Designation | D2: Payroll Currency | E2: Month Days | F2: From | G2: To | H2: Payroll Days | I2: EC - Basic Salary | J2: EC - Housing Allowance | K2: EC - Transport Allowance | L2: EC - School Allowance | M2: EC - Other allowance | N2: EC - Mobile Allowance | O2: EC - Food Allowance | P2: OT Eligible | Q2: EC - Gross Salary | R2: EC - OT1 | S2: EC - OT2 | T2: EC - Workmen Comp | U2: EC - Localization | V2: EC - Gratuity Accrual | W2: EC - Health Insurance Installment | X2: EC - GOSI | Y2: EC - Admin Fees | Z2: Absence Days | AA2: Days w/o Absence | AB2: Overtime 1 | AC2: Overtime 2 | AD2: Basic Salary | AE2: Housing Allowance | AF2: Transport Allowance | AG2: School Allowance | AH2: Mobile Allowance | AI2: Food Allowance | AJ2: Other Allowance | AK2: OT1 | AL2: OT2 | AM2: Other Adjustments | AN2: Deduction | AO2: Total Payout | AP2: Visa | AQ2: Medical Insurance | AR2: Total Installments | AS2: Gratuity | AT2: Airfare | AU2: Annual Leave | AV2: Other Accruals | AW2: Total Accruals | AX2: Ajeer | AY2: LMRA | AZ2: Localization | BA2: GOSI | BB2: Workmen Comp | BC2: Zakat | BD2: Family Visa Levy | BE2: Total Government Fees | BF2: Employee payout | BG2: Installments | BH2: Accruals | BI2: Government Fees | BJ2: Admin Fees | BK2: Invoice total | BM2: =BL2+1 | BN2: =BM2+1 | BO2: =BN2+1 | BP2: =BO2+1 | BQ2: =BP2+1 | BR2: =BQ2+1 | BS2: =BR2+1 | BT2: =BS2+1 | ... CQ2: =CP2+1 | CR2: Total
A3: AX01669 | B3: KUTAY SAMIM GOKSU | C3: Sales Manager | D3: AED | E3: 30 | F3: 46174 | G3: 46203 | H3: 22 | I3: 19635 | J3: 9817.5 | K3: 3272.5 | L3: 0 | M3: 2913 | N3: 0 | O3: 0 | P3: No | Q3: =I3+J3+K3+L3+M3+N3+O3 | T3: 0 | U3: 800 | V3: 1130 | W3: 0 | X3: 0 | Z3: 0 | AA3: 22 | AB3: 0 | AC3: 0 | AD3: 19635 | AE3: 9817.5 | AF3: 3272.5 | AJ3: 2913 | AM3: 3644.8 | AN3: 0 | AO3: 39282.8 | AR3: 0 | AS3: 1130 | AW3: 1130 | AZ3: 800 | BE3: 800 | BF3: 39282.8 | BG3: 0 | BH3: 1130 | BI3: 800 | BK3: 42525.3 | BM3: 0 | BN3: 0 | BO3: 0 | BR3: 0 | BS3: 0 | BT3: 0 | BU3: 0 | BV3: 0 | BY3: 0 | BZ3: 0 | CA3: 0 | CB3: 0 | CC3: 0 | CF3: 0 | CG3: 0 | CH3: 0 | CI3: 0 | CJ3: 0 | CM3: 0 | CN3: 0 | CO3: 0 | CP3: 0 | CR3: =SUM(BM3:CQ3)
A4: Total | AO4: =SUBTOTAL(109,AO4) | AR4: =SUBTOTAL(109,AR4) | AW4: =SUBTOTAL(109,AW4) | BE4: =SUBTOTAL(109,BE4) | BF4: =SUBTOTAL(109,BF4) | BG4: =SUBTOTAL(109,BG4) | BH4: =SUBTOTAL(109,BH4) | BI4: =SUBTOTAL(109,BI4) | BJ4: =SUBTOTAL(109,BJ4) | BK4: =SUBTOTAL(109,BK4) | BM4: =SUM(BM3:BM3) | BN4: =SUM(BN3:BN3) | BO4: =SUM(BO3:BO3) | BP4: =SUM(BP3:BP3) | BQ4: =SUM(BQ3:BQ3) | BR4: =SUM(BR3:BR3) | BS4: =SUM(BS3:BS3) | BT4: =SUM(BT3:BT3) | ... CR4: =SUM(CR3:CR3)
