Workbook

Sheet PN
B1: NNRoad – Employer of Record, Payroll Worldwide
B2: 333 W San Carlos St., Suite 600, San Jose, CA 95113, USA
B3: USA: +1 (669) 377-5080 | www.NNRoad.com
A5: INVOICE
A7: Bill to:
A8: Company name: | B8: Crosslake Fiber USA LP | D8: Currency | F8: USD
A9: Client ID: | B9: CUS1506 | D9: Invoice number | F9: PN-CUS1506-030420261
A10: Address: | B10: c/o Tiger Infrastructure Partners 590 Madison Avenue, 41st Floor New York, NY 10022 United States | D10: Invoice date | F10: =TODAY() -> 46085
D11: Due date | F11: 46099
A14: Description | E14: ="Amount "&India!C6 -> Amount (INR) | F14: Approx. In USD*
A15: EOR/PEO Cost | E15: =SUM(E16:E17) -> 267335 | F15: =SUM(F16:F17) -> 2986.6495
A16: ="- Labor cost for "&India!B9 -> - Labor cost for Rekha | E16: =ROUND(India!J9,0) -> 267335 | F16: =E16/$B$28 -> 2986.6495
A17: ="- "&+"Expense claim for "&India!B9 -> - Expense claim for Rekha | E17: =India!R9 -> 0 | F17: =E17/$B$28 -> 0
A20: Service Fee | E20: =SUM(E21:E22) -> 32080.2 | F20: =SUM(F21:F22) -> 358.39794
A21: ="- "&+"Management Fee - "&MONTH(India!B2) &"-"& YEAR(India!B2) -> - Management Fee - 3-2026 | E21: =India!H9 -> 32080.2 | F21: =E21/$B$28 -> 358.39794
A25: EOR/PEO Service Cost | E25: =E15+E20 -> 299415.2 | F25: =F15+F20 -> 3345.0475
A28: ="*FX rate USD: "&India!C6 -> *FX rate USD: (INR) | B28: =ROUND(92.28037171 *0.97,2) -> 89.51 | D28: EOR/PEO Service Cost | F28: =F25 -> 3345.0475
D29: Outstanding payment | F29: =India!E23 -> 0
D30: FX difference | F30: =India!E24 -> 0
D31: Interests of delay | F31: =India!E25 -> 0
D32: Bank Charges | F32: =India!E26 -> 10
D33: Sub Total (Excluding Tax) | F33: =SUM(F28:F32) -> 3355.0475
D34: Tax | F34: =India!F9/PN!$B$28 -> 575.2278
D35: Total | F35: =SUM(F33:F34) -> 3930.2753
A39: Please pay the Invoice in FULL AMOUNT
A40: Beneficiary: NNROAD, INC. Bank Name: Chase Bank Bank Account: 132827913 Bank Add.: 690 River Oaks Parkway Ste A, San Jose, CA 95134, USA | D40: SWIFT BIC (international transfer): CHASUS33XXX Routing Number (domestic wire transfer): 021000021 Routing Number (domestic ACH and direct deposit): 322271627
A41: Notes:
A42: 1. Please ensure that you include the Invoice Number when making your payment. This will help us accurately process and allocate your payment .
A43: 2. This document becomes a Tax Invoice/Receipt upon payment. Please retain a copy for your records.
A44: 3. This is a computer generated document. No Signature required.

Sheet India
A1: =MID(CELL("filename",A1),FIND("]",CELL("filename",A1))+1,256) -> India
A2: Pay Period | B2: ='India-L'!B8 -> 2026/3/1 | C2: ='India-L'!C8 -> 2026/3/31 | E2: ER
E3: Sum | F3: Business Tax | G3: Management Fee Fee | J3: Gross Salary | R3: Expense Claim
G4: Subtotal | H4: Recurring Fee | I4: Expense Fee | J4: Subtotal | K4: Basic salary | L4: HRA | M4: Telephone allowance | N4: LTA | O4: Special allowance | P4: Bonus | Q4: Other | R4: Subtotal | S4: Expense Claim
B6: Sum | C6: (INR) | E6: =SUM(E9:E18) -> 350904.2 | F6: =SUM(F9:F18) -> 51488.64 | G6: =SUM(G9:G18) -> 32080.2 | H6: =SUM(H9:H18) -> 32080.2 | I6: =SUM(I9:I18) -> 0 | J6: =SUM(J9:J18) -> 267335 | K6: =SUM(K9:K18) -> 133667 | L6: =SUM(L9:L18) -> 53467 | ... S6: =SUM(S9:S18) -> 0
B9: ='India-L'!B10 -> Rekha | E9: =G9+ROUNDUP((F9+J9+R9),0) -> 350904.2 | F9: ='India-L'!E10 -> 51488.64 | G9: =SUM(H9:I9) -> 32080.2 | H9: =MAX((J9)*12%, 300*PN!$B$28) -> 32080.2 | I9: =IF((R9>0), 15*PN!B28, 0) -> 0 | J9: =SUM(K9:Q9) -> 267335 | K9: ='India-L'!G10 -> 133667 | L9: ='India-L'!H10 -> 53467 | M9: ='India-L'!I10 -> 2000 | N9: ='India-L'!J10 -> 13367 | O9: ='India-L'!K10 -> 64834 | P9: ='India-L'!L10 -> 0 | Q9: ='India-L'!M10 -> 0 | R9: =SUM(S9:S9) -> 0 | S9: ='India-L'!O10 -> 0
E19: =E9-F9-G9 -> 267335.36
E21: (USD) | F21: (INR)
A22: Other Fee | B22: Total | E22: =SUM(E23:E27) -> 10 | F22: =SUM(F23:F27) -> 0
B23: Outstanding payment | E23: 0
B24: FX difference | E24: 0 | F24: =80*0 -> 0
B25: Interests of delay | E25: 0 | F25: 0
B26: Bank Charges | E26: 10
B27: Invoice adjustment | E27: 0

Sheet India EE
A1: =MID(CELL("filename",A1),FIND("]",CELL("filename",A1))+1,256) -> India EE
H2: EE
B3: Client Code | C3: Client Name | D3: EE Code | E3: EE Name | F3: Pay Period | H3: Net Income | I3: Gross Salary | Q3: Expense Claim | S3: Mandatory Contribution | U3: Deduction | V3: IIT
F4: From | G4: To | I4: Subtotal | J4: Basic salary | K4: HRA | L4: Telephone allowance | M4: LTA | N4: Special allowance | O4: Bonus | P4: Other | Q4: Subtotal | R4: Expense Claim | S4: Subtotal | T4: Professional Tax
A6: EOR/PEO(INR)
B9: =PN!$B$9 -> CUS1506 | C9: =PN!$B$8 -> Crosslake Fiber USA LP | D9: =PN!$B$9&"-0001" -> CUS1506-0001 | E9: ='India-L'!B10 -> Rekha | F9: ='India-L'!$B$8 -> 2026/3/1 | G9: ='India-L'!$C$8 -> 2026/3/31 | H9: =I9+Q9-S9-U9-V9 -> 226930 | I9: =SUM(J9:P9) -> 253968 | J9: ='India-L'!S10 -> 133667 | K9: ='India-L'!T10 -> 53467 | L9: ='India-L'!U10 -> 2000 | M9: ='India-L'!V10 -> 0 | N9: ='India-L'!W10 -> 64834 | O9: ='India-L'!X10 -> 0 | P9: ='India-L'!Y10 -> 0 | Q9: =SUM(R9:R9) -> 0 | R9: ='India-L'!AA10 -> 0 | S9: =SUM(T9:T9) -> 200 | T9: ='India-L'!AC10 -> 200 | U9: ='India-L'!AD10 -> 0 | V9: ='India-L'!AE10 -> 26838

Sheet India-L
D2: ER | Q2: EE
D3: Sum | E3: Business Tax | F3: Gross Salary | N3: Expense Claim | Q3: Net Income | R3: Gross Salary | Z3: Expense Claim | AB3: Mandatory Contribution | AD3: Deduction | AE3: IIT
F4: Subtotal | G4: Basic salary | H4: HRA | I4: Telephone allowance | J4: LTA | K4: Special allowance | L4: Bonus | M4: Other | N4: Subtotal | O4: Expense Claim | R4: Subtotal | S4: Basic salary | T4: HRA | U4: Telephone allowance | V4: LTA | W4: Special allowance | X4: Bonus | Y4: Other | Z4: Subtotal | AA4: Expense Claim | AB4: Subtotal | AC4: Professional tax
A6: EOR/PEO
A8: Pay Period | B8: 2026/3/1 | C8: 2026/3/31
B10: Rekha | E10: =ROUND(25744.32*2,2) -> 51488.64 | F10: =SUM(G10:M10) -> 267335 | G10: 133667 | H10: 53467 | I10: 2000 | J10: 13367 | K10: 64834 | L10: 0 | M10: 0 | N10: 0 | O10: 0 | Q10: =R10+Z10-AB10-AD10-AE10 -> 226930 | R10: =SUM(S10:Y10) -> 253968 | S10: =G10 -> 133667 | T10: =H10 -> 53467 | U10: =I10 -> 2000 | V10: 0 | W10: =K10 -> 64834 | X10: =L10 -> 0 | Y10: =M10 -> 0 | Z10: =AA10 -> 0 | AA10: =O10 -> 0 | AB10: =AC10 -> 200 | AC10: 200 | AD10: 0 | AE10: 26838
