Workbook

Sheet S-Payment Notice
A4: HROne Co., Ltd.
A6: INVOICE
A7: 付款通知
A9: Attn 发至：NNRoad-Hermetic Solutions
D10: Date: | E10: =TODAY() -> 45855
D11: 日期：
D12: Ref. No.: | E12: 45820.581
A13: Service Month 服务月： | B13: ='S-Payslip'!C4 -> 45820 | D13: 编号：
A15: Items 收款项目 | D15: Amount 金额
D17: RMB
A18: Net Salary (To Individual Bank Account) 实发工资（至员工银行账号） | E18: ='S-Payroll Report'!E11 -> 29914.13
A19: Charge On Behalf 代收代付 | E19: =SUM(D20:D31) -> 21150.58
A20: - Social Insurance (To Social Insurance Accounts) 社保（至社保账户） | D20: =SUM('S-Payroll Report'!H11:J11)+SUM('S-Payroll Report'!P11:U11) -> 10099.63
A21: - Housing Fund (To Housing Fund Accounts) 公积金（至公积金账户） | D21: ='S-Payroll Report'!K11+'S-Payroll Report'!V11 -> 8731.8
A22: - Enterprise Annuity (To Annuity Accounts) 企业年金（至年金账户） | D22: ='S-Payroll Report'!L11+'S-Payroll Report'!W11 -> 0
A23: - Commercial Insurance 商业保险 | D23: ='S-Payroll Report'!Y11 -> 0
A24: - Other Benefits 其他福利 | D24: ='S-Payroll Report'!Z11 -> 0
A25: - Union Fee 工会会费 | D25: ='S-Payroll Report'!M11+'S-Payroll Report'!X11 -> 0
A26: - Employer Liability Insurance 雇主责任险 | D26: ='S-Payroll Report'!AD11 -> 0
A27: - IIT 个税 | D27: ='S-Payroll Report'!N11 -> 1879.35
A28: - Expense 报销款 | D28: ='S-Payroll Report'!F11 -> 439.8
A29: - Subsistence Allowance for Foreigners 外籍生活津贴 | D29: ='S-Payroll Report'!G11 -> 0
A30: - Business Tax for Expense 报销款税额 | D30: ='S-Payroll Report'!AB11 -> 0
A31: - Others 其他 | D31: ='S-Payroll Report'!O11+'S-Payroll Report'!AE11 -> 0
A32: Recurring Service Fee 常规服务费 | E32: ='S-Payroll Report'!AA11 -> 450
A33: Other Fee 其他费用 | E33: =SUM(D34:D35) -> 200
A34: - Other Service Fee 其他服务费 | D34: ='Other Fee'!E14 -> 200
A35: - Other charge on behalf Fee 其他代收代付 | D35: ='Other Fee'!E26 -> 0
A36: Deposit 押金 | E36: ='S-Payroll Report'!AC11 -> 0
A37: Balance 差额 | E37: 0
A38: Delay Fee 滞纳金 | E38: 0
A39: Value Added Tax 增值税 | E39: =ROUND(E32*0.0677,2) -> 30.47
B48: Total 总计 | D48: RMB | E48: =SUM(E16:E47) -> 51745.18
B49: Exchange rate 汇率 | C49: 7.16
D50: or USD | E50: =E48/C49 -> 7226.9804
A51: Note 注：
A53: Prepared By 制单 | B53: Checked By 复核 | D53: Approved By 批准
A55: Siyu | B55: Gina | D55: Ann Rui
A57: If payment is made from overseas and Hong Kong/Macao/Taiwan, please make the transfer to the following account. Please DON'T mention any other comments except SERVICE FEE in bank remark. 如果您是在境外、香港、澳门或者台湾支付的，请汇款至以下账户 | C57: If payment is made from Mainland China in RMB, please make the transfer to the following account 如果您是在中国大陆支付的人民币，请汇款至以下账户
A58: Bank Account: 652 369240 838 Beneficiary: HRONE COMPANY LIMITED SWIFT BIC: HSBCHKHHHKH (For areas other than Hong Kong) Bank: HSBC Hong Kong Bank Address: 1 Queen’s Road Central Hong Kong Bank Code: 004 (For local transactions)
A60: Finance Dept., HROne Co., Ltd., Suite 2703, Greentech Tower, 436 HengFeng Road, Shanghai, China, 200070
A61: Tel: +86 21 5211 0025 Email: info@HROne.com
A62: www.HROne.com
A63: 联系地址：中国 上海 恒丰路436号 环智国际大厦2703室 上海杰而杰人才服务有限公司 财务部
A64: 总机：+86 21 5211 0025 电子邮箱：info@HROne.com
A65: www.HROne.com

Sheet Other Fee
A4: HROne Co., Ltd.
A6: Other Fee
A7: 其他服务费
A10: Items 收款项目 | D10: Amount 金额
D12: RMB
A13: Other Service Fee Tax 其他服务费税
A14: Other Service Fee 其他服务费 | E14: =SUM(D15:D25) -> 200
A15: 报销服务费 | B15: 1笔报销
A16: 签证&户口
A17: 外勤服务
A18: 背景调查
A19: 其他 | B19: 异地大礼包 | D19: 200
A26: Other charge on behalf Fee 其他代收代付 | E26: =SUM(D27:D38) -> 0
A27: 快递费
A28: 签证政府费用
A29: Ukey更新
A30: Payment for XX's social benefit
A31: 深圳人服报销退费
A39: Total 合计 | D39: =SUM(D24:D38) -> 0

Sheet MLC to China
A1: Region: | D1: Mainland China
A2: Payment Month: | D2: ='S-Payslip'!C4 -> 45820
A3: Currency: | D3: RMB
A4: Exchange Rate (to USD): | D4: ='S-Payment Notice'!C49 -> 7.16
A7: No. | B7: EE No. | C7: Name | D7: Total Cost | E7: Gross Salary | H7: Other Payment To EE | L7: Expense Claim | Q7: Statutory Payment | AB7: Other Payment Borne By Employer | AF7: Deposit | AG7: Service Fee | AH7: Business Tax | AI7: Remark
E8: Subtotal | F8: Basic Salary | G8: Salary Adjustment | H8: Subtotal | I8: Foreigner Allowance | J8: Bonus(Preferential Tax) | K8: Other | L8: Subtotal | M8: IIT Free Portion | O8: IIT Not Free Portion | Q8: Subtotal | R8: Pension | S8: Medical | T8: Unemployment | U8: Maternity | V8: Work-Related-Injury | W8: Housing Fund | X8: Disability | Y8: Union Fee | Z8: Employer Liability | AA8: Others | AB8: Subtotal | AC8: Commercial Insurance | AD8: IIT ER&BIT | AE8: Others
M9: CIT Free Portion | N9: 25% CIT Applicable | O9: IIT afford by Employer | P9: IIT afford by Employee | S9: Medical | T9: Unemployment | U9: Maternity | V9: Work-Related-Injury | W9: Housing Fund | X9: Disability | Y9: Union Fee | Z9: Employer Liability | AA9: Others | AB9: Subtotal | AC9: Commercial Insurance | AE9: Others
A10: 1 | B10: ='S-Payslip'!C7 -> CUS1525-0002 | C10: ='S-Payslip'!D7 -> 杨明华 Minghua Yang | D10: =E10+H10+L10+Q10+AB10+AF10+AG10+AH10 -> 50324.58 | E10: =SUM(F10:G10) -> 37337.5 | F10: ='S-Payslip'!E7 -> 37337.5 | G10: 0 | H10: =SUM(I10:K10) -> 562 | I10: 0 | J10: ='S-Payslip'!G7 -> 0 | K10: ='S-Payslip'!F7+'S-Payslip'!J7+'S-Payroll Report'!N8-'S-Payslip'!AA7 -> 562 | L10: =SUM(M10:P10) -> 439.8 | M10: =基本信息!EB2 -> 439.8 | N10: =基本信息!EC2 -> 0 | O10: 0 | P10: =基本信息!DR2 -> 0 | Q10: =SUM(R10:AA10) -> 11504.81 | R10: ='S-Payroll Report'!P8 -> 4675.17 | S10: ='S-Payroll Report'!Q8 -> 1683.3 | T10: ='S-Payroll Report'!R8 -> 349.27 | U10: ='S-Payroll Report'!S8 -> 168.33 | V10: ='S-Payroll Report'!T8 -> 206.84 | W10: ='S-Payroll Report'!V8 -> 4365.9 | X10: ='S-Payroll Report'!U8 -> 56 | Y10: ='S-Payroll Report'!X8 -> 0 | Z10: ='S-Payroll Report'!AD8 -> 0 | AA10: ='S-Payroll Report'!AE8+'S-Payroll Report'!Z8 -> 0 | AB10: =SUM(AC10:AE10) -> 0 | AC10: 0 | AD10: ='S-Payroll Report'!AB8 -> 0 | AE10: 0 | AF10: ='S-Payroll Report'!AC8 -> 0 | AG10: ='S-Payroll Report'!AA8 -> 450 | AH10: ='S-Payroll Report'!AF8 -> 30.47
A12: Sum | D12: =SUM(D10:D11) -> 50324.58 | E12: =SUM(E10:E11) -> 37337.5 | F12: =SUM(F10:F11) -> 37337.5 | G12: =SUM(G10:G11) -> 0 | H12: =SUM(H10:H11) -> 562 | I12: =SUM(I10:I11) -> 0 | J12: =SUM(J10:J11) -> 0 | K12: =SUM(K10:K11) -> 562 | ... AH12: =SUM(AH10:AH11) -> 30.47
A13: Sum in USD | D13: =D12/$D$4 -> 7028.5726 | E13: =E12/$D$4 -> 5214.7346 | H13: =H12/$D$4 -> 78.49162 | L13: =L12/$D$4 -> 61.424581 | Q13: =Q12/$D$4 -> 1606.817 | AB13: =AB12/$D$4 -> 0 | AF13: =AF12/$D$4 -> 0 | AG13: =AG12/$D$4 -> 62.849162 | AH13: =AH12/$D$4 -> 4.2555866

Sheet S-Payroll Report
A1: HROne Payroll Report 工资汇总
A4: Duration 发薪月 | C4: ='S-Payslip'!C4 -> 45820 | E4: Client 客户 | H4: ='S-Payslip'!G4 -> NNRoad-Hermetic Solutions
A6: No. 序号 | B6: Department 部门 | C6: ID No. 工号 | D6: Name 姓名 | E6: Net Income 员工实得 | F6: Expense 报销款 | G6: Subsistence Allowance for Foreigners 外籍生活津贴 | H6: Individual Portion 个人部分 | P6: Employer Portion 雇主部分 | AG6: Total Cost 总成本 | AH6: Remark 备注
H7: Pension 养老 | I7: Medical 医疗 | J7: Unemployment 失业 | K7: Housing Fund 公积金 | L7: Annuity 年金 | M7: Union Fee 工会费 | N7: IIT 个税 | O7: Balance For Charge On Behalf 代缴费用补差 | P7: Pension 养老 | Q7: Medical 医疗 | R7: Unemployment 失业 | S7: Maternity 生育 | T7: Work-Related-Injury 工伤 | U7: Disability 残保金 | V7: Housing Fund 公积金 | W7: Annuity 年金 | X7: Union Fee 工会费 | Y7: Commercial Insurance 商业保险 | Z7: Other Benefits 其他福利 | AA7: Service Fee 服务费 | AB7: Business Tax for Expense 报销款税额 | AC7: Deposit 押金 | AD7: Employer Liability Insurance 雇主责任险 | AE7: Others 其他 | AF7: Value Added Tax 增值税
A8: 1 | C8: =IF('S-Payslip'!C7="","",'S-Payslip'!C7) -> CUS1525-0002 | D8: ='S-Payslip'!D7 -> 杨明华 Minghua Yang | E8: ='S-Payslip'!AE7 -> 29914.13 | F8: ='S-Payslip'!AC7 -> 439.8 | G8: ='S-Payslip'!AD7 -> 0 | H8: ='S-Payslip'!P7 -> 2200.08 | I8: ='S-Payslip'!Q7 -> 673.32 | J8: ='S-Payslip'!R7 -> 87.32 | K8: ='S-Payslip'!S7 -> 4365.9 | L8: ='S-Payslip'!X7 -> 0 | M8: ='S-Payslip'!Y7 -> 0 | N8: ='S-Payslip'!AA7+计算结果!BE2 -> 1879.35 | O8: ='S-Payslip'!AB7 -> 0 | P8: =计算结果!BV2 -> 4675.17 | Q8: =计算结果!BW2 -> 1683.3 | R8: =计算结果!BX2 -> 349.27 | S8: =计算结果!BY2 -> 168.33 | T8: =计算结果!BZ2 -> 206.84 | U8: =计算结果!CA2 -> 56 | V8: =计算结果!CB2+计算结果!CC2 -> 4365.9 | W8: =基本信息!BF2 -> 0 | X8: =ROUND(SUM(E8,G8:O8)*2%,2)*0 -> 0 | Y8: =基本信息!CE2 -> 0 | Z8: =基本信息!EM2+基本信息!EN2+基本信息!EO2 -> 0 | AA8: 450 | AB8: =计算结果!BI2*25% -> 0 | AC8: 0 | AF8: =ROUND(AA8*6.77%,2) -> 30.47 | AG8: =SUM(E8:O8)+SUM(P8:AF8) -> 51545.18 | AI8: =基本信息!H2 -> 深圳 | AJ8: =SUM(H8:K8,O8) -> 7326.62 | AK8: =SUM(P8:U8,V8,Z8) -> 11504.81
A11: Sum 合计 | E11: =SUM(E8:E10) -> 29914.13 | F11: =SUM(F8:F10) -> 439.8 | G11: =SUM(G8:G10) -> 0 | H11: =SUM(H8:H10) -> 2200.08 | I11: =SUM(I8:I10) -> 673.32 | J11: =SUM(J8:J10) -> 87.32 | K11: =SUM(K8:K10) -> 4365.9 | L11: =SUM(L8:L10) -> 0 | ... AG11: =SUM(AG8:AG10) -> 51545.18

Sheet S-Payslip
A1: HROne Pay Slip 工资单
A4: Duration 发薪月 | C4: 45820 | E4: Employer 雇主 | G4: =基本信息!A2 -> NNRoad-Hermetic Solutions
A5: No. 序号 | B5: Department 部门 | C5: ID No. 工号 | D5: Name 姓名 | E5: Plus Item 加项 | N5: Basis for Social Benefits Calculation 社保基数 | O5: Basis for Housing Fund Calculation 公积金基数 | P5: Minus Item 减项 | Z5: Adjustment after Tax/税后调整 | AA5: IIT 个税 | AB5: Balance For Charge On Behalf 代缴费用补差 | AC5: Expense 报销款 | AD5: Subsistence Allowance for Foreigners 外籍生活津贴 | AE5: Net Income 实发
E6: Basic Salary 基本工资 | F6: Normal Bonus 日常奖金 | G6: Annual Bonus/13th Salary 年终奖/13薪 | H6: Allowance/Subsidy 津贴/补贴 | I6: OT Payment 加班费 | J6: Income Employer Afford Tax 公司负税项 | K6: Adjustment before Tax/税前调整 | L6: Stock option incentive/股权激励 | M6: Compensation离职补偿金/赔偿金 | N6: Basis for Social Benefits Calculation 社保基数 | O6: Basis for Housing Fund Calculation 公积金基数 | P6: Pension 缴养老 | Q6: Medical 缴医疗 | R6: Unemployment 缴失业 | S6: Housing Fund 缴公积金 | T6: Deduction for 1st/last Month' Absence 入离职缺勤扣 | U6: Deduction for Personal Affair Leave 扣事假 | V6: Deduction for Absenteeism 扣旷工 | W6: Deduction for Sick Leave 扣病假 | X6: Annuity 缴年金 | Y6: Union Fee 工会费
A7: 1 | C7: =IF(基本信息!B2="","",基本信息!B2) -> CUS1525-0002 | D7: =IF(基本信息!C2&基本信息!D2="","",基本信息!C2&" "&基本信息!D2) -> 杨明华 Minghua Yang | E7: =计算结果!C2+计算结果!D2 -> 37337.5 | F7: =计算结果!E2+计算结果!F2+计算结果!G2 -> 497 | G7: =计算结果!BM2 -> 0 | H7: =SUM(计算结果!O2:V2)+计算结果!BG2 -> 1220.6 | I7: =SUM(计算结果!H2:J2) -> 0 | J7: =计算结果!AZ2 -> 58.5 | K7: =计算结果!W2-计算结果!X2+计算结果!Y2 -> 0 | L7: =计算结果!BQ2 -> 0 | M7: =计算结果!BO2 -> 0 | N7: =基本信息!AF2 -> 27501 | O7: =基本信息!AL2 -> 43659 | P7: =计算结果!Z2 -> 2200.08 | Q7: =计算结果!AA2 -> 673.32 | R7: =计算结果!AB2 -> 87.32 | S7: =计算结果!AC2+计算结果!AD2 -> 4365.9 | T7: =计算结果!K2 -> 0 | U7: =计算结果!L2 -> 0 | V7: =计算结果!M2 -> 0 | W7: =计算结果!N2 -> 0 | X7: =计算结果!AG2 -> 0 | Y7: =计算结果!AH2 -> 0 | Z7: =计算结果!BK2-计算结果!BL2 -> 0 | AA7: =计算结果!AX2+计算结果!BN2+计算结果!BP2+计算结果!BR2 -> 1872.85 | AB7: =计算结果!AE2+计算结果!AF2+计算结果!BG2 -> 0 | AC7: =计算结果!BH2+计算结果!BI2 -> 439.8 | AD7: =计算结果!BJ2 -> 0 | AE7: =计算结果!BU2-AC7-AD7 -> 29914.13
A10: Sum 合计 | E10: =SUM(E7:E9) -> 37337.5 | F10: =SUM(F7:F9) -> 497 | G10: =SUM(G7:G9) -> 0 | H10: =SUM(H7:H9) -> 1220.6 | I10: =SUM(I7:I9) -> 0 | J10: =SUM(J7:J9) -> 58.5 | K10: =SUM(K7:K9) -> 0 | L10: =SUM(L7:L9) -> 0 | M10: =SUM(M7:M9) -> 0 | P10: =SUM(P7:P9) -> 2200.08 | Q10: =SUM(Q7:Q9) -> 673.32 | R10: =SUM(R7:R9) -> 87.32 | S10: =SUM(S7:S9) -> 4365.9 | T10: =SUM(T7:T9) -> 0 | U10: =SUM(U7:U9) -> 0 | V10: =SUM(V7:V9) -> 0 | W10: =SUM(W7:W9) -> 0 | ... AE10: =SUM(AE7:AE9) -> 29914.13

Sheet 基本信息
A1: 客户简称 | B1: 工号 | C1: 姓名 | D1: 英文名 | E1: 性别 | F1: 客户类型 | G1: 工作地 | H1: 社保缴纳地 | I1: 公积金缴纳地 | J1: 用工性质 | K1: 服务起始日 | L1: 合同所属地 | M1: 合同起始日 | N1: 合同终止日 | O1: 离职日期 | P1: 税前/税后 | Q1: 基本工资 | R1: 日薪 | S1: 浮动工资 | T1: 交通津贴 | U1: 通讯津贴 | V1: 其他固定津贴 | W1: 中班津贴基数 | X1: 夜班津贴基数 | Y1: 高温津贴基数 | Z1: 高温作业保健食品费基数 | AA1: 有毒有害保健食品费基数 | AB1: 独生子女出生日期 | AC1: 独生子女津贴基数 | AD1: 固定补 | AE1: 固定扣 | AF1: 养老基数 | AG1: 医疗基数 | AH1: 失业基数 | AI1: 生育基数 | AJ1: 工伤基数 | AK1: 残保金基数 | AL1: 公积金基数 | AM1: 补充公积金基数 | AN1: 个人养老% | AO1: 个人医疗% | AP1: 个人失业% | AQ1: 个人公积金% | AR1: 个人补充公积金%（免税） | AS1: 个人补充公积金%（不免税） | AT1: 个人医疗固定数 | AU1: 公司养老% | AV1: 公司医疗% | AW1: 公司失业% | AX1: 公司生育% | AY1: 公司工伤% | AZ1: 公司残保金% | BA1: 公司公积金% | BB1: 公司补充公积金% | BC1: 公司医疗固定数 | BD1: 公司工伤固定数 | BE1: 公司残保固定数 | BF1: 年金% | BG1: 工会费 | BH1: 商业保险计税不发 | BI1: 公司负税1 | BJ1: 外籍生活津贴（免税） | BK1: 税后扣1 | BL1: 免税收入1 | BM1: 证件类型 | BN1: 证件号码 | BO1: 生日 | BP1: 公积金账号 | BQ1: 银行户名 | BR1: 银行账号 | BS1: 银行 | BT1: 部门 | BU1: 岗位 | BV1: 国籍/民族 | BW1: 国籍代码 | BX1: 工资单 | BY1: 电话/手机 | BZ1: 邮箱 | CA1: 账单邮寄地址 | CB1: 邮编 | CC1: 户口性质 | CD1: 户籍地址 | CE1: 商业保险总费用 | CF1: 商业险级别 | CG1: 配偶/子女险 | CH1: 绿色津贴 | CI1: 体检 | CJ1: 档案管理费 | CK1: 13薪/年终奖信息 | CL1: 13薪月份 | CM1: 备注1 | CN1: 个税缴纳地 | CO1: 累计子女教育 | CP1: 累计继续教育 | CQ1: 累计住房贷款利息 | CR1: 累计住房租金 | CS1: 累计赡养老人 | CT1: 累计婴幼儿照护费用 | CU1: 税延养老保险 | CV1: 其他免税扣除（捐款） | CW1: 日薪出勤天数 | CX1: 月奖 | CY1: 季奖 | CZ1: 其他奖金 | DA1: 加班小时150 | DB1: 加班小时200 | DC1: 加班小时300 | DD1: 当月全勤日 | DE1: 入离职缺勤天数 | DF1: 事假天数 | DG1: 旷工天数 | DH1: 病假天数 | DI1: 扣病假工资 | DJ1: 交通费 | DK1: 通讯费 | DL1: 中班天数 | DM1: 夜班天数 | DN1: 高温天数 | DO1: 一次性高温费 | DP1: 高温作业天数 | DQ1: 有毒有害作业天数 | DR1: 补发 | DS1: 补扣 | DT1: 税前调整 | DU1: 养老补缴 | DV1: 医疗补缴 | DW1: 失业补缴 | DX1: 公积金补缴 | DY1: 免税收入2 | DZ1: 计税不发2 | EA1: 公司负税2 | EB1: 报销款 | EC1: 报销款25% | ED1: 税后补 | EE1: 税后扣2 | EF1: 个税调整 | EG1: 13薪/年终奖 | EH1: 离职补偿金/赔偿金 | EI1: 离职补偿金/赔偿金免税额 | EJ1: 补偿计算年限 | EK1: 股权激励 | EL1: 备注2 | EM1: 公司社保补缴 | EN1: 公司公积金补缴 | EO1: 残保金补缴 | EP1: 发薪所属 | EQ1: 开户行所在地 | ER1: 是否代缴社保 | ES1: 是否代缴公积金 | ET1: 是否代缴个税 | EU1: 客户编号
A2: NNRoad-Hermetic Solutions | B2: CUS1525-0002 | C2: 杨明华 | D2: Minghua Yang | E2: Male | F2: Dispatching | G2: 深圳 | H2: 深圳 | I2: 深圳 | J2: 1 | K2: 2019-12-01 | M2: 2023-10-01 | N2: 2025-09-30 | P2: 税前 | Q2: 37337.5 | AF2: 27501 | AG2: 33666 | AH2: 43659 | AI2: 33666 | AJ2: 51709 | AL2: 43659 | AN2: 0.08 | AO2: 0.02 | AP2: 0.002 | AQ2: 0.1 | AU2: 0.17 | AV2: 0.05 | AW2: 0.008 | AX2: 0.005 | AY2: 0.004 | BA2: 0.1 | BE2: 56 | BM2: 1 | BN2: 340403197908151230 | BO2: 29082 | BQ2: 杨明华 | BR2: 6227007200020223600 | BS2: 中国建设银行股份有限公司深圳分行福田支行 | BV2: 中国 | BW2: 156 | BY2: 13510035528 | BZ2: minghua.yang@139.com | CA2: 深圳市龙华区龙华大道世纪春城四期5#楼402 | CB2: 518131 | CC2: Urban | CD2: 深圳市龙华区龙华大道世纪春城四期5#楼402 | CN2: 深圳人服 | CO2: =IFERROR(VLOOKUP($BN2,专项附加!$D:$Q,10,0),0) -> 24000 | CP2: =IFERROR(VLOOKUP($BN2,专项附加!$D:$Q,11,0),0) -> 0 | CQ2: =IFERROR(VLOOKUP($BN2,专项附加!$D:$Q,12,0),0) -> 6000 | CR2: =IFERROR(VLOOKUP($BN2,专项附加!$D:$Q,13,0),0) -> 0 | CS2: =IFERROR(VLOOKUP($BN2,专项附加!$D:$Q,14,0),0) -> 18000 | CT2: =IFERROR(VLOOKUP($BN2,专项附加!$D:$Q,15,0),0) -> 0 | CZ2: 497 | DJ2: 1220.6 | EA2: 58.5 | EB2: 439.8 | EP2: 深圳人服 | EQ2: 深圳 | ER2: Y | ES2: Y | ET2: Y | EU2: CUS1525

Sheet 专项附加
A1: 工号 | B1: 姓名 | C1: 证件类型 | D1: 证件号码 | E1: 所得期间起 | F1: 所得期间止 | G1: 本期收入 | H1: 本期免税收入 | I1: 基本养老保险费 | J1: 基本医疗保险费 | K1: 失业保险费 | L1: 住房公积金 | M1: 累计子女教育 | N1: 累计继续教育 | O1: 累计住房贷款利息 | P1: 累计住房租金 | Q1: 累计赡养老人 | R1: 累计婴幼儿照护费用 | S1: 企业(职业)年金 | T1: 商业健康保险 | U1: 税延养老保险 | V1: 其他 | W1: 准予扣除的捐赠额 | X1: 税前扣除项目合计 | Y1: 减免税额 | Z1: 减除费用标准 | AA1: 已缴税额 | AB1: 备注
B2: 杨明华 | D2: 340403197908151230 | M2: 24000 | O2: 6000 | Q2: 18000

Sheet 计算结果
A1: 工号 | B1: 姓名 | C1: 基本工资 | D1: 浮动工资 | E1: 月奖 | F1: 季奖 | G1: 其他奖金 | H1: 加班工资150 | I1: 加班工资200 | J1: 加班工资300 | K1: 入离职缺勤扣 | L1: 扣事假 | M1: 扣旷工 | N1: 扣病假 | O1: 交通费 | P1: 通讯费 | Q1: 其他津贴 | R1: 中班费 | S1: 夜班费 | T1: 高温费 | U1: 高温作业费 | V1: 有毒有害作业费 | W1: 补发 | X1: 补扣 | Y1: 税前调整 | Z1: 缴养老 | AA1: 缴医疗 | AB1: 缴失业 | AC1: 缴公积金 | AD1: 缴补充公积金（免税） | AE1: 社保调整 | AF1: 公积金调整 | AG1: 年金 | AH1: 工会费 | AI1: 计税不发 | AJ1: 当月税前收入额 | AK1: 当月基本扣除 | AL1: 累计税前收入-员工 | AM1: 累计个人社保公积金 | AN1: 累计基本扣除 | AO1: 累计子女教育 | AP1: 累计继续教育 | AQ1: 累计住房贷款利息 | AR1: 累计住房租金 | AS1: 累计赡养老人 | AT1: 累计其他税前扣除 | AU1: 累计免税扣除合计(不含社保公积金） | AV1: 累计应税总额 | AW1: 累计个税（个人） | AX1: 当月个税（个人） | AY1: 公司负税项 | AZ1: 当月公司负税合计 | BA1: 累计税后计税收入 | BB1: 累计税前收入 | BC1: 导算当月应发工资 | BD1: 累计个税（公司+个人） | BE1: 当月个税（公司） | BF1: 独生子女费 | BG1: 缴补充公积金（不免税） | BH1: 报销款 | BI1: 报销款25% | BJ1: 外籍生活津贴 | BK1: 税后补 | BL1: 税后扣 | BM1: 13薪/年终奖 | BN1: 13薪/年终奖税 | BO1: 离职补偿金/赔偿金 | BP1: 离职补偿金税/赔偿金税 | BQ1: 股权激励 | BR1: 股权激励税 | BS1: 应发 | BT1: 应扣 | BU1: 实发 | BV1: 公司养老 | BW1: 公司医疗 | BX1: 公司失业 | BY1: 生育 | BZ1: 工伤 | CA1: 残保金 | CB1: 公积金 | CC1: 补充公积金（免税） | CD1: 累计已扣工资税 | CE1: 累计婴幼儿照护费用 | CF1: 工会费 | CG1: 雇主责任险 | CH1: 押金 | CI1: 服务费 | CJ1: 增值税
A2: =IF(基本信息!B2="","",基本信息!B2) -> CUS1525-0002 | B2: =IF(基本信息!C2="","",基本信息!C2) -> 杨明华 | C2: =基本信息!Q2+基本信息!R2*基本信息!CW2 -> 37337.5 | D2: =基本信息!S2 -> 0 | E2: =基本信息!CX2 -> 0 | F2: =基本信息!CY2 -> 0 | G2: =基本信息!CZ2 -> 497 | H2: =ROUND(C2*基本信息!DA2*1.5/(21.75*8),2) -> 0 | I2: =ROUND(C2*基本信息!DB2*2/(21.75*8),2) -> 0 | J2: =ROUND(C2*基本信息!DC2*3/(21.75*8),2) -> 0 | K2: =ROUND(IF(AND(基本信息!DD2=23,基本信息!DE2=12),((C2+D2)*12/21.75+(C2+D2)-(C2+D2)*11/21.75)/2,IF(基本信息!DE2>基本信息!DD2/2,(C2+D2)-(C2+D2)*(基本信息!DD2-基本信息!DE2)/21.75,(C2+D2)*基本信息!DE2/21.75)),2) -> 0 | L2: =MAX(0,ROUND((C2+D2)*基本信息!DF2/21.75,2)) -> 0 | M2: =MAX(0,ROUND((C2+D2)*基本信息!DG2/21.75,2)) -> 0 | N2: =基本信息!DI2 -> 0 | O2: =基本信息!T2+基本信息!DJ2 -> 1220.6 | P2: =基本信息!U2+基本信息!DK2 -> 0 | Q2: =基本信息!V2 -> 0 | R2: =基本信息!W2*基本信息!DL2 -> 0 | S2: =基本信息!X2*基本信息!DM2 -> 0 | T2: =基本信息!Y2*基本信息!DN2+基本信息!DO2 -> 0 | U2: =基本信息!Z2*基本信息!DP2 -> 0 | V2: =基本信息!AA2*基本信息!DQ2 -> 0 | W2: =基本信息!AD2+基本信息!DR2 -> 0 | X2: =基本信息!AE2+基本信息!DS2 -> 0 | Y2: =基本信息!DT2 -> 0 | Z2: =IF(VLOOKUP(基本信息!$H2,各地政策!$A:$X,21,0)="进位",ROUNDUP(基本信息!AF2*基本信息!AN2,VLOOKUP(基本信息!$H2,各地政策!$A:$X,20,0)),IF(VLOOKUP(基本信息!$H2,各地政策!$A:$X,21,0)="四舍五入",ROUND(基本信息!AF2*基本信息!AN2,VLOOKUP(基本信息!$H2,各地政策!$A:$X,20,0)),ROUND(基本信息!AF2*基本信息!AN2-IF(VLOOKUP(基本信息!$H2,各地政策!$A:$X,20,0)=0,0.5,IF(VLOOKUP(基本信息!$H2,各地政策!$A:$X,20,0)=1,0.05,0.005)),VLOOKUP(基本信息!$H2,各地政策!$A:$X,20,0)))) -> 2200.08 | AA2: =IF(VLOOKUP(基本信息!$H2,各地政策!$A:$X,21,0)="进位",ROUNDUP(基本信息!AG2*基本信息!AO2,VLOOKUP(基本信息!$H2,各地政策!$A:$X,20,0)),IF(VLOOKUP(基本信息!$H2,各地政策!$A:$X,21,0)="四舍五入",ROUND(基本信息!AG2*基本信息!AO2,VLOOKUP(基本信息!$H2,各地政策!$A:$X,20,0)),ROUND(基本信息!AG2*基本信息!AO2-IF(VLOOKUP(基本信息!$H2,各地政策!$A:$X,20,0)=0,0.5,IF(VLOOKUP(基本信息!$H2,各地政策!$A:$X,20,0)=1,0.05,0.005)),VLOOKUP(基本信息!$H2,各地政策!$A:$X,20,0))))+基本信息!AT2 -> 673.32 | AB2: =IF(VLOOKUP(基本信息!$H2,各地政策!$A:$X,21,0)="进位",ROUNDUP(基本信息!AH2*基本信息!AP2,VLOOKUP(基本信息!$H2,各地政策!$A:$X,20,0)),IF(VLOOKUP(基本信息!$H2,各地政策!$A:$X,21,0)="四舍五入",ROUND(基本信息!AH2*基本信息!AP2,VLOOKUP(基本信息!$H2,各地政策!$A:$X,20,0)),ROUND(基本信息!AH2*基本信息!AP2-IF(VLOOKUP(基本信息!$H2,各地政策!$A:$X,20,0)=0,0.5,IF(VLOOKUP(基本信息!$H2,各地政策!$A:$X,20,0)=1,0.05,0.005)),VLOOKUP(基本信息!$H2,各地政策!$A:$X,20,0)))) -> 87.32 | AC2: =IF(VLOOKUP(基本信息!$I2,各地政策!$A:$X,24,0)="进位",ROUNDUP(基本信息!AL2*基本信息!AQ2,VLOOKUP(基本信息!$I2,各地政策!$A:$X,23,0)),IF(VLOOKUP(基本信息!$I2,各地政策!$A:$X,24,0)="四舍五入",ROUND(基本信息!AL2*基本信息!AQ2,VLOOKUP(基本信息!$I2,各地政策!$A:$X,23,0)),ROUND(基本信息!AL2*基本信息!AQ2-IF(VLOOKUP(基本信息!$I2,各地政策!$A:$X,23,0)=0,0.5,IF(VLOOKUP(基本信息!$I2,各地政策!$A:$X,23,0)=1,0.05,0.005)),VLOOKUP(基本信息!$I2,各地政策!$A:$X,23,0)))) -> 4365.9 | AD2: =IF(VLOOKUP(基本信息!$I2,各地政策!$A:$X,24,0)="进位",ROUNDUP(基本信息!AM2*基本信息!AR2,VLOOKUP(基本信息!$I2,各地政策!$A:$X,23,0)),IF(VLOOKUP(基本信息!$I2,各地政策!$A:$X,24,0)="四舍五入",ROUND(基本信息!AM2*基本信息!AR2,VLOOKUP(基本信息!$I2,各地政策!$A:$X,23,0)),ROUND(基本信息!AM2*基本信息!AR2-IF(VLOOKUP(基本信息!$I2,各地政策!$A:$X,23,0)=0,0.5,IF(VLOOKUP(基本信息!$I2,各地政策!$A:$X,23,0)=1,0.05,0.005)),VLOOKUP(基本信息!$I2,各地政策!$A:$X,23,0)))) -> 0 | AE2: =基本信息!DU2+基本信息!DV2+基本信息!DW2 -> 0 | AF2: =基本信息!DX2 -> 0 | AG2: =基本信息!BF2 -> 0 | AH2: =基本信息!BG2 -> 0 | AI2: =基本信息!BH2+基本信息!DZ2 -> 0 | AJ2: =IF(基本信息!P2="税前",SUM(C2:J2)+SUM(O2:W2)-SUM(K2:N2)-SUM(X2:X2)+Y2-AG2-AH2+AI2,0) -> 39055.1 | AK2: =IF(基本信息!J2=3,MAX(AJ2*0.2,800),5000) -> 5000 | AL2: =IF(基本信息!P2="税前",SUMIF(YTD!$A$2:$A$2386,$A2,YTD!$BB$2:$BB$2386)+SUMIF(YTD!$A$2:$A$2386,$A2,YTD!$AM$2:$AM$2386)+AJ2,0) -> 240461.98 | AM2: =SUMIF(YTD!$A$2:$A$2386,$A2,YTD!$AM$2:$AM$2386)+SUM(Z2:AF2) -> 44478.12 | AN2: =SUMIF(YTD!$A$2:$A$2386,$A2,YTD!$AN$2:$AN$2386)+计算结果!AK2 -> 30000 | AO2: =基本信息!CO2 -> 24000 | AP2: =基本信息!CP2 -> 0 | AQ2: =基本信息!CQ2 -> 6000 | AR2: =基本信息!CR2 -> 0 | AS2: =基本信息!CS2 -> 18000 | AT2: {=SUMPRODUCT((基本信息!$B$2:$B$2375=$A2)*(基本信息!$CU$2:$CV$2375))+SUMIF(YTD!$A$2:$A$2386,$A2,YTD!$AT$2:$AT$2386)} -> 0 | AU2: =SUM(AN2:AT2,CE2) -> 78000 | AV2: =IF(基本信息!P2="税前",AL2-AM2-AU2,0) -> 117983.86 | AW2: {=IF(基本信息!J2=1,MAX((AV2)*{0.03,0.1,0.2,0.25,0.3,0.35,0.45}-12*{0,210,1410,2660,4410,7160,15160},0),IF(基本信息!J2=4,MAX((AL2-AL2*0.2-AU2)*{0.03,0.1,0.2,0.25,0.3,0.35,0.45}-12*{0,210,1410,2660,4410,7160,15160},0),0))} -> 9278.3859 | AX2: {=MAX(ROUND(IF(基本信息!J2=3,MAX((AJ2-IF(AJ2<4000,800,AJ2*0.2))*10%*{2,3,4}-1000*{0,2,7},0),IF(基本信息!J2=2,MAX((AJ2-SUM(Z2:AG2)-AK2)*{0.03,0.1,0.2,0.25,0.3,0.35,0.45}-{0,210,1410,2660,4410,7160,15160},0),IF(基本信息!P2="税前",AW2-ROUND(SUMIF(YTD!$A$2:$A$2386,$A2,YTD!$CD$2:$CD$2386),2),0))),2),0)} -> 1872.85 | AY2: =基本信息!BI2+基本信息!EA2 -> 58.5 | AZ2: =IF(基本信息!P2="税前",0,SUM(C2:J2)-SUM(K2:N2)+SUM(O2:W2)-X2+Y2+AI2)+AY2 -> 58.5 | BA2: =IF(OR(基本信息!J2=1,基本信息!J2=4),IF(基本信息!P2="税前",AL2-AM2-AW2+AZ2,AZ2+SUMIF(YTD!$A$2:$A$2386,$A2,YTD!$BA$2:$BA$2386)),IF(基本信息!P2="税前",AJ2-SUM(Z2:AG2)-AX2+AZ2,AZ2)) -> 186763.97 | BB2: {=IF(基本信息!J2=3,LOOKUP(AJ2-AX2+AZ2,{0,800,3360,21000,49500},(AJ2-AX2+AZ2-{0,160,0,2000,7000})*{1,5,25,25,25}/{1,4,21,19,17}),IF(基本信息!J2=2,MAX((BA2-AK2-10*{0,21,141,266,441,716,1516})/(1-5%*{0.6,2,4,5,6,7,9})+AK2,BA2),IF(基本信息!J2=4,MAX((BA2-AU2-(AL2*0.2)-120*{0,21,141,266,441,716,1516})/(1-5%*{0.6,2,4,5,6,7,9})+AU2+(AL2*0.2),BA2),MAX((BA2-AU2-120*{0,21,141,266,441,716,1516})/(1-5%*{0.6,2,4,5,6,7,9})+AU2,BA2))))} -> 196048.86 | BC2: =IF(OR(基本信息!J2=1,基本信息!J2=4),BB2-IFERROR(VLOOKUP($A2,YTD!$A:$BB,54,0),0),BB2)+SUM(Z2:AF2) -> 39120.1 | BD2: {=IF(基本信息!J2=4,MAX((BB2-BB2*0.2-AU2)*{0.03,0.1,0.2,0.25,0.3,0.35,0.45}-12*{0,210,1410,2660,4410,7160,15160},0),IF(基本信息!J2=3,MAX((BB2-IF(BB2<4000,800,BB2*0.2))*10%*{2,3,4}-1000*{0,2,7},0),IF(基本信息!J2=2,MAX((BB2-AK2)*{0.03,0.1,0.2,0.25,0.3,0.35,0.45}-{0,210,1410,2660,4410,7160,15160},0),MAX((BB2-AU2)*{0.03,0.1,0.2,0.25,0.3,0.35,0.45}-12*{0,210,1410,2660,4410,7160,15160},0))))} -> 9284.8859 | BE2: =MAX(ROUND(IF(基本信息!J2=1,BD2-AX2-ROUND(SUMIF(YTD!$A$2:$A$2386,$A2,YTD!$CD$2:$CD$2386),2),IF(基本信息!J2=4,BD2-AX2-ROUND(SUMIF(YTD!$A$2:$A$2386,$A2,YTD!$CD$2:$CD$2386),2),BD2-AX2)),2),0) -> 6.5 | BF2: =IF(YEARFRAC(基本信息!AB2,TODAY())*12-1<192,基本信息!AC2,0) -> 0 | BG2: =IF(VLOOKUP(基本信息!$I2,各地政策!$A:$X,24,0)="进位",ROUNDUP(基本信息!AM2*基本信息!AS2,VLOOKUP(基本信息!$I2,各地政策!$A:$X,23,0)),IF(VLOOKUP(基本信息!$I2,各地政策!$A:$X,24,0)="四舍五入",ROUND(基本信息!AM2*基本信息!AS2,VLOOKUP(基本信息!$I2,各地政策!$A:$X,23,0)),ROUND(基本信息!AM2*基本信息!AS2-IF(VLOOKUP(基本信息!$I2,各地政策!$A:$X,23,0)=0,0.5,IF(VLOOKUP(基本信息!$I2,各地政策!$A:$X,23,0)=1,0.05,0.005)),VLOOKUP(基本信息!$I2,各地政策!$A:$X,23,0)))) -> 0 | BH2: =基本信息!EB2 -> 439.8 | BI2: =基本信息!EC2 -> 0 | BJ2: =基本信息!BJ2 -> 0 | BK2: =基本信息!BL2+基本信息!DY2+基本信息!ED2 -> 0 | BL2: =基本信息!BK2+基本信息!EE2 -> 0 | BM2: =基本信息!EG2 -> 0 | BN2: {=IF(基本信息!J2=2,MAX((BM2/6)*{0.03,0.1,0.2,0.25,0.3,0.35,0.45}-{0,210,1410,2660,4410,7160,15160},0)*6,ROUND((BM2)*LOOKUP(-(BM2)/12,-{99999,80,55,35,25,12,3,0,-9}*1000,{9,7,6,5,4,2,0.6,0,0}*5%)-LOOKUP(-(BM2)/12,-{99999,80,55,35,25,12,3,0,-9}*1000,{1516,716,441,266,141,21,0,0}*10),2))} -> 0 | BO2: =基本信息!EH2 -> 0 | BP2: {=IFERROR(ROUND(MAX((基本信息!EH2-基本信息!EI2)*{0.03,0.1,0.2,0.25,0.3,0.35,0.45}-12*{0,210,1410,2660,4410,7160,15160},0),2),0)} -> 0 | BQ2: =基本信息!EK2 -> 0 | BR2: {=ROUND((BQ2)*LOOKUP(-BQ2,-{99999,96,66,42,30,14.4,3.6,0,-9}*10000,{9,7,6,5,4,2,0.6,0,0}*5%)-LOOKUP(-BQ2,-{99999,96,66,42,30,14.4,3.6,0,-9}*10000,{18192,8592,5292,3192,1692,252,0,0}*10),2)} -> 0 | BS2: =SUM(C2:J2)+SUM(O2:W2)+Y2+AY2+BF2+BK2+BM2+BO2+BH2+BJ2+BI2+BQ2 -> 39553.4 | BT2: =IF(基本信息!P2="税前",SUM(K2:N2)+SUM(X2,Z2:AH2)+AX2+BG2+BL2+BN2+BP2+BR2,SUM(K2:N2,X2,BL2,BN2,BP2,BR2)) -> 9199.47 | BU2: =ROUND(BS2-BT2,2) -> 30353.93 | BV2: =IF(VLOOKUP(基本信息!$H2,各地政策!$A:$X,21,0)="进位",ROUNDUP(基本信息!AF2*基本信息!AU2,VLOOKUP(基本信息!$H2,各地政策!$A:$X,20,0)),IF(VLOOKUP(基本信息!$H2,各地政策!$A:$X,21,0)="四舍五入",ROUND(基本信息!AF2*基本信息!AU2,VLOOKUP(基本信息!$H2,各地政策!$A:$X,20,0)),ROUND(基本信息!AF2*基本信息!AU2-IF(VLOOKUP(基本信息!$H2,各地政策!$A:$X,20,0)=0,0.5,IF(VLOOKUP(基本信息!$H2,各地政策!$A:$X,20,0)=1,0.05,0.005)),VLOOKUP(基本信息!$H2,各地政策!$A:$X,20,0)))) -> 4675.17 | BW2: =IF(VLOOKUP(基本信息!$H2,各地政策!$A:$X,21,0)="进位",ROUNDUP(基本信息!AG2*基本信息!AV2,VLOOKUP(基本信息!$H2,各地政策!$A:$X,20,0)),IF(VLOOKUP(基本信息!$H2,各地政策!$A:$X,21,0)="四舍五入",ROUND(基本信息!AG2*基本信息!AV2,VLOOKUP(基本信息!$H2,各地政策!$A:$X,20,0)),ROUND(基本信息!AG2*基本信息!AV2-IF(VLOOKUP(基本信息!$H2,各地政策!$A:$X,20,0)=0,0.5,IF(VLOOKUP(基本信息!$H2,各地政策!$A:$X,20,0)=1,0.05,0.005)),VLOOKUP(基本信息!$H2,各地政策!$A:$X,20,0))))+基本信息!BC2 -> 1683.3 | BX2: =IF(VLOOKUP(基本信息!$H2,各地政策!$A:$X,21,0)="进位",ROUNDUP(基本信息!AH2*基本信息!AW2,VLOOKUP(基本信息!$H2,各地政策!$A:$X,20,0)),IF(VLOOKUP(基本信息!$H2,各地政策!$A:$X,21,0)="四舍五入",ROUND(基本信息!AH2*基本信息!AW2,VLOOKUP(基本信息!$H2,各地政策!$A:$X,20,0)),ROUND(基本信息!AH2*基本信息!AW2-IF(VLOOKUP(基本信息!$H2,各地政策!$A:$X,20,0)=0,0.5,IF(VLOOKUP(基本信息!$H2,各地政策!$A:$X,20,0)=1,0.05,0.005)),VLOOKUP(基本信息!$H2,各地政策!$A:$X,20,0)))) -> 349.27 | BY2: =IF(VLOOKUP(基本信息!$H2,各地政策!$A:$X,21,0)="进位",ROUNDUP(基本信息!AI2*基本信息!AX2,VLOOKUP(基本信息!$H2,各地政策!$A:$X,20,0)),IF(VLOOKUP(基本信息!$H2,各地政策!$A:$X,21,0)="四舍五入",ROUND(基本信息!AI2*基本信息!AX2,VLOOKUP(基本信息!$H2,各地政策!$A:$X,20,0)),ROUND(基本信息!AI2*基本信息!AX2-IF(VLOOKUP(基本信息!$H2,各地政策!$A:$X,20,0)=0,0.5,IF(VLOOKUP(基本信息!$H2,各地政策!$A:$X,20,0)=1,0.05,0.005)),VLOOKUP(基本信息!$H2,各地政策!$A:$X,20,0)))) -> 168.33 | BZ2: =IF(VLOOKUP(基本信息!$H2,各地政策!$A:$X,21,0)="进位",ROUNDUP(基本信息!AJ2*基本信息!AY2,VLOOKUP(基本信息!$H2,各地政策!$A:$X,20,0)),IF(VLOOKUP(基本信息!$H2,各地政策!$A:$X,21,0)="四舍五入",ROUND(基本信息!AJ2*基本信息!AY2,VLOOKUP(基本信息!$H2,各地政策!$A:$X,20,0)),ROUND(基本信息!AJ2*基本信息!AY2-IF(VLOOKUP(基本信息!$H2,各地政策!$A:$X,20,0)=0,0.5,IF(VLOOKUP(基本信息!$H2,各地政策!$A:$X,20,0)=1,0.05,0.005)),VLOOKUP(基本信息!$H2,各地政策!$A:$X,20,0))))+基本信息!BD2 -> 206.84 | CA2: =IF(VLOOKUP(基本信息!$H2,各地政策!$A:$X,21,0)="进位",ROUNDUP(基本信息!AK2*基本信息!AZ2+基本信息!BE2,VLOOKUP(基本信息!$H2,各地政策!$A:$X,20,0)),IF(VLOOKUP(基本信息!$H2,各地政策!$A:$X,21,0)="四舍五入",ROUND(基本信息!AK2*基本信息!AZ2+基本信息!BE2,VLOOKUP(基本信息!$H2,各地政策!$A:$X,20,0)),ROUND(基本信息!AK2*基本信息!AZ2+基本信息!BE2-IF(VLOOKUP(基本信息!$H2,各地政策!$A:$X,20,0)=0,0.5,IF(VLOOKUP(基本信息!$H2,各地政策!$A:$X,20,0)=1,0.05,0.005)),VLOOKUP(基本信息!$H2,各地政策!$A:$X,20,0)))) -> 56 | CB2: =IF(VLOOKUP(基本信息!$I2,各地政策!$A:$X,24,0)="进位",ROUNDUP(基本信息!AL2*(基本信息!BA2),VLOOKUP(基本信息!$I2,各地政策!$A:$X,23,0)),IF(VLOOKUP(基本信息!$I2,各地政策!$A:$X,24,0)="四舍五入",ROUND(基本信息!AL2*(基本信息!BA2),VLOOKUP(基本信息!$I2,各地政策!$A:$X,23,0)),ROUND(基本信息!AL2*(基本信息!BA2)-IF(VLOOKUP(基本信息!$I2,各地政策!$A:$X,23,0)=0,0.5,IF(VLOOKUP(基本信息!$I2,各地政策!$A:$X,23,0)=1,0.05,0.005)),VLOOKUP(基本信息!$I2,各地政策!$A:$X,23,0)))) -> 4365.9 | CC2: =IF(VLOOKUP(基本信息!$I2,各地政策!$A:$X,24,0)="进位",ROUNDUP(基本信息!AM2*(基本信息!BB2),VLOOKUP(基本信息!$I2,各地政策!$A:$X,23,0)),IF(VLOOKUP(基本信息!$I2,各地政策!$A:$X,24,0)="四舍五入",ROUND(基本信息!AM2*(基本信息!BB2),VLOOKUP(基本信息!$I2,各地政策!$A:$X,23,0)),ROUND(基本信息!AM2*(基本信息!BB2)-IF(VLOOKUP(基本信息!$I2,各地政策!$A:$X,23,0)=0,0.5,IF(VLOOKUP(基本信息!$I2,各地政策!$A:$X,23,0)=1,0.05,0.005)),VLOOKUP(基本信息!$I2,各地政策!$A:$X,23,0)))) -> 0 | CD2: =AX2+BE2+IFERROR(VLOOKUP($A2,YTD!$A:$CD,82,0),0) -> 9284.89 | CE2: =基本信息!CT2 -> 0 | CF2: ='S-Payroll Report'!X8 -> 0 | CG2: ='S-Payroll Report'!AD8 -> 0 | CH2: ='S-Payroll Report'!AC8 -> 0 | CI2: ='S-Payroll Report'!AA8 -> 450 | CJ2: ='S-Payroll Report'!AF8 -> 30.47 | CK2: =基本信息!EM2+基本信息!EN2+基本信息!EO2 -> 0
A3: =IF(基本信息!B3="","",基本信息!B3) | B3: =IF(基本信息!C3="","",基本信息!C3) | C3: =基本信息!Q3+基本信息!R3*基本信息!CW3 -> 0 | D3: =基本信息!S3 -> 0 | E3: =基本信息!CX3 -> 0 | F3: =基本信息!CY3 -> 0 | G3: =基本信息!CZ3 -> 0 | H3: =ROUND(C3*基本信息!DA3*1.5/(21.75*8),2) -> 0 | I3: =ROUND(C3*基本信息!DB3*2/(21.75*8),2) -> 0 | J3: =ROUND(C3*基本信息!DC3*3/(21.75*8),2) -> 0 | K3: =ROUND(IF(AND(基本信息!DD3=23,基本信息!DE3=12),((C3+D3)*12/21.75+(C3+D3)-(C3+D3)*11/21.75)/2,IF(基本信息!DE3>基本信息!DD3/2,(C3+D3)-(C3+D3)*(基本信息!DD3-基本信息!DE3)/21.75,(C3+D3)*基本信息!DE3/21.75)),2) -> 0 | L3: =MAX(0,ROUND((C3+D3)*基本信息!DF3/21.75,2)) -> 0 | M3: =MAX(0,ROUND((C3+D3)*基本信息!DG3/21.75,2)) -> 0 | N3: =基本信息!DI3 -> 0 | O3: =基本信息!T3+基本信息!DJ3 -> 0 | P3: =基本信息!U3+基本信息!DK3 -> 0 | Q3: =基本信息!V3 -> 0 | R3: =基本信息!W3*基本信息!DL3 -> 0 | S3: =基本信息!X3*基本信息!DM3 -> 0 | T3: =基本信息!Y3*基本信息!DN3+基本信息!DO3 -> 0 | U3: =基本信息!Z3*基本信息!DP3 -> 0 | V3: =基本信息!AA3*基本信息!DQ3 -> 0 | W3: =基本信息!AD3+基本信息!DR3 -> 0 | X3: =基本信息!AE3+基本信息!DS3 -> 0 | Y3: =基本信息!DT3 -> 0 | Z3: =IF(VLOOKUP(基本信息!$H3,各地政策!$A:$X,21,0)="进位",ROUNDUP(基本信息!AF3*基本信息!AN3,VLOOKUP(基本信息!$H3,各地政策!$A:$X,20,0)),IF(VLOOKUP(基本信息!$H3,各地政策!$A:$X,21,0)="四舍五入",ROUND(基本信息!AF3*基本信息!AN3,VLOOKUP(基本信息!$H3,各地政策!$A:$X,20,0)),ROUND(基本信息!AF3*基本信息!AN3-IF(VLOOKUP(基本信息!$H3,各地政策!$A:$X,20,0)=0,0.5,IF(VLOOKUP(基本信息!$H3,各地政策!$A:$X,20,0)=1,0.05,0.005)),VLOOKUP(基本信息!$H3,各地政策!$A:$X,20,0)))) -> #N/A | AA3: =IF(VLOOKUP(基本信息!$H3,各地政策!$A:$X,21,0)="进位",ROUNDUP(基本信息!AG3*基本信息!AO3,VLOOKUP(基本信息!$H3,各地政策!$A:$X,20,0)),IF(VLOOKUP(基本信息!$H3,各地政策!$A:$X,21,0)="四舍五入",ROUND(基本信息!AG3*基本信息!AO3,VLOOKUP(基本信息!$H3,各地政策!$A:$X,20,0)),ROUND(基本信息!AG3*基本信息!AO3-IF(VLOOKUP(基本信息!$H3,各地政策!$A:$X,20,0)=0,0.5,IF(VLOOKUP(基本信息!$H3,各地政策!$A:$X,20,0)=1,0.05,0.005)),VLOOKUP(基本信息!$H3,各地政策!$A:$X,20,0))))+基本信息!AT3 -> #N/A | AB3: =IF(VLOOKUP(基本信息!$H3,各地政策!$A:$X,21,0)="进位",ROUNDUP(基本信息!AH3*基本信息!AP3,VLOOKUP(基本信息!$H3,各地政策!$A:$X,20,0)),IF(VLOOKUP(基本信息!$H3,各地政策!$A:$X,21,0)="四舍五入",ROUND(基本信息!AH3*基本信息!AP3,VLOOKUP(基本信息!$H3,各地政策!$A:$X,20,0)),ROUND(基本信息!AH3*基本信息!AP3-IF(VLOOKUP(基本信息!$H3,各地政策!$A:$X,20,0)=0,0.5,IF(VLOOKUP(基本信息!$H3,各地政策!$A:$X,20,0)=1,0.05,0.005)),VLOOKUP(基本信息!$H3,各地政策!$A:$X,20,0)))) -> #N/A | AC3: =IF(VLOOKUP(基本信息!$I3,各地政策!$A:$X,24,0)="进位",ROUNDUP(基本信息!AL3*基本信息!AQ3,VLOOKUP(基本信息!$I3,各地政策!$A:$X,23,0)),IF(VLOOKUP(基本信息!$I3,各地政策!$A:$X,24,0)="四舍五入",ROUND(基本信息!AL3*基本信息!AQ3,VLOOKUP(基本信息!$I3,各地政策!$A:$X,23,0)),ROUND(基本信息!AL3*基本信息!AQ3-IF(VLOOKUP(基本信息!$I3,各地政策!$A:$X,23,0)=0,0.5,IF(VLOOKUP(基本信息!$I3,各地政策!$A:$X,23,0)=1,0.05,0.005)),VLOOKUP(基本信息!$I3,各地政策!$A:$X,23,0)))) -> #N/A | AD3: =IF(VLOOKUP(基本信息!$I3,各地政策!$A:$X,24,0)="进位",ROUNDUP(基本信息!AM3*基本信息!AR3,VLOOKUP(基本信息!$I3,各地政策!$A:$X,23,0)),IF(VLOOKUP(基本信息!$I3,各地政策!$A:$X,24,0)="四舍五入",ROUND(基本信息!AM3*基本信息!AR3,VLOOKUP(基本信息!$I3,各地政策!$A:$X,23,0)),ROUND(基本信息!AM3*基本信息!AR3-IF(VLOOKUP(基本信息!$I3,各地政策!$A:$X,23,0)=0,0.5,IF(VLOOKUP(基本信息!$I3,各地政策!$A:$X,23,0)=1,0.05,0.005)),VLOOKUP(基本信息!$I3,各地政策!$A:$X,23,0)))) -> #N/A | AE3: =基本信息!DU3+基本信息!DV3+基本信息!DW3 -> 0 | AF3: =基本信息!DX3 -> 0 | AG3: =基本信息!BF3 -> 0 | AH3: =基本信息!BG3 -> 0 | AI3: =基本信息!BH3+基本信息!DZ3 -> 0 | AJ3: =IF(基本信息!P3="税前",SUM(C3:J3)+SUM(O3:W3)-SUM(K3:N3)-SUM(X3:X3)+Y3-AG3-AH3+AI3,0) -> 0 | AK3: =IF(基本信息!J3=3,MAX(AJ3*0.2,800),5000) -> 5000 | AL3: =IF(基本信息!P3="税前",SUMIF(YTD!$A$2:$A$2386,$A3,YTD!$BB$2:$BB$2386)+SUMIF(YTD!$A$2:$A$2386,$A3,YTD!$AM$2:$AM$2386)+AJ3,0) -> 0 | AM3: =SUMIF(YTD!$A$2:$A$2386,$A3,YTD!$AM$2:$AM$2386)+SUM(Z3:AF3) -> #N/A | AN3: =SUMIF(YTD!$A$2:$A$2386,$A3,YTD!$AN$2:$AN$2386)+计算结果!AK3 -> 5000 | AO3: =基本信息!CO3 -> 0 | AP3: =基本信息!CP3 -> 0 | AQ3: =基本信息!CQ3 -> 0 | AR3: =基本信息!CR3 -> 0 | AS3: =基本信息!CS3 -> 0 | AT3: {=SUMPRODUCT((基本信息!$B$2:$B$2375=$A3)*(基本信息!$CU$2:$CV$2375))+SUMIF(YTD!$A$2:$A$2386,$A3,YTD!$AT$2:$AT$2386)} -> 0 | AU3: =SUM(AN3:AT3,CE3) -> 5000 | AV3: =IF(基本信息!P3="税前",AL3-AM3-AU3,0) -> 0 | AW3: {=IF(基本信息!J3=1,MAX((AV3)*{0.03,0.1,0.2,0.25,0.3,0.35,0.45}-12*{0,210,1410,2660,4410,7160,15160},0),IF(基本信息!J3=4,MAX((AL3-AL3*0.2-AU3)*{0.03,0.1,0.2,0.25,0.3,0.35,0.45}-12*{0,210,1410,2660,4410,7160,15160},0),0))} -> 0 | AX3: {=MAX(ROUND(IF(基本信息!J3=3,MAX((AJ3-IF(AJ3<4000,800,AJ3*0.2))*10%*{2,3,4}-1000*{0,2,7},0),IF(基本信息!J3=2,MAX((AJ3-SUM(Z3:AG3)-AK3)*{0.03,0.1,0.2,0.25,0.3,0.35,0.45}-{0,210,1410,2660,4410,7160,15160},0),IF(基本信息!P3="税前",AW3-ROUND(SUMIF(YTD!$A$2:$A$2386,$A3,YTD!$CD$2:$CD$2386),2),0))),2),0)} -> 0 | AY3: =基本信息!BI3+基本信息!EA3 -> 0 | AZ3: =IF(基本信息!P3="税前",0,SUM(C3:J3)-SUM(K3:N3)+SUM(O3:W3)-X3+Y3+AI3)+AY3 -> 0 | BA3: =IF(OR(基本信息!J3=1,基本信息!J3=4),IF(基本信息!P3="税前",AL3-AM3-AW3+AZ3,AZ3+SUMIF(YTD!$A$2:$A$2386,$A3,YTD!$BA$2:$BA$2386)),IF(基本信息!P3="税前",AJ3-SUM(Z3:AG3)-AX3+AZ3+SUMIF(YTD!$A$2:$A$2386,$A3,YTD!$BA$2:$BA$2386),AZ3)) -> 0 | BB3: {=IF(基本信息!J3=3,LOOKUP(AJ3-AX3+AZ3,{0,800,3360,21000,49500},(AJ3-AX3+AZ3-{0,160,0,2000,7000})*{1,5,25,25,25}/{1,4,21,19,17}),IF(基本信息!J3=2,MAX((BA3-AK3-10*{0,21,141,266,441,716,1516})/(1-5%*{0.6,2,4,5,6,7,9})+AK3,BA3),IF(基本信息!J3=4,MAX((BA3-AU3-(AL3*0.2)-120*{0,21,141,266,441,716,1516})/(1-5%*{0.6,2,4,5,6,7,9})+AU3+(AL3*0.2),BA3),MAX((BA3-AU3-120*{0,21,141,266,441,716,1516})/(1-5%*{0.6,2,4,5,6,7,9})+AU3,BA3))))} -> 0 | BC3: =IF(OR(基本信息!J3=1,基本信息!J3=4),BB3-IFERROR(VLOOKUP($A3,YTD!$A:$BB,54,0),0),BB3)+SUM(Z3:AF3) -> #N/A | BD3: {=IF(基本信息!J3=4,MAX((BB3-BB3*0.2-AU3)*{0.03,0.1,0.2,0.25,0.3,0.35,0.45}-12*{0,210,1410,2660,4410,7160,15160},0),IF(基本信息!J3=3,MAX((BB3-IF(BB3<4000,800,BB3*0.2))*10%*{2,3,4}-1000*{0,2,7},0),IF(基本信息!J3=2,MAX((BB3-AK3)*{0.03,0.1,0.2,0.25,0.3,0.35,0.45}-{0,210,1410,2660,4410,7160,15160},0),MAX((BB3-AU3)*{0.03,0.1,0.2,0.25,0.3,0.35,0.45}-12*{0,210,1410,2660,4410,7160,15160},0))))} -> 0 | BE3: =MAX(ROUND(IF(基本信息!J3=1,BD3-AX3-ROUND(SUMIF(YTD!$A$2:$A$2386,$A3,YTD!$CD$2:$CD$2386),2),IF(基本信息!J3=4,BD3-AX3-ROUND(SUMIF(YTD!$A$2:$A$2386,$A3,YTD!$CD$2:$CD$2386),2),BD3-AX3)),2),0) -> 0 | BF3: =IF(YEARFRAC(基本信息!AB3,TODAY())*12-1<192,基本信息!AC3,0) -> 0 | BG3: =IF(VLOOKUP(基本信息!$I3,各地政策!$A:$X,24,0)="进位",ROUNDUP(基本信息!AM3*基本信息!AS3,VLOOKUP(基本信息!$I3,各地政策!$A:$X,23,0)),IF(VLOOKUP(基本信息!$I3,各地政策!$A:$X,24,0)="四舍五入",ROUND(基本信息!AM3*基本信息!AS3,VLOOKUP(基本信息!$I3,各地政策!$A:$X,23,0)),ROUND(基本信息!AM3*基本信息!AS3-IF(VLOOKUP(基本信息!$I3,各地政策!$A:$X,23,0)=0,0.5,IF(VLOOKUP(基本信息!$I3,各地政策!$A:$X,23,0)=1,0.05,0.005)),VLOOKUP(基本信息!$I3,各地政策!$A:$X,23,0)))) -> #N/A | BH3: =基本信息!EB3 -> 0 | BI3: =基本信息!EC3 -> 0 | BJ3: =基本信息!BJ3 -> 0 | BK3: =基本信息!BL3+基本信息!DY3+基本信息!ED3 -> 0 | BL3: =基本信息!BK3+基本信息!EE3 -> 0 | BM3: =基本信息!EG3 -> 0 | BN3: {=IF(基本信息!J3=2,MAX((BM3/6)*{0.03,0.1,0.2,0.25,0.3,0.35,0.45}-{0,210,1410,2660,4410,7160,15160},0)*6,ROUND((BM3)*LOOKUP(-(BM3)/12,-{99999,80,55,35,25,12,3,0,-9}*1000,{9,7,6,5,4,2,0.6,0,0}*5%)-LOOKUP(-(BM3)/12,-{99999,80,55,35,25,12,3,0,-9}*1000,{1516,716,441,266,141,21,0,0}*10),2))} -> 0 | BO3: =基本信息!EH3 -> 0 | BP3: {=IFERROR(ROUND(MAX((基本信息!EH3-基本信息!EI3)*{0.03,0.1,0.2,0.25,0.3,0.35,0.45}-12*{0,210,1410,2660,4410,7160,15160},0),2),0)} -> 0 | BQ3: =基本信息!EK3 -> 0 | BR3: {=ROUND((BQ3)*LOOKUP(-BQ3,-{99999,96,66,42,30,14.4,3.6,0,-9}*10000,{9,7,6,5,4,2,0.6,0,0}*5%)-LOOKUP(-BQ3,-{99999,96,66,42,30,14.4,3.6,0,-9}*10000,{18192,8592,5292,3192,1692,252,0,0}*10),2)} -> 0 | BS3: =SUM(C3:J3)+SUM(O3:W3)+Y3+AY3+BF3+BK3+BM3+BO3+BH3+BJ3+BI3+BQ3 -> 0 | BT3: =IF(基本信息!P3="税前",SUM(K3:N3)+SUM(X3,Z3:AH3)+AX3+BG3+BL3+BN3+BP3+BR3,SUM(K3:N3,X3,BL3,BN3,BP3,BR3)) -> 0 | BU3: =ROUND(BS3-BT3,2) -> 0 | BV3: =IF(VLOOKUP(基本信息!$H3,各地政策!$A:$X,21,0)="进位",ROUNDUP(基本信息!AF3*基本信息!AU3,VLOOKUP(基本信息!$H3,各地政策!$A:$X,20,0)),IF(VLOOKUP(基本信息!$H3,各地政策!$A:$X,21,0)="四舍五入",ROUND(基本信息!AF3*基本信息!AU3,VLOOKUP(基本信息!$H3,各地政策!$A:$X,20,0)),ROUND(基本信息!AF3*基本信息!AU3-IF(VLOOKUP(基本信息!$H3,各地政策!$A:$X,20,0)=0,0.5,IF(VLOOKUP(基本信息!$H3,各地政策!$A:$X,20,0)=1,0.05,0.005)),VLOOKUP(基本信息!$H3,各地政策!$A:$X,20,0)))) -> #N/A | BW3: =IF(VLOOKUP(基本信息!$H3,各地政策!$A:$X,21,0)="进位",ROUNDUP(基本信息!AG3*基本信息!AV3,VLOOKUP(基本信息!$H3,各地政策!$A:$X,20,0)),IF(VLOOKUP(基本信息!$H3,各地政策!$A:$X,21,0)="四舍五入",ROUND(基本信息!AG3*基本信息!AV3,VLOOKUP(基本信息!$H3,各地政策!$A:$X,20,0)),ROUND(基本信息!AG3*基本信息!AV3-IF(VLOOKUP(基本信息!$H3,各地政策!$A:$X,20,0)=0,0.5,IF(VLOOKUP(基本信息!$H3,各地政策!$A:$X,20,0)=1,0.05,0.005)),VLOOKUP(基本信息!$H3,各地政策!$A:$X,20,0))))+基本信息!BC3 -> #N/A | BX3: =IF(VLOOKUP(基本信息!$H3,各地政策!$A:$X,21,0)="进位",ROUNDUP(基本信息!AH3*基本信息!AW3,VLOOKUP(基本信息!$H3,各地政策!$A:$X,20,0)),IF(VLOOKUP(基本信息!$H3,各地政策!$A:$X,21,0)="四舍五入",ROUND(基本信息!AH3*基本信息!AW3,VLOOKUP(基本信息!$H3,各地政策!$A:$X,20,0)),ROUND(基本信息!AH3*基本信息!AW3-IF(VLOOKUP(基本信息!$H3,各地政策!$A:$X,20,0)=0,0.5,IF(VLOOKUP(基本信息!$H3,各地政策!$A:$X,20,0)=1,0.05,0.005)),VLOOKUP(基本信息!$H3,各地政策!$A:$X,20,0)))) -> #N/A | BY3: =IF(VLOOKUP(基本信息!$H3,各地政策!$A:$X,21,0)="进位",ROUNDUP(基本信息!AI3*基本信息!AX3,VLOOKUP(基本信息!$H3,各地政策!$A:$X,20,0)),IF(VLOOKUP(基本信息!$H3,各地政策!$A:$X,21,0)="四舍五入",ROUND(基本信息!AI3*基本信息!AX3,VLOOKUP(基本信息!$H3,各地政策!$A:$X,20,0)),ROUND(基本信息!AI3*基本信息!AX3-IF(VLOOKUP(基本信息!$H3,各地政策!$A:$X,20,0)=0,0.5,IF(VLOOKUP(基本信息!$H3,各地政策!$A:$X,20,0)=1,0.05,0.005)),VLOOKUP(基本信息!$H3,各地政策!$A:$X,20,0)))) -> #N/A | BZ3: =IF(VLOOKUP(基本信息!$H3,各地政策!$A:$X,21,0)="进位",ROUNDUP(基本信息!AJ3*基本信息!AY3,VLOOKUP(基本信息!$H3,各地政策!$A:$X,20,0)),IF(VLOOKUP(基本信息!$H3,各地政策!$A:$X,21,0)="四舍五入",ROUND(基本信息!AJ3*基本信息!AY3,VLOOKUP(基本信息!$H3,各地政策!$A:$X,20,0)),ROUND(基本信息!AJ3*基本信息!AY3-IF(VLOOKUP(基本信息!$H3,各地政策!$A:$X,20,0)=0,0.5,IF(VLOOKUP(基本信息!$H3,各地政策!$A:$X,20,0)=1,0.05,0.005)),VLOOKUP(基本信息!$H3,各地政策!$A:$X,20,0))))+基本信息!BD3 -> #N/A | CA3: =IF(VLOOKUP(基本信息!$H3,各地政策!$A:$X,21,0)="进位",ROUNDUP(基本信息!AK3*基本信息!AZ3+基本信息!BE3,VLOOKUP(基本信息!$H3,各地政策!$A:$X,20,0)),IF(VLOOKUP(基本信息!$H3,各地政策!$A:$X,21,0)="四舍五入",ROUND(基本信息!AK3*基本信息!AZ3+基本信息!BE3,VLOOKUP(基本信息!$H3,各地政策!$A:$X,20,0)),ROUND(基本信息!AK3*基本信息!AZ3+基本信息!BE3-IF(VLOOKUP(基本信息!$H3,各地政策!$A:$X,20,0)=0,0.5,IF(VLOOKUP(基本信息!$H3,各地政策!$A:$X,20,0)=1,0.05,0.005)),VLOOKUP(基本信息!$H3,各地政策!$A:$X,20,0)))) -> #N/A | CB3: =IF(VLOOKUP(基本信息!$I3,各地政策!$A:$X,24,0)="进位",ROUNDUP(基本信息!AL3*(基本信息!BA3),VLOOKUP(基本信息!$I3,各地政策!$A:$X,23,0)),IF(VLOOKUP(基本信息!$I3,各地政策!$A:$X,24,0)="四舍五入",ROUND(基本信息!AL3*(基本信息!BA3),VLOOKUP(基本信息!$I3,各地政策!$A:$X,23,0)),ROUND(基本信息!AL3*(基本信息!BA3)-IF(VLOOKUP(基本信息!$I3,各地政策!$A:$X,23,0)=0,0.5,IF(VLOOKUP(基本信息!$I3,各地政策!$A:$X,23,0)=1,0.05,0.005)),VLOOKUP(基本信息!$I3,各地政策!$A:$X,23,0)))) -> #N/A | CC3: =IF(VLOOKUP(基本信息!$I3,各地政策!$A:$X,24,0)="进位",ROUNDUP(基本信息!AM3*(基本信息!BB3),VLOOKUP(基本信息!$I3,各地政策!$A:$X,23,0)),IF(VLOOKUP(基本信息!$I3,各地政策!$A:$X,24,0)="四舍五入",ROUND(基本信息!AM3*(基本信息!BB3),VLOOKUP(基本信息!$I3,各地政策!$A:$X,23,0)),ROUND(基本信息!AM3*(基本信息!BB3)-IF(VLOOKUP(基本信息!$I3,各地政策!$A:$X,23,0)=0,0.5,IF(VLOOKUP(基本信息!$I3,各地政策!$A:$X,23,0)=1,0.05,0.005)),VLOOKUP(基本信息!$I3,各地政策!$A:$X,23,0)))) -> #N/A | CD3: =AX3+BE3+IFERROR(VLOOKUP($A3,YTD!$A:$CD,82,0),0) -> 0 | CE3: =基本信息!CT3 -> 0 | CF3: ='S-Payroll Report'!X9 -> 0 | CG3: ='S-Payroll Report'!AD9 -> 0 | CH3: ='S-Payroll Report'!AC9 -> 0 | CI3: ='S-Payroll Report'!AA9 -> 0 | CJ3: ='S-Payroll Report'!AF9 -> 0 | CK3: =基本信息!EM3+基本信息!EN3+基本信息!EO3 -> 0
A4: =IF(基本信息!B4="","",基本信息!B4) | B4: =IF(基本信息!C4="","",基本信息!C4) | C4: =基本信息!Q4+基本信息!R4*基本信息!CW4 -> 0 | D4: =基本信息!S4 -> 0 | E4: =基本信息!CX4 -> 0 | F4: =基本信息!CY4 -> 0 | G4: =基本信息!CZ4 -> 0 | H4: =ROUND(C4*基本信息!DA4*1.5/(21.75*8),2) -> 0 | I4: =ROUND(C4*基本信息!DB4*2/(21.75*8),2) -> 0 | J4: =ROUND(C4*基本信息!DC4*3/(21.75*8),2) -> 0 | K4: =ROUND(IF(AND(基本信息!DD4=23,基本信息!DE4=12),((C4+D4)*12/21.75+(C4+D4)-(C4+D4)*11/21.75)/2,IF(基本信息!DE4>基本信息!DD4/2,(C4+D4)-(C4+D4)*(基本信息!DD4-基本信息!DE4)/21.75,(C4+D4)*基本信息!DE4/21.75)),2) -> 0 | L4: =MAX(0,ROUND((C4+D4)*基本信息!DF4/21.75,2)) -> 0 | M4: =MAX(0,ROUND((C4+D4)*基本信息!DG4/21.75,2)) -> 0 | N4: =基本信息!DI4 -> 0 | O4: =基本信息!T4+基本信息!DJ4 -> 0 | P4: =基本信息!U4+基本信息!DK4 -> 0 | Q4: =基本信息!V4 -> 0 | R4: =基本信息!W4*基本信息!DL4 -> 0 | S4: =基本信息!X4*基本信息!DM4 -> 0 | T4: =基本信息!Y4*基本信息!DN4+基本信息!DO4 -> 0 | U4: =基本信息!Z4*基本信息!DP4 -> 0 | V4: =基本信息!AA4*基本信息!DQ4 -> 0 | W4: =基本信息!AD4+基本信息!DR4 -> 0 | X4: =基本信息!AE4+基本信息!DS4 -> 0 | Y4: =基本信息!DT4 -> 0 | Z4: =IF(VLOOKUP(基本信息!$H4,各地政策!$A:$X,21,0)="进位",ROUNDUP(基本信息!AF4*基本信息!AN4,VLOOKUP(基本信息!$H4,各地政策!$A:$X,20,0)),IF(VLOOKUP(基本信息!$H4,各地政策!$A:$X,21,0)="四舍五入",ROUND(基本信息!AF4*基本信息!AN4,VLOOKUP(基本信息!$H4,各地政策!$A:$X,20,0)),ROUND(基本信息!AF4*基本信息!AN4-IF(VLOOKUP(基本信息!$H4,各地政策!$A:$X,20,0)=0,0.5,IF(VLOOKUP(基本信息!$H4,各地政策!$A:$X,20,0)=1,0.05,0.005)),VLOOKUP(基本信息!$H4,各地政策!$A:$X,20,0)))) -> #N/A | AA4: =IF(VLOOKUP(基本信息!$H4,各地政策!$A:$X,21,0)="进位",ROUNDUP(基本信息!AG4*基本信息!AO4,VLOOKUP(基本信息!$H4,各地政策!$A:$X,20,0)),IF(VLOOKUP(基本信息!$H4,各地政策!$A:$X,21,0)="四舍五入",ROUND(基本信息!AG4*基本信息!AO4,VLOOKUP(基本信息!$H4,各地政策!$A:$X,20,0)),ROUND(基本信息!AG4*基本信息!AO4-IF(VLOOKUP(基本信息!$H4,各地政策!$A:$X,20,0)=0,0.5,IF(VLOOKUP(基本信息!$H4,各地政策!$A:$X,20,0)=1,0.05,0.005)),VLOOKUP(基本信息!$H4,各地政策!$A:$X,20,0))))+基本信息!AT4 -> #N/A | AB4: =IF(VLOOKUP(基本信息!$H4,各地政策!$A:$X,21,0)="进位",ROUNDUP(基本信息!AH4*基本信息!AP4,VLOOKUP(基本信息!$H4,各地政策!$A:$X,20,0)),IF(VLOOKUP(基本信息!$H4,各地政策!$A:$X,21,0)="四舍五入",ROUND(基本信息!AH4*基本信息!AP4,VLOOKUP(基本信息!$H4,各地政策!$A:$X,20,0)),ROUND(基本信息!AH4*基本信息!AP4-IF(VLOOKUP(基本信息!$H4,各地政策!$A:$X,20,0)=0,0.5,IF(VLOOKUP(基本信息!$H4,各地政策!$A:$X,20,0)=1,0.05,0.005)),VLOOKUP(基本信息!$H4,各地政策!$A:$X,20,0)))) -> #N/A | AC4: =IF(VLOOKUP(基本信息!$I4,各地政策!$A:$X,24,0)="进位",ROUNDUP(基本信息!AL4*基本信息!AQ4,VLOOKUP(基本信息!$I4,各地政策!$A:$X,23,0)),IF(VLOOKUP(基本信息!$I4,各地政策!$A:$X,24,0)="四舍五入",ROUND(基本信息!AL4*基本信息!AQ4,VLOOKUP(基本信息!$I4,各地政策!$A:$X,23,0)),ROUND(基本信息!AL4*基本信息!AQ4-IF(VLOOKUP(基本信息!$I4,各地政策!$A:$X,23,0)=0,0.5,IF(VLOOKUP(基本信息!$I4,各地政策!$A:$X,23,0)=1,0.05,0.005)),VLOOKUP(基本信息!$I4,各地政策!$A:$X,23,0)))) -> #N/A | AD4: =IF(VLOOKUP(基本信息!$I4,各地政策!$A:$X,24,0)="进位",ROUNDUP(基本信息!AM4*基本信息!AR4,VLOOKUP(基本信息!$I4,各地政策!$A:$X,23,0)),IF(VLOOKUP(基本信息!$I4,各地政策!$A:$X,24,0)="四舍五入",ROUND(基本信息!AM4*基本信息!AR4,VLOOKUP(基本信息!$I4,各地政策!$A:$X,23,0)),ROUND(基本信息!AM4*基本信息!AR4-IF(VLOOKUP(基本信息!$I4,各地政策!$A:$X,23,0)=0,0.5,IF(VLOOKUP(基本信息!$I4,各地政策!$A:$X,23,0)=1,0.05,0.005)),VLOOKUP(基本信息!$I4,各地政策!$A:$X,23,0)))) -> #N/A | AE4: =基本信息!DU4+基本信息!DV4+基本信息!DW4 -> 0 | AF4: =基本信息!DX4 -> 0 | AG4: =基本信息!BF4 -> 0 | AH4: =基本信息!BG4 -> 0 | AI4: =基本信息!BH4+基本信息!DZ4 -> 0 | AJ4: =IF(基本信息!P4="税前",SUM(C4:J4)+SUM(O4:W4)-SUM(K4:N4)-SUM(X4:X4)+Y4-AG4-AH4+AI4,0) -> 0 | AK4: =IF(基本信息!J4=3,MAX(AJ4*0.2,800),5000) -> 5000 | AL4: =IF(基本信息!P4="税前",SUMIF(YTD!$A$2:$A$2386,$A4,YTD!$BB$2:$BB$2386)+SUMIF(YTD!$A$2:$A$2386,$A4,YTD!$AM$2:$AM$2386)+AJ4,0) -> 0 | AM4: =SUMIF(YTD!$A$2:$A$2386,$A4,YTD!$AM$2:$AM$2386)+SUM(Z4:AF4) -> #N/A | AN4: =SUMIF(YTD!$A$2:$A$2386,$A4,YTD!$AN$2:$AN$2386)+计算结果!AK4 -> 5000 | AO4: =基本信息!CO4 -> 0 | AP4: =基本信息!CP4 -> 0 | AQ4: =基本信息!CQ4 -> 0 | AR4: =基本信息!CR4 -> 0 | AS4: =基本信息!CS4 -> 0 | AT4: {=SUMPRODUCT((基本信息!$B$2:$B$2375=$A4)*(基本信息!$CU$2:$CV$2375))+SUMIF(YTD!$A$2:$A$2386,$A4,YTD!$AT$2:$AT$2386)} -> 0 | AU4: =SUM(AN4:AT4,CE4) -> 5000 | AV4: =IF(基本信息!P4="税前",AL4-AM4-AU4,0) -> 0 | AW4: {=IF(基本信息!J4=1,MAX((AV4)*{0.03,0.1,0.2,0.25,0.3,0.35,0.45}-12*{0,210,1410,2660,4410,7160,15160},0),IF(基本信息!J4=4,MAX((AL4-AL4*0.2-AU4)*{0.03,0.1,0.2,0.25,0.3,0.35,0.45}-12*{0,210,1410,2660,4410,7160,15160},0),0))} -> 0 | AX4: {=MAX(ROUND(IF(基本信息!J4=3,MAX((AJ4-IF(AJ4<4000,800,AJ4*0.2))*10%*{2,3,4}-1000*{0,2,7},0),IF(基本信息!J4=2,MAX((AJ4-SUM(Z4:AG4)-AK4)*{0.03,0.1,0.2,0.25,0.3,0.35,0.45}-{0,210,1410,2660,4410,7160,15160},0),IF(基本信息!P4="税前",AW4-ROUND(SUMIF(YTD!$A$2:$A$2386,$A4,YTD!$CD$2:$CD$2386),2),0))),2),0)} -> 0 | AY4: =基本信息!BI4+基本信息!EA4 -> 0 | AZ4: =IF(基本信息!P4="税前",0,SUM(C4:J4)-SUM(K4:N4)+SUM(O4:W4)-X4+Y4+AI4)+AY4 -> 0 | BA4: =IF(OR(基本信息!J4=1,基本信息!J4=4),IF(基本信息!P4="税前",AL4-AM4-AW4+AZ4,AZ4+SUMIF(YTD!$A$2:$A$2386,$A4,YTD!$BA$2:$BA$2386)),IF(基本信息!P4="税前",AJ4-SUM(Z4:AG4)-AX4+AZ4+SUMIF(YTD!$A$2:$A$2386,$A4,YTD!$BA$2:$BA$2386),AZ4)) -> 0 | BB4: {=IF(基本信息!J4=3,LOOKUP(AJ4-AX4+AZ4,{0,800,3360,21000,49500},(AJ4-AX4+AZ4-{0,160,0,2000,7000})*{1,5,25,25,25}/{1,4,21,19,17}),IF(基本信息!J4=2,MAX((BA4-AK4-10*{0,21,141,266,441,716,1516})/(1-5%*{0.6,2,4,5,6,7,9})+AK4,BA4),IF(基本信息!J4=4,MAX((BA4-AU4-(AL4*0.2)-120*{0,21,141,266,441,716,1516})/(1-5%*{0.6,2,4,5,6,7,9})+AU4+(AL4*0.2),BA4),MAX((BA4-AU4-120*{0,21,141,266,441,716,1516})/(1-5%*{0.6,2,4,5,6,7,9})+AU4,BA4))))} -> 0 | BC4: =IF(OR(基本信息!J4=1,基本信息!J4=4),BB4-IFERROR(VLOOKUP($A4,YTD!$A:$BB,54,0),0),BB4)+SUM(Z4:AF4) -> #N/A | BD4: {=IF(基本信息!J4=4,MAX((BB4-BB4*0.2-AU4)*{0.03,0.1,0.2,0.25,0.3,0.35,0.45}-12*{0,210,1410,2660,4410,7160,15160},0),IF(基本信息!J4=3,MAX((BB4-IF(BB4<4000,800,BB4*0.2))*10%*{2,3,4}-1000*{0,2,7},0),IF(基本信息!J4=2,MAX((BB4-AK4)*{0.03,0.1,0.2,0.25,0.3,0.35,0.45}-{0,210,1410,2660,4410,7160,15160},0),MAX((BB4-AU4)*{0.03,0.1,0.2,0.25,0.3,0.35,0.45}-12*{0,210,1410,2660,4410,7160,15160},0))))} -> 0 | BE4: =MAX(ROUND(IF(基本信息!J4=1,BD4-AX4-ROUND(SUMIF(YTD!$A$2:$A$2386,$A4,YTD!$CD$2:$CD$2386),2),IF(基本信息!J4=4,BD4-AX4-ROUND(SUMIF(YTD!$A$2:$A$2386,$A4,YTD!$CD$2:$CD$2386),2),BD4-AX4)),2),0) -> 0 | BF4: =IF(YEARFRAC(基本信息!AB4,TODAY())*12-1<192,基本信息!AC4,0) -> 0 | BG4: =IF(VLOOKUP(基本信息!$I4,各地政策!$A:$X,24,0)="进位",ROUNDUP(基本信息!AM4*基本信息!AS4,VLOOKUP(基本信息!$I4,各地政策!$A:$X,23,0)),IF(VLOOKUP(基本信息!$I4,各地政策!$A:$X,24,0)="四舍五入",ROUND(基本信息!AM4*基本信息!AS4,VLOOKUP(基本信息!$I4,各地政策!$A:$X,23,0)),ROUND(基本信息!AM4*基本信息!AS4-IF(VLOOKUP(基本信息!$I4,各地政策!$A:$X,23,0)=0,0.5,IF(VLOOKUP(基本信息!$I4,各地政策!$A:$X,23,0)=1,0.05,0.005)),VLOOKUP(基本信息!$I4,各地政策!$A:$X,23,0)))) -> #N/A | BH4: =基本信息!EB4 -> 0 | BI4: =基本信息!EC4 -> 0 | BJ4: =基本信息!BJ4 -> 0 | BK4: =基本信息!BL4+基本信息!DY4+基本信息!ED4 -> 0 | BL4: =基本信息!BK4+基本信息!EE4 -> 0 | BM4: =基本信息!EG4 -> 0 | BN4: {=IF(基本信息!J4=2,MAX((BM4/6)*{0.03,0.1,0.2,0.25,0.3,0.35,0.45}-{0,210,1410,2660,4410,7160,15160},0)*6,ROUND((BM4)*LOOKUP(-(BM4)/12,-{99999,80,55,35,25,12,3,0,-9}*1000,{9,7,6,5,4,2,0.6,0,0}*5%)-LOOKUP(-(BM4)/12,-{99999,80,55,35,25,12,3,0,-9}*1000,{1516,716,441,266,141,21,0,0}*10),2))} -> 0 | BO4: =基本信息!EH4 -> 0 | BP4: {=IFERROR(ROUND(MAX((基本信息!EH4-基本信息!EI4)*{0.03,0.1,0.2,0.25,0.3,0.35,0.45}-12*{0,210,1410,2660,4410,7160,15160},0),2),0)} -> 0 | BQ4: =基本信息!EK4 -> 0 | BR4: {=ROUND((BQ4)*LOOKUP(-BQ4,-{99999,96,66,42,30,14.4,3.6,0,-9}*10000,{9,7,6,5,4,2,0.6,0,0}*5%)-LOOKUP(-BQ4,-{99999,96,66,42,30,14.4,3.6,0,-9}*10000,{18192,8592,5292,3192,1692,252,0,0}*10),2)} -> 0 | BS4: =SUM(C4:J4)+SUM(O4:W4)+Y4+AY4+BF4+BK4+BM4+BO4+BH4+BJ4+BI4+BQ4 -> 0 | BT4: =IF(基本信息!P4="税前",SUM(K4:N4)+SUM(X4,Z4:AH4)+AX4+BG4+BL4+BN4+BP4+BR4,SUM(K4:N4,X4,BL4,BN4,BP4,BR4)) -> 0 | BU4: =ROUND(BS4-BT4,2) -> 0 | BV4: =IF(VLOOKUP(基本信息!$H4,各地政策!$A:$X,21,0)="进位",ROUNDUP(基本信息!AF4*基本信息!AU4,VLOOKUP(基本信息!$H4,各地政策!$A:$X,20,0)),IF(VLOOKUP(基本信息!$H4,各地政策!$A:$X,21,0)="四舍五入",ROUND(基本信息!AF4*基本信息!AU4,VLOOKUP(基本信息!$H4,各地政策!$A:$X,20,0)),ROUND(基本信息!AF4*基本信息!AU4-IF(VLOOKUP(基本信息!$H4,各地政策!$A:$X,20,0)=0,0.5,IF(VLOOKUP(基本信息!$H4,各地政策!$A:$X,20,0)=1,0.05,0.005)),VLOOKUP(基本信息!$H4,各地政策!$A:$X,20,0)))) -> #N/A | BW4: =IF(VLOOKUP(基本信息!$H4,各地政策!$A:$X,21,0)="进位",ROUNDUP(基本信息!AG4*基本信息!AV4,VLOOKUP(基本信息!$H4,各地政策!$A:$X,20,0)),IF(VLOOKUP(基本信息!$H4,各地政策!$A:$X,21,0)="四舍五入",ROUND(基本信息!AG4*基本信息!AV4,VLOOKUP(基本信息!$H4,各地政策!$A:$X,20,0)),ROUND(基本信息!AG4*基本信息!AV4-IF(VLOOKUP(基本信息!$H4,各地政策!$A:$X,20,0)=0,0.5,IF(VLOOKUP(基本信息!$H4,各地政策!$A:$X,20,0)=1,0.05,0.005)),VLOOKUP(基本信息!$H4,各地政策!$A:$X,20,0))))+基本信息!BC4 -> #N/A | BX4: =IF(VLOOKUP(基本信息!$H4,各地政策!$A:$X,21,0)="进位",ROUNDUP(基本信息!AH4*基本信息!AW4,VLOOKUP(基本信息!$H4,各地政策!$A:$X,20,0)),IF(VLOOKUP(基本信息!$H4,各地政策!$A:$X,21,0)="四舍五入",ROUND(基本信息!AH4*基本信息!AW4,VLOOKUP(基本信息!$H4,各地政策!$A:$X,20,0)),ROUND(基本信息!AH4*基本信息!AW4-IF(VLOOKUP(基本信息!$H4,各地政策!$A:$X,20,0)=0,0.5,IF(VLOOKUP(基本信息!$H4,各地政策!$A:$X,20,0)=1,0.05,0.005)),VLOOKUP(基本信息!$H4,各地政策!$A:$X,20,0)))) -> #N/A | BY4: =IF(VLOOKUP(基本信息!$H4,各地政策!$A:$X,21,0)="进位",ROUNDUP(基本信息!AI4*基本信息!AX4,VLOOKUP(基本信息!$H4,各地政策!$A:$X,20,0)),IF(VLOOKUP(基本信息!$H4,各地政策!$A:$X,21,0)="四舍五入",ROUND(基本信息!AI4*基本信息!AX4,VLOOKUP(基本信息!$H4,各地政策!$A:$X,20,0)),ROUND(基本信息!AI4*基本信息!AX4-IF(VLOOKUP(基本信息!$H4,各地政策!$A:$X,20,0)=0,0.5,IF(VLOOKUP(基本信息!$H4,各地政策!$A:$X,20,0)=1,0.05,0.005)),VLOOKUP(基本信息!$H4,各地政策!$A:$X,20,0)))) -> #N/A | BZ4: =IF(VLOOKUP(基本信息!$H4,各地政策!$A:$X,21,0)="进位",ROUNDUP(基本信息!AJ4*基本信息!AY4,VLOOKUP(基本信息!$H4,各地政策!$A:$X,20,0)),IF(VLOOKUP(基本信息!$H4,各地政策!$A:$X,21,0)="四舍五入",ROUND(基本信息!AJ4*基本信息!AY4,VLOOKUP(基本信息!$H4,各地政策!$A:$X,20,0)),ROUND(基本信息!AJ4*基本信息!AY4-IF(VLOOKUP(基本信息!$H4,各地政策!$A:$X,20,0)=0,0.5,IF(VLOOKUP(基本信息!$H4,各地政策!$A:$X,20,0)=1,0.05,0.005)),VLOOKUP(基本信息!$H4,各地政策!$A:$X,20,0))))+基本信息!BD4 -> #N/A | CA4: =IF(VLOOKUP(基本信息!$H4,各地政策!$A:$X,21,0)="进位",ROUNDUP(基本信息!AK4*基本信息!AZ4+基本信息!BE4,VLOOKUP(基本信息!$H4,各地政策!$A:$X,20,0)),IF(VLOOKUP(基本信息!$H4,各地政策!$A:$X,21,0)="四舍五入",ROUND(基本信息!AK4*基本信息!AZ4+基本信息!BE4,VLOOKUP(基本信息!$H4,各地政策!$A:$X,20,0)),ROUND(基本信息!AK4*基本信息!AZ4+基本信息!BE4-IF(VLOOKUP(基本信息!$H4,各地政策!$A:$X,20,0)=0,0.5,IF(VLOOKUP(基本信息!$H4,各地政策!$A:$X,20,0)=1,0.05,0.005)),VLOOKUP(基本信息!$H4,各地政策!$A:$X,20,0)))) -> #N/A | CB4: =IF(VLOOKUP(基本信息!$I4,各地政策!$A:$X,24,0)="进位",ROUNDUP(基本信息!AL4*(基本信息!BA4),VLOOKUP(基本信息!$I4,各地政策!$A:$X,23,0)),IF(VLOOKUP(基本信息!$I4,各地政策!$A:$X,24,0)="四舍五入",ROUND(基本信息!AL4*(基本信息!BA4),VLOOKUP(基本信息!$I4,各地政策!$A:$X,23,0)),ROUND(基本信息!AL4*(基本信息!BA4)-IF(VLOOKUP(基本信息!$I4,各地政策!$A:$X,23,0)=0,0.5,IF(VLOOKUP(基本信息!$I4,各地政策!$A:$X,23,0)=1,0.05,0.005)),VLOOKUP(基本信息!$I4,各地政策!$A:$X,23,0)))) -> #N/A | CC4: =IF(VLOOKUP(基本信息!$I4,各地政策!$A:$X,24,0)="进位",ROUNDUP(基本信息!AM4*(基本信息!BB4),VLOOKUP(基本信息!$I4,各地政策!$A:$X,23,0)),IF(VLOOKUP(基本信息!$I4,各地政策!$A:$X,24,0)="四舍五入",ROUND(基本信息!AM4*(基本信息!BB4),VLOOKUP(基本信息!$I4,各地政策!$A:$X,23,0)),ROUND(基本信息!AM4*(基本信息!BB4)-IF(VLOOKUP(基本信息!$I4,各地政策!$A:$X,23,0)=0,0.5,IF(VLOOKUP(基本信息!$I4,各地政策!$A:$X,23,0)=1,0.05,0.005)),VLOOKUP(基本信息!$I4,各地政策!$A:$X,23,0)))) -> #N/A | CD4: =AX4+BE4+IFERROR(VLOOKUP($A4,YTD!$A:$CD,82,0),0) -> 0 | CE4: =基本信息!CT4 -> 0 | CF4: ='S-Payroll Report'!X10 -> 0 | CG4: ='S-Payroll Report'!AD10 -> 0 | CH4: ='S-Payroll Report'!AC10 -> 0 | CI4: ='S-Payroll Report'!AA10 -> 0 | CJ4: ='S-Payroll Report'!AF10 -> 0 | CK4: =基本信息!EM4+基本信息!EN4+基本信息!EO4 -> 0
A5: =IF(基本信息!B5="","",基本信息!B5) | B5: =IF(基本信息!C5="","",基本信息!C5) | C5: =基本信息!Q5+基本信息!R5*基本信息!CW5 -> 0 | D5: =基本信息!S5 -> 0 | E5: =基本信息!CX5 -> 0 | F5: =基本信息!CY5 -> 0 | G5: =基本信息!CZ5 -> 0 | H5: =ROUND(C5*基本信息!DA5*1.5/(21.75*8),2) -> 0 | I5: =ROUND(C5*基本信息!DB5*2/(21.75*8),2) -> 0 | J5: =ROUND(C5*基本信息!DC5*3/(21.75*8),2) -> 0 | K5: =ROUND(IF(AND(基本信息!DD5=23,基本信息!DE5=12),((C5+D5)*12/21.75+(C5+D5)-(C5+D5)*11/21.75)/2,IF(基本信息!DE5>基本信息!DD5/2,(C5+D5)-(C5+D5)*(基本信息!DD5-基本信息!DE5)/21.75,(C5+D5)*基本信息!DE5/21.75)),2) -> 0 | L5: =MAX(0,ROUND((C5+D5)*基本信息!DF5/21.75,2)) -> 0 | M5: =MAX(0,ROUND((C5+D5)*基本信息!DG5/21.75,2)) -> 0 | N5: =基本信息!DI5 -> 0 | O5: =基本信息!T5+基本信息!DJ5 -> 0 | P5: =基本信息!U5+基本信息!DK5 -> 0 | Q5: =基本信息!V5 -> 0 | R5: =基本信息!W5*基本信息!DL5 -> 0 | S5: =基本信息!X5*基本信息!DM5 -> 0 | T5: =基本信息!Y5*基本信息!DN5+基本信息!DO5 -> 0 | U5: =基本信息!Z5*基本信息!DP5 -> 0 | V5: =基本信息!AA5*基本信息!DQ5 -> 0 | W5: =基本信息!AD5+基本信息!DR5 -> 0 | X5: =基本信息!AE5+基本信息!DS5 -> 0 | Y5: =基本信息!DT5 -> 0 | Z5: =IF(VLOOKUP(基本信息!$H5,各地政策!$A:$X,21,0)="进位",ROUNDUP(基本信息!AF5*基本信息!AN5,VLOOKUP(基本信息!$H5,各地政策!$A:$X,20,0)),IF(VLOOKUP(基本信息!$H5,各地政策!$A:$X,21,0)="四舍五入",ROUND(基本信息!AF5*基本信息!AN5,VLOOKUP(基本信息!$H5,各地政策!$A:$X,20,0)),ROUND(基本信息!AF5*基本信息!AN5-IF(VLOOKUP(基本信息!$H5,各地政策!$A:$X,20,0)=0,0.5,IF(VLOOKUP(基本信息!$H5,各地政策!$A:$X,20,0)=1,0.05,0.005)),VLOOKUP(基本信息!$H5,各地政策!$A:$X,20,0)))) -> #N/A | AA5: =IF(VLOOKUP(基本信息!$H5,各地政策!$A:$X,21,0)="进位",ROUNDUP(基本信息!AG5*基本信息!AO5,VLOOKUP(基本信息!$H5,各地政策!$A:$X,20,0)),IF(VLOOKUP(基本信息!$H5,各地政策!$A:$X,21,0)="四舍五入",ROUND(基本信息!AG5*基本信息!AO5,VLOOKUP(基本信息!$H5,各地政策!$A:$X,20,0)),ROUND(基本信息!AG5*基本信息!AO5-IF(VLOOKUP(基本信息!$H5,各地政策!$A:$X,20,0)=0,0.5,IF(VLOOKUP(基本信息!$H5,各地政策!$A:$X,20,0)=1,0.05,0.005)),VLOOKUP(基本信息!$H5,各地政策!$A:$X,20,0))))+基本信息!AT5 -> #N/A | AB5: =IF(VLOOKUP(基本信息!$H5,各地政策!$A:$X,21,0)="进位",ROUNDUP(基本信息!AH5*基本信息!AP5,VLOOKUP(基本信息!$H5,各地政策!$A:$X,20,0)),IF(VLOOKUP(基本信息!$H5,各地政策!$A:$X,21,0)="四舍五入",ROUND(基本信息!AH5*基本信息!AP5,VLOOKUP(基本信息!$H5,各地政策!$A:$X,20,0)),ROUND(基本信息!AH5*基本信息!AP5-IF(VLOOKUP(基本信息!$H5,各地政策!$A:$X,20,0)=0,0.5,IF(VLOOKUP(基本信息!$H5,各地政策!$A:$X,20,0)=1,0.05,0.005)),VLOOKUP(基本信息!$H5,各地政策!$A:$X,20,0)))) -> #N/A | AC5: =IF(VLOOKUP(基本信息!$I5,各地政策!$A:$X,24,0)="进位",ROUNDUP(基本信息!AL5*基本信息!AQ5,VLOOKUP(基本信息!$I5,各地政策!$A:$X,23,0)),IF(VLOOKUP(基本信息!$I5,各地政策!$A:$X,24,0)="四舍五入",ROUND(基本信息!AL5*基本信息!AQ5,VLOOKUP(基本信息!$I5,各地政策!$A:$X,23,0)),ROUND(基本信息!AL5*基本信息!AQ5-IF(VLOOKUP(基本信息!$I5,各地政策!$A:$X,23,0)=0,0.5,IF(VLOOKUP(基本信息!$I5,各地政策!$A:$X,23,0)=1,0.05,0.005)),VLOOKUP(基本信息!$I5,各地政策!$A:$X,23,0)))) -> #N/A | AD5: =IF(VLOOKUP(基本信息!$I5,各地政策!$A:$X,24,0)="进位",ROUNDUP(基本信息!AM5*基本信息!AR5,VLOOKUP(基本信息!$I5,各地政策!$A:$X,23,0)),IF(VLOOKUP(基本信息!$I5,各地政策!$A:$X,24,0)="四舍五入",ROUND(基本信息!AM5*基本信息!AR5,VLOOKUP(基本信息!$I5,各地政策!$A:$X,23,0)),ROUND(基本信息!AM5*基本信息!AR5-IF(VLOOKUP(基本信息!$I5,各地政策!$A:$X,23,0)=0,0.5,IF(VLOOKUP(基本信息!$I5,各地政策!$A:$X,23,0)=1,0.05,0.005)),VLOOKUP(基本信息!$I5,各地政策!$A:$X,23,0)))) -> #N/A | AE5: =基本信息!DU5+基本信息!DV5+基本信息!DW5 -> 0 | AF5: =基本信息!DX5 -> 0 | AG5: =基本信息!BF5 -> 0 | AH5: =基本信息!BG5 -> 0 | AI5: =基本信息!BH5+基本信息!DZ5 -> 0 | AJ5: =IF(基本信息!P5="税前",SUM(C5:J5)+SUM(O5:W5)-SUM(K5:N5)-SUM(X5:X5)+Y5-AG5-AH5+AI5,0) -> 0 | AK5: =IF(基本信息!J5=3,MAX(AJ5*0.2,800),5000) -> 5000 | AL5: =IF(基本信息!P5="税前",SUMIF(YTD!$A$2:$A$2386,$A5,YTD!$BB$2:$BB$2386)+SUMIF(YTD!$A$2:$A$2386,$A5,YTD!$AM$2:$AM$2386)+AJ5,0) -> 0 | AM5: =SUMIF(YTD!$A$2:$A$2386,$A5,YTD!$AM$2:$AM$2386)+SUM(Z5:AF5) -> #N/A | AN5: =SUMIF(YTD!$A$2:$A$2386,$A5,YTD!$AN$2:$AN$2386)+计算结果!AK5 -> 5000 | AO5: =基本信息!CO5 -> 0 | AP5: =基本信息!CP5 -> 0 | AQ5: =基本信息!CQ5 -> 0 | AR5: =基本信息!CR5 -> 0 | AS5: =基本信息!CS5 -> 0 | AT5: {=SUMPRODUCT((基本信息!$B$2:$B$2375=$A5)*(基本信息!$CU$2:$CV$2375))+SUMIF(YTD!$A$2:$A$2386,$A5,YTD!$AT$2:$AT$2386)} -> 0 | AU5: =SUM(AN5:AT5,CE5) -> 5000 | AV5: =IF(基本信息!P5="税前",AL5-AM5-AU5,0) -> 0 | AW5: {=IF(基本信息!J5=1,MAX((AV5)*{0.03,0.1,0.2,0.25,0.3,0.35,0.45}-12*{0,210,1410,2660,4410,7160,15160},0),IF(基本信息!J5=4,MAX((AL5-AL5*0.2-AU5)*{0.03,0.1,0.2,0.25,0.3,0.35,0.45}-12*{0,210,1410,2660,4410,7160,15160},0),0))} -> 0 | AX5: {=MAX(ROUND(IF(基本信息!J5=3,MAX((AJ5-IF(AJ5<4000,800,AJ5*0.2))*10%*{2,3,4}-1000*{0,2,7},0),IF(基本信息!J5=2,MAX((AJ5-SUM(Z5:AG5)-AK5)*{0.03,0.1,0.2,0.25,0.3,0.35,0.45}-{0,210,1410,2660,4410,7160,15160},0),IF(基本信息!P5="税前",AW5-ROUND(SUMIF(YTD!$A$2:$A$2386,$A5,YTD!$CD$2:$CD$2386),2),0))),2),0)} -> 0 | AY5: =基本信息!BI5+基本信息!EA5 -> 0 | AZ5: =IF(基本信息!P5="税前",0,SUM(C5:J5)-SUM(K5:N5)+SUM(O5:W5)-X5+Y5+AI5)+AY5 -> 0 | BA5: =IF(OR(基本信息!J5=1,基本信息!J5=4),IF(基本信息!P5="税前",AL5-AM5-AW5+AZ5,AZ5+SUMIF(YTD!$A$2:$A$2386,$A5,YTD!$BA$2:$BA$2386)),IF(基本信息!P5="税前",AJ5-SUM(Z5:AG5)-AX5+AZ5+SUMIF(YTD!$A$2:$A$2386,$A5,YTD!$BA$2:$BA$2386),AZ5)) -> 0 | BB5: {=IF(基本信息!J5=3,LOOKUP(AJ5-AX5+AZ5,{0,800,3360,21000,49500},(AJ5-AX5+AZ5-{0,160,0,2000,7000})*{1,5,25,25,25}/{1,4,21,19,17}),IF(基本信息!J5=2,MAX((BA5-AK5-10*{0,21,141,266,441,716,1516})/(1-5%*{0.6,2,4,5,6,7,9})+AK5,BA5),IF(基本信息!J5=4,MAX((BA5-AU5-(AL5*0.2)-120*{0,21,141,266,441,716,1516})/(1-5%*{0.6,2,4,5,6,7,9})+AU5+(AL5*0.2),BA5),MAX((BA5-AU5-120*{0,21,141,266,441,716,1516})/(1-5%*{0.6,2,4,5,6,7,9})+AU5,BA5))))} -> 0 | BC5: =IF(OR(基本信息!J5=1,基本信息!J5=4),BB5-IFERROR(VLOOKUP($A5,YTD!$A:$BB,54,0),0),BB5)+SUM(Z5:AF5) -> #N/A | BD5: {=IF(基本信息!J5=4,MAX((BB5-BB5*0.2-AU5)*{0.03,0.1,0.2,0.25,0.3,0.35,0.45}-12*{0,210,1410,2660,4410,7160,15160},0),IF(基本信息!J5=3,MAX((BB5-IF(BB5<4000,800,BB5*0.2))*10%*{2,3,4}-1000*{0,2,7},0),IF(基本信息!J5=2,MAX((BB5-AK5)*{0.03,0.1,0.2,0.25,0.3,0.35,0.45}-{0,210,1410,2660,4410,7160,15160},0),MAX((BB5-AU5)*{0.03,0.1,0.2,0.25,0.3,0.35,0.45}-12*{0,210,1410,2660,4410,7160,15160},0))))} -> 0 | BE5: =MAX(ROUND(IF(基本信息!J5=1,BD5-AX5-ROUND(SUMIF(YTD!$A$2:$A$2386,$A5,YTD!$CD$2:$CD$2386),2),IF(基本信息!J5=4,BD5-AX5-ROUND(SUMIF(YTD!$A$2:$A$2386,$A5,YTD!$CD$2:$CD$2386),2),BD5-AX5)),2),0) -> 0 | BF5: =IF(YEARFRAC(基本信息!AB5,TODAY())*12-1<192,基本信息!AC5,0) -> 0 | BG5: =IF(VLOOKUP(基本信息!$I5,各地政策!$A:$X,24,0)="进位",ROUNDUP(基本信息!AM5*基本信息!AS5,VLOOKUP(基本信息!$I5,各地政策!$A:$X,23,0)),IF(VLOOKUP(基本信息!$I5,各地政策!$A:$X,24,0)="四舍五入",ROUND(基本信息!AM5*基本信息!AS5,VLOOKUP(基本信息!$I5,各地政策!$A:$X,23,0)),ROUND(基本信息!AM5*基本信息!AS5-IF(VLOOKUP(基本信息!$I5,各地政策!$A:$X,23,0)=0,0.5,IF(VLOOKUP(基本信息!$I5,各地政策!$A:$X,23,0)=1,0.05,0.005)),VLOOKUP(基本信息!$I5,各地政策!$A:$X,23,0)))) -> #N/A | BH5: =基本信息!EB5 -> 0 | BI5: =基本信息!EC5 -> 0 | BJ5: =基本信息!BJ5 -> 0 | BK5: =基本信息!BL5+基本信息!DY5+基本信息!ED5 -> 0 | BL5: =基本信息!BK5+基本信息!EE5 -> 0 | BM5: =基本信息!EG5 -> 0 | BN5: {=IF(基本信息!J5=2,MAX((BM5/6)*{0.03,0.1,0.2,0.25,0.3,0.35,0.45}-{0,210,1410,2660,4410,7160,15160},0)*6,ROUND((BM5)*LOOKUP(-(BM5)/12,-{99999,80,55,35,25,12,3,0,-9}*1000,{9,7,6,5,4,2,0.6,0,0}*5%)-LOOKUP(-(BM5)/12,-{99999,80,55,35,25,12,3,0,-9}*1000,{1516,716,441,266,141,21,0,0}*10),2))} -> 0 | BO5: =基本信息!EH5 -> 0 | BP5: {=IFERROR(ROUND(MAX((基本信息!EH5-基本信息!EI5)*{0.03,0.1,0.2,0.25,0.3,0.35,0.45}-12*{0,210,1410,2660,4410,7160,15160},0),2),0)} -> 0 | BQ5: =基本信息!EK5 -> 0 | BR5: {=ROUND((BQ5)*LOOKUP(-BQ5,-{99999,96,66,42,30,14.4,3.6,0,-9}*10000,{9,7,6,5,4,2,0.6,0,0}*5%)-LOOKUP(-BQ5,-{99999,96,66,42,30,14.4,3.6,0,-9}*10000,{18192,8592,5292,3192,1692,252,0,0}*10),2)} -> 0 | BS5: =SUM(C5:J5)+SUM(O5:W5)+Y5+AY5+BF5+BK5+BM5+BO5+BH5+BJ5+BI5+BQ5 -> 0 | BT5: =IF(基本信息!P5="税前",SUM(K5:N5)+SUM(X5,Z5:AH5)+AX5+BG5+BL5+BN5+BP5+BR5,SUM(K5:N5,X5,BL5,BN5,BP5,BR5)) -> 0 | BU5: =ROUND(BS5-BT5,2) -> 0 | BV5: =IF(VLOOKUP(基本信息!$H5,各地政策!$A:$X,21,0)="进位",ROUNDUP(基本信息!AF5*基本信息!AU5,VLOOKUP(基本信息!$H5,各地政策!$A:$X,20,0)),IF(VLOOKUP(基本信息!$H5,各地政策!$A:$X,21,0)="四舍五入",ROUND(基本信息!AF5*基本信息!AU5,VLOOKUP(基本信息!$H5,各地政策!$A:$X,20,0)),ROUND(基本信息!AF5*基本信息!AU5-IF(VLOOKUP(基本信息!$H5,各地政策!$A:$X,20,0)=0,0.5,IF(VLOOKUP(基本信息!$H5,各地政策!$A:$X,20,0)=1,0.05,0.005)),VLOOKUP(基本信息!$H5,各地政策!$A:$X,20,0)))) -> #N/A | BW5: =IF(VLOOKUP(基本信息!$H5,各地政策!$A:$X,21,0)="进位",ROUNDUP(基本信息!AG5*基本信息!AV5,VLOOKUP(基本信息!$H5,各地政策!$A:$X,20,0)),IF(VLOOKUP(基本信息!$H5,各地政策!$A:$X,21,0)="四舍五入",ROUND(基本信息!AG5*基本信息!AV5,VLOOKUP(基本信息!$H5,各地政策!$A:$X,20,0)),ROUND(基本信息!AG5*基本信息!AV5-IF(VLOOKUP(基本信息!$H5,各地政策!$A:$X,20,0)=0,0.5,IF(VLOOKUP(基本信息!$H5,各地政策!$A:$X,20,0)=1,0.05,0.005)),VLOOKUP(基本信息!$H5,各地政策!$A:$X,20,0))))+基本信息!BC5 -> #N/A | BX5: =IF(VLOOKUP(基本信息!$H5,各地政策!$A:$X,21,0)="进位",ROUNDUP(基本信息!AH5*基本信息!AW5,VLOOKUP(基本信息!$H5,各地政策!$A:$X,20,0)),IF(VLOOKUP(基本信息!$H5,各地政策!$A:$X,21,0)="四舍五入",ROUND(基本信息!AH5*基本信息!AW5,VLOOKUP(基本信息!$H5,各地政策!$A:$X,20,0)),ROUND(基本信息!AH5*基本信息!AW5-IF(VLOOKUP(基本信息!$H5,各地政策!$A:$X,20,0)=0,0.5,IF(VLOOKUP(基本信息!$H5,各地政策!$A:$X,20,0)=1,0.05,0.005)),VLOOKUP(基本信息!$H5,各地政策!$A:$X,20,0)))) -> #N/A | BY5: =IF(VLOOKUP(基本信息!$H5,各地政策!$A:$X,21,0)="进位",ROUNDUP(基本信息!AI5*基本信息!AX5,VLOOKUP(基本信息!$H5,各地政策!$A:$X,20,0)),IF(VLOOKUP(基本信息!$H5,各地政策!$A:$X,21,0)="四舍五入",ROUND(基本信息!AI5*基本信息!AX5,VLOOKUP(基本信息!$H5,各地政策!$A:$X,20,0)),ROUND(基本信息!AI5*基本信息!AX5-IF(VLOOKUP(基本信息!$H5,各地政策!$A:$X,20,0)=0,0.5,IF(VLOOKUP(基本信息!$H5,各地政策!$A:$X,20,0)=1,0.05,0.005)),VLOOKUP(基本信息!$H5,各地政策!$A:$X,20,0)))) -> #N/A | BZ5: =IF(VLOOKUP(基本信息!$H5,各地政策!$A:$X,21,0)="进位",ROUNDUP(基本信息!AJ5*基本信息!AY5,VLOOKUP(基本信息!$H5,各地政策!$A:$X,20,0)),IF(VLOOKUP(基本信息!$H5,各地政策!$A:$X,21,0)="四舍五入",ROUND(基本信息!AJ5*基本信息!AY5,VLOOKUP(基本信息!$H5,各地政策!$A:$X,20,0)),ROUND(基本信息!AJ5*基本信息!AY5-IF(VLOOKUP(基本信息!$H5,各地政策!$A:$X,20,0)=0,0.5,IF(VLOOKUP(基本信息!$H5,各地政策!$A:$X,20,0)=1,0.05,0.005)),VLOOKUP(基本信息!$H5,各地政策!$A:$X,20,0))))+基本信息!BD5 -> #N/A | CA5: =IF(VLOOKUP(基本信息!$H5,各地政策!$A:$X,21,0)="进位",ROUNDUP(基本信息!AK5*基本信息!AZ5+基本信息!BE5,VLOOKUP(基本信息!$H5,各地政策!$A:$X,20,0)),IF(VLOOKUP(基本信息!$H5,各地政策!$A:$X,21,0)="四舍五入",ROUND(基本信息!AK5*基本信息!AZ5+基本信息!BE5,VLOOKUP(基本信息!$H5,各地政策!$A:$X,20,0)),ROUND(基本信息!AK5*基本信息!AZ5+基本信息!BE5-IF(VLOOKUP(基本信息!$H5,各地政策!$A:$X,20,0)=0,0.5,IF(VLOOKUP(基本信息!$H5,各地政策!$A:$X,20,0)=1,0.05,0.005)),VLOOKUP(基本信息!$H5,各地政策!$A:$X,20,0)))) -> #N/A | CB5: =IF(VLOOKUP(基本信息!$I5,各地政策!$A:$X,24,0)="进位",ROUNDUP(基本信息!AL5*(基本信息!BA5),VLOOKUP(基本信息!$I5,各地政策!$A:$X,23,0)),IF(VLOOKUP(基本信息!$I5,各地政策!$A:$X,24,0)="四舍五入",ROUND(基本信息!AL5*(基本信息!BA5),VLOOKUP(基本信息!$I5,各地政策!$A:$X,23,0)),ROUND(基本信息!AL5*(基本信息!BA5)-IF(VLOOKUP(基本信息!$I5,各地政策!$A:$X,23,0)=0,0.5,IF(VLOOKUP(基本信息!$I5,各地政策!$A:$X,23,0)=1,0.05,0.005)),VLOOKUP(基本信息!$I5,各地政策!$A:$X,23,0)))) -> #N/A | CC5: =IF(VLOOKUP(基本信息!$I5,各地政策!$A:$X,24,0)="进位",ROUNDUP(基本信息!AM5*(基本信息!BB5),VLOOKUP(基本信息!$I5,各地政策!$A:$X,23,0)),IF(VLOOKUP(基本信息!$I5,各地政策!$A:$X,24,0)="四舍五入",ROUND(基本信息!AM5*(基本信息!BB5),VLOOKUP(基本信息!$I5,各地政策!$A:$X,23,0)),ROUND(基本信息!AM5*(基本信息!BB5)-IF(VLOOKUP(基本信息!$I5,各地政策!$A:$X,23,0)=0,0.5,IF(VLOOKUP(基本信息!$I5,各地政策!$A:$X,23,0)=1,0.05,0.005)),VLOOKUP(基本信息!$I5,各地政策!$A:$X,23,0)))) -> #N/A | CD5: =AX5+BE5+IFERROR(VLOOKUP($A5,YTD!$A:$CD,82,0),0) -> 0 | CE5: =基本信息!CT5 -> 0 | CF5: ='S-Payroll Report'!X11 -> 0 | CG5: ='S-Payroll Report'!AD11 -> 0 | CH5: ='S-Payroll Report'!AC11 -> 0 | CI5: ='S-Payroll Report'!AA11 -> 450 | CJ5: ='S-Payroll Report'!AF11 -> 30.47 | CK5: =基本信息!EM5+基本信息!EN5+基本信息!EO5 -> 0
A6: =IF(基本信息!B6="","",基本信息!B6) | B6: =IF(基本信息!C6="","",基本信息!C6) | C6: =基本信息!Q6+基本信息!R6*基本信息!CW6 -> 0 | D6: =基本信息!S6 -> 0 | E6: =基本信息!CX6 -> 0 | F6: =基本信息!CY6 -> 0 | G6: =基本信息!CZ6 -> 0 | H6: =ROUND(C6*基本信息!DA6*1.5/(21.75*8),2) -> 0 | I6: =ROUND(C6*基本信息!DB6*2/(21.75*8),2) -> 0 | J6: =ROUND(C6*基本信息!DC6*3/(21.75*8),2) -> 0 | K6: =ROUND(IF(AND(基本信息!DD6=23,基本信息!DE6=12),((C6+D6)*12/21.75+(C6+D6)-(C6+D6)*11/21.75)/2,IF(基本信息!DE6>基本信息!DD6/2,(C6+D6)-(C6+D6)*(基本信息!DD6-基本信息!DE6)/21.75,(C6+D6)*基本信息!DE6/21.75)),2) -> 0 | L6: =MAX(0,ROUND((C6+D6)*基本信息!DF6/21.75,2)) -> 0 | M6: =MAX(0,ROUND((C6+D6)*基本信息!DG6/21.75,2)) -> 0 | N6: =基本信息!DI6 -> 0 | O6: =基本信息!T6+基本信息!DJ6 -> 0 | P6: =基本信息!U6+基本信息!DK6 -> 0 | Q6: =基本信息!V6 -> 0 | R6: =基本信息!W6*基本信息!DL6 -> 0 | S6: =基本信息!X6*基本信息!DM6 -> 0 | T6: =基本信息!Y6*基本信息!DN6+基本信息!DO6 -> 0 | U6: =基本信息!Z6*基本信息!DP6 -> 0 | V6: =基本信息!AA6*基本信息!DQ6 -> 0 | W6: =基本信息!AD6+基本信息!DR6 -> 0 | X6: =基本信息!AE6+基本信息!DS6 -> 0 | Y6: =基本信息!DT6 -> 0 | Z6: =IF(VLOOKUP(基本信息!$H6,各地政策!$A:$X,21,0)="进位",ROUNDUP(基本信息!AF6*基本信息!AN6,VLOOKUP(基本信息!$H6,各地政策!$A:$X,20,0)),IF(VLOOKUP(基本信息!$H6,各地政策!$A:$X,21,0)="四舍五入",ROUND(基本信息!AF6*基本信息!AN6,VLOOKUP(基本信息!$H6,各地政策!$A:$X,20,0)),ROUND(基本信息!AF6*基本信息!AN6-IF(VLOOKUP(基本信息!$H6,各地政策!$A:$X,20,0)=0,0.5,IF(VLOOKUP(基本信息!$H6,各地政策!$A:$X,20,0)=1,0.05,0.005)),VLOOKUP(基本信息!$H6,各地政策!$A:$X,20,0)))) -> #N/A | AA6: =IF(VLOOKUP(基本信息!$H6,各地政策!$A:$X,21,0)="进位",ROUNDUP(基本信息!AG6*基本信息!AO6,VLOOKUP(基本信息!$H6,各地政策!$A:$X,20,0)),IF(VLOOKUP(基本信息!$H6,各地政策!$A:$X,21,0)="四舍五入",ROUND(基本信息!AG6*基本信息!AO6,VLOOKUP(基本信息!$H6,各地政策!$A:$X,20,0)),ROUND(基本信息!AG6*基本信息!AO6-IF(VLOOKUP(基本信息!$H6,各地政策!$A:$X,20,0)=0,0.5,IF(VLOOKUP(基本信息!$H6,各地政策!$A:$X,20,0)=1,0.05,0.005)),VLOOKUP(基本信息!$H6,各地政策!$A:$X,20,0))))+基本信息!AT6 -> #N/A | AB6: =IF(VLOOKUP(基本信息!$H6,各地政策!$A:$X,21,0)="进位",ROUNDUP(基本信息!AH6*基本信息!AP6,VLOOKUP(基本信息!$H6,各地政策!$A:$X,20,0)),IF(VLOOKUP(基本信息!$H6,各地政策!$A:$X,21,0)="四舍五入",ROUND(基本信息!AH6*基本信息!AP6,VLOOKUP(基本信息!$H6,各地政策!$A:$X,20,0)),ROUND(基本信息!AH6*基本信息!AP6-IF(VLOOKUP(基本信息!$H6,各地政策!$A:$X,20,0)=0,0.5,IF(VLOOKUP(基本信息!$H6,各地政策!$A:$X,20,0)=1,0.05,0.005)),VLOOKUP(基本信息!$H6,各地政策!$A:$X,20,0)))) -> #N/A | AC6: =IF(VLOOKUP(基本信息!$I6,各地政策!$A:$X,24,0)="进位",ROUNDUP(基本信息!AL6*基本信息!AQ6,VLOOKUP(基本信息!$I6,各地政策!$A:$X,23,0)),IF(VLOOKUP(基本信息!$I6,各地政策!$A:$X,24,0)="四舍五入",ROUND(基本信息!AL6*基本信息!AQ6,VLOOKUP(基本信息!$I6,各地政策!$A:$X,23,0)),ROUND(基本信息!AL6*基本信息!AQ6-IF(VLOOKUP(基本信息!$I6,各地政策!$A:$X,23,0)=0,0.5,IF(VLOOKUP(基本信息!$I6,各地政策!$A:$X,23,0)=1,0.05,0.005)),VLOOKUP(基本信息!$I6,各地政策!$A:$X,23,0)))) -> #N/A | AD6: =IF(VLOOKUP(基本信息!$I6,各地政策!$A:$X,24,0)="进位",ROUNDUP(基本信息!AM6*基本信息!AR6,VLOOKUP(基本信息!$I6,各地政策!$A:$X,23,0)),IF(VLOOKUP(基本信息!$I6,各地政策!$A:$X,24,0)="四舍五入",ROUND(基本信息!AM6*基本信息!AR6,VLOOKUP(基本信息!$I6,各地政策!$A:$X,23,0)),ROUND(基本信息!AM6*基本信息!AR6-IF(VLOOKUP(基本信息!$I6,各地政策!$A:$X,23,0)=0,0.5,IF(VLOOKUP(基本信息!$I6,各地政策!$A:$X,23,0)=1,0.05,0.005)),VLOOKUP(基本信息!$I6,各地政策!$A:$X,23,0)))) -> #N/A | AE6: =基本信息!DU6+基本信息!DV6+基本信息!DW6 -> 0 | AF6: =基本信息!DX6 -> 0 | AG6: =基本信息!BF6 -> 0 | AH6: =基本信息!BG6 -> 0 | AI6: =基本信息!BH6+基本信息!DZ6 -> 0 | AJ6: =IF(基本信息!P6="税前",SUM(C6:J6)+SUM(O6:W6)-SUM(K6:N6)-SUM(X6:X6)+Y6-AG6-AH6+AI6,0) -> 0 | AK6: =IF(基本信息!J6=3,MAX(AJ6*0.2,800),5000) -> 5000 | AL6: =IF(基本信息!P6="税前",SUMIF(YTD!$A$2:$A$2386,$A6,YTD!$BB$2:$BB$2386)+SUMIF(YTD!$A$2:$A$2386,$A6,YTD!$AM$2:$AM$2386)+AJ6,0) -> 0 | AM6: =SUMIF(YTD!$A$2:$A$2386,$A6,YTD!$AM$2:$AM$2386)+SUM(Z6:AF6) -> #N/A | AN6: =SUMIF(YTD!$A$2:$A$2386,$A6,YTD!$AN$2:$AN$2386)+计算结果!AK6 -> 5000 | AO6: =基本信息!CO6 -> 0 | AP6: =基本信息!CP6 -> 0 | AQ6: =基本信息!CQ6 -> 0 | AR6: =基本信息!CR6 -> 0 | AS6: =基本信息!CS6 -> 0 | AT6: {=SUMPRODUCT((基本信息!$B$2:$B$2375=$A6)*(基本信息!$CU$2:$CV$2375))+SUMIF(YTD!$A$2:$A$2386,$A6,YTD!$AT$2:$AT$2386)} -> 0 | AU6: =SUM(AN6:AT6,CE6) -> 5000 | AV6: =IF(基本信息!P6="税前",AL6-AM6-AU6,0) -> 0 | AW6: {=IF(基本信息!J6=1,MAX((AV6)*{0.03,0.1,0.2,0.25,0.3,0.35,0.45}-12*{0,210,1410,2660,4410,7160,15160},0),IF(基本信息!J6=4,MAX((AL6-AL6*0.2-AU6)*{0.03,0.1,0.2,0.25,0.3,0.35,0.45}-12*{0,210,1410,2660,4410,7160,15160},0),0))} -> 0 | AX6: {=MAX(ROUND(IF(基本信息!J6=3,MAX((AJ6-IF(AJ6<4000,800,AJ6*0.2))*10%*{2,3,4}-1000*{0,2,7},0),IF(基本信息!J6=2,MAX((AJ6-SUM(Z6:AG6)-AK6)*{0.03,0.1,0.2,0.25,0.3,0.35,0.45}-{0,210,1410,2660,4410,7160,15160},0),IF(基本信息!P6="税前",AW6-ROUND(SUMIF(YTD!$A$2:$A$2386,$A6,YTD!$CD$2:$CD$2386),2),0))),2),0)} -> 0 | AY6: =基本信息!BI6+基本信息!EA6 -> 0 | AZ6: =IF(基本信息!P6="税前",0,SUM(C6:J6)-SUM(K6:N6)+SUM(O6:W6)-X6+Y6+AI6)+AY6 -> 0 | BA6: =IF(OR(基本信息!J6=1,基本信息!J6=4),IF(基本信息!P6="税前",AL6-AM6-AW6+AZ6,AZ6+SUMIF(YTD!$A$2:$A$2386,$A6,YTD!$BA$2:$BA$2386)),IF(基本信息!P6="税前",AJ6-SUM(Z6:AG6)-AX6+AZ6+SUMIF(YTD!$A$2:$A$2386,$A6,YTD!$BA$2:$BA$2386),AZ6)) -> 0 | BB6: {=IF(基本信息!J6=3,LOOKUP(AJ6-AX6+AZ6,{0,800,3360,21000,49500},(AJ6-AX6+AZ6-{0,160,0,2000,7000})*{1,5,25,25,25}/{1,4,21,19,17}),IF(基本信息!J6=2,MAX((BA6-AK6-10*{0,21,141,266,441,716,1516})/(1-5%*{0.6,2,4,5,6,7,9})+AK6,BA6),IF(基本信息!J6=4,MAX((BA6-AU6-(AL6*0.2)-120*{0,21,141,266,441,716,1516})/(1-5%*{0.6,2,4,5,6,7,9})+AU6+(AL6*0.2),BA6),MAX((BA6-AU6-120*{0,21,141,266,441,716,1516})/(1-5%*{0.6,2,4,5,6,7,9})+AU6,BA6))))} -> 0 | BC6: =IF(OR(基本信息!J6=1,基本信息!J6=4),BB6-IFERROR(VLOOKUP($A6,YTD!$A:$BB,54,0),0),BB6)+SUM(Z6:AF6) -> #N/A | BD6: {=IF(基本信息!J6=4,MAX((BB6-BB6*0.2-AU6)*{0.03,0.1,0.2,0.25,0.3,0.35,0.45}-12*{0,210,1410,2660,4410,7160,15160},0),IF(基本信息!J6=3,MAX((BB6-IF(BB6<4000,800,BB6*0.2))*10%*{2,3,4}-1000*{0,2,7},0),IF(基本信息!J6=2,MAX((BB6-AK6)*{0.03,0.1,0.2,0.25,0.3,0.35,0.45}-{0,210,1410,2660,4410,7160,15160},0),MAX((BB6-AU6)*{0.03,0.1,0.2,0.25,0.3,0.35,0.45}-12*{0,210,1410,2660,4410,7160,15160},0))))} -> 0 | BE6: =MAX(ROUND(IF(基本信息!J6=1,BD6-AX6-ROUND(SUMIF(YTD!$A$2:$A$2386,$A6,YTD!$CD$2:$CD$2386),2),IF(基本信息!J6=4,BD6-AX6-ROUND(SUMIF(YTD!$A$2:$A$2386,$A6,YTD!$CD$2:$CD$2386),2),BD6-AX6)),2),0) -> 0 | BF6: =IF(YEARFRAC(基本信息!AB6,TODAY())*12-1<192,基本信息!AC6,0) -> 0 | BG6: =IF(VLOOKUP(基本信息!$I6,各地政策!$A:$X,24,0)="进位",ROUNDUP(基本信息!AM6*基本信息!AS6,VLOOKUP(基本信息!$I6,各地政策!$A:$X,23,0)),IF(VLOOKUP(基本信息!$I6,各地政策!$A:$X,24,0)="四舍五入",ROUND(基本信息!AM6*基本信息!AS6,VLOOKUP(基本信息!$I6,各地政策!$A:$X,23,0)),ROUND(基本信息!AM6*基本信息!AS6-IF(VLOOKUP(基本信息!$I6,各地政策!$A:$X,23,0)=0,0.5,IF(VLOOKUP(基本信息!$I6,各地政策!$A:$X,23,0)=1,0.05,0.005)),VLOOKUP(基本信息!$I6,各地政策!$A:$X,23,0)))) -> #N/A | BH6: =基本信息!EB6 -> 0 | BI6: =基本信息!EC6 -> 0 | BJ6: =基本信息!BJ6 -> 0 | BK6: =基本信息!BL6+基本信息!DY6+基本信息!ED6 -> 0 | BL6: =基本信息!BK6+基本信息!EE6 -> 0 | BM6: =基本信息!EG6 -> 0 | BN6: {=IF(基本信息!J6=2,MAX((BM6/6)*{0.03,0.1,0.2,0.25,0.3,0.35,0.45}-{0,210,1410,2660,4410,7160,15160},0)*6,ROUND((BM6)*LOOKUP(-(BM6)/12,-{99999,80,55,35,25,12,3,0,-9}*1000,{9,7,6,5,4,2,0.6,0,0}*5%)-LOOKUP(-(BM6)/12,-{99999,80,55,35,25,12,3,0,-9}*1000,{1516,716,441,266,141,21,0,0}*10),2))} -> 0 | BO6: =基本信息!EH6 -> 0 | BP6: {=IFERROR(ROUND(MAX((基本信息!EH6-基本信息!EI6)*{0.03,0.1,0.2,0.25,0.3,0.35,0.45}-12*{0,210,1410,2660,4410,7160,15160},0),2),0)} -> 0 | BQ6: =基本信息!EK6 -> 0 | BR6: {=ROUND((BQ6)*LOOKUP(-BQ6,-{99999,96,66,42,30,14.4,3.6,0,-9}*10000,{9,7,6,5,4,2,0.6,0,0}*5%)-LOOKUP(-BQ6,-{99999,96,66,42,30,14.4,3.6,0,-9}*10000,{18192,8592,5292,3192,1692,252,0,0}*10),2)} -> 0 | BS6: =SUM(C6:J6)+SUM(O6:W6)+Y6+AY6+BF6+BK6+BM6+BO6+BH6+BJ6+BI6+BQ6 -> 0 | BT6: =IF(基本信息!P6="税前",SUM(K6:N6)+SUM(X6,Z6:AH6)+AX6+BG6+BL6+BN6+BP6+BR6,SUM(K6:N6,X6,BL6,BN6,BP6,BR6)) -> 0 | BU6: =ROUND(BS6-BT6,2) -> 0 | BV6: =IF(VLOOKUP(基本信息!$H6,各地政策!$A:$X,21,0)="进位",ROUNDUP(基本信息!AF6*基本信息!AU6,VLOOKUP(基本信息!$H6,各地政策!$A:$X,20,0)),IF(VLOOKUP(基本信息!$H6,各地政策!$A:$X,21,0)="四舍五入",ROUND(基本信息!AF6*基本信息!AU6,VLOOKUP(基本信息!$H6,各地政策!$A:$X,20,0)),ROUND(基本信息!AF6*基本信息!AU6-IF(VLOOKUP(基本信息!$H6,各地政策!$A:$X,20,0)=0,0.5,IF(VLOOKUP(基本信息!$H6,各地政策!$A:$X,20,0)=1,0.05,0.005)),VLOOKUP(基本信息!$H6,各地政策!$A:$X,20,0)))) -> #N/A | BW6: =IF(VLOOKUP(基本信息!$H6,各地政策!$A:$X,21,0)="进位",ROUNDUP(基本信息!AG6*基本信息!AV6,VLOOKUP(基本信息!$H6,各地政策!$A:$X,20,0)),IF(VLOOKUP(基本信息!$H6,各地政策!$A:$X,21,0)="四舍五入",ROUND(基本信息!AG6*基本信息!AV6,VLOOKUP(基本信息!$H6,各地政策!$A:$X,20,0)),ROUND(基本信息!AG6*基本信息!AV6-IF(VLOOKUP(基本信息!$H6,各地政策!$A:$X,20,0)=0,0.5,IF(VLOOKUP(基本信息!$H6,各地政策!$A:$X,20,0)=1,0.05,0.005)),VLOOKUP(基本信息!$H6,各地政策!$A:$X,20,0))))+基本信息!BC6 -> #N/A | BX6: =IF(VLOOKUP(基本信息!$H6,各地政策!$A:$X,21,0)="进位",ROUNDUP(基本信息!AH6*基本信息!AW6,VLOOKUP(基本信息!$H6,各地政策!$A:$X,20,0)),IF(VLOOKUP(基本信息!$H6,各地政策!$A:$X,21,0)="四舍五入",ROUND(基本信息!AH6*基本信息!AW6,VLOOKUP(基本信息!$H6,各地政策!$A:$X,20,0)),ROUND(基本信息!AH6*基本信息!AW6-IF(VLOOKUP(基本信息!$H6,各地政策!$A:$X,20,0)=0,0.5,IF(VLOOKUP(基本信息!$H6,各地政策!$A:$X,20,0)=1,0.05,0.005)),VLOOKUP(基本信息!$H6,各地政策!$A:$X,20,0)))) -> #N/A | BY6: =IF(VLOOKUP(基本信息!$H6,各地政策!$A:$X,21,0)="进位",ROUNDUP(基本信息!AI6*基本信息!AX6,VLOOKUP(基本信息!$H6,各地政策!$A:$X,20,0)),IF(VLOOKUP(基本信息!$H6,各地政策!$A:$X,21,0)="四舍五入",ROUND(基本信息!AI6*基本信息!AX6,VLOOKUP(基本信息!$H6,各地政策!$A:$X,20,0)),ROUND(基本信息!AI6*基本信息!AX6-IF(VLOOKUP(基本信息!$H6,各地政策!$A:$X,20,0)=0,0.5,IF(VLOOKUP(基本信息!$H6,各地政策!$A:$X,20,0)=1,0.05,0.005)),VLOOKUP(基本信息!$H6,各地政策!$A:$X,20,0)))) -> #N/A | BZ6: =IF(VLOOKUP(基本信息!$H6,各地政策!$A:$X,21,0)="进位",ROUNDUP(基本信息!AJ6*基本信息!AY6,VLOOKUP(基本信息!$H6,各地政策!$A:$X,20,0)),IF(VLOOKUP(基本信息!$H6,各地政策!$A:$X,21,0)="四舍五入",ROUND(基本信息!AJ6*基本信息!AY6,VLOOKUP(基本信息!$H6,各地政策!$A:$X,20,0)),ROUND(基本信息!AJ6*基本信息!AY6-IF(VLOOKUP(基本信息!$H6,各地政策!$A:$X,20,0)=0,0.5,IF(VLOOKUP(基本信息!$H6,各地政策!$A:$X,20,0)=1,0.05,0.005)),VLOOKUP(基本信息!$H6,各地政策!$A:$X,20,0))))+基本信息!BD6 -> #N/A | CA6: =IF(VLOOKUP(基本信息!$H6,各地政策!$A:$X,21,0)="进位",ROUNDUP(基本信息!AK6*基本信息!AZ6+基本信息!BE6,VLOOKUP(基本信息!$H6,各地政策!$A:$X,20,0)),IF(VLOOKUP(基本信息!$H6,各地政策!$A:$X,21,0)="四舍五入",ROUND(基本信息!AK6*基本信息!AZ6+基本信息!BE6,VLOOKUP(基本信息!$H6,各地政策!$A:$X,20,0)),ROUND(基本信息!AK6*基本信息!AZ6+基本信息!BE6-IF(VLOOKUP(基本信息!$H6,各地政策!$A:$X,20,0)=0,0.5,IF(VLOOKUP(基本信息!$H6,各地政策!$A:$X,20,0)=1,0.05,0.005)),VLOOKUP(基本信息!$H6,各地政策!$A:$X,20,0)))) -> #N/A | CB6: =IF(VLOOKUP(基本信息!$I6,各地政策!$A:$X,24,0)="进位",ROUNDUP(基本信息!AL6*(基本信息!BA6),VLOOKUP(基本信息!$I6,各地政策!$A:$X,23,0)),IF(VLOOKUP(基本信息!$I6,各地政策!$A:$X,24,0)="四舍五入",ROUND(基本信息!AL6*(基本信息!BA6),VLOOKUP(基本信息!$I6,各地政策!$A:$X,23,0)),ROUND(基本信息!AL6*(基本信息!BA6)-IF(VLOOKUP(基本信息!$I6,各地政策!$A:$X,23,0)=0,0.5,IF(VLOOKUP(基本信息!$I6,各地政策!$A:$X,23,0)=1,0.05,0.005)),VLOOKUP(基本信息!$I6,各地政策!$A:$X,23,0)))) -> #N/A | CC6: =IF(VLOOKUP(基本信息!$I6,各地政策!$A:$X,24,0)="进位",ROUNDUP(基本信息!AM6*(基本信息!BB6),VLOOKUP(基本信息!$I6,各地政策!$A:$X,23,0)),IF(VLOOKUP(基本信息!$I6,各地政策!$A:$X,24,0)="四舍五入",ROUND(基本信息!AM6*(基本信息!BB6),VLOOKUP(基本信息!$I6,各地政策!$A:$X,23,0)),ROUND(基本信息!AM6*(基本信息!BB6)-IF(VLOOKUP(基本信息!$I6,各地政策!$A:$X,23,0)=0,0.5,IF(VLOOKUP(基本信息!$I6,各地政策!$A:$X,23,0)=1,0.05,0.005)),VLOOKUP(基本信息!$I6,各地政策!$A:$X,23,0)))) -> #N/A | CD6: =AX6+BE6+IFERROR(VLOOKUP($A6,YTD!$A:$CD,82,0),0) -> 0 | CE6: =基本信息!CT6 -> 0 | CF6: ='S-Payroll Report'!X12 -> 0 | CG6: ='S-Payroll Report'!AD12 -> 0 | CH6: ='S-Payroll Report'!AC12 -> 0 | CI6: ='S-Payroll Report'!AA12 -> 0 | CJ6: ='S-Payroll Report'!AF12 -> 0 | CK6: =基本信息!EM6+基本信息!EN6+基本信息!EO6 -> 0
A7: =IF(基本信息!B7="","",基本信息!B7) | B7: =IF(基本信息!C7="","",基本信息!C7) | C7: =基本信息!Q7+基本信息!R7*基本信息!CW7 -> 0 | D7: =基本信息!S7 -> 0 | E7: =基本信息!CX7 -> 0 | F7: =基本信息!CY7 -> 0 | G7: =基本信息!CZ7 -> 0 | H7: =ROUND(C7*基本信息!DA7*1.5/(21.75*8),2) -> 0 | I7: =ROUND(C7*基本信息!DB7*2/(21.75*8),2) -> 0 | J7: =ROUND(C7*基本信息!DC7*3/(21.75*8),2) -> 0 | K7: =ROUND(IF(AND(基本信息!DD7=23,基本信息!DE7=12),((C7+D7)*12/21.75+(C7+D7)-(C7+D7)*11/21.75)/2,IF(基本信息!DE7>基本信息!DD7/2,(C7+D7)-(C7+D7)*(基本信息!DD7-基本信息!DE7)/21.75,(C7+D7)*基本信息!DE7/21.75)),2) -> 0 | L7: =MAX(0,ROUND((C7+D7)*基本信息!DF7/21.75,2)) -> 0 | M7: =MAX(0,ROUND((C7+D7)*基本信息!DG7/21.75,2)) -> 0 | N7: =基本信息!DI7 -> 0 | O7: =基本信息!T7+基本信息!DJ7 -> 0 | P7: =基本信息!U7+基本信息!DK7 -> 0 | Q7: =基本信息!V7 -> 0 | R7: =基本信息!W7*基本信息!DL7 -> 0 | S7: =基本信息!X7*基本信息!DM7 -> 0 | T7: =基本信息!Y7*基本信息!DN7+基本信息!DO7 -> 0 | U7: =基本信息!Z7*基本信息!DP7 -> 0 | V7: =基本信息!AA7*基本信息!DQ7 -> 0 | W7: =基本信息!AD7+基本信息!DR7 -> 0 | X7: =基本信息!AE7+基本信息!DS7 -> 0 | Y7: =基本信息!DT7 -> 0 | Z7: =IF(VLOOKUP(基本信息!$H7,各地政策!$A:$X,21,0)="进位",ROUNDUP(基本信息!AF7*基本信息!AN7,VLOOKUP(基本信息!$H7,各地政策!$A:$X,20,0)),IF(VLOOKUP(基本信息!$H7,各地政策!$A:$X,21,0)="四舍五入",ROUND(基本信息!AF7*基本信息!AN7,VLOOKUP(基本信息!$H7,各地政策!$A:$X,20,0)),ROUND(基本信息!AF7*基本信息!AN7-IF(VLOOKUP(基本信息!$H7,各地政策!$A:$X,20,0)=0,0.5,IF(VLOOKUP(基本信息!$H7,各地政策!$A:$X,20,0)=1,0.05,0.005)),VLOOKUP(基本信息!$H7,各地政策!$A:$X,20,0)))) -> #N/A | AA7: =IF(VLOOKUP(基本信息!$H7,各地政策!$A:$X,21,0)="进位",ROUNDUP(基本信息!AG7*基本信息!AO7,VLOOKUP(基本信息!$H7,各地政策!$A:$X,20,0)),IF(VLOOKUP(基本信息!$H7,各地政策!$A:$X,21,0)="四舍五入",ROUND(基本信息!AG7*基本信息!AO7,VLOOKUP(基本信息!$H7,各地政策!$A:$X,20,0)),ROUND(基本信息!AG7*基本信息!AO7-IF(VLOOKUP(基本信息!$H7,各地政策!$A:$X,20,0)=0,0.5,IF(VLOOKUP(基本信息!$H7,各地政策!$A:$X,20,0)=1,0.05,0.005)),VLOOKUP(基本信息!$H7,各地政策!$A:$X,20,0))))+基本信息!AT7 -> #N/A | AB7: =IF(VLOOKUP(基本信息!$H7,各地政策!$A:$X,21,0)="进位",ROUNDUP(基本信息!AH7*基本信息!AP7,VLOOKUP(基本信息!$H7,各地政策!$A:$X,20,0)),IF(VLOOKUP(基本信息!$H7,各地政策!$A:$X,21,0)="四舍五入",ROUND(基本信息!AH7*基本信息!AP7,VLOOKUP(基本信息!$H7,各地政策!$A:$X,20,0)),ROUND(基本信息!AH7*基本信息!AP7-IF(VLOOKUP(基本信息!$H7,各地政策!$A:$X,20,0)=0,0.5,IF(VLOOKUP(基本信息!$H7,各地政策!$A:$X,20,0)=1,0.05,0.005)),VLOOKUP(基本信息!$H7,各地政策!$A:$X,20,0)))) -> #N/A | AC7: =IF(VLOOKUP(基本信息!$I7,各地政策!$A:$X,24,0)="进位",ROUNDUP(基本信息!AL7*基本信息!AQ7,VLOOKUP(基本信息!$I7,各地政策!$A:$X,23,0)),IF(VLOOKUP(基本信息!$I7,各地政策!$A:$X,24,0)="四舍五入",ROUND(基本信息!AL7*基本信息!AQ7,VLOOKUP(基本信息!$I7,各地政策!$A:$X,23,0)),ROUND(基本信息!AL7*基本信息!AQ7-IF(VLOOKUP(基本信息!$I7,各地政策!$A:$X,23,0)=0,0.5,IF(VLOOKUP(基本信息!$I7,各地政策!$A:$X,23,0)=1,0.05,0.005)),VLOOKUP(基本信息!$I7,各地政策!$A:$X,23,0)))) -> #N/A | AD7: =IF(VLOOKUP(基本信息!$I7,各地政策!$A:$X,24,0)="进位",ROUNDUP(基本信息!AM7*基本信息!AR7,VLOOKUP(基本信息!$I7,各地政策!$A:$X,23,0)),IF(VLOOKUP(基本信息!$I7,各地政策!$A:$X,24,0)="四舍五入",ROUND(基本信息!AM7*基本信息!AR7,VLOOKUP(基本信息!$I7,各地政策!$A:$X,23,0)),ROUND(基本信息!AM7*基本信息!AR7-IF(VLOOKUP(基本信息!$I7,各地政策!$A:$X,23,0)=0,0.5,IF(VLOOKUP(基本信息!$I7,各地政策!$A:$X,23,0)=1,0.05,0.005)),VLOOKUP(基本信息!$I7,各地政策!$A:$X,23,0)))) -> #N/A | AE7: =基本信息!DU7+基本信息!DV7+基本信息!DW7 -> 0 | AF7: =基本信息!DX7 -> 0 | AG7: =基本信息!BF7 -> 0 | AH7: =基本信息!BG7 -> 0 | AI7: =基本信息!BH7+基本信息!DZ7 -> 0 | AJ7: =IF(基本信息!P7="税前",SUM(C7:J7)+SUM(O7:W7)-SUM(K7:N7)-SUM(X7:X7)+Y7-AG7-AH7+AI7,0) -> 0 | AK7: =IF(基本信息!J7=3,MAX(AJ7*0.2,800),5000) -> 5000 | AL7: =IF(基本信息!P7="税前",SUMIF(YTD!$A$2:$A$2386,$A7,YTD!$BB$2:$BB$2386)+SUMIF(YTD!$A$2:$A$2386,$A7,YTD!$AM$2:$AM$2386)+AJ7,0) -> 0 | AM7: =SUMIF(YTD!$A$2:$A$2386,$A7,YTD!$AM$2:$AM$2386)+SUM(Z7:AF7) -> #N/A | AN7: =SUMIF(YTD!$A$2:$A$2386,$A7,YTD!$AN$2:$AN$2386)+计算结果!AK7 -> 5000 | AO7: =基本信息!CO7 -> 0 | AP7: =基本信息!CP7 -> 0 | AQ7: =基本信息!CQ7 -> 0 | AR7: =基本信息!CR7 -> 0 | AS7: =基本信息!CS7 -> 0 | AT7: {=SUMPRODUCT((基本信息!$B$2:$B$2375=$A7)*(基本信息!$CU$2:$CV$2375))+SUMIF(YTD!$A$2:$A$2386,$A7,YTD!$AT$2:$AT$2386)} -> 0 | AU7: =SUM(AN7:AT7,CE7) -> 5000 | AV7: =IF(基本信息!P7="税前",AL7-AM7-AU7,0) -> 0 | AW7: {=IF(基本信息!J7=1,MAX((AV7)*{0.03,0.1,0.2,0.25,0.3,0.35,0.45}-12*{0,210,1410,2660,4410,7160,15160},0),IF(基本信息!J7=4,MAX((AL7-AL7*0.2-AU7)*{0.03,0.1,0.2,0.25,0.3,0.35,0.45}-12*{0,210,1410,2660,4410,7160,15160},0),0))} -> 0 | AX7: {=MAX(ROUND(IF(基本信息!J7=3,MAX((AJ7-IF(AJ7<4000,800,AJ7*0.2))*10%*{2,3,4}-1000*{0,2,7},0),IF(基本信息!J7=2,MAX((AJ7-SUM(Z7:AG7)-AK7)*{0.03,0.1,0.2,0.25,0.3,0.35,0.45}-{0,210,1410,2660,4410,7160,15160},0),IF(基本信息!P7="税前",AW7-ROUND(SUMIF(YTD!$A$2:$A$2386,$A7,YTD!$CD$2:$CD$2386),2),0))),2),0)} -> 0 | AY7: =基本信息!BI7+基本信息!EA7 -> 0 | AZ7: =IF(基本信息!P7="税前",0,SUM(C7:J7)-SUM(K7:N7)+SUM(O7:W7)-X7+Y7+AI7)+AY7 -> 0 | BA7: =IF(OR(基本信息!J7=1,基本信息!J7=4),IF(基本信息!P7="税前",AL7-AM7-AW7+AZ7,AZ7+SUMIF(YTD!$A$2:$A$2386,$A7,YTD!$BA$2:$BA$2386)),IF(基本信息!P7="税前",AJ7-SUM(Z7:AG7)-AX7+AZ7+SUMIF(YTD!$A$2:$A$2386,$A7,YTD!$BA$2:$BA$2386),AZ7)) -> 0 | BB7: {=IF(基本信息!J7=3,LOOKUP(AJ7-AX7+AZ7,{0,800,3360,21000,49500},(AJ7-AX7+AZ7-{0,160,0,2000,7000})*{1,5,25,25,25}/{1,4,21,19,17}),IF(基本信息!J7=2,MAX((BA7-AK7-10*{0,21,141,266,441,716,1516})/(1-5%*{0.6,2,4,5,6,7,9})+AK7,BA7),IF(基本信息!J7=4,MAX((BA7-AU7-(AL7*0.2)-120*{0,21,141,266,441,716,1516})/(1-5%*{0.6,2,4,5,6,7,9})+AU7+(AL7*0.2),BA7),MAX((BA7-AU7-120*{0,21,141,266,441,716,1516})/(1-5%*{0.6,2,4,5,6,7,9})+AU7,BA7))))} -> 0 | BC7: =IF(OR(基本信息!J7=1,基本信息!J7=4),BB7-IFERROR(VLOOKUP($A7,YTD!$A:$BB,54,0),0),BB7)+SUM(Z7:AF7) -> #N/A | BD7: {=IF(基本信息!J7=4,MAX((BB7-BB7*0.2-AU7)*{0.03,0.1,0.2,0.25,0.3,0.35,0.45}-12*{0,210,1410,2660,4410,7160,15160},0),IF(基本信息!J7=3,MAX((BB7-IF(BB7<4000,800,BB7*0.2))*10%*{2,3,4}-1000*{0,2,7},0),IF(基本信息!J7=2,MAX((BB7-AK7)*{0.03,0.1,0.2,0.25,0.3,0.35,0.45}-{0,210,1410,2660,4410,7160,15160},0),MAX((BB7-AU7)*{0.03,0.1,0.2,0.25,0.3,0.35,0.45}-12*{0,210,1410,2660,4410,7160,15160},0))))} -> 0 | BE7: =MAX(ROUND(IF(基本信息!J7=1,BD7-AX7-ROUND(SUMIF(YTD!$A$2:$A$2386,$A7,YTD!$CD$2:$CD$2386),2),IF(基本信息!J7=4,BD7-AX7-ROUND(SUMIF(YTD!$A$2:$A$2386,$A7,YTD!$CD$2:$CD$2386),2),BD7-AX7)),2),0) -> 0 | BF7: =IF(YEARFRAC(基本信息!AB7,TODAY())*12-1<192,基本信息!AC7,0) -> 0 | BG7: =IF(VLOOKUP(基本信息!$I7,各地政策!$A:$X,24,0)="进位",ROUNDUP(基本信息!AM7*基本信息!AS7,VLOOKUP(基本信息!$I7,各地政策!$A:$X,23,0)),IF(VLOOKUP(基本信息!$I7,各地政策!$A:$X,24,0)="四舍五入",ROUND(基本信息!AM7*基本信息!AS7,VLOOKUP(基本信息!$I7,各地政策!$A:$X,23,0)),ROUND(基本信息!AM7*基本信息!AS7-IF(VLOOKUP(基本信息!$I7,各地政策!$A:$X,23,0)=0,0.5,IF(VLOOKUP(基本信息!$I7,各地政策!$A:$X,23,0)=1,0.05,0.005)),VLOOKUP(基本信息!$I7,各地政策!$A:$X,23,0)))) -> #N/A | BH7: =基本信息!EB7 -> 0 | BI7: =基本信息!EC7 -> 0 | BJ7: =基本信息!BJ7 -> 0 | BK7: =基本信息!BL7+基本信息!DY7+基本信息!ED7 -> 0 | BL7: =基本信息!BK7+基本信息!EE7 -> 0 | BM7: =基本信息!EG7 -> 0 | BN7: {=IF(基本信息!J7=2,MAX((BM7/6)*{0.03,0.1,0.2,0.25,0.3,0.35,0.45}-{0,210,1410,2660,4410,7160,15160},0)*6,ROUND((BM7)*LOOKUP(-(BM7)/12,-{99999,80,55,35,25,12,3,0,-9}*1000,{9,7,6,5,4,2,0.6,0,0}*5%)-LOOKUP(-(BM7)/12,-{99999,80,55,35,25,12,3,0,-9}*1000,{1516,716,441,266,141,21,0,0}*10),2))} -> 0 | BO7: =基本信息!EH7 -> 0 | BP7: {=IFERROR(ROUND(MAX((基本信息!EH7-基本信息!EI7)*{0.03,0.1,0.2,0.25,0.3,0.35,0.45}-12*{0,210,1410,2660,4410,7160,15160},0),2),0)} -> 0 | BQ7: =基本信息!EK7 -> 0 | BR7: {=ROUND((BQ7)*LOOKUP(-BQ7,-{99999,96,66,42,30,14.4,3.6,0,-9}*10000,{9,7,6,5,4,2,0.6,0,0}*5%)-LOOKUP(-BQ7,-{99999,96,66,42,30,14.4,3.6,0,-9}*10000,{18192,8592,5292,3192,1692,252,0,0}*10),2)} -> 0 | BS7: =SUM(C7:J7)+SUM(O7:W7)+Y7+AY7+BF7+BK7+BM7+BO7+BH7+BJ7+BI7+BQ7 -> 0 | BT7: =IF(基本信息!P7="税前",SUM(K7:N7)+SUM(X7,Z7:AH7)+AX7+BG7+BL7+BN7+BP7+BR7,SUM(K7:N7,X7,BL7,BN7,BP7,BR7)) -> 0 | BU7: =ROUND(BS7-BT7,2) -> 0 | BV7: =IF(VLOOKUP(基本信息!$H7,各地政策!$A:$X,21,0)="进位",ROUNDUP(基本信息!AF7*基本信息!AU7,VLOOKUP(基本信息!$H7,各地政策!$A:$X,20,0)),IF(VLOOKUP(基本信息!$H7,各地政策!$A:$X,21,0)="四舍五入",ROUND(基本信息!AF7*基本信息!AU7,VLOOKUP(基本信息!$H7,各地政策!$A:$X,20,0)),ROUND(基本信息!AF7*基本信息!AU7-IF(VLOOKUP(基本信息!$H7,各地政策!$A:$X,20,0)=0,0.5,IF(VLOOKUP(基本信息!$H7,各地政策!$A:$X,20,0)=1,0.05,0.005)),VLOOKUP(基本信息!$H7,各地政策!$A:$X,20,0)))) -> #N/A | BW7: =IF(VLOOKUP(基本信息!$H7,各地政策!$A:$X,21,0)="进位",ROUNDUP(基本信息!AG7*基本信息!AV7,VLOOKUP(基本信息!$H7,各地政策!$A:$X,20,0)),IF(VLOOKUP(基本信息!$H7,各地政策!$A:$X,21,0)="四舍五入",ROUND(基本信息!AG7*基本信息!AV7,VLOOKUP(基本信息!$H7,各地政策!$A:$X,20,0)),ROUND(基本信息!AG7*基本信息!AV7-IF(VLOOKUP(基本信息!$H7,各地政策!$A:$X,20,0)=0,0.5,IF(VLOOKUP(基本信息!$H7,各地政策!$A:$X,20,0)=1,0.05,0.005)),VLOOKUP(基本信息!$H7,各地政策!$A:$X,20,0))))+基本信息!BC7 -> #N/A | BX7: =IF(VLOOKUP(基本信息!$H7,各地政策!$A:$X,21,0)="进位",ROUNDUP(基本信息!AH7*基本信息!AW7,VLOOKUP(基本信息!$H7,各地政策!$A:$X,20,0)),IF(VLOOKUP(基本信息!$H7,各地政策!$A:$X,21,0)="四舍五入",ROUND(基本信息!AH7*基本信息!AW7,VLOOKUP(基本信息!$H7,各地政策!$A:$X,20,0)),ROUND(基本信息!AH7*基本信息!AW7-IF(VLOOKUP(基本信息!$H7,各地政策!$A:$X,20,0)=0,0.5,IF(VLOOKUP(基本信息!$H7,各地政策!$A:$X,20,0)=1,0.05,0.005)),VLOOKUP(基本信息!$H7,各地政策!$A:$X,20,0)))) -> #N/A | BY7: =IF(VLOOKUP(基本信息!$H7,各地政策!$A:$X,21,0)="进位",ROUNDUP(基本信息!AI7*基本信息!AX7,VLOOKUP(基本信息!$H7,各地政策!$A:$X,20,0)),IF(VLOOKUP(基本信息!$H7,各地政策!$A:$X,21,0)="四舍五入",ROUND(基本信息!AI7*基本信息!AX7,VLOOKUP(基本信息!$H7,各地政策!$A:$X,20,0)),ROUND(基本信息!AI7*基本信息!AX7-IF(VLOOKUP(基本信息!$H7,各地政策!$A:$X,20,0)=0,0.5,IF(VLOOKUP(基本信息!$H7,各地政策!$A:$X,20,0)=1,0.05,0.005)),VLOOKUP(基本信息!$H7,各地政策!$A:$X,20,0)))) -> #N/A | BZ7: =IF(VLOOKUP(基本信息!$H7,各地政策!$A:$X,21,0)="进位",ROUNDUP(基本信息!AJ7*基本信息!AY7,VLOOKUP(基本信息!$H7,各地政策!$A:$X,20,0)),IF(VLOOKUP(基本信息!$H7,各地政策!$A:$X,21,0)="四舍五入",ROUND(基本信息!AJ7*基本信息!AY7,VLOOKUP(基本信息!$H7,各地政策!$A:$X,20,0)),ROUND(基本信息!AJ7*基本信息!AY7-IF(VLOOKUP(基本信息!$H7,各地政策!$A:$X,20,0)=0,0.5,IF(VLOOKUP(基本信息!$H7,各地政策!$A:$X,20,0)=1,0.05,0.005)),VLOOKUP(基本信息!$H7,各地政策!$A:$X,20,0))))+基本信息!BD7 -> #N/A | CA7: =IF(VLOOKUP(基本信息!$H7,各地政策!$A:$X,21,0)="进位",ROUNDUP(基本信息!AK7*基本信息!AZ7+基本信息!BE7,VLOOKUP(基本信息!$H7,各地政策!$A:$X,20,0)),IF(VLOOKUP(基本信息!$H7,各地政策!$A:$X,21,0)="四舍五入",ROUND(基本信息!AK7*基本信息!AZ7+基本信息!BE7,VLOOKUP(基本信息!$H7,各地政策!$A:$X,20,0)),ROUND(基本信息!AK7*基本信息!AZ7+基本信息!BE7-IF(VLOOKUP(基本信息!$H7,各地政策!$A:$X,20,0)=0,0.5,IF(VLOOKUP(基本信息!$H7,各地政策!$A:$X,20,0)=1,0.05,0.005)),VLOOKUP(基本信息!$H7,各地政策!$A:$X,20,0)))) -> #N/A | CB7: =IF(VLOOKUP(基本信息!$I7,各地政策!$A:$X,24,0)="进位",ROUNDUP(基本信息!AL7*(基本信息!BA7),VLOOKUP(基本信息!$I7,各地政策!$A:$X,23,0)),IF(VLOOKUP(基本信息!$I7,各地政策!$A:$X,24,0)="四舍五入",ROUND(基本信息!AL7*(基本信息!BA7),VLOOKUP(基本信息!$I7,各地政策!$A:$X,23,0)),ROUND(基本信息!AL7*(基本信息!BA7)-IF(VLOOKUP(基本信息!$I7,各地政策!$A:$X,23,0)=0,0.5,IF(VLOOKUP(基本信息!$I7,各地政策!$A:$X,23,0)=1,0.05,0.005)),VLOOKUP(基本信息!$I7,各地政策!$A:$X,23,0)))) -> #N/A | CC7: =IF(VLOOKUP(基本信息!$I7,各地政策!$A:$X,24,0)="进位",ROUNDUP(基本信息!AM7*(基本信息!BB7),VLOOKUP(基本信息!$I7,各地政策!$A:$X,23,0)),IF(VLOOKUP(基本信息!$I7,各地政策!$A:$X,24,0)="四舍五入",ROUND(基本信息!AM7*(基本信息!BB7),VLOOKUP(基本信息!$I7,各地政策!$A:$X,23,0)),ROUND(基本信息!AM7*(基本信息!BB7)-IF(VLOOKUP(基本信息!$I7,各地政策!$A:$X,23,0)=0,0.5,IF(VLOOKUP(基本信息!$I7,各地政策!$A:$X,23,0)=1,0.05,0.005)),VLOOKUP(基本信息!$I7,各地政策!$A:$X,23,0)))) -> #N/A | CD7: =AX7+BE7+IFERROR(VLOOKUP($A7,YTD!$A:$CD,82,0),0) -> 0 | CE7: =基本信息!CT7 -> 0 | CF7: ='S-Payroll Report'!X13 -> 0 | CG7: ='S-Payroll Report'!AD13 -> 0 | CH7: ='S-Payroll Report'!AC13 -> 0 | CI7: ='S-Payroll Report'!AA13 -> 0 | CJ7: ='S-Payroll Report'!AF13 -> 0 | CK7: =基本信息!EM7+基本信息!EN7+基本信息!EO7 -> 0
A8: =IF(基本信息!B8="","",基本信息!B8) | B8: =IF(基本信息!C8="","",基本信息!C8) | C8: =基本信息!Q8+基本信息!R8*基本信息!CW8 -> 0 | D8: =基本信息!S8 -> 0 | E8: =基本信息!CX8 -> 0 | F8: =基本信息!CY8 -> 0 | G8: =基本信息!CZ8 -> 0 | H8: =ROUND(C8*基本信息!DA8*1.5/(21.75*8),2) -> 0 | I8: =ROUND(C8*基本信息!DB8*2/(21.75*8),2) -> 0 | J8: =ROUND(C8*基本信息!DC8*3/(21.75*8),2) -> 0 | K8: =ROUND(IF(AND(基本信息!DD8=23,基本信息!DE8=12),((C8+D8)*12/21.75+(C8+D8)-(C8+D8)*11/21.75)/2,IF(基本信息!DE8>基本信息!DD8/2,(C8+D8)-(C8+D8)*(基本信息!DD8-基本信息!DE8)/21.75,(C8+D8)*基本信息!DE8/21.75)),2) -> 0 | L8: =MAX(0,ROUND((C8+D8)*基本信息!DF8/21.75,2)) -> 0 | M8: =MAX(0,ROUND((C8+D8)*基本信息!DG8/21.75,2)) -> 0 | N8: =基本信息!DI8 -> 0 | O8: =基本信息!T8+基本信息!DJ8 -> 0 | P8: =基本信息!U8+基本信息!DK8 -> 0 | Q8: =基本信息!V8 -> 0 | R8: =基本信息!W8*基本信息!DL8 -> 0 | S8: =基本信息!X8*基本信息!DM8 -> 0 | T8: =基本信息!Y8*基本信息!DN8+基本信息!DO8 -> 0 | U8: =基本信息!Z8*基本信息!DP8 -> 0 | V8: =基本信息!AA8*基本信息!DQ8 -> 0 | W8: =基本信息!AD8+基本信息!DR8 -> 0 | X8: =基本信息!AE8+基本信息!DS8 -> 0 | Y8: =基本信息!DT8 -> 0 | Z8: =IF(VLOOKUP(基本信息!$H8,各地政策!$A:$X,21,0)="进位",ROUNDUP(基本信息!AF8*基本信息!AN8,VLOOKUP(基本信息!$H8,各地政策!$A:$X,20,0)),IF(VLOOKUP(基本信息!$H8,各地政策!$A:$X,21,0)="四舍五入",ROUND(基本信息!AF8*基本信息!AN8,VLOOKUP(基本信息!$H8,各地政策!$A:$X,20,0)),ROUND(基本信息!AF8*基本信息!AN8-IF(VLOOKUP(基本信息!$H8,各地政策!$A:$X,20,0)=0,0.5,IF(VLOOKUP(基本信息!$H8,各地政策!$A:$X,20,0)=1,0.05,0.005)),VLOOKUP(基本信息!$H8,各地政策!$A:$X,20,0)))) -> #N/A | AA8: =IF(VLOOKUP(基本信息!$H8,各地政策!$A:$X,21,0)="进位",ROUNDUP(基本信息!AG8*基本信息!AO8,VLOOKUP(基本信息!$H8,各地政策!$A:$X,20,0)),IF(VLOOKUP(基本信息!$H8,各地政策!$A:$X,21,0)="四舍五入",ROUND(基本信息!AG8*基本信息!AO8,VLOOKUP(基本信息!$H8,各地政策!$A:$X,20,0)),ROUND(基本信息!AG8*基本信息!AO8-IF(VLOOKUP(基本信息!$H8,各地政策!$A:$X,20,0)=0,0.5,IF(VLOOKUP(基本信息!$H8,各地政策!$A:$X,20,0)=1,0.05,0.005)),VLOOKUP(基本信息!$H8,各地政策!$A:$X,20,0))))+基本信息!AT8 -> #N/A | AB8: =IF(VLOOKUP(基本信息!$H8,各地政策!$A:$X,21,0)="进位",ROUNDUP(基本信息!AH8*基本信息!AP8,VLOOKUP(基本信息!$H8,各地政策!$A:$X,20,0)),IF(VLOOKUP(基本信息!$H8,各地政策!$A:$X,21,0)="四舍五入",ROUND(基本信息!AH8*基本信息!AP8,VLOOKUP(基本信息!$H8,各地政策!$A:$X,20,0)),ROUND(基本信息!AH8*基本信息!AP8-IF(VLOOKUP(基本信息!$H8,各地政策!$A:$X,20,0)=0,0.5,IF(VLOOKUP(基本信息!$H8,各地政策!$A:$X,20,0)=1,0.05,0.005)),VLOOKUP(基本信息!$H8,各地政策!$A:$X,20,0)))) -> #N/A | AC8: =IF(VLOOKUP(基本信息!$I8,各地政策!$A:$X,24,0)="进位",ROUNDUP(基本信息!AL8*基本信息!AQ8,VLOOKUP(基本信息!$I8,各地政策!$A:$X,23,0)),IF(VLOOKUP(基本信息!$I8,各地政策!$A:$X,24,0)="四舍五入",ROUND(基本信息!AL8*基本信息!AQ8,VLOOKUP(基本信息!$I8,各地政策!$A:$X,23,0)),ROUND(基本信息!AL8*基本信息!AQ8-IF(VLOOKUP(基本信息!$I8,各地政策!$A:$X,23,0)=0,0.5,IF(VLOOKUP(基本信息!$I8,各地政策!$A:$X,23,0)=1,0.05,0.005)),VLOOKUP(基本信息!$I8,各地政策!$A:$X,23,0)))) -> #N/A | AD8: =IF(VLOOKUP(基本信息!$I8,各地政策!$A:$X,24,0)="进位",ROUNDUP(基本信息!AM8*基本信息!AR8,VLOOKUP(基本信息!$I8,各地政策!$A:$X,23,0)),IF(VLOOKUP(基本信息!$I8,各地政策!$A:$X,24,0)="四舍五入",ROUND(基本信息!AM8*基本信息!AR8,VLOOKUP(基本信息!$I8,各地政策!$A:$X,23,0)),ROUND(基本信息!AM8*基本信息!AR8-IF(VLOOKUP(基本信息!$I8,各地政策!$A:$X,23,0)=0,0.5,IF(VLOOKUP(基本信息!$I8,各地政策!$A:$X,23,0)=1,0.05,0.005)),VLOOKUP(基本信息!$I8,各地政策!$A:$X,23,0)))) -> #N/A | AE8: =基本信息!DU8+基本信息!DV8+基本信息!DW8 -> 0 | AF8: =基本信息!DX8 -> 0 | AG8: =基本信息!BF8 -> 0 | AH8: =基本信息!BG8 -> 0 | AI8: =基本信息!BH8+基本信息!DZ8 -> 0 | AJ8: =IF(基本信息!P8="税前",SUM(C8:J8)+SUM(O8:W8)-SUM(K8:N8)-SUM(X8:X8)+Y8-AG8-AH8+AI8,0) -> 0 | AK8: =IF(基本信息!J8=3,MAX(AJ8*0.2,800),5000) -> 5000 | AL8: =IF(基本信息!P8="税前",SUMIF(YTD!$A$2:$A$2386,$A8,YTD!$BB$2:$BB$2386)+SUMIF(YTD!$A$2:$A$2386,$A8,YTD!$AM$2:$AM$2386)+AJ8,0) -> 0 | AM8: =SUMIF(YTD!$A$2:$A$2386,$A8,YTD!$AM$2:$AM$2386)+SUM(Z8:AF8) -> #N/A | AN8: =SUMIF(YTD!$A$2:$A$2386,$A8,YTD!$AN$2:$AN$2386)+计算结果!AK8 -> 5000 | AO8: =基本信息!CO8 -> 0 | AP8: =基本信息!CP8 -> 0 | AQ8: =基本信息!CQ8 -> 0 | AR8: =基本信息!CR8 -> 0 | AS8: =基本信息!CS8 -> 0 | AT8: {=SUMPRODUCT((基本信息!$B$2:$B$2375=$A8)*(基本信息!$CU$2:$CV$2375))+SUMIF(YTD!$A$2:$A$2386,$A8,YTD!$AT$2:$AT$2386)} -> 0 | AU8: =SUM(AN8:AT8,CE8) -> 5000 | AV8: =IF(基本信息!P8="税前",AL8-AM8-AU8,0) -> 0 | AW8: {=IF(基本信息!J8=1,MAX((AV8)*{0.03,0.1,0.2,0.25,0.3,0.35,0.45}-12*{0,210,1410,2660,4410,7160,15160},0),IF(基本信息!J8=4,MAX((AL8-AL8*0.2-AU8)*{0.03,0.1,0.2,0.25,0.3,0.35,0.45}-12*{0,210,1410,2660,4410,7160,15160},0),0))} -> 0 | AX8: {=MAX(ROUND(IF(基本信息!J8=3,MAX((AJ8-IF(AJ8<4000,800,AJ8*0.2))*10%*{2,3,4}-1000*{0,2,7},0),IF(基本信息!J8=2,MAX((AJ8-SUM(Z8:AG8)-AK8)*{0.03,0.1,0.2,0.25,0.3,0.35,0.45}-{0,210,1410,2660,4410,7160,15160},0),IF(基本信息!P8="税前",AW8-ROUND(SUMIF(YTD!$A$2:$A$2386,$A8,YTD!$CD$2:$CD$2386),2),0))),2),0)} -> 0 | AY8: =基本信息!BI8+基本信息!EA8 -> 0 | AZ8: =IF(基本信息!P8="税前",0,SUM(C8:J8)-SUM(K8:N8)+SUM(O8:W8)-X8+Y8+AI8)+AY8 -> 0 | BA8: =IF(OR(基本信息!J8=1,基本信息!J8=4),IF(基本信息!P8="税前",AL8-AM8-AW8+AZ8,AZ8+SUMIF(YTD!$A$2:$A$2386,$A8,YTD!$BA$2:$BA$2386)),IF(基本信息!P8="税前",AJ8-SUM(Z8:AG8)-AX8+AZ8+SUMIF(YTD!$A$2:$A$2386,$A8,YTD!$BA$2:$BA$2386),AZ8)) -> 0 | BB8: {=IF(基本信息!J8=3,LOOKUP(AJ8-AX8+AZ8,{0,800,3360,21000,49500},(AJ8-AX8+AZ8-{0,160,0,2000,7000})*{1,5,25,25,25}/{1,4,21,19,17}),IF(基本信息!J8=2,MAX((BA8-AK8-10*{0,21,141,266,441,716,1516})/(1-5%*{0.6,2,4,5,6,7,9})+AK8,BA8),IF(基本信息!J8=4,MAX((BA8-AU8-(AL8*0.2)-120*{0,21,141,266,441,716,1516})/(1-5%*{0.6,2,4,5,6,7,9})+AU8+(AL8*0.2),BA8),MAX((BA8-AU8-120*{0,21,141,266,441,716,1516})/(1-5%*{0.6,2,4,5,6,7,9})+AU8,BA8))))} -> 0 | BC8: =IF(OR(基本信息!J8=1,基本信息!J8=4),BB8-IFERROR(VLOOKUP($A8,YTD!$A:$BB,54,0),0),BB8)+SUM(Z8:AF8) -> #N/A | BD8: {=IF(基本信息!J8=4,MAX((BB8-BB8*0.2-AU8)*{0.03,0.1,0.2,0.25,0.3,0.35,0.45}-12*{0,210,1410,2660,4410,7160,15160},0),IF(基本信息!J8=3,MAX((BB8-IF(BB8<4000,800,BB8*0.2))*10%*{2,3,4}-1000*{0,2,7},0),IF(基本信息!J8=2,MAX((BB8-AK8)*{0.03,0.1,0.2,0.25,0.3,0.35,0.45}-{0,210,1410,2660,4410,7160,15160},0),MAX((BB8-AU8)*{0.03,0.1,0.2,0.25,0.3,0.35,0.45}-12*{0,210,1410,2660,4410,7160,15160},0))))} -> 0 | BE8: =MAX(ROUND(IF(基本信息!J8=1,BD8-AX8-ROUND(SUMIF(YTD!$A$2:$A$2386,$A8,YTD!$CD$2:$CD$2386),2),IF(基本信息!J8=4,BD8-AX8-ROUND(SUMIF(YTD!$A$2:$A$2386,$A8,YTD!$CD$2:$CD$2386),2),BD8-AX8)),2),0) -> 0 | BF8: =IF(YEARFRAC(基本信息!AB8,TODAY())*12-1<192,基本信息!AC8,0) -> 0 | BG8: =IF(VLOOKUP(基本信息!$I8,各地政策!$A:$X,24,0)="进位",ROUNDUP(基本信息!AM8*基本信息!AS8,VLOOKUP(基本信息!$I8,各地政策!$A:$X,23,0)),IF(VLOOKUP(基本信息!$I8,各地政策!$A:$X,24,0)="四舍五入",ROUND(基本信息!AM8*基本信息!AS8,VLOOKUP(基本信息!$I8,各地政策!$A:$X,23,0)),ROUND(基本信息!AM8*基本信息!AS8-IF(VLOOKUP(基本信息!$I8,各地政策!$A:$X,23,0)=0,0.5,IF(VLOOKUP(基本信息!$I8,各地政策!$A:$X,23,0)=1,0.05,0.005)),VLOOKUP(基本信息!$I8,各地政策!$A:$X,23,0)))) -> #N/A | BH8: =基本信息!EB8 -> 0 | BI8: =基本信息!EC8 -> 0 | BJ8: =基本信息!BJ8 -> 0 | BK8: =基本信息!BL8+基本信息!DY8+基本信息!ED8 -> 0 | BL8: =基本信息!BK8+基本信息!EE8 -> 0 | BM8: =基本信息!EG8 -> 0 | BN8: {=IF(基本信息!J8=2,MAX((BM8/6)*{0.03,0.1,0.2,0.25,0.3,0.35,0.45}-{0,210,1410,2660,4410,7160,15160},0)*6,ROUND((BM8)*LOOKUP(-(BM8)/12,-{99999,80,55,35,25,12,3,0,-9}*1000,{9,7,6,5,4,2,0.6,0,0}*5%)-LOOKUP(-(BM8)/12,-{99999,80,55,35,25,12,3,0,-9}*1000,{1516,716,441,266,141,21,0,0}*10),2))} -> 0 | BO8: =基本信息!EH8 -> 0 | BP8: {=IFERROR(ROUND(MAX((基本信息!EH8-基本信息!EI8)*{0.03,0.1,0.2,0.25,0.3,0.35,0.45}-12*{0,210,1410,2660,4410,7160,15160},0),2),0)} -> 0 | BQ8: =基本信息!EK8 -> 0 | BR8: {=ROUND((BQ8)*LOOKUP(-BQ8,-{99999,96,66,42,30,14.4,3.6,0,-9}*10000,{9,7,6,5,4,2,0.6,0,0}*5%)-LOOKUP(-BQ8,-{99999,96,66,42,30,14.4,3.6,0,-9}*10000,{18192,8592,5292,3192,1692,252,0,0}*10),2)} -> 0 | BS8: =SUM(C8:J8)+SUM(O8:W8)+Y8+AY8+BF8+BK8+BM8+BO8+BH8+BJ8+BI8+BQ8 -> 0 | BT8: =IF(基本信息!P8="税前",SUM(K8:N8)+SUM(X8,Z8:AH8)+AX8+BG8+BL8+BN8+BP8+BR8,SUM(K8:N8,X8,BL8,BN8,BP8,BR8)) -> 0 | BU8: =ROUND(BS8-BT8,2) -> 0 | BV8: =IF(VLOOKUP(基本信息!$H8,各地政策!$A:$X,21,0)="进位",ROUNDUP(基本信息!AF8*基本信息!AU8,VLOOKUP(基本信息!$H8,各地政策!$A:$X,20,0)),IF(VLOOKUP(基本信息!$H8,各地政策!$A:$X,21,0)="四舍五入",ROUND(基本信息!AF8*基本信息!AU8,VLOOKUP(基本信息!$H8,各地政策!$A:$X,20,0)),ROUND(基本信息!AF8*基本信息!AU8-IF(VLOOKUP(基本信息!$H8,各地政策!$A:$X,20,0)=0,0.5,IF(VLOOKUP(基本信息!$H8,各地政策!$A:$X,20,0)=1,0.05,0.005)),VLOOKUP(基本信息!$H8,各地政策!$A:$X,20,0)))) -> #N/A | BW8: =IF(VLOOKUP(基本信息!$H8,各地政策!$A:$X,21,0)="进位",ROUNDUP(基本信息!AG8*基本信息!AV8,VLOOKUP(基本信息!$H8,各地政策!$A:$X,20,0)),IF(VLOOKUP(基本信息!$H8,各地政策!$A:$X,21,0)="四舍五入",ROUND(基本信息!AG8*基本信息!AV8,VLOOKUP(基本信息!$H8,各地政策!$A:$X,20,0)),ROUND(基本信息!AG8*基本信息!AV8-IF(VLOOKUP(基本信息!$H8,各地政策!$A:$X,20,0)=0,0.5,IF(VLOOKUP(基本信息!$H8,各地政策!$A:$X,20,0)=1,0.05,0.005)),VLOOKUP(基本信息!$H8,各地政策!$A:$X,20,0))))+基本信息!BC8 -> #N/A | BX8: =IF(VLOOKUP(基本信息!$H8,各地政策!$A:$X,21,0)="进位",ROUNDUP(基本信息!AH8*基本信息!AW8,VLOOKUP(基本信息!$H8,各地政策!$A:$X,20,0)),IF(VLOOKUP(基本信息!$H8,各地政策!$A:$X,21,0)="四舍五入",ROUND(基本信息!AH8*基本信息!AW8,VLOOKUP(基本信息!$H8,各地政策!$A:$X,20,0)),ROUND(基本信息!AH8*基本信息!AW8-IF(VLOOKUP(基本信息!$H8,各地政策!$A:$X,20,0)=0,0.5,IF(VLOOKUP(基本信息!$H8,各地政策!$A:$X,20,0)=1,0.05,0.005)),VLOOKUP(基本信息!$H8,各地政策!$A:$X,20,0)))) -> #N/A | BY8: =IF(VLOOKUP(基本信息!$H8,各地政策!$A:$X,21,0)="进位",ROUNDUP(基本信息!AI8*基本信息!AX8,VLOOKUP(基本信息!$H8,各地政策!$A:$X,20,0)),IF(VLOOKUP(基本信息!$H8,各地政策!$A:$X,21,0)="四舍五入",ROUND(基本信息!AI8*基本信息!AX8,VLOOKUP(基本信息!$H8,各地政策!$A:$X,20,0)),ROUND(基本信息!AI8*基本信息!AX8-IF(VLOOKUP(基本信息!$H8,各地政策!$A:$X,20,0)=0,0.5,IF(VLOOKUP(基本信息!$H8,各地政策!$A:$X,20,0)=1,0.05,0.005)),VLOOKUP(基本信息!$H8,各地政策!$A:$X,20,0)))) -> #N/A | BZ8: =IF(VLOOKUP(基本信息!$H8,各地政策!$A:$X,21,0)="进位",ROUNDUP(基本信息!AJ8*基本信息!AY8,VLOOKUP(基本信息!$H8,各地政策!$A:$X,20,0)),IF(VLOOKUP(基本信息!$H8,各地政策!$A:$X,21,0)="四舍五入",ROUND(基本信息!AJ8*基本信息!AY8,VLOOKUP(基本信息!$H8,各地政策!$A:$X,20,0)),ROUND(基本信息!AJ8*基本信息!AY8-IF(VLOOKUP(基本信息!$H8,各地政策!$A:$X,20,0)=0,0.5,IF(VLOOKUP(基本信息!$H8,各地政策!$A:$X,20,0)=1,0.05,0.005)),VLOOKUP(基本信息!$H8,各地政策!$A:$X,20,0))))+基本信息!BD8 -> #N/A | CA8: =IF(VLOOKUP(基本信息!$H8,各地政策!$A:$X,21,0)="进位",ROUNDUP(基本信息!AK8*基本信息!AZ8+基本信息!BE8,VLOOKUP(基本信息!$H8,各地政策!$A:$X,20,0)),IF(VLOOKUP(基本信息!$H8,各地政策!$A:$X,21,0)="四舍五入",ROUND(基本信息!AK8*基本信息!AZ8+基本信息!BE8,VLOOKUP(基本信息!$H8,各地政策!$A:$X,20,0)),ROUND(基本信息!AK8*基本信息!AZ8+基本信息!BE8-IF(VLOOKUP(基本信息!$H8,各地政策!$A:$X,20,0)=0,0.5,IF(VLOOKUP(基本信息!$H8,各地政策!$A:$X,20,0)=1,0.05,0.005)),VLOOKUP(基本信息!$H8,各地政策!$A:$X,20,0)))) -> #N/A | CB8: =IF(VLOOKUP(基本信息!$I8,各地政策!$A:$X,24,0)="进位",ROUNDUP(基本信息!AL8*(基本信息!BA8),VLOOKUP(基本信息!$I8,各地政策!$A:$X,23,0)),IF(VLOOKUP(基本信息!$I8,各地政策!$A:$X,24,0)="四舍五入",ROUND(基本信息!AL8*(基本信息!BA8),VLOOKUP(基本信息!$I8,各地政策!$A:$X,23,0)),ROUND(基本信息!AL8*(基本信息!BA8)-IF(VLOOKUP(基本信息!$I8,各地政策!$A:$X,23,0)=0,0.5,IF(VLOOKUP(基本信息!$I8,各地政策!$A:$X,23,0)=1,0.05,0.005)),VLOOKUP(基本信息!$I8,各地政策!$A:$X,23,0)))) -> #N/A | CC8: =IF(VLOOKUP(基本信息!$I8,各地政策!$A:$X,24,0)="进位",ROUNDUP(基本信息!AM8*(基本信息!BB8),VLOOKUP(基本信息!$I8,各地政策!$A:$X,23,0)),IF(VLOOKUP(基本信息!$I8,各地政策!$A:$X,24,0)="四舍五入",ROUND(基本信息!AM8*(基本信息!BB8),VLOOKUP(基本信息!$I8,各地政策!$A:$X,23,0)),ROUND(基本信息!AM8*(基本信息!BB8)-IF(VLOOKUP(基本信息!$I8,各地政策!$A:$X,23,0)=0,0.5,IF(VLOOKUP(基本信息!$I8,各地政策!$A:$X,23,0)=1,0.05,0.005)),VLOOKUP(基本信息!$I8,各地政策!$A:$X,23,0)))) -> #N/A | CD8: =AX8+BE8+IFERROR(VLOOKUP($A8,YTD!$A:$CD,82,0),0) -> 0 | CE8: =基本信息!CT8 -> 0 | CF8: ='S-Payroll Report'!X14 -> 0 | CG8: ='S-Payroll Report'!AD14 -> 0 | CH8: ='S-Payroll Report'!AC14 -> 0 | CI8: ='S-Payroll Report'!AA14 -> 0 | CJ8: ='S-Payroll Report'!AF14 -> 0 | CK8: =基本信息!EM8+基本信息!EN8+基本信息!EO8 -> 0
A9: =IF(基本信息!B9="","",基本信息!B9) | B9: =IF(基本信息!C9="","",基本信息!C9) | C9: =基本信息!Q9+基本信息!R9*基本信息!CW9 -> 0 | D9: =基本信息!S9 -> 0 | E9: =基本信息!CX9 -> 0 | F9: =基本信息!CY9 -> 0 | G9: =基本信息!CZ9 -> 0 | H9: =ROUND(C9*基本信息!DA9*1.5/(21.75*8),2) -> 0 | I9: =ROUND(C9*基本信息!DB9*2/(21.75*8),2) -> 0 | J9: =ROUND(C9*基本信息!DC9*3/(21.75*8),2) -> 0 | K9: =ROUND(IF(AND(基本信息!DD9=23,基本信息!DE9=12),((C9+D9)*12/21.75+(C9+D9)-(C9+D9)*11/21.75)/2,IF(基本信息!DE9>基本信息!DD9/2,(C9+D9)-(C9+D9)*(基本信息!DD9-基本信息!DE9)/21.75,(C9+D9)*基本信息!DE9/21.75)),2) -> 0 | L9: =MAX(0,ROUND((C9+D9)*基本信息!DF9/21.75,2)) -> 0 | M9: =MAX(0,ROUND((C9+D9)*基本信息!DG9/21.75,2)) -> 0 | N9: =基本信息!DI9 -> 0 | O9: =基本信息!T9+基本信息!DJ9 -> 0 | P9: =基本信息!U9+基本信息!DK9 -> 0 | Q9: =基本信息!V9 -> 0 | R9: =基本信息!W9*基本信息!DL9 -> 0 | S9: =基本信息!X9*基本信息!DM9 -> 0 | T9: =基本信息!Y9*基本信息!DN9+基本信息!DO9 -> 0 | U9: =基本信息!Z9*基本信息!DP9 -> 0 | V9: =基本信息!AA9*基本信息!DQ9 -> 0 | W9: =基本信息!AD9+基本信息!DR9 -> 0 | X9: =基本信息!AE9+基本信息!DS9 -> 0 | Y9: =基本信息!DT9 -> 0 | Z9: =IF(VLOOKUP(基本信息!$H9,各地政策!$A:$X,21,0)="进位",ROUNDUP(基本信息!AF9*基本信息!AN9,VLOOKUP(基本信息!$H9,各地政策!$A:$X,20,0)),IF(VLOOKUP(基本信息!$H9,各地政策!$A:$X,21,0)="四舍五入",ROUND(基本信息!AF9*基本信息!AN9,VLOOKUP(基本信息!$H9,各地政策!$A:$X,20,0)),ROUND(基本信息!AF9*基本信息!AN9-IF(VLOOKUP(基本信息!$H9,各地政策!$A:$X,20,0)=0,0.5,IF(VLOOKUP(基本信息!$H9,各地政策!$A:$X,20,0)=1,0.05,0.005)),VLOOKUP(基本信息!$H9,各地政策!$A:$X,20,0)))) -> #N/A | AA9: =IF(VLOOKUP(基本信息!$H9,各地政策!$A:$X,21,0)="进位",ROUNDUP(基本信息!AG9*基本信息!AO9,VLOOKUP(基本信息!$H9,各地政策!$A:$X,20,0)),IF(VLOOKUP(基本信息!$H9,各地政策!$A:$X,21,0)="四舍五入",ROUND(基本信息!AG9*基本信息!AO9,VLOOKUP(基本信息!$H9,各地政策!$A:$X,20,0)),ROUND(基本信息!AG9*基本信息!AO9-IF(VLOOKUP(基本信息!$H9,各地政策!$A:$X,20,0)=0,0.5,IF(VLOOKUP(基本信息!$H9,各地政策!$A:$X,20,0)=1,0.05,0.005)),VLOOKUP(基本信息!$H9,各地政策!$A:$X,20,0))))+基本信息!AT9 -> #N/A | AB9: =IF(VLOOKUP(基本信息!$H9,各地政策!$A:$X,21,0)="进位",ROUNDUP(基本信息!AH9*基本信息!AP9,VLOOKUP(基本信息!$H9,各地政策!$A:$X,20,0)),IF(VLOOKUP(基本信息!$H9,各地政策!$A:$X,21,0)="四舍五入",ROUND(基本信息!AH9*基本信息!AP9,VLOOKUP(基本信息!$H9,各地政策!$A:$X,20,0)),ROUND(基本信息!AH9*基本信息!AP9-IF(VLOOKUP(基本信息!$H9,各地政策!$A:$X,20,0)=0,0.5,IF(VLOOKUP(基本信息!$H9,各地政策!$A:$X,20,0)=1,0.05,0.005)),VLOOKUP(基本信息!$H9,各地政策!$A:$X,20,0)))) -> #N/A | AC9: =IF(VLOOKUP(基本信息!$I9,各地政策!$A:$X,24,0)="进位",ROUNDUP(基本信息!AL9*基本信息!AQ9,VLOOKUP(基本信息!$I9,各地政策!$A:$X,23,0)),IF(VLOOKUP(基本信息!$I9,各地政策!$A:$X,24,0)="四舍五入",ROUND(基本信息!AL9*基本信息!AQ9,VLOOKUP(基本信息!$I9,各地政策!$A:$X,23,0)),ROUND(基本信息!AL9*基本信息!AQ9-IF(VLOOKUP(基本信息!$I9,各地政策!$A:$X,23,0)=0,0.5,IF(VLOOKUP(基本信息!$I9,各地政策!$A:$X,23,0)=1,0.05,0.005)),VLOOKUP(基本信息!$I9,各地政策!$A:$X,23,0)))) -> #N/A | AD9: =IF(VLOOKUP(基本信息!$I9,各地政策!$A:$X,24,0)="进位",ROUNDUP(基本信息!AM9*基本信息!AR9,VLOOKUP(基本信息!$I9,各地政策!$A:$X,23,0)),IF(VLOOKUP(基本信息!$I9,各地政策!$A:$X,24,0)="四舍五入",ROUND(基本信息!AM9*基本信息!AR9,VLOOKUP(基本信息!$I9,各地政策!$A:$X,23,0)),ROUND(基本信息!AM9*基本信息!AR9-IF(VLOOKUP(基本信息!$I9,各地政策!$A:$X,23,0)=0,0.5,IF(VLOOKUP(基本信息!$I9,各地政策!$A:$X,23,0)=1,0.05,0.005)),VLOOKUP(基本信息!$I9,各地政策!$A:$X,23,0)))) -> #N/A | AE9: =基本信息!DU9+基本信息!DV9+基本信息!DW9 -> 0 | AF9: =基本信息!DX9 -> 0 | AG9: =基本信息!BF9 -> 0 | AH9: =基本信息!BG9 -> 0 | AI9: =基本信息!BH9+基本信息!DZ9 -> 0 | AJ9: =IF(基本信息!P9="税前",SUM(C9:J9)+SUM(O9:W9)-SUM(K9:N9)-SUM(X9:X9)+Y9-AG9-AH9+AI9,0) -> 0 | AK9: =IF(基本信息!J9=3,MAX(AJ9*0.2,800),5000) -> 5000 | AL9: =IF(基本信息!P9="税前",SUMIF(YTD!$A$2:$A$2386,$A9,YTD!$BB$2:$BB$2386)+SUMIF(YTD!$A$2:$A$2386,$A9,YTD!$AM$2:$AM$2386)+AJ9,0) -> 0 | AM9: =SUMIF(YTD!$A$2:$A$2386,$A9,YTD!$AM$2:$AM$2386)+SUM(Z9:AF9) -> #N/A | AN9: =SUMIF(YTD!$A$2:$A$2386,$A9,YTD!$AN$2:$AN$2386)+计算结果!AK9 -> 5000 | AO9: =基本信息!CO9 -> 0 | AP9: =基本信息!CP9 -> 0 | AQ9: =基本信息!CQ9 -> 0 | AR9: =基本信息!CR9 -> 0 | AS9: =基本信息!CS9 -> 0 | AT9: {=SUMPRODUCT((基本信息!$B$2:$B$2375=$A9)*(基本信息!$CU$2:$CV$2375))+SUMIF(YTD!$A$2:$A$2386,$A9,YTD!$AT$2:$AT$2386)} -> 0 | AU9: =SUM(AN9:AT9,CE9) -> 5000 | AV9: =IF(基本信息!P9="税前",AL9-AM9-AU9,0) -> 0 | AW9: {=IF(基本信息!J9=1,MAX((AV9)*{0.03,0.1,0.2,0.25,0.3,0.35,0.45}-12*{0,210,1410,2660,4410,7160,15160},0),IF(基本信息!J9=4,MAX((AL9-AL9*0.2-AU9)*{0.03,0.1,0.2,0.25,0.3,0.35,0.45}-12*{0,210,1410,2660,4410,7160,15160},0),0))} -> 0 | AX9: {=MAX(ROUND(IF(基本信息!J9=3,MAX((AJ9-IF(AJ9<4000,800,AJ9*0.2))*10%*{2,3,4}-1000*{0,2,7},0),IF(基本信息!J9=2,MAX((AJ9-SUM(Z9:AG9)-AK9)*{0.03,0.1,0.2,0.25,0.3,0.35,0.45}-{0,210,1410,2660,4410,7160,15160},0),IF(基本信息!P9="税前",AW9-ROUND(SUMIF(YTD!$A$2:$A$2386,$A9,YTD!$CD$2:$CD$2386),2),0))),2),0)} -> 0 | AY9: =基本信息!BI9+基本信息!EA9 -> 0 | AZ9: =IF(基本信息!P9="税前",0,SUM(C9:J9)-SUM(K9:N9)+SUM(O9:W9)-X9+Y9+AI9)+AY9 -> 0 | BA9: =IF(OR(基本信息!J9=1,基本信息!J9=4),IF(基本信息!P9="税前",AL9-AM9-AW9+AZ9,AZ9+SUMIF(YTD!$A$2:$A$2386,$A9,YTD!$BA$2:$BA$2386)),IF(基本信息!P9="税前",AJ9-SUM(Z9:AG9)-AX9+AZ9+SUMIF(YTD!$A$2:$A$2386,$A9,YTD!$BA$2:$BA$2386),AZ9)) -> 0 | BB9: {=IF(基本信息!J9=3,LOOKUP(AJ9-AX9+AZ9,{0,800,3360,21000,49500},(AJ9-AX9+AZ9-{0,160,0,2000,7000})*{1,5,25,25,25}/{1,4,21,19,17}),IF(基本信息!J9=2,MAX((BA9-AK9-10*{0,21,141,266,441,716,1516})/(1-5%*{0.6,2,4,5,6,7,9})+AK9,BA9),IF(基本信息!J9=4,MAX((BA9-AU9-(AL9*0.2)-120*{0,21,141,266,441,716,1516})/(1-5%*{0.6,2,4,5,6,7,9})+AU9+(AL9*0.2),BA9),MAX((BA9-AU9-120*{0,21,141,266,441,716,1516})/(1-5%*{0.6,2,4,5,6,7,9})+AU9,BA9))))} -> 0 | BC9: =IF(OR(基本信息!J9=1,基本信息!J9=4),BB9-IFERROR(VLOOKUP($A9,YTD!$A:$BB,54,0),0),BB9)+SUM(Z9:AF9) -> #N/A | BD9: {=IF(基本信息!J9=4,MAX((BB9-BB9*0.2-AU9)*{0.03,0.1,0.2,0.25,0.3,0.35,0.45}-12*{0,210,1410,2660,4410,7160,15160},0),IF(基本信息!J9=3,MAX((BB9-IF(BB9<4000,800,BB9*0.2))*10%*{2,3,4}-1000*{0,2,7},0),IF(基本信息!J9=2,MAX((BB9-AK9)*{0.03,0.1,0.2,0.25,0.3,0.35,0.45}-{0,210,1410,2660,4410,7160,15160},0),MAX((BB9-AU9)*{0.03,0.1,0.2,0.25,0.3,0.35,0.45}-12*{0,210,1410,2660,4410,7160,15160},0))))} -> 0 | BE9: =MAX(ROUND(IF(基本信息!J9=1,BD9-AX9-ROUND(SUMIF(YTD!$A$2:$A$2386,$A9,YTD!$CD$2:$CD$2386),2),IF(基本信息!J9=4,BD9-AX9-ROUND(SUMIF(YTD!$A$2:$A$2386,$A9,YTD!$CD$2:$CD$2386),2),BD9-AX9)),2),0) -> 0 | BF9: =IF(YEARFRAC(基本信息!AB9,TODAY())*12-1<192,基本信息!AC9,0) -> 0 | BG9: =IF(VLOOKUP(基本信息!$I9,各地政策!$A:$X,24,0)="进位",ROUNDUP(基本信息!AM9*基本信息!AS9,VLOOKUP(基本信息!$I9,各地政策!$A:$X,23,0)),IF(VLOOKUP(基本信息!$I9,各地政策!$A:$X,24,0)="四舍五入",ROUND(基本信息!AM9*基本信息!AS9,VLOOKUP(基本信息!$I9,各地政策!$A:$X,23,0)),ROUND(基本信息!AM9*基本信息!AS9-IF(VLOOKUP(基本信息!$I9,各地政策!$A:$X,23,0)=0,0.5,IF(VLOOKUP(基本信息!$I9,各地政策!$A:$X,23,0)=1,0.05,0.005)),VLOOKUP(基本信息!$I9,各地政策!$A:$X,23,0)))) -> #N/A | BH9: =基本信息!EB9 -> 0 | BI9: =基本信息!EC9 -> 0 | BJ9: =基本信息!BJ9 -> 0 | BK9: =基本信息!BL9+基本信息!DY9+基本信息!ED9 -> 0 | BL9: =基本信息!BK9+基本信息!EE9 -> 0 | BM9: =基本信息!EG9 -> 0 | BN9: {=IF(基本信息!J9=2,MAX((BM9/6)*{0.03,0.1,0.2,0.25,0.3,0.35,0.45}-{0,210,1410,2660,4410,7160,15160},0)*6,ROUND((BM9)*LOOKUP(-(BM9)/12,-{99999,80,55,35,25,12,3,0,-9}*1000,{9,7,6,5,4,2,0.6,0,0}*5%)-LOOKUP(-(BM9)/12,-{99999,80,55,35,25,12,3,0,-9}*1000,{1516,716,441,266,141,21,0,0}*10),2))} -> 0 | BO9: =基本信息!EH9 -> 0 | BP9: {=IFERROR(ROUND(MAX((基本信息!EH9-基本信息!EI9)*{0.03,0.1,0.2,0.25,0.3,0.35,0.45}-12*{0,210,1410,2660,4410,7160,15160},0),2),0)} -> 0 | BQ9: =基本信息!EK9 -> 0 | BR9: {=ROUND((BQ9)*LOOKUP(-BQ9,-{99999,96,66,42,30,14.4,3.6,0,-9}*10000,{9,7,6,5,4,2,0.6,0,0}*5%)-LOOKUP(-BQ9,-{99999,96,66,42,30,14.4,3.6,0,-9}*10000,{18192,8592,5292,3192,1692,252,0,0}*10),2)} -> 0 | BS9: =SUM(C9:J9)+SUM(O9:W9)+Y9+AY9+BF9+BK9+BM9+BO9+BH9+BJ9+BI9+BQ9 -> 0 | BT9: =IF(基本信息!P9="税前",SUM(K9:N9)+SUM(X9,Z9:AH9)+AX9+BG9+BL9+BN9+BP9+BR9,SUM(K9:N9,X9,BL9,BN9,BP9,BR9)) -> 0 | BU9: =ROUND(BS9-BT9,2) -> 0 | BV9: =IF(VLOOKUP(基本信息!$H9,各地政策!$A:$X,21,0)="进位",ROUNDUP(基本信息!AF9*基本信息!AU9,VLOOKUP(基本信息!$H9,各地政策!$A:$X,20,0)),IF(VLOOKUP(基本信息!$H9,各地政策!$A:$X,21,0)="四舍五入",ROUND(基本信息!AF9*基本信息!AU9,VLOOKUP(基本信息!$H9,各地政策!$A:$X,20,0)),ROUND(基本信息!AF9*基本信息!AU9-IF(VLOOKUP(基本信息!$H9,各地政策!$A:$X,20,0)=0,0.5,IF(VLOOKUP(基本信息!$H9,各地政策!$A:$X,20,0)=1,0.05,0.005)),VLOOKUP(基本信息!$H9,各地政策!$A:$X,20,0)))) -> #N/A | BW9: =IF(VLOOKUP(基本信息!$H9,各地政策!$A:$X,21,0)="进位",ROUNDUP(基本信息!AG9*基本信息!AV9,VLOOKUP(基本信息!$H9,各地政策!$A:$X,20,0)),IF(VLOOKUP(基本信息!$H9,各地政策!$A:$X,21,0)="四舍五入",ROUND(基本信息!AG9*基本信息!AV9,VLOOKUP(基本信息!$H9,各地政策!$A:$X,20,0)),ROUND(基本信息!AG9*基本信息!AV9-IF(VLOOKUP(基本信息!$H9,各地政策!$A:$X,20,0)=0,0.5,IF(VLOOKUP(基本信息!$H9,各地政策!$A:$X,20,0)=1,0.05,0.005)),VLOOKUP(基本信息!$H9,各地政策!$A:$X,20,0))))+基本信息!BC9 -> #N/A | BX9: =IF(VLOOKUP(基本信息!$H9,各地政策!$A:$X,21,0)="进位",ROUNDUP(基本信息!AH9*基本信息!AW9,VLOOKUP(基本信息!$H9,各地政策!$A:$X,20,0)),IF(VLOOKUP(基本信息!$H9,各地政策!$A:$X,21,0)="四舍五入",ROUND(基本信息!AH9*基本信息!AW9,VLOOKUP(基本信息!$H9,各地政策!$A:$X,20,0)),ROUND(基本信息!AH9*基本信息!AW9-IF(VLOOKUP(基本信息!$H9,各地政策!$A:$X,20,0)=0,0.5,IF(VLOOKUP(基本信息!$H9,各地政策!$A:$X,20,0)=1,0.05,0.005)),VLOOKUP(基本信息!$H9,各地政策!$A:$X,20,0)))) -> #N/A | BY9: =IF(VLOOKUP(基本信息!$H9,各地政策!$A:$X,21,0)="进位",ROUNDUP(基本信息!AI9*基本信息!AX9,VLOOKUP(基本信息!$H9,各地政策!$A:$X,20,0)),IF(VLOOKUP(基本信息!$H9,各地政策!$A:$X,21,0)="四舍五入",ROUND(基本信息!AI9*基本信息!AX9,VLOOKUP(基本信息!$H9,各地政策!$A:$X,20,0)),ROUND(基本信息!AI9*基本信息!AX9-IF(VLOOKUP(基本信息!$H9,各地政策!$A:$X,20,0)=0,0.5,IF(VLOOKUP(基本信息!$H9,各地政策!$A:$X,20,0)=1,0.05,0.005)),VLOOKUP(基本信息!$H9,各地政策!$A:$X,20,0)))) -> #N/A | BZ9: =IF(VLOOKUP(基本信息!$H9,各地政策!$A:$X,21,0)="进位",ROUNDUP(基本信息!AJ9*基本信息!AY9,VLOOKUP(基本信息!$H9,各地政策!$A:$X,20,0)),IF(VLOOKUP(基本信息!$H9,各地政策!$A:$X,21,0)="四舍五入",ROUND(基本信息!AJ9*基本信息!AY9,VLOOKUP(基本信息!$H9,各地政策!$A:$X,20,0)),ROUND(基本信息!AJ9*基本信息!AY9-IF(VLOOKUP(基本信息!$H9,各地政策!$A:$X,20,0)=0,0.5,IF(VLOOKUP(基本信息!$H9,各地政策!$A:$X,20,0)=1,0.05,0.005)),VLOOKUP(基本信息!$H9,各地政策!$A:$X,20,0))))+基本信息!BD9 -> #N/A | CA9: =IF(VLOOKUP(基本信息!$H9,各地政策!$A:$X,21,0)="进位",ROUNDUP(基本信息!AK9*基本信息!AZ9+基本信息!BE9,VLOOKUP(基本信息!$H9,各地政策!$A:$X,20,0)),IF(VLOOKUP(基本信息!$H9,各地政策!$A:$X,21,0)="四舍五入",ROUND(基本信息!AK9*基本信息!AZ9+基本信息!BE9,VLOOKUP(基本信息!$H9,各地政策!$A:$X,20,0)),ROUND(基本信息!AK9*基本信息!AZ9+基本信息!BE9-IF(VLOOKUP(基本信息!$H9,各地政策!$A:$X,20,0)=0,0.5,IF(VLOOKUP(基本信息!$H9,各地政策!$A:$X,20,0)=1,0.05,0.005)),VLOOKUP(基本信息!$H9,各地政策!$A:$X,20,0)))) -> #N/A | CB9: =IF(VLOOKUP(基本信息!$I9,各地政策!$A:$X,24,0)="进位",ROUNDUP(基本信息!AL9*(基本信息!BA9),VLOOKUP(基本信息!$I9,各地政策!$A:$X,23,0)),IF(VLOOKUP(基本信息!$I9,各地政策!$A:$X,24,0)="四舍五入",ROUND(基本信息!AL9*(基本信息!BA9),VLOOKUP(基本信息!$I9,各地政策!$A:$X,23,0)),ROUND(基本信息!AL9*(基本信息!BA9)-IF(VLOOKUP(基本信息!$I9,各地政策!$A:$X,23,0)=0,0.5,IF(VLOOKUP(基本信息!$I9,各地政策!$A:$X,23,0)=1,0.05,0.005)),VLOOKUP(基本信息!$I9,各地政策!$A:$X,23,0)))) -> #N/A | CC9: =IF(VLOOKUP(基本信息!$I9,各地政策!$A:$X,24,0)="进位",ROUNDUP(基本信息!AM9*(基本信息!BB9),VLOOKUP(基本信息!$I9,各地政策!$A:$X,23,0)),IF(VLOOKUP(基本信息!$I9,各地政策!$A:$X,24,0)="四舍五入",ROUND(基本信息!AM9*(基本信息!BB9),VLOOKUP(基本信息!$I9,各地政策!$A:$X,23,0)),ROUND(基本信息!AM9*(基本信息!BB9)-IF(VLOOKUP(基本信息!$I9,各地政策!$A:$X,23,0)=0,0.5,IF(VLOOKUP(基本信息!$I9,各地政策!$A:$X,23,0)=1,0.05,0.005)),VLOOKUP(基本信息!$I9,各地政策!$A:$X,23,0)))) -> #N/A | CD9: =AX9+BE9+IFERROR(VLOOKUP($A9,YTD!$A:$CD,82,0),0) -> 0 | CE9: =基本信息!CT9 -> 0 | CF9: ='S-Payroll Report'!X15 -> 0 | CG9: ='S-Payroll Report'!AD15 -> 0 | CH9: ='S-Payroll Report'!AC15 -> 0 | CI9: ='S-Payroll Report'!AA15 -> 0 | CJ9: ='S-Payroll Report'!AF15 -> 0 | CK9: =基本信息!EM9+基本信息!EN9+基本信息!EO9 -> 0

Sheet YTD
A1: 工号 | B1: 姓名 | C1: 基本工资 | D1: 浮动工资 | E1: 月奖 | F1: 季奖 | G1: 其他奖金 | H1: 加班工资150 | I1: 加班工资200 | J1: 加班工资300 | K1: 入离职缺勤扣 | L1: 扣事假 | M1: 扣旷工 | N1: 扣病假 | O1: 交通费 | P1: 通讯费 | Q1: 其他津贴 | R1: 中班费 | S1: 夜班费 | T1: 高温费 | U1: 高温作业费 | V1: 有毒有害作业费 | W1: 补发 | X1: 补扣 | Y1: 税前调整 | Z1: 缴养老 | AA1: 缴医疗 | AB1: 缴失业 | AC1: 缴公积金 | AD1: 缴补充公积金（免税） | AE1: 社保调整 | AF1: 公积金调整 | AG1: 年金 | AH1: 工会费 | AI1: 计税不发 | AJ1: 当月税前收入额 | AK1: 当月基本扣除 | AL1: 累计税前收入-员工 | AM1: 累计个人社保公积金 | AN1: 累计基本扣除 | AO1: 累计子女教育 | AP1: 累计继续教育 | AQ1: 累计住房贷款利息 | AR1: 累计住房租金 | AS1: 累计赡养老人 | AT1: 累计其他税前扣除 | AU1: 累计免税扣除合计(不含社保公积金） | AV1: 累计应税总额 | AW1: 累计个税（个人） | AX1: 当月个税（个人） | AY1: 公司负税项 | AZ1: 当月公司负税合计 | BA1: 累计税后计税收入 | BB1: 累计税前收入 | BC1: 导算当月应发工资 | BD1: 累计个税（公司+个人） | BE1: 当月个税（公司） | BF1: 独生子女费 | BG1: 缴补充公积金（不免税） | BH1: 报销款 | BI1: 报销款25% | BJ1: 外籍生活津贴 | BK1: 税后补 | BL1: 税后扣 | BM1: 13薪/年终奖 | BN1: 13薪/年终奖税 | BO1: 离职补偿金/赔偿金 | BP1: 离职补偿金税/赔偿金税 | BQ1: 股权激励 | BR1: 股权激励税 | BS1: 应发 | BT1: 应扣 | BU1: 实发 | BV1: 公司养老 | BW1: 公司医疗 | BX1: 公司失业 | BY1: 生育 | BZ1: 工伤 | CA1: 残保金 | CB1: 公积金 | CC1: 补充公积金（免税） | CD1: 累计已扣工资税 | CE1: 累计婴幼儿照护费用 | CF1: 工会费 | CG1: 雇主责任险 | CH1: 押金 | CI1: 服务费 | CJ1: 增值税
A2: CUS1525-0002 | B2: 杨明华 | C2: 37337.5 | D2: 0 | E2: 0 | F2: 0 | G2: 792 | H2: 0 | I2: 0 | J2: 0 | K2: 0 | L2: 0 | M2: 0 | N2: 0 | O2: 1224 | P2: 0 | Q2: 0 | R2: 0 | S2: 0 | T2: 0 | U2: 0 | V2: 0 | W2: 0 | X2: 0 | Y2: 0 | Z2: 2200.08 | AA2: 673.32 | AB2: 87.32 | AC2: 4365.9 | AD2: 0 | AE2: 0 | AF2: 0 | AG2: 0 | AH2: 0 | AI2: 0 | AJ2: 39353.5 | AK2: 5000 | AL2: 201395.77 | AM2: 37151.5 | AN2: 25000 | AO2: 20000 | AP2: 0 | AQ2: 5000 | AR2: 0 | AS2: 15000 | AT2: 0 | AU2: 65000 | AV2: 99244.267 | AW2: 7404.4267 | AX2: 1902.69 | AY2: 10 | AZ2: 10 | BA2: 156849.84 | BB2: 164255.38 | BC2: 39364.611 | BD2: 7405.5379 | BE2: 1.11 | BF2: 0 | BG2: 0 | BH2: 1215.93 | BI2: 0 | BJ2: 0 | BK2: 0 | BL2: 0 | BM2: 0 | BN2: 0 | BO2: 0 | BP2: 0 | BQ2: 0 | BR2: 0 | BS2: 40579.43 | BT2: 9229.31 | BU2: 31350.12 | BV2: 4675.17 | BW2: 1683.3 | BX2: 349.27 | BY2: 168.33 | BZ2: 206.84 | CA2: 56 | CB2: 4365.9 | CC2: 0 | CD2: 7405.54 | CE2: 0 | CF2: 0 | CG2: 0 | CH2: 0 | CI2: 450 | CJ2: 30.47 | CK2: 0

Sheet 工资税
A1: 工号 | B1: 客户简称 | C1: 用工性质 | D1: 姓名 | E1: 证照类型 | F1: 证照号码 | G1: *本期收入 | H1: 本期免税收入 | I1: 基本养老保险费 | J1: 基本医疗保险费 | K1: 失业保险费 | L1: 住房公积金 | M1: 累计子女教育 | N1: 累计继续教育 | O1: 累计住房贷款利息 | P1: 累计住房租金 | Q1: 累计赡养老人 | R1: 累计婴幼儿照护费用 | S1: 企业(职业)年金 | T1: 商业健康保险 | U1: 税延养老保险 | V1: 其它 | W1: 准予扣除的捐赠额 | X1: 减免税额 | Y1: 备注 | Z1: 应缴税款 | AA1: 实缴税额 | AB1: 年终奖个税 | AC1: 个税缴纳地
A2: =IF(基本信息!B2="","",基本信息!B2) -> CUS1525-0002 | B2: =IF($A2="","",基本信息!A2) -> NNRoad-Hermetic Solutions | C2: =IF($A2="","",基本信息!J2) -> 1 | D2: =IF($A2="","",基本信息!C2) -> 杨明华 | E2: =IF($A2="","",基本信息!BM2) -> 1 | F2: =IF($A2="","",基本信息!BN2) -> 340403197908151230 | G2: =ROUND(MAX(计算结果!AJ2,计算结果!BC2),2) -> 39120.1 | I2: =IF($A2="","",计算结果!Z2+基本信息!DU2) -> 2200.08 | J2: =IF($A2="","",计算结果!AA2+基本信息!DV2) -> 673.32 | K2: =IF($A2="","",计算结果!AB2+基本信息!DW2) -> 87.32 | L2: =IF($A2="","",计算结果!AC2+计算结果!AD2+计算结果!AF2) -> 4365.9 | M2: =IF($A2="","",计算结果!AO2) -> 24000 | N2: =IF($A2="","",计算结果!AP2) -> 0 | O2: =IF($A2="","",计算结果!AQ2) -> 6000 | P2: =IF($A2="","",计算结果!AR2) -> 0 | Q2: =IF($A2="","",计算结果!AS2) -> 18000 | R2: =IF($A2="","",计算结果!CE2) -> 0 | S2: =IF($A2="","",基本信息!BF2) -> 0 | U2: =IF($A2="","",基本信息!CU2) -> 0 | W2: =IF($A2="","",基本信息!CV2) -> 0 | Z2: =IF($A2="","",计算结果!BD2) -> 9284.8859 | AA2: =(IF($A2="","",计算结果!BE2+计算结果!AX2)) -> 1879.35 | AB2: =IF($A2="","",计算结果!BN2) -> 0 | AC2: =VLOOKUP($A$2:$A$29,基本信息!$B$2:$CN$1048576,91,0) -> 深圳人服
A3: =IF(基本信息!B3="","",基本信息!B3) | B3: =IF($A3="","",基本信息!A3) | C3: =IF($A3="","",基本信息!J3) | D3: =IF($A3="","",基本信息!C3) | E3: =IF($A3="","",基本信息!BM3) | F3: =IF($A3="","",基本信息!BN3) | G3: =ROUND(MAX(计算结果!AJ3,计算结果!BC3),2) -> #N/A | I3: =IF($A3="","",计算结果!Z3+基本信息!DU3) | J3: =IF($A3="","",计算结果!AA3+基本信息!DV3) | K3: =IF($A3="","",计算结果!AB3+基本信息!DW3) | L3: =IF($A3="","",计算结果!AC3+计算结果!AD3+计算结果!AF3) | M3: =IF($A3="","",计算结果!AO3) | N3: =IF($A3="","",计算结果!AP3) | O3: =IF($A3="","",计算结果!AQ3) | P3: =IF($A3="","",计算结果!AR3) | Q3: =IF($A3="","",计算结果!AS3) | R3: =IF($A3="","",计算结果!CE3) | S3: =IF($A3="","",基本信息!BF3) | U3: =IF($A3="","",基本信息!CU3) | W3: =IF($A3="","",基本信息!CV3) | Z3: =IF($A3="","",计算结果!BD3) | AA3: =(IF($A3="","",计算结果!BE3+计算结果!AX3)) | AB3: =IF($A3="","",计算结果!BN3) | AC3: =VLOOKUP($A$2:$A$29,基本信息!$B$2:$CN$1048576,91,0) -> #N/A
A4: =IF(基本信息!B4="","",基本信息!B4) | B4: =IF($A4="","",基本信息!A4) | C4: =IF($A4="","",基本信息!J4) | D4: =IF($A4="","",基本信息!C4) | E4: =IF($A4="","",基本信息!BM4) | F4: =IF($A4="","",基本信息!BN4) | G4: =ROUND(MAX(计算结果!AJ4,计算结果!BC4),2) -> #N/A | I4: =IF($A4="","",计算结果!Z4+基本信息!DU4) | J4: =IF($A4="","",计算结果!AA4+基本信息!DV4) | K4: =IF($A4="","",计算结果!AB4+基本信息!DW4) | L4: =IF($A4="","",计算结果!AC4+计算结果!AD4+计算结果!AF4) | M4: =IF($A4="","",计算结果!AO4) | N4: =IF($A4="","",计算结果!AP4) | O4: =IF($A4="","",计算结果!AQ4) | P4: =IF($A4="","",计算结果!AR4) | Q4: =IF($A4="","",计算结果!AS4) | R4: =IF($A4="","",计算结果!CE4) | S4: =IF($A4="","",基本信息!BF4) | U4: =IF($A4="","",基本信息!CU4) | W4: =IF($A4="","",基本信息!CV4) | Z4: =IF($A4="","",计算结果!BD4) | AA4: =(IF($A4="","",计算结果!BE4+计算结果!AX4)) | AB4: =IF($A4="","",计算结果!BN4) | AC4: =VLOOKUP($A$2:$A$29,基本信息!$B$2:$CN$1048576,91,0) -> #N/A
A5: =IF(基本信息!B5="","",基本信息!B5) | B5: =IF($A5="","",基本信息!A5) | C5: =IF($A5="","",基本信息!J5) | D5: =IF($A5="","",基本信息!C5) | E5: =IF($A5="","",基本信息!BM5) | F5: =IF($A5="","",基本信息!BN5) | G5: =ROUND(MAX(计算结果!AJ5,计算结果!BC5),2) -> #N/A | I5: =IF($A5="","",计算结果!Z5+基本信息!DU5) | J5: =IF($A5="","",计算结果!AA5+基本信息!DV5) | K5: =IF($A5="","",计算结果!AB5+基本信息!DW5) | L5: =IF($A5="","",计算结果!AC5+计算结果!AD5+计算结果!AF5) | M5: =IF($A5="","",计算结果!AO5) | N5: =IF($A5="","",计算结果!AP5) | O5: =IF($A5="","",计算结果!AQ5) | P5: =IF($A5="","",计算结果!AR5) | Q5: =IF($A5="","",计算结果!AS5) | R5: =IF($A5="","",计算结果!CE5) | S5: =IF($A5="","",基本信息!BF5) | U5: =IF($A5="","",基本信息!CU5) | W5: =IF($A5="","",基本信息!CV5) | Z5: =IF($A5="","",计算结果!BD5) | AA5: =(IF($A5="","",计算结果!BE5+计算结果!AX5)) | AB5: =IF($A5="","",计算结果!BN5) | AC5: =VLOOKUP($A$2:$A$29,基本信息!$B$2:$CN$1048576,91,0) -> #N/A
A6: =IF(基本信息!B6="","",基本信息!B6) | B6: =IF($A6="","",基本信息!A6) | C6: =IF($A6="","",基本信息!J6) | D6: =IF($A6="","",基本信息!C6) | E6: =IF($A6="","",基本信息!BM6) | F6: =IF($A6="","",基本信息!BN6) | G6: =ROUND(MAX(计算结果!AJ6,计算结果!BC6),2) -> #N/A | I6: =IF($A6="","",计算结果!Z6+基本信息!DU6) | J6: =IF($A6="","",计算结果!AA6+基本信息!DV6) | K6: =IF($A6="","",计算结果!AB6+基本信息!DW6) | L6: =IF($A6="","",计算结果!AC6+计算结果!AD6+计算结果!AF6) | M6: =IF($A6="","",计算结果!AO6) | N6: =IF($A6="","",计算结果!AP6) | O6: =IF($A6="","",计算结果!AQ6) | P6: =IF($A6="","",计算结果!AR6) | Q6: =IF($A6="","",计算结果!AS6) | R6: =IF($A6="","",计算结果!CE6) | S6: =IF($A6="","",基本信息!BF6) | U6: =IF($A6="","",基本信息!CU6) | W6: =IF($A6="","",基本信息!CV6) | Z6: =IF($A6="","",计算结果!BD6) | AA6: =(IF($A6="","",计算结果!BE6+计算结果!AX6)) | AB6: =IF($A6="","",计算结果!BN6) | AC6: =VLOOKUP($A$2:$A$29,基本信息!$B$2:$CN$1048576,91,0) -> #N/A
A7: =IF(基本信息!B7="","",基本信息!B7) | B7: =IF($A7="","",基本信息!A7) | C7: =IF($A7="","",基本信息!J7) | D7: =IF($A7="","",基本信息!C7) | E7: =IF($A7="","",基本信息!BM7) | F7: =IF($A7="","",基本信息!BN7) | G7: =ROUND(MAX(计算结果!AJ7,计算结果!BC7),2) -> #N/A | I7: =IF($A7="","",计算结果!Z7+基本信息!DU7) | J7: =IF($A7="","",计算结果!AA7+基本信息!DV7) | K7: =IF($A7="","",计算结果!AB7+基本信息!DW7) | L7: =IF($A7="","",计算结果!AC7+计算结果!AD7+计算结果!AF7) | M7: =IF($A7="","",计算结果!AO7) | N7: =IF($A7="","",计算结果!AP7) | O7: =IF($A7="","",计算结果!AQ7) | P7: =IF($A7="","",计算结果!AR7) | Q7: =IF($A7="","",计算结果!AS7) | R7: =IF($A7="","",计算结果!CE7) | S7: =IF($A7="","",基本信息!BF7) | U7: =IF($A7="","",基本信息!CU7) | W7: =IF($A7="","",基本信息!CV7) | Z7: =IF($A7="","",计算结果!BD7) | AA7: =(IF($A7="","",计算结果!BE7+计算结果!AX7)) | AB7: =IF($A7="","",计算结果!BN7) | AC7: =VLOOKUP($A$2:$A$29,基本信息!$B$2:$CN$1048576,91,0) -> #N/A
A8: =IF(基本信息!B8="","",基本信息!B8) | B8: =IF($A8="","",基本信息!A8) | C8: =IF($A8="","",基本信息!J8) | D8: =IF($A8="","",基本信息!C8) | E8: =IF($A8="","",基本信息!BM8) | F8: =IF($A8="","",基本信息!BN8) | G8: =ROUND(MAX(计算结果!AJ8,计算结果!BC8),2) -> #N/A | I8: =IF($A8="","",计算结果!Z8+基本信息!DU8) | J8: =IF($A8="","",计算结果!AA8+基本信息!DV8) | K8: =IF($A8="","",计算结果!AB8+基本信息!DW8) | L8: =IF($A8="","",计算结果!AC8+计算结果!AD8+计算结果!AF8) | M8: =IF($A8="","",计算结果!AO8) | N8: =IF($A8="","",计算结果!AP8) | O8: =IF($A8="","",计算结果!AQ8) | P8: =IF($A8="","",计算结果!AR8) | Q8: =IF($A8="","",计算结果!AS8) | R8: =IF($A8="","",计算结果!CE8) | S8: =IF($A8="","",基本信息!BF8) | U8: =IF($A8="","",基本信息!CU8) | W8: =IF($A8="","",基本信息!CV8) | Z8: =IF($A8="","",计算结果!BD8) | AA8: =(IF($A8="","",计算结果!BE8+计算结果!AX8)) | AB8: =IF($A8="","",计算结果!BN8) | AC8: =VLOOKUP($A$2:$A$29,基本信息!$B$2:$CN$1048576,91,0) -> #N/A
A9: =IF(基本信息!B9="","",基本信息!B9) | B9: =IF($A9="","",基本信息!A9) | C9: =IF($A9="","",基本信息!J9) | D9: =IF($A9="","",基本信息!C9) | E9: =IF($A9="","",基本信息!BM9) | F9: =IF($A9="","",基本信息!BN9) | G9: =ROUND(MAX(计算结果!AJ9,计算结果!BC9),2) -> #N/A | I9: =IF($A9="","",计算结果!Z9+基本信息!DU9) | J9: =IF($A9="","",计算结果!AA9+基本信息!DV9) | K9: =IF($A9="","",计算结果!AB9+基本信息!DW9) | L9: =IF($A9="","",计算结果!AC9+计算结果!AD9+计算结果!AF9) | M9: =IF($A9="","",计算结果!AO9) | N9: =IF($A9="","",计算结果!AP9) | O9: =IF($A9="","",计算结果!AQ9) | P9: =IF($A9="","",计算结果!AR9) | Q9: =IF($A9="","",计算结果!AS9) | R9: =IF($A9="","",计算结果!CE9) | S9: =IF($A9="","",基本信息!BF9) | U9: =IF($A9="","",基本信息!CU9) | W9: =IF($A9="","",基本信息!CV9) | Z9: =IF($A9="","",计算结果!BD9) | AA9: =(IF($A9="","",计算结果!BE9+计算结果!AX9)) | AB9: =IF($A9="","",计算结果!BN9) | AC9: =VLOOKUP($A$2:$A$29,基本信息!$B$2:$CN$1048576,91,0) -> #N/A
A10: =IF(基本信息!B10="","",基本信息!B10) | B10: =IF($A10="","",基本信息!A10) | C10: =IF($A10="","",基本信息!J10) | D10: =IF($A10="","",基本信息!C10) | E10: =IF($A10="","",基本信息!BM10) | F10: =IF($A10="","",基本信息!BN10) | G10: =ROUND(MAX(计算结果!AJ10,计算结果!BC10),2) -> 0 | I10: =IF($A10="","",计算结果!Z10+基本信息!DU10) | J10: =IF($A10="","",计算结果!AA10+基本信息!DV10) | K10: =IF($A10="","",计算结果!AB10+基本信息!DW10) | L10: =IF($A10="","",计算结果!AC10+计算结果!AD10+计算结果!AF10) | M10: =IF($A10="","",计算结果!AO10) | N10: =IF($A10="","",计算结果!AP10) | O10: =IF($A10="","",计算结果!AQ10) | P10: =IF($A10="","",计算结果!AR10) | Q10: =IF($A10="","",计算结果!AS10) | R10: =IF($A10="","",计算结果!CE10) | S10: =IF($A10="","",基本信息!BF10) | U10: =IF($A10="","",基本信息!CU10) | W10: =IF($A10="","",基本信息!CV10) | Z10: =IF($A10="","",计算结果!BD10) | AA10: =(IF($A10="","",计算结果!BE10+计算结果!AX10)) | AB10: =IF($A10="","",计算结果!BN10) | AC10: =VLOOKUP($A$2:$A$29,基本信息!$B$2:$CN$1048576,91,0) -> #N/A
A11: =IF(基本信息!B11="","",基本信息!B11) | B11: =IF($A11="","",基本信息!A11) | C11: =IF($A11="","",基本信息!J11) | D11: =IF($A11="","",基本信息!C11) | E11: =IF($A11="","",基本信息!BM11) | F11: =IF($A11="","",基本信息!BN11) | G11: =ROUND(MAX(计算结果!AJ11,计算结果!BC11),2) -> 0 | I11: =IF($A11="","",计算结果!Z11+基本信息!DU11) | J11: =IF($A11="","",计算结果!AA11+基本信息!DV11) | K11: =IF($A11="","",计算结果!AB11+基本信息!DW11) | L11: =IF($A11="","",计算结果!AC11+计算结果!AD11+计算结果!AF11) | M11: =IF($A11="","",计算结果!AO11) | N11: =IF($A11="","",计算结果!AP11) | O11: =IF($A11="","",计算结果!AQ11) | P11: =IF($A11="","",计算结果!AR11) | Q11: =IF($A11="","",计算结果!AS11) | R11: =IF($A11="","",计算结果!CE11) | S11: =IF($A11="","",基本信息!BF11) | U11: =IF($A11="","",基本信息!CU11) | W11: =IF($A11="","",基本信息!CV11) | Z11: =IF($A11="","",计算结果!BD11) | AA11: =(IF($A11="","",计算结果!BE11+计算结果!AX11)) | AB11: =IF($A11="","",计算结果!BN11) | AC11: =VLOOKUP($A$2:$A$29,基本信息!$B$2:$CN$1048576,91,0) -> #N/A
A12: =IF(基本信息!B12="","",基本信息!B12) | B12: =IF($A12="","",基本信息!A12) | C12: =IF($A12="","",基本信息!J12) | D12: =IF($A12="","",基本信息!C12) | E12: =IF($A12="","",基本信息!BM12) | F12: =IF($A12="","",基本信息!BN12) | G12: =ROUND(MAX(计算结果!AJ12,计算结果!BC12),2) -> 0 | I12: =IF($A12="","",计算结果!Z12+基本信息!DU12) | J12: =IF($A12="","",计算结果!AA12+基本信息!DV12) | K12: =IF($A12="","",计算结果!AB12+基本信息!DW12) | L12: =IF($A12="","",计算结果!AC12+计算结果!AD12+计算结果!AF12) | M12: =IF($A12="","",计算结果!AO12) | N12: =IF($A12="","",计算结果!AP12) | O12: =IF($A12="","",计算结果!AQ12) | P12: =IF($A12="","",计算结果!AR12) | Q12: =IF($A12="","",计算结果!AS12) | R12: =IF($A12="","",计算结果!CE12) | S12: =IF($A12="","",基本信息!BF12) | U12: =IF($A12="","",基本信息!CU12) | W12: =IF($A12="","",基本信息!CV12) | Z12: =IF($A12="","",计算结果!BD12) | AA12: =(IF($A12="","",计算结果!BE12+计算结果!AX12)) | AB12: =IF($A12="","",计算结果!BN12) | AC12: =VLOOKUP($A$2:$A$29,基本信息!$B$2:$CN$1048576,91,0) -> #N/A
A13: =IF(基本信息!B13="","",基本信息!B13) | B13: =IF($A13="","",基本信息!A13) | C13: =IF($A13="","",基本信息!J13) | D13: =IF($A13="","",基本信息!C13) | E13: =IF($A13="","",基本信息!BM13) | F13: =IF($A13="","",基本信息!BN13) | G13: =ROUND(MAX(计算结果!AJ13,计算结果!BC13),2) -> 0 | I13: =IF($A13="","",计算结果!Z13+基本信息!DU13) | J13: =IF($A13="","",计算结果!AA13+基本信息!DV13) | K13: =IF($A13="","",计算结果!AB13+基本信息!DW13) | L13: =IF($A13="","",计算结果!AC13+计算结果!AD13+计算结果!AF13) | M13: =IF($A13="","",计算结果!AO13) | N13: =IF($A13="","",计算结果!AP13) | O13: =IF($A13="","",计算结果!AQ13) | P13: =IF($A13="","",计算结果!AR13) | Q13: =IF($A13="","",计算结果!AS13) | R13: =IF($A13="","",计算结果!CE13) | S13: =IF($A13="","",基本信息!BF13) | U13: =IF($A13="","",基本信息!CU13) | W13: =IF($A13="","",基本信息!CV13) | Z13: =IF($A13="","",计算结果!BD13) | AA13: =(IF($A13="","",计算结果!BE13+计算结果!AX13)) | AB13: =IF($A13="","",计算结果!BN13) | AC13: =VLOOKUP($A$2:$A$29,基本信息!$B$2:$CN$1048576,91,0) -> #N/A
... A29: =IF(基本信息!B29="","",基本信息!B29) | B29: =IF($A29="","",基本信息!A29) | C29: =IF($A29="","",基本信息!J29) | D29: =IF($A29="","",基本信息!C29) | E29: =IF($A29="","",基本信息!BM29) | F29: =IF($A29="","",基本信息!BN29) | G29: =ROUND(MAX(计算结果!AJ29,计算结果!BC29),2) -> 0 | I29: =IF($A29="","",计算结果!Z29+基本信息!DU29) | J29: =IF($A29="","",计算结果!AA29+基本信息!DV29) | K29: =IF($A29="","",计算结果!AB29+基本信息!DW29) | L29: =IF($A29="","",计算结果!AC29+计算结果!AD29+计算结果!AF29) | M29: =IF($A29="","",计算结果!AO29) | N29: =IF($A29="","",计算结果!AP29) | O29: =IF($A29="","",计算结果!AQ29) | P29: =IF($A29="","",计算结果!AR29) | Q29: =IF($A29="","",计算结果!AS29) | R29: =IF($A29="","",计算结果!CE29) | S29: =IF($A29="","",基本信息!BF29) | U29: =IF($A29="","",基本信息!CU29) | W29: =IF($A29="","",基本信息!CV29) | Z29: =IF($A29="","",计算结果!BD29) | AA29: =(IF($A29="","",计算结果!BE29+计算结果!AX29)) | AB29: =IF($A29="","",计算结果!BN29) | AC29: =VLOOKUP($A$2:$A$29,基本信息!$B$2:$CN$1048576,91,0) -> #N/A

Sheet 年终奖税
A1: 工号 | B1: 客户简称 | C1: 用工性质 | D1: 姓名 | E1: *证照类型 | F1: *证照号码 | G1: *全年一次性奖金额 | H1: 免税收入 | I1: 企业(职业)年金 | J1: 商业健康保险 | K1: 税延养老保险 | L1: 其他 | M1: 准予扣除的捐赠额 | N1: 减免税额 | O1: 已扣缴税额 | P1: 备注 | Q1: 年终奖个税 | R1: 个税缴纳地
A2: =IF(基本信息!B2="","",基本信息!B2) -> CUS1525-0002 | B2: =IF($A2="","",基本信息!A2) -> NNRoad-Hermetic Solutions | C2: =IF($A2="","",基本信息!J2) -> 1 | D2: =IF($A2="","",基本信息!C2) -> 杨明华 | E2: =IF($A2="","",基本信息!BM2) -> 1 | F2: =IF($A2="","",基本信息!BN2) -> 340403197908151230 | G2: =ROUND(计算结果!BM2,2) -> 0 | Q2: =ROUND(IF($A2="","",计算结果!BN2),2) -> 0 | R2: =VLOOKUP($A$2:$A$14,基本信息!$B$2:$CO$1048576,91,0) -> 深圳人服

Sheet 离职补偿金税
A1: 工号 | B1: 客户简称 | C1: 用工性质 | D1: 姓名 | E1: *证照类型 | F1: *证照号码 | G1: *离职补偿金金额 | H1: 免税收入 | I1: 企业(职业)年金 | J1: 商业健康保险 | K1: 税延养老保险 | L1: 其他 | M1: 准予扣除的捐赠额 | N1: 减免税额 | O1: 已扣缴税额 | P1: 备注 | Q1: 离职补偿金税 | R1: 个税缴纳地
A2: =IF(基本信息!B2="","",基本信息!B2) -> CUS1525-0002 | B2: =IF($A2="","",基本信息!A2) -> NNRoad-Hermetic Solutions | C2: =IF($A2="","",基本信息!J2) -> 1 | D2: =IF($A2="","",基本信息!C2) -> 杨明华 | E2: =IF($A2="","",基本信息!BM2) -> 1 | F2: =IF($A2="","",基本信息!BN2) -> 340403197908151230 | G2: =ROUND(计算结果!BO2,2) -> 0 | Q2: =ROUND(IF($A2="","",计算结果!BP2),2) -> 0 | R2: =VLOOKUP($A$2:$A$29,基本信息!$B$2:$CN$1048576,91,0) -> 深圳人服
A3: =IF(基本信息!B3="","",基本信息!B3) | B3: =IF($A3="","",基本信息!A3) | C3: =IF($A3="","",基本信息!J3) | D3: =IF($A3="","",基本信息!C3) | E3: =IF($A3="","",基本信息!BM3) | F3: =IF($A3="","",基本信息!BN3) | G3: =ROUND(计算结果!BO3,2) -> 0 | Q3: =ROUND(IF($A3="","",计算结果!BP3),2) -> #VALUE! | R3: =VLOOKUP($A$2:$A$29,基本信息!$B$2:$CN$1048576,91,0) -> #N/A
A4: =IF(基本信息!B4="","",基本信息!B4) | B4: =IF($A4="","",基本信息!A4) | C4: =IF($A4="","",基本信息!J4) | D4: =IF($A4="","",基本信息!C4) | E4: =IF($A4="","",基本信息!BM4) | F4: =IF($A4="","",基本信息!BN4) | G4: =ROUND(计算结果!BO4,2) -> 0 | Q4: =ROUND(IF($A4="","",计算结果!BP4),2) -> #VALUE! | R4: =VLOOKUP($A$2:$A$29,基本信息!$B$2:$CN$1048576,91,0) -> #N/A
A5: =IF(基本信息!B5="","",基本信息!B5) | B5: =IF($A5="","",基本信息!A5) | C5: =IF($A5="","",基本信息!J5) | D5: =IF($A5="","",基本信息!C5) | E5: =IF($A5="","",基本信息!BM5) | F5: =IF($A5="","",基本信息!BN5) | G5: =ROUND(计算结果!BO5,2) -> 0 | Q5: =ROUND(IF($A5="","",计算结果!BP5),2) -> #VALUE! | R5: =VLOOKUP($A$2:$A$29,基本信息!$B$2:$CN$1048576,91,0) -> #N/A
A6: =IF(基本信息!B6="","",基本信息!B6) | B6: =IF($A6="","",基本信息!A6) | C6: =IF($A6="","",基本信息!J6) | D6: =IF($A6="","",基本信息!C6) | E6: =IF($A6="","",基本信息!BM6) | F6: =IF($A6="","",基本信息!BN6) | G6: =ROUND(计算结果!BO6,2) -> 0 | Q6: =ROUND(IF($A6="","",计算结果!BP6),2) -> #VALUE! | R6: =VLOOKUP($A$2:$A$29,基本信息!$B$2:$CN$1048576,91,0) -> #N/A
A7: =IF(基本信息!B7="","",基本信息!B7) | B7: =IF($A7="","",基本信息!A7) | C7: =IF($A7="","",基本信息!J7) | D7: =IF($A7="","",基本信息!C7) | E7: =IF($A7="","",基本信息!BM7) | F7: =IF($A7="","",基本信息!BN7) | G7: =ROUND(计算结果!BO7,2) -> 0 | Q7: =ROUND(IF($A7="","",计算结果!BP7),2) -> #VALUE! | R7: =VLOOKUP($A$2:$A$29,基本信息!$B$2:$CN$1048576,91,0) -> #N/A
A8: =IF(基本信息!B8="","",基本信息!B8) | B8: =IF($A8="","",基本信息!A8) | C8: =IF($A8="","",基本信息!J8) | D8: =IF($A8="","",基本信息!C8) | E8: =IF($A8="","",基本信息!BM8) | F8: =IF($A8="","",基本信息!BN8) | G8: =ROUND(计算结果!BO8,2) -> 0 | Q8: =ROUND(IF($A8="","",计算结果!BP8),2) -> #VALUE! | R8: =VLOOKUP($A$2:$A$29,基本信息!$B$2:$CN$1048576,91,0) -> #N/A
A9: =IF(基本信息!B9="","",基本信息!B9) | B9: =IF($A9="","",基本信息!A9) | C9: =IF($A9="","",基本信息!J9) | D9: =IF($A9="","",基本信息!C9) | E9: =IF($A9="","",基本信息!BM9) | F9: =IF($A9="","",基本信息!BN9) | G9: =ROUND(计算结果!BO9,2) -> 0 | Q9: =ROUND(IF($A9="","",计算结果!BP9),2) -> #VALUE! | R9: =VLOOKUP($A$2:$A$29,基本信息!$B$2:$CN$1048576,91,0) -> #N/A
A10: =IF(基本信息!B10="","",基本信息!B10) | B10: =IF($A10="","",基本信息!A10) | C10: =IF($A10="","",基本信息!J10) | D10: =IF($A10="","",基本信息!C10) | E10: =IF($A10="","",基本信息!BM10) | F10: =IF($A10="","",基本信息!BN10) | G10: =ROUND(计算结果!BO10,2) -> 0 | Q10: =ROUND(IF($A10="","",计算结果!BP10),2) -> #VALUE! | R10: =VLOOKUP($A$2:$A$29,基本信息!$B$2:$CN$1048576,91,0) -> #N/A
A11: =IF(基本信息!B11="","",基本信息!B11) | B11: =IF($A11="","",基本信息!A11) | C11: =IF($A11="","",基本信息!J11) | D11: =IF($A11="","",基本信息!C11) | E11: =IF($A11="","",基本信息!BM11) | F11: =IF($A11="","",基本信息!BN11) | G11: =ROUND(计算结果!BO11,2) -> 0 | Q11: =ROUND(IF($A11="","",计算结果!BP11),2) -> #VALUE! | R11: =VLOOKUP($A$2:$A$29,基本信息!$B$2:$CN$1048576,91,0) -> #N/A
A12: =IF(基本信息!B12="","",基本信息!B12) | B12: =IF($A12="","",基本信息!A12) | C12: =IF($A12="","",基本信息!J12) | D12: =IF($A12="","",基本信息!C12) | E12: =IF($A12="","",基本信息!BM12) | F12: =IF($A12="","",基本信息!BN12) | G12: =ROUND(计算结果!BO12,2) -> 0 | Q12: =ROUND(IF($A12="","",计算结果!BP12),2) -> #VALUE! | R12: =VLOOKUP($A$2:$A$29,基本信息!$B$2:$CN$1048576,91,0) -> #N/A
A13: =IF(基本信息!B13="","",基本信息!B13) | B13: =IF($A13="","",基本信息!A13) | C13: =IF($A13="","",基本信息!J13) | D13: =IF($A13="","",基本信息!C13) | E13: =IF($A13="","",基本信息!BM13) | F13: =IF($A13="","",基本信息!BN13) | G13: =ROUND(计算结果!BO13,2) -> 0 | Q13: =ROUND(IF($A13="","",计算结果!BP13),2) -> #VALUE! | R13: =VLOOKUP($A$2:$A$29,基本信息!$B$2:$CN$1048576,91,0) -> #N/A
... A29: =IF(基本信息!B29="","",基本信息!B29) | B29: =IF($A29="","",基本信息!A29) | C29: =IF($A29="","",基本信息!J29) | D29: =IF($A29="","",基本信息!C29) | E29: =IF($A29="","",基本信息!BM29) | F29: =IF($A29="","",基本信息!BN29) | G29: =ROUND(计算结果!BO29,2) -> 0 | Q29: =ROUND(IF($A29="","",计算结果!BP29),2) -> #VALUE! | R29: =VLOOKUP($A$2:$A$29,基本信息!$B$2:$CN$1048576,91,0) -> #N/A

Sheet 股权激励税
A1: 工号 | B1: 客户简称 | C1: 用工性质 | D1: 姓名 | E1: *证照类型 | F1: *证照号码 | G1: *股权激励金额 | H1: 免税收入 | I1: 企业(职业)年金 | J1: 商业健康保险 | K1: 税延养老保险 | L1: 其他 | M1: 准予扣除的捐赠额 | N1: 减免税额 | O1: 已扣缴税额 | P1: 备注 | Q1: 股权激励个税 | R1: 个税缴纳地
A2: =IF(基本信息!B2="","",基本信息!B2) -> CUS1525-0002 | B2: =IF($A2="","",基本信息!A2) -> NNRoad-Hermetic Solutions | C2: =IF($A2="","",基本信息!J2) -> 1 | D2: =IF($A2="","",基本信息!C2) -> 杨明华 | E2: =IF($A2="","",基本信息!BM2) -> 1 | F2: =IF($A2="","",基本信息!BN2) -> 340403197908151230 | G2: =ROUND(计算结果!BQ2,2) -> 0 | Q2: =ROUND(IF($A2="","",计算结果!BR2),2) -> 0 | R2: =VLOOKUP($A$2:$A$29,基本信息!$B$2:$CN$1048576,91,0) -> 深圳人服
A3: =IF(基本信息!B3="","",基本信息!B3) | B3: =IF($A3="","",基本信息!A3) | C3: =IF($A3="","",基本信息!J3) | D3: =IF($A3="","",基本信息!C3) | E3: =IF($A3="","",基本信息!BM3) | F3: =IF($A3="","",基本信息!BN3) | G3: =ROUND(计算结果!BQ3,2) -> 0 | Q3: =ROUND(IF($A3="","",计算结果!BR3),2) -> #VALUE! | R3: =VLOOKUP($A$2:$A$29,基本信息!$B$2:$CN$1048576,91,0) -> #N/A
A4: =IF(基本信息!B4="","",基本信息!B4) | B4: =IF($A4="","",基本信息!A4) | C4: =IF($A4="","",基本信息!J4) | D4: =IF($A4="","",基本信息!C4) | E4: =IF($A4="","",基本信息!BM4) | F4: =IF($A4="","",基本信息!BN4) | G4: =ROUND(计算结果!BQ4,2) -> 0 | Q4: =ROUND(IF($A4="","",计算结果!BR4),2) -> #VALUE! | R4: =VLOOKUP($A$2:$A$29,基本信息!$B$2:$CN$1048576,91,0) -> #N/A
A5: =IF(基本信息!B5="","",基本信息!B5) | B5: =IF($A5="","",基本信息!A5) | C5: =IF($A5="","",基本信息!J5) | D5: =IF($A5="","",基本信息!C5) | E5: =IF($A5="","",基本信息!BM5) | F5: =IF($A5="","",基本信息!BN5) | G5: =ROUND(计算结果!BQ5,2) -> 0 | Q5: =ROUND(IF($A5="","",计算结果!BR5),2) -> #VALUE! | R5: =VLOOKUP($A$2:$A$29,基本信息!$B$2:$CN$1048576,91,0) -> #N/A
A6: =IF(基本信息!B6="","",基本信息!B6) | B6: =IF($A6="","",基本信息!A6) | C6: =IF($A6="","",基本信息!J6) | D6: =IF($A6="","",基本信息!C6) | E6: =IF($A6="","",基本信息!BM6) | F6: =IF($A6="","",基本信息!BN6) | G6: =ROUND(计算结果!BQ6,2) -> 0 | Q6: =ROUND(IF($A6="","",计算结果!BR6),2) -> #VALUE! | R6: =VLOOKUP($A$2:$A$29,基本信息!$B$2:$CN$1048576,91,0) -> #N/A
A7: =IF(基本信息!B7="","",基本信息!B7) | B7: =IF($A7="","",基本信息!A7) | C7: =IF($A7="","",基本信息!J7) | D7: =IF($A7="","",基本信息!C7) | E7: =IF($A7="","",基本信息!BM7) | F7: =IF($A7="","",基本信息!BN7) | G7: =ROUND(计算结果!BQ7,2) -> 0 | Q7: =ROUND(IF($A7="","",计算结果!BR7),2) -> #VALUE! | R7: =VLOOKUP($A$2:$A$29,基本信息!$B$2:$CN$1048576,91,0) -> #N/A
A8: =IF(基本信息!B8="","",基本信息!B8) | B8: =IF($A8="","",基本信息!A8) | C8: =IF($A8="","",基本信息!J8) | D8: =IF($A8="","",基本信息!C8) | E8: =IF($A8="","",基本信息!BM8) | F8: =IF($A8="","",基本信息!BN8) | G8: =ROUND(计算结果!BQ8,2) -> 0 | Q8: =ROUND(IF($A8="","",计算结果!BR8),2) -> #VALUE! | R8: =VLOOKUP($A$2:$A$29,基本信息!$B$2:$CN$1048576,91,0) -> #N/A
A9: =IF(基本信息!B9="","",基本信息!B9) | B9: =IF($A9="","",基本信息!A9) | C9: =IF($A9="","",基本信息!J9) | D9: =IF($A9="","",基本信息!C9) | E9: =IF($A9="","",基本信息!BM9) | F9: =IF($A9="","",基本信息!BN9) | G9: =ROUND(计算结果!BQ9,2) -> 0 | Q9: =ROUND(IF($A9="","",计算结果!BR9),2) -> #VALUE! | R9: =VLOOKUP($A$2:$A$29,基本信息!$B$2:$CN$1048576,91,0) -> #N/A
A10: =IF(基本信息!B10="","",基本信息!B10) | B10: =IF($A10="","",基本信息!A10) | C10: =IF($A10="","",基本信息!J10) | D10: =IF($A10="","",基本信息!C10) | E10: =IF($A10="","",基本信息!BM10) | F10: =IF($A10="","",基本信息!BN10) | G10: =ROUND(计算结果!BQ10,2) -> 0 | Q10: =ROUND(IF($A10="","",计算结果!BR10),2) -> #VALUE! | R10: =VLOOKUP($A$2:$A$29,基本信息!$B$2:$CN$1048576,91,0) -> #N/A
A11: =IF(基本信息!B11="","",基本信息!B11) | B11: =IF($A11="","",基本信息!A11) | C11: =IF($A11="","",基本信息!J11) | D11: =IF($A11="","",基本信息!C11) | E11: =IF($A11="","",基本信息!BM11) | F11: =IF($A11="","",基本信息!BN11) | G11: =ROUND(计算结果!BQ11,2) -> 0 | Q11: =ROUND(IF($A11="","",计算结果!BR11),2) -> #VALUE! | R11: =VLOOKUP($A$2:$A$29,基本信息!$B$2:$CN$1048576,91,0) -> #N/A
A12: =IF(基本信息!B12="","",基本信息!B12) | B12: =IF($A12="","",基本信息!A12) | C12: =IF($A12="","",基本信息!J12) | D12: =IF($A12="","",基本信息!C12) | E12: =IF($A12="","",基本信息!BM12) | F12: =IF($A12="","",基本信息!BN12) | G12: =ROUND(计算结果!BQ12,2) -> 0 | Q12: =ROUND(IF($A12="","",计算结果!BR12),2) -> #VALUE! | R12: =VLOOKUP($A$2:$A$29,基本信息!$B$2:$CN$1048576,91,0) -> #N/A
A13: =IF(基本信息!B13="","",基本信息!B13) | B13: =IF($A13="","",基本信息!A13) | C13: =IF($A13="","",基本信息!J13) | D13: =IF($A13="","",基本信息!C13) | E13: =IF($A13="","",基本信息!BM13) | F13: =IF($A13="","",基本信息!BN13) | G13: =ROUND(计算结果!BQ13,2) -> 0 | Q13: =ROUND(IF($A13="","",计算结果!BR13),2) -> #VALUE! | R13: =VLOOKUP($A$2:$A$29,基本信息!$B$2:$CN$1048576,91,0) -> #N/A
... A29: =IF(基本信息!B29="","",基本信息!B29) | B29: =IF($A29="","",基本信息!A29) | C29: =IF($A29="","",基本信息!J29) | D29: =IF($A29="","",基本信息!C29) | E29: =IF($A29="","",基本信息!BM29) | F29: =IF($A29="","",基本信息!BN29) | G29: =ROUND(计算结果!BQ29,2) -> 0 | Q29: =ROUND(IF($A29="","",计算结果!BR29),2) -> #VALUE! | R29: =VLOOKUP($A$2:$A$29,基本信息!$B$2:$CN$1048576,91,0) -> #N/A

Sheet 交行发薪
A1: =基本信息!BR1 -> 银行账号 | B1: =基本信息!BQ1 -> 银行户名 | C1: =计算结果!BT1 -> 应扣 | D1: =基本信息!BS1 -> 银行 | E1: 开户地 | F1: =基本信息!A1 -> 客户简称 | G1: 报销款 | H1: 外籍生活津贴
A2: =IF(AND(OR(IFERROR(FIND("交行",基本信息!BS2),0)>0,IFERROR(FIND("交通银行",基本信息!BS2),0)>0),计算结果!BT2=0>0),基本信息!BR2,"") | B2: =IF($A2="","",基本信息!BQ2) | C2: =IF($A2="","",计算结果!BT2-G2-H2) | D2: =IF($A2="","",基本信息!BS2) | F2: =IF($A2="","",基本信息!A2) | G2: =IF($A2="","",计算结果!BI2+计算结果!BJ2) | H2: =IF($A2="","",计算结果!BK2)
A3: =IF(AND(OR(IFERROR(FIND("交行",基本信息!BS3),0)>0,IFERROR(FIND("交通银行",基本信息!BS3),0)>0),计算结果!BT3=0>0),基本信息!BR3,"") | B3: =IF($A3="","",基本信息!BQ3) | C3: =IF($A3="","",计算结果!BT3-G3-H3) | D3: =IF($A3="","",基本信息!BS3) | F3: =IF($A3="","",基本信息!A3) | G3: =IF($A3="","",计算结果!BI3+计算结果!BJ3) | H3: =IF($A3="","",计算结果!BK3)
A4: =IF(AND(OR(IFERROR(FIND("交行",基本信息!BS4),0)>0,IFERROR(FIND("交通银行",基本信息!BS4),0)>0),计算结果!BT4=0>0),基本信息!BR4,"") | B4: =IF($A4="","",基本信息!BQ4) | C4: =IF($A4="","",计算结果!BT4-G4-H4) | D4: =IF($A4="","",基本信息!BS4) | F4: =IF($A4="","",基本信息!A4) | G4: =IF($A4="","",计算结果!BI4+计算结果!BJ4) | H4: =IF($A4="","",计算结果!BK4)
A5: =IF(AND(OR(IFERROR(FIND("交行",基本信息!BS5),0)>0,IFERROR(FIND("交通银行",基本信息!BS5),0)>0),计算结果!BT5=0>0),基本信息!BR5,"") | B5: =IF($A5="","",基本信息!BQ5) | C5: =IF($A5="","",计算结果!BT5-G5-H5) | D5: =IF($A5="","",基本信息!BS5) | F5: =IF($A5="","",基本信息!A5) | G5: =IF($A5="","",计算结果!BI5+计算结果!BJ5) | H5: =IF($A5="","",计算结果!BK5)
A6: =IF(AND(OR(IFERROR(FIND("交行",基本信息!BS6),0)>0,IFERROR(FIND("交通银行",基本信息!BS6),0)>0),计算结果!BT6=0>0),基本信息!BR6,"") | B6: =IF($A6="","",基本信息!BQ6) | C6: =IF($A6="","",计算结果!BT6-G6-H6) | D6: =IF($A6="","",基本信息!BS6) | F6: =IF($A6="","",基本信息!A6) | G6: =IF($A6="","",计算结果!BI6+计算结果!BJ6) | H6: =IF($A6="","",计算结果!BK6)
A7: =IF(AND(OR(IFERROR(FIND("交行",基本信息!BS7),0)>0,IFERROR(FIND("交通银行",基本信息!BS7),0)>0),计算结果!BT7=0>0),基本信息!BR7,"") | B7: =IF($A7="","",基本信息!BQ7) | C7: =IF($A7="","",计算结果!BT7-G7-H7) | D7: =IF($A7="","",基本信息!BS7) | F7: =IF($A7="","",基本信息!A7) | G7: =IF($A7="","",计算结果!BI7+计算结果!BJ7) | H7: =IF($A7="","",计算结果!BK7)
A8: =IF(AND(OR(IFERROR(FIND("交行",基本信息!BS8),0)>0,IFERROR(FIND("交通银行",基本信息!BS8),0)>0),计算结果!BT8=0>0),基本信息!BR8,"") | B8: =IF($A8="","",基本信息!BQ8) | C8: =IF($A8="","",计算结果!BT8-G8-H8) | D8: =IF($A8="","",基本信息!BS8) | F8: =IF($A8="","",基本信息!A8) | G8: =IF($A8="","",计算结果!BI8+计算结果!BJ8) | H8: =IF($A8="","",计算结果!BK8)
A9: =IF(AND(OR(IFERROR(FIND("交行",基本信息!BS9),0)>0,IFERROR(FIND("交通银行",基本信息!BS9),0)>0),计算结果!BT9=0>0),基本信息!BR9,"") | B9: =IF($A9="","",基本信息!BQ9) | C9: =IF($A9="","",计算结果!BT9-G9-H9) | D9: =IF($A9="","",基本信息!BS9) | F9: =IF($A9="","",基本信息!A9) | G9: =IF($A9="","",计算结果!BI9+计算结果!BJ9) | H9: =IF($A9="","",计算结果!BK9)
A10: =IF(AND(OR(IFERROR(FIND("交行",基本信息!BS10),0)>0,IFERROR(FIND("交通银行",基本信息!BS10),0)>0),计算结果!BT10=0>0),基本信息!BR10,"") | B10: =IF($A10="","",基本信息!BQ10) | C10: =IF($A10="","",计算结果!BT10-G10-H10) | D10: =IF($A10="","",基本信息!BS10) | F10: =IF($A10="","",基本信息!A10) | G10: =IF($A10="","",计算结果!BI10+计算结果!BJ10) | H10: =IF($A10="","",计算结果!BK10)
A11: =IF(AND(OR(IFERROR(FIND("交行",基本信息!BS11),0)>0,IFERROR(FIND("交通银行",基本信息!BS11),0)>0),计算结果!BT11=0>0),基本信息!BR11,"") | B11: =IF($A11="","",基本信息!BQ11) | C11: =IF($A11="","",计算结果!BT11-G11-H11) | D11: =IF($A11="","",基本信息!BS11) | F11: =IF($A11="","",基本信息!A11) | G11: =IF($A11="","",计算结果!BI11+计算结果!BJ11) | H11: =IF($A11="","",计算结果!BK11)
A12: =IF(AND(OR(IFERROR(FIND("交行",基本信息!BS12),0)>0,IFERROR(FIND("交通银行",基本信息!BS12),0)>0),计算结果!BT12=0>0),基本信息!BR12,"") | B12: =IF($A12="","",基本信息!BQ12) | C12: =IF($A12="","",计算结果!BT12-G12-H12) | D12: =IF($A12="","",基本信息!BS12) | F12: =IF($A12="","",基本信息!A12) | G12: =IF($A12="","",计算结果!BI12+计算结果!BJ12) | H12: =IF($A12="","",计算结果!BK12)
A13: =IF(AND(OR(IFERROR(FIND("交行",基本信息!BS13),0)>0,IFERROR(FIND("交通银行",基本信息!BS13),0)>0),计算结果!BT13=0>0),基本信息!BR13,"") | B13: =IF($A13="","",基本信息!BQ13) | C13: =IF($A13="","",计算结果!BT13-G13-H13) | D13: =IF($A13="","",基本信息!BS13) | F13: =IF($A13="","",基本信息!A13) | G13: =IF($A13="","",计算结果!BI13+计算结果!BJ13) | H13: =IF($A13="","",计算结果!BK13)
A14: =IF(AND(OR(IFERROR(FIND("交行",基本信息!BS14),0)>0,IFERROR(FIND("交通银行",基本信息!BS14),0)>0),计算结果!BT14=0>0),基本信息!BR14,"") | B14: =IF($A14="","",基本信息!BQ14) | C14: =IF($A14="","",计算结果!BT14-G14-H14) | D14: =IF($A14="","",基本信息!BS14) | F14: =IF($A14="","",基本信息!A14) | G14: =IF($A14="","",计算结果!BI14+计算结果!BJ14) | H14: =IF($A14="","",计算结果!BK14)
A15: =IF(AND(OR(IFERROR(FIND("交行",基本信息!BS4),0)>0,IFERROR(FIND("交通银行",基本信息!BS4),0)>0),计算结果!BT4>0),基本信息!BR4,"") | B15: =IF($A15="","",基本信息!BQ4) | C15: =IF($A15="","",计算结果!BT4-G15-H15) | D15: =IF($A15="","",基本信息!BS4) | F15: =IF($A15="","",基本信息!A4) | G15: =IF($A15="","",计算结果!BI4+计算结果!BJ4) | H15: =IF($A15="","",计算结果!BK4)
A16: =IF(AND(OR(IFERROR(FIND("交行",基本信息!BS5),0)>0,IFERROR(FIND("交通银行",基本信息!BS5),0)>0),计算结果!BT5>0),基本信息!BR5,"") | B16: =IF($A16="","",基本信息!BQ5) | C16: =IF($A16="","",计算结果!BT5-G16-H16) | D16: =IF($A16="","",基本信息!BS5) | F16: =IF($A16="","",基本信息!A5) | G16: =IF($A16="","",计算结果!BI5+计算结果!BJ5) | H16: =IF($A16="","",计算结果!BK5)
A17: =IF(AND(OR(IFERROR(FIND("交行",基本信息!BS6),0)>0,IFERROR(FIND("交通银行",基本信息!BS6),0)>0),计算结果!BT6>0),基本信息!BR6,"") | B17: =IF($A17="","",基本信息!BQ6) | C17: =IF($A17="","",计算结果!BT6-G17-H17) | D17: =IF($A17="","",基本信息!BS6) | F17: =IF($A17="","",基本信息!A6) | G17: =IF($A17="","",计算结果!BI6+计算结果!BJ6) | H17: =IF($A17="","",计算结果!BK6)
A18: =IF(AND(OR(IFERROR(FIND("交行",基本信息!BS7),0)>0,IFERROR(FIND("交通银行",基本信息!BS7),0)>0),计算结果!BT7>0),基本信息!BR7,"") | B18: =IF($A18="","",基本信息!BQ7) | C18: =IF($A18="","",计算结果!BT7-G18-H18) | D18: =IF($A18="","",基本信息!BS7) | F18: =IF($A18="","",基本信息!A7) | G18: =IF($A18="","",计算结果!BI7+计算结果!BJ7) | H18: =IF($A18="","",计算结果!BK7)
A19: =IF(AND(OR(IFERROR(FIND("交行",基本信息!BS8),0)>0,IFERROR(FIND("交通银行",基本信息!BS8),0)>0),计算结果!BT8>0),基本信息!BR8,"") | B19: =IF($A19="","",基本信息!BQ8) | C19: =IF($A19="","",计算结果!BT8-G19-H19) | D19: =IF($A19="","",基本信息!BS8) | F19: =IF($A19="","",基本信息!A8) | G19: =IF($A19="","",计算结果!BI8+计算结果!BJ8) | H19: =IF($A19="","",计算结果!BK8)
A20: =IF(AND(OR(IFERROR(FIND("交行",基本信息!BS9),0)>0,IFERROR(FIND("交通银行",基本信息!BS9),0)>0),计算结果!BT9>0),基本信息!BR9,"") | B20: =IF($A20="","",基本信息!BQ9) | C20: =IF($A20="","",计算结果!BT9-G20-H20) | D20: =IF($A20="","",基本信息!BS9) | F20: =IF($A20="","",基本信息!A9) | G20: =IF($A20="","",计算结果!BI9+计算结果!BJ9) | H20: =IF($A20="","",计算结果!BK9)
A21: =IF(AND(OR(IFERROR(FIND("交行",基本信息!BS10),0)>0,IFERROR(FIND("交通银行",基本信息!BS10),0)>0),计算结果!BT10>0),基本信息!BR10,"") | B21: =IF($A21="","",基本信息!BQ10) | C21: =IF($A21="","",计算结果!BT10-G21-H21) | D21: =IF($A21="","",基本信息!BS10) | F21: =IF($A21="","",基本信息!A10) | G21: =IF($A21="","",计算结果!BI10+计算结果!BJ10) | H21: =IF($A21="","",计算结果!BK10)
A22: =IF(AND(OR(IFERROR(FIND("交行",基本信息!BS11),0)>0,IFERROR(FIND("交通银行",基本信息!BS11),0)>0),计算结果!BT11>0),基本信息!BR11,"") | B22: =IF($A22="","",基本信息!BQ11) | C22: =IF($A22="","",计算结果!BT11-G22-H22) | D22: =IF($A22="","",基本信息!BS11) | F22: =IF($A22="","",基本信息!A11) | G22: =IF($A22="","",计算结果!BI11+计算结果!BJ11) | H22: =IF($A22="","",计算结果!BK11)
A23: =IF(AND(OR(IFERROR(FIND("交行",基本信息!BS12),0)>0,IFERROR(FIND("交通银行",基本信息!BS12),0)>0),计算结果!BT12>0),基本信息!BR12,"") | B23: =IF($A23="","",基本信息!BQ12) | C23: =IF($A23="","",计算结果!BT12-G23-H23) | D23: =IF($A23="","",基本信息!BS12) | F23: =IF($A23="","",基本信息!A12) | G23: =IF($A23="","",计算结果!BI12+计算结果!BJ12) | H23: =IF($A23="","",计算结果!BK12)
A24: =IF(AND(OR(IFERROR(FIND("交行",基本信息!BS13),0)>0,IFERROR(FIND("交通银行",基本信息!BS13),0)>0),计算结果!BT13>0),基本信息!BR13,"") | B24: =IF($A24="","",基本信息!BQ13) | C24: =IF($A24="","",计算结果!BT13-G24-H24) | D24: =IF($A24="","",基本信息!BS13) | F24: =IF($A24="","",基本信息!A13) | G24: =IF($A24="","",计算结果!BI13+计算结果!BJ13) | H24: =IF($A24="","",计算结果!BK13)
A25: =IF(AND(OR(IFERROR(FIND("交行",基本信息!BS14),0)>0,IFERROR(FIND("交通银行",基本信息!BS14),0)>0),计算结果!BT14>0),基本信息!BR14,"") | B25: =IF($A25="","",基本信息!BQ14) | C25: =IF($A25="","",计算结果!BT14-G25-H25) | D25: =IF($A25="","",基本信息!BS14) | F25: =IF($A25="","",基本信息!A14) | G25: =IF($A25="","",计算结果!BI14+计算结果!BJ14) | H25: =IF($A25="","",计算结果!BK14)
A26: =IF(AND(OR(IFERROR(FIND("交行",基本信息!BS15),0)>0,IFERROR(FIND("交通银行",基本信息!BS15),0)>0),计算结果!BT15>0),基本信息!BR15,"") | B26: =IF($A26="","",基本信息!BQ15) | C26: =IF($A26="","",计算结果!BT15-G26-H26) | D26: =IF($A26="","",基本信息!BS15) | F26: =IF($A26="","",基本信息!A15) | G26: =IF($A26="","",计算结果!BI15+计算结果!BJ15) | H26: =IF($A26="","",计算结果!BK15)
... A584: =IF(AND(OR(IFERROR(FIND("交行",基本信息!BS573),0)>0,IFERROR(FIND("交通银行",基本信息!BS573),0)>0),计算结果!BT573>0),基本信息!BR573,"") | B584: =IF($A584="","",基本信息!BQ573) | C584: =IF($A584="","",计算结果!BT573-G584-H584) | D584: =IF($A584="","",基本信息!BS573) | F584: =IF($A584="","",基本信息!A573) | G584: =IF($A584="","",计算结果!BI573+计算结果!BJ573) | H584: =IF($A584="","",计算结果!BK573)
A585: =IF(AND(OR(IFERROR(FIND("交行",基本信息!#REF!),0)>0,IFERROR(FIND("交通银行",基本信息!#REF!),0)>0),计算结果!BT574>0),基本信息!#REF!,"") | B585: =IF($A585="","",基本信息!#REF!) | C585: =IF($A585="","",计算结果!BT574-G585-H585) | D585: =IF($A585="","",基本信息!#REF!) | F585: =IF($A585="","",基本信息!#REF!) | G585: =IF($A585="","",计算结果!BI574) | H585: =IF($A585="","",计算结果!BK574)
A586: =IF(AND(OR(IFERROR(FIND("交行",基本信息!#REF!),0)>0,IFERROR(FIND("交通银行",基本信息!#REF!),0)>0),计算结果!BT575>0),基本信息!#REF!,"") | B586: =IF($A586="","",基本信息!#REF!) | C586: =IF($A586="","",计算结果!BT575-G586-H586) | D586: =IF($A586="","",基本信息!#REF!) | F586: =IF($A586="","",基本信息!#REF!) | G586: =IF($A586="","",计算结果!BI575) | H586: =IF($A586="","",计算结果!BK575)
A587: =IF(AND(OR(IFERROR(FIND("交行",基本信息!#REF!),0)>0,IFERROR(FIND("交通银行",基本信息!#REF!),0)>0),计算结果!BT576>0),基本信息!#REF!,"") | B587: =IF($A587="","",基本信息!#REF!) | C587: =IF($A587="","",计算结果!BT576-G587-H587) | D587: =IF($A587="","",基本信息!#REF!) | F587: =IF($A587="","",基本信息!#REF!) | G587: =IF($A587="","",计算结果!BI576) | H587: =IF($A587="","",计算结果!BK576)
A588: =IF(AND(OR(IFERROR(FIND("交行",基本信息!#REF!),0)>0,IFERROR(FIND("交通银行",基本信息!#REF!),0)>0),计算结果!BT577>0),基本信息!#REF!,"") | B588: =IF($A588="","",基本信息!#REF!) | C588: =IF($A588="","",计算结果!BT577-G588-H588) | D588: =IF($A588="","",基本信息!#REF!) | F588: =IF($A588="","",基本信息!#REF!) | G588: =IF($A588="","",计算结果!BI577) | H588: =IF($A588="","",计算结果!BK577)
A589: =IF(AND(OR(IFERROR(FIND("交行",基本信息!#REF!),0)>0,IFERROR(FIND("交通银行",基本信息!#REF!),0)>0),计算结果!BT578>0),基本信息!#REF!,"") | B589: =IF($A589="","",基本信息!#REF!) | C589: =IF($A589="","",计算结果!BT578-G589-H589) | D589: =IF($A589="","",基本信息!#REF!) | F589: =IF($A589="","",基本信息!#REF!) | G589: =IF($A589="","",计算结果!BI578) | H589: =IF($A589="","",计算结果!BK578)
A590: =IF(AND(OR(IFERROR(FIND("交行",基本信息!#REF!),0)>0,IFERROR(FIND("交通银行",基本信息!#REF!),0)>0),计算结果!BT579>0),基本信息!#REF!,"") | B590: =IF($A590="","",基本信息!#REF!) | C590: =IF($A590="","",计算结果!BT579-G590-H590) | D590: =IF($A590="","",基本信息!#REF!) | F590: =IF($A590="","",基本信息!#REF!) | G590: =IF($A590="","",计算结果!BI579) | H590: =IF($A590="","",计算结果!BK579)
A591: =IF(AND(OR(IFERROR(FIND("交行",基本信息!#REF!),0)>0,IFERROR(FIND("交通银行",基本信息!#REF!),0)>0),计算结果!BT580>0),基本信息!#REF!,"") | B591: =IF($A591="","",基本信息!#REF!) | C591: =IF($A591="","",计算结果!BT580-G591-H591) | D591: =IF($A591="","",基本信息!#REF!) | F591: =IF($A591="","",基本信息!#REF!) | G591: =IF($A591="","",计算结果!BI580) | H591: =IF($A591="","",计算结果!BK580)
A592: =IF(AND(OR(IFERROR(FIND("交行",基本信息!#REF!),0)>0,IFERROR(FIND("交通银行",基本信息!#REF!),0)>0),计算结果!BT581>0),基本信息!#REF!,"") | B592: =IF($A592="","",基本信息!#REF!) | C592: =IF($A592="","",计算结果!BT581-G592-H592) | D592: =IF($A592="","",基本信息!#REF!) | F592: =IF($A592="","",基本信息!#REF!) | G592: =IF($A592="","",计算结果!BI581) | H592: =IF($A592="","",计算结果!BK581)
A593: =IF(AND(OR(IFERROR(FIND("交行",基本信息!#REF!),0)>0,IFERROR(FIND("交通银行",基本信息!#REF!),0)>0),计算结果!BT582>0),基本信息!#REF!,"") | B593: =IF($A593="","",基本信息!#REF!) | C593: =IF($A593="","",计算结果!BT582-G593-H593) | D593: =IF($A593="","",基本信息!#REF!) | F593: =IF($A593="","",基本信息!#REF!) | G593: =IF($A593="","",计算结果!BI582) | H593: =IF($A593="","",计算结果!BK582)
A594: =IF(AND(OR(IFERROR(FIND("交行",基本信息!#REF!),0)>0,IFERROR(FIND("交通银行",基本信息!#REF!),0)>0),计算结果!BT583>0),基本信息!#REF!,"") | B594: =IF($A594="","",基本信息!#REF!) | C594: =IF($A594="","",计算结果!BT583-G594-H594) | D594: =IF($A594="","",基本信息!#REF!) | F594: =IF($A594="","",基本信息!#REF!) | G594: =IF($A594="","",计算结果!BI583) | H594: =IF($A594="","",计算结果!BK583)

Sheet 其他行发薪
A1: =基本信息!BR1 -> 银行账号 | B1: =基本信息!BQ1 -> 银行户名 | C1: =计算结果!BU1 -> 实发 | D1: =基本信息!BS1 -> 银行 | E1: 开户地 | F1: =基本信息!A1 -> 客户简称 | G1: 报销款 | H1: 外籍生活津贴
A2: =IF(OR(OR(IFERROR(FIND("交行",基本信息!BS2),0)>0,IFERROR(FIND("交通银行",基本信息!BS2),0)>0),计算结果!BT2=0),"",基本信息!BR2) -> 6227007200020223600 | B2: =IF($A2="","",基本信息!BQ2) -> 杨明华 | C2: =IF($A2="","",计算结果!BU2-G2-H2) -> 30353.93 | D2: =IF($A2="","",基本信息!BS2) -> 中国建设银行股份有限公司深圳分行福田支行 | F2: =IF($A2="","",基本信息!A2) -> NNRoad-Hermetic Solutions | G2: =IF($A2="","",计算结果!BI2+计算结果!BJ2) -> 0 | H2: =IF($A2="","",计算结果!BK2) -> 0
A3: =IF(OR(OR(IFERROR(FIND("交行",基本信息!BS3),0)>0,IFERROR(FIND("交通银行",基本信息!BS3),0)>0),计算结果!BT3=0),"",基本信息!BR3) | B3: =IF($A3="","",基本信息!BQ3) | C3: =IF($A3="","",计算结果!BT3-G3-H3) | D3: =IF($A3="","",基本信息!BS3) | F3: =IF($A3="","",基本信息!A3) | G3: =IF($A3="","",计算结果!BI3+计算结果!BJ3) | H3: =IF($A3="","",计算结果!BK3)
A4: =IF(OR(OR(IFERROR(FIND("交行",基本信息!BS4),0)>0,IFERROR(FIND("交通银行",基本信息!BS4),0)>0),计算结果!BT4=0),"",基本信息!BR4) | B4: =IF($A4="","",基本信息!BQ4) | C4: =IF($A4="","",计算结果!BT4-G4-H4) | D4: =IF($A4="","",基本信息!BS4) | F4: =IF($A4="","",基本信息!A4) | G4: =IF($A4="","",计算结果!BI4+计算结果!BJ4) | H4: =IF($A4="","",计算结果!BK4)
A5: =IF(OR(OR(IFERROR(FIND("交行",基本信息!BS5),0)>0,IFERROR(FIND("交通银行",基本信息!BS5),0)>0),计算结果!BT5=0),"",基本信息!BR5) | B5: =IF($A5="","",基本信息!BQ5) | C5: =IF($A5="","",计算结果!BT5-G5-H5) | D5: =IF($A5="","",基本信息!BS5) | F5: =IF($A5="","",基本信息!A5) | G5: =IF($A5="","",计算结果!BI5+计算结果!BJ5) | H5: =IF($A5="","",计算结果!BK5)
A6: =IF(OR(OR(IFERROR(FIND("交行",基本信息!BS6),0)>0,IFERROR(FIND("交通银行",基本信息!BS6),0)>0),计算结果!BT6=0),"",基本信息!BR6) | B6: =IF($A6="","",基本信息!BQ6) | C6: =IF($A6="","",计算结果!BT6-G6-H6) | D6: =IF($A6="","",基本信息!BS6) | F6: =IF($A6="","",基本信息!A6) | G6: =IF($A6="","",计算结果!BI6+计算结果!BJ6) | H6: =IF($A6="","",计算结果!BK6)
A7: =IF(OR(OR(IFERROR(FIND("交行",基本信息!BS7),0)>0,IFERROR(FIND("交通银行",基本信息!BS7),0)>0),计算结果!BT7=0),"",基本信息!BR7) | B7: =IF($A7="","",基本信息!BQ7) | C7: =IF($A7="","",计算结果!BT7-G7-H7) | D7: =IF($A7="","",基本信息!BS7) | F7: =IF($A7="","",基本信息!A7) | G7: =IF($A7="","",计算结果!BI7+计算结果!BJ7) | H7: =IF($A7="","",计算结果!BK7)
A8: =IF(OR(OR(IFERROR(FIND("交行",基本信息!BS8),0)>0,IFERROR(FIND("交通银行",基本信息!BS8),0)>0),计算结果!BT8=0),"",基本信息!BR8) | B8: =IF($A8="","",基本信息!BQ8) | C8: =IF($A8="","",计算结果!BT8-G8-H8) | D8: =IF($A8="","",基本信息!BS8) | F8: =IF($A8="","",基本信息!A8) | G8: =IF($A8="","",计算结果!BI8+计算结果!BJ8) | H8: =IF($A8="","",计算结果!BK8)
A9: =IF(OR(OR(IFERROR(FIND("交行",基本信息!BS9),0)>0,IFERROR(FIND("交通银行",基本信息!BS9),0)>0),计算结果!BT9=0),"",基本信息!BR9) | B9: =IF($A9="","",基本信息!BQ9) | C9: =IF($A9="","",计算结果!BT9-G9-H9) | D9: =IF($A9="","",基本信息!BS9) | F9: =IF($A9="","",基本信息!A9) | G9: =IF($A9="","",计算结果!BI9+计算结果!BJ9) | H9: =IF($A9="","",计算结果!BK9)
A10: =IF(OR(OR(IFERROR(FIND("交行",基本信息!BS10),0)>0,IFERROR(FIND("交通银行",基本信息!BS10),0)>0),计算结果!BT10=0),"",基本信息!BR10) | B10: =IF($A10="","",基本信息!BQ10) | C10: =IF($A10="","",计算结果!BT10-G10-H10) | D10: =IF($A10="","",基本信息!BS10) | F10: =IF($A10="","",基本信息!A10) | G10: =IF($A10="","",计算结果!BI10+计算结果!BJ10) | H10: =IF($A10="","",计算结果!BK10)
A11: =IF(OR(OR(IFERROR(FIND("交行",基本信息!BS11),0)>0,IFERROR(FIND("交通银行",基本信息!BS11),0)>0),计算结果!BT11=0),"",基本信息!BR11) | B11: =IF($A11="","",基本信息!BQ11) | C11: =IF($A11="","",计算结果!BT11-G11-H11) | D11: =IF($A11="","",基本信息!BS11) | F11: =IF($A11="","",基本信息!A11) | G11: =IF($A11="","",计算结果!BI11+计算结果!BJ11) | H11: =IF($A11="","",计算结果!BK11)
A12: =IF(OR(OR(IFERROR(FIND("交行",基本信息!BS12),0)>0,IFERROR(FIND("交通银行",基本信息!BS12),0)>0),计算结果!BT12=0),"",基本信息!BR12) | B12: =IF($A12="","",基本信息!BQ12) | C12: =IF($A12="","",计算结果!BT12-G12-H12) | D12: =IF($A12="","",基本信息!BS12) | F12: =IF($A12="","",基本信息!A12) | G12: =IF($A12="","",计算结果!BI12+计算结果!BJ12) | H12: =IF($A12="","",计算结果!BK12)
A13: =IF(OR(OR(IFERROR(FIND("交行",基本信息!BS13),0)>0,IFERROR(FIND("交通银行",基本信息!BS13),0)>0),计算结果!BT13=0),"",基本信息!BR13) | B13: =IF($A13="","",基本信息!BQ13) | C13: =IF($A13="","",计算结果!BT13-G13-H13) | D13: =IF($A13="","",基本信息!BS13) | F13: =IF($A13="","",基本信息!A13) | G13: =IF($A13="","",计算结果!BI13+计算结果!BJ13) | H13: =IF($A13="","",计算结果!BK13)
A14: =IF(OR(OR(IFERROR(FIND("交行",基本信息!BS14),0)>0,IFERROR(FIND("交通银行",基本信息!BS14),0)>0),计算结果!BT14=0),"",基本信息!BR14) | B14: =IF($A14="","",基本信息!BQ14) | C14: =IF($A14="","",计算结果!BT14-G14-H14) | D14: =IF($A14="","",基本信息!BS14) | F14: =IF($A14="","",基本信息!A14) | G14: =IF($A14="","",计算结果!BI14+计算结果!BJ14) | H14: =IF($A14="","",计算结果!BK14)
... A389: =IF(OR(OR(IFERROR(FIND("交行",基本信息!BS389),0)>0,IFERROR(FIND("交通银行",基本信息!BS389),0)>0),计算结果!BT389=0),"",基本信息!BR389) | B389: =IF($A389="","",基本信息!BQ389) | C389: =IF($A389="","",计算结果!BT389-G389-H389) | D389: =IF($A389="","",基本信息!BS389) | F389: =IF($A389="","",基本信息!A389) | G389: =IF($A389="","",计算结果!BI389+计算结果!BJ389) | H389: =IF($A389="","",计算结果!BK389)

Sheet Formula Statement
A1: S-Payslip 公式说明
A2: No. 序号 | B2: Department 部门 | C2: ID No. 工号 | D2: Name 姓名 | E2: Plus Item 加项 | K2: Basis for Social Benefits Calculation 社保基数 | L2: Basis for Housing Fund Calculation 公积金基数 | M2: Minus Item 减项 | W2: Other 其他 | X2: IIT 个税 | Y2: Balance For Charge On Behalf 代缴费用补差 | Z2: Expenses 报销款 | AA2: Subsistence Allowance for Foreigners 外籍生活津贴 | AB2: Net Income 实发
E3: Basic Salary 基本工资 | F3: Bonus 日常奖金 | G3: Annual Bonus/13th Salary 年终奖/13薪 | H3: Allowance/Subsidy 津贴/补贴 | I3: OT Payment 加班费 | J3: Income Employer Afford Tax 公司负税项 | K3: Basis for Social Benefits Calculation 社保基数 | L3: Basis for Housing Fund Calculation 公积金基数 | M3: Pension 缴养老 | N3: Medical 缴医疗 | O3: Unemployment 缴失业 | P3: Housing Fund 缴公积金 | Q3: Deduction for 1st/last Month' Absence 入离职缺勤扣 | R3: Deduction for Personal Leave 扣事假 | S3: Deduction for Absenteeism 扣旷工 | T3: Deduction for Sick Leave 扣病假 | U3: Annuity 缴年金 | V3: Union Fee 工会费
A4: 1 | C4: 0001 | D4: AAA | E4: 28644.3 | F4: 0 | G4: 0 | H4: 0 | I4: 0 | J4: 0 | K4: 16208 | L4: 17300 | M4: 1296.64 | N4: 329.16 | O4: 81.04 | P4: 1730 | Q4: 0 | R4: 0 | S4: 0 | T4: 0 | U4: 0 | V4: 0 | W4: 0 | X4: 4421.87 | Y4: 0 | Z4: 0 | AA4: 0 | AB4: 20785.59
E5: E | F5: F | G5: G | H5: H | I5: I | J5: J | K5: K | L5: L | M5: M | N5: N | O5: O | P5: P | Q5: Q | R5: R | S5: S | T5: T | U5: U | V5: V | W5: W | X5: X | Y5: Y | Z5: Z | AA5: AA | AB5: AB
A7: E（工资）=基本工资+日薪*日薪出勤天数+浮动工资 E(Salary) = Basic Salary + Daily Salary*Attendance Days of Daily Salary + Floating Salary
A8: F（日常奖金）=月奖+季奖 F(Bonus) = Monthly Bonus + Quarterly Bonus
A9: G（年终奖/13薪）=年终奖或13薪 G(Annual Bonus/13th Salary) = Annual Bonus or 13th Salary
A10: H（津贴/补贴）=（交通津贴+交通费）+（通讯津贴+通讯费）+其他固定津贴+（中班津贴基数*中班天数）+（夜班津贴基数*夜班天数）+（高温津贴基数*高温天数+一次性高温费）+（高温作业保健食品费基数*高温作业天数）+（有毒有害保健食品费基数*有毒有害作业天数）+独生子女费 H(Allowance/Subsidy)=(Transportation Allowance + Travelling Expenses) +(Phone Allowance + Phone Expenses)+Other Regular Allowance +(Basis for Middle Shift Allowance Calculation * Middle Shift Days) +(Basis for Night Shift Allowance Calculation * Night Shift Days)+(Basis for High Temperature Allowance Calculation * High Temperature Days + One-off High Temperature Charges)+(Basis for Health Foods Allowance for Employees Working in High Temperature Environment Calculation * Days of Working in High Temperature Environment)+(Basis for Health Food Allowance of Poisonous or Noxious Substances * Days of Contacting with Poisonous or Noxious Substances) + The Only-child Allowance
A11: I（加班费）=（（基本工资+日薪*日薪出勤天数）*加班小时*倍数/21.75*8） I(OT Payment) = ((Basic Salary + Daily Salary * Attendance Days of Daily Salary)* Overtime Hours * Multiple/21.75*8 )
B12: 倍数：平时加班1.5倍；双休日加班2倍；国定假日加班3倍 Multiple: 1.5 times salary when work overtime during workdays; double salary when work overtime during rest days; 3 times salary when work overtime during national holidays
A13: J（公司负税项）=税后补发 J(Income Employer Afford Tax) = Reissue After-tax
A14: K（当年社保基数） K(Basis for Social Benefits Calculation of the Year)
A15: L（当年公积金基数） L(Basis for Housing Fund Calculation of the Year)
A16: M（缴养老）=K*个人养老保险比例 M(Pension) = K*Rate of Individual Pension Insurance
A17: N（缴医疗）=K*个人医疗保险比例 N(Medical) = K*Rate of Individual Medical Insurance
A18: O（缴失业）=K*个人失业保险比例 O(Unemployment) = K*Rate of Individual Unemployment Insurance
A19: P（缴公积金）=个人基本公积金+个人补充公积金（免税） P(Housing Fund)=Individual Basic Housing Fund + Supplementary Housing Fund(duty free)
A20: Q（入离职缺勤扣）Deduction for 1st/last Month' Absence
A21: R（扣事假） | B21: Deduction for Personal Leave
A22: S（扣旷工） | B22: Deduction for Absenteeism
A23: T（扣病假） | B23: Deduction for Sick Leave
A24: U（缴年金）=E*年金% U(Annuity) = E*Annuity%
A25: V（工会费）=工会费 V(Union Fee) = Union Fee
A26: W（其他）=(固定补+补发)-(固定扣+补扣)+(免税收入+税后补)-税后扣 W(Other) = (Fixed Deduction+Reissue)+(Duty-free Income+Reissue After-tax)-Deducton After-tax
A27: X（个税）=应纳税所得额*所得额税率（%）－速算扣除数 X(IIT) = Taxable Income*Income Tax rate(%) - Deduction for Fast Calculation
A28: Y（代缴费用补差）=个人社保调整+个人公积金调整 Y(Balance For Charge On Behalf) = Adjusted Individual Social Insurance+Adjusted Individual Housing Fund
A29: Z（报销款）(Expenses)
A30: AA（外籍生活津贴） | B30: (Subsistence Allowance for Foreigners)
A31: AB（实发）=加项-减项+其他-个税+代缴费用补差 AB(Net Income) = Plus Item-Minus Item+Other+Balance For Charge On Behalf
A33: 社保缴纳地 Socil Benefit Location | B33: 个人养老% Individual Pension | C33: 个人医疗% Individual Medical | D33: 个人失业% Individual Unemployment | E33: 个人公积金% Individual Housing Fund | F33: 个人医疗固定数 Individual Medical Fixed Amount | G33: 公司养老% Employer Pension | H33: 公司医疗% Employer Medical | I33: 公司失业% Employer Unemployment | J33: 公司生育% Employer Maternity | K33: 公司工伤% Employer Work-Related-Injury | L33: 公司残保金% Employer Disability | M33: 公司公积金% Employer Housing Fund | N33: 公司医疗固定数 Employer Medical Fixed Amount | O33: 公司残保固定数 Employer Disability Fixed Amount
A35: s | B35: 0.08 | C35: 0.02 | D35: 0.005 | E35: 0.12 | G35: 0.14 | H35: 0.105 | I35: 0.005 | J35: 0.012 | K35: 0.005 | L35: 0.015 | M35: 0.12
A36: 上海 | B36: 0.08 | C36: 0.02 | D36: 0.005 | E36: 0.07 | G36: 0.2 | H36: 0.095 | I36: 0.005 | J36: 0.01 | K36: 0.0032 | L36: 0.015 | M36: 0.07
A37: 成都 | B37: 0.08 | C37: 0.02 | D37: 0.004 | E37: 0.06 | G37: 0.19 | H37: 0.075 | I37: 0.006 | J37: 0.008 | K37: 0.0022 | M37: 0.06
A38: 北京 | B38: 0.08 | C38: 0.02 | D38: 0.002 | E38: 0.12 | F38: 3 | G38: 0.19 | H38: 0.1 | I38: 0.008 | J38: 0.008 | K38: 0.004 | L38: 0.017 | M38: 0.12
A39: 深圳 | B39: 0.08 | C39: 0.02 | D39: 0.005 | E39: 0.12 | G39: 0.14 | H39: 0.062 | I39: 0.01 | J39: 0.005 | K39: 0.0022 | M39: 0.12
A40: 济南 | B40: 0.08 | C40: 0.02 | D40: 0.003 | E40: 0.12 | G40: 0.18 | H40: 0.09 | I40: 0.007 | J40: 0.01 | K40: 0.004 | M40: 0.12
A41: 南京 | B41: 0.08 | C41: 0.02 | D41: 0.005 | E41: 0.08 | G41: 0.19 | H41: 0.09 | I41: 0.005 | J41: 0.008 | K41: 0.002 | M41: 0.08
A42: 哈尔滨 | B42: 0.08 | C42: 0.02 | D42: 0.005 | E42: 0.08 | F42: 2.5 | G42: 0.2 | H42: 0.075 | I42: 0.005 | J42: 0.006 | K42: 0.009 | M42: 0.08 | N42: 2.5
A43: 广州 | B43: 0.08 | C43: 0.02 | D43: 0.002 | E43: 0.1 | G43: 0.14 | H43: 0.07 | I43: 0.006 | J43: 0.0085 | K43: 0.0032 | M43: 0.08 | N43: 21.37 | O43: 63.76
A46: S-Payroll Report 公式说明
A47: No. 序号 | B47: Department 部门 | C47: ID No. 工号 | D47: Name 姓名 | E47: Net Income 员工实得 | F47: Expenses 报销款 | G47: Expenses+Subsistence Allowance for Foreigners 外籍生活津贴 | H47: Individual Portion 个人部分 | P47: Employer Portion 雇主部分 | AD47: Total Cost 总成本 | AE47: Remark 备注
G48: 外籍生活津贴 | H48: Pension 养老 | I48: Medical 医疗 | J48: Unemployment 失业 | K48: Housing Fund 公积金 | L48: Annuity 年金 | M48: Union Fee 工会费 | N48: IIT 个税 | O48: Balance For Charge On Behalf 代缴费用补差 | P48: Pension 养老 | Q48: Medical 医疗 | R48: Unemployment 失业 | S48: Maternity 生育 | T48: Work-Related-Injury 工伤 | U48: Disability 残保金 | V48: Housing Fund 公积金 | W48: Annuity 年金 | X48: Union Fee 工会费 | Y48: Commercial Insurance 商业保险 | Z48: Other Benefits 其他福利 | AA48: Service Fee 服务费 | AB48: Deposit 押金 | AC48: Others 其他
A49: 1 | C49: 0001 | D49: AAA | E49: 20785.59 | F49: 0 | G49: 0 | H49: 1296.64 | I49: 329.16 | J49: 81.04 | K49: 1730 | L49: 0 | M49: 0 | N49: 4421.87 | O49: 0 | P49: 3241.6 | Q49: 1458.72 | R49: 243.12 | S49: 162.08 | T49: 162.08 | U49: 0 | V49: 1730 | Y49: 0 | AA49: 200 | AD49: 35841.9
E50: AB | F50: Z | G50: AA | H50: M | I50: N | J50: O | K50: P | L50: U | M50: V | N50: X | O50: Y | P50: AC | Q50: AD | R50: AE | S50: AF | T50: AG | U50: AH | V50: AJ | W50: AK | X50: AL | Y50: AM | Z50: AN | AA50: AO | AB50: AP | AC50: AQ | AD50: AR | AE50: AS
A52: AC（养老）=K*单位养老保险比例 AC(Pension) = K*Rate of Employer Pension Insurance
A53: AD（医疗）=K*单位医疗保险比例 AD(Medical) = K*Rate of Employer Medical Insurance
A54: AE（失业）=K*单位失业保险比例 AE(Unemplyment) = K*Rate of Employer Unemployment Insurance
A55: AF（生育）=K*单位生育保险比例 AF(Maternity) = K*Rate of Employer Maternity Insurance
A56: AG（工伤）=K*单位工伤保险比例 AG(Work-Related-Injury) = K*Rate of Employer Work-Related-Injury Insurance
A57: AH（残保金）=(单位上年度在职职工总数*1.5%(上海市为1.6%)－已安排残疾职工人数)*本地区上年度职工年平均工资 AH(Disability) = (Total of Staff of the Last Year *1.5%(1.6% for Shanghai)- Number of Arranged Disabled Staff)*Average Salary of the Local Staff Last Year
A58: AJ（公积金）=单位基本公积金+单位补充公积金（免税）+单位补充公积金（不免税）AJ(Housing Fund)=Employer Basic Housing Fund + Employer Supplementary Housing Fund(duty free) + Supplementary Housing Fund(not duty freee)
A59: AK（年金）=年金 Annuity
A60: AL（工会费）=工会费 Union Fee
A61: AM（商业保险）=商业保险总费用 Commercial Insurance
A62: AN（其他福利）=单位社保调整+单位公积金调整 AN(Other Benefits) = Adjusted Employer Social Insurance+Adjusted Employer Housing Fund
A63: AO（服务费）=服务费 Service Fee
... A67: AS（备注）=当月特殊说明 AS(Remark) = Special Enquiries of the month

Sheet 各地政策
C1: Individual | J1: Employer | T1: Social Insurance | W1: Housing Fund
A2: 城市 | C2: 养老% | D2: 医疗% | E2: 失业% | F2: 公积金% | G2: 医疗固定数 | J2: 养老% | K2: 医疗% | L2: 失业% | M2: 生育 | N2: 工伤 | O2: 公积金 | P2: 医疗固定数 | Q2: 工伤固定数 | T2: 保留小数位 | U2: 末尾后处理 | W2: 保留小数位 | X2: 末尾后处理 | Y2: 离职补偿金免税额
A3: 北京 | C3: 0.08 | D3: 0.02 | E3: 0.002 | F3: 0.12 | G3: 3 | J3: 0.2 | K3: 0.1 | L3: 0.01 | M3: 0.008 | N3: 0.005 | O3: 0.12 | T3: 2 | U3: 四舍五入 | W3: 0 | X3: 四舍五入 | Y3: 454080
A4: 常州 | T4: 2 | U4: 四舍五入 | W4: 0 | X4: 四舍五入
A5: 成都 | C5: 0.08 | D5: 0.02 | E5: 0.01 | F5: 0.08 | J5: 0.2 | K5: 0.077 | L5: 0.02 | M5: 0.006 | N5: 0.006 | O5: 0.08 | T5: 2 | U5: 四舍五入 | W5: 0 | X5: 四舍五入
A6: 大连 | C6: 0.08 | D6: 0.02 | E6: 0.01 | F6: 0.12 | J6: 0.2 | K6: 0.08 | L6: 0.02 | M6: 0.008 | N6: 0.006 | O6: 0.12 | T6: 2 | U6: 四舍五入 | W6: 0 | X6: 四舍五入
A7: 佛山 | C7: 0.08 | D7: 0.02 | E7: 0.01 | F7: 0.05 | J7: 0.1 | K7: 0.06 | L7: 0.01 | M7: 0.005 | N7: 0.005 | O7: 0.05 | T7: 2 | U7: 四舍五入 | W7: 0 | X7: 四舍五入
A8: 广州 | C8: 0.08 | D8: 0.02 | E8: 0.01 | F8: 0.12 | J8: 0.12 | K8: 0.08 | L8: 0.02 | M8: 0.0085 | N8: 0.005 | O8: 0.08 | P8: 11.81 | T8: 2 | U8: 四舍五入 | W8: 0 | X8: 四舍五入
A9: 哈尔滨 | T9: 2 | U9: 四舍五入 | W9: 0 | X9: 四舍五入
A10: 海宁 | T10: 2 | U10: 四舍五入 | W10: 0 | X10: 四舍五入
A11: 杭州 | C11: 0.08 | D11: 0.02 | E11: 0.01 | F11: 0.12 | G11: 4 | J11: 0.14 | K11: 0.115 | L11: 0.02 | M11: 0.008 | N11: 0.005 | O11: 0.12 | T11: 2 | U11: 四舍五入 | W11: 0 | X11: 四舍五入
A12: 惠州
A13: 吉林 | C13: 0.08 | D13: 0.02 | E13: 0.01 | F13: 0.05 | J13: 0.2 | K13: 0.06 | L13: 0.02 | M13: 0.007 | N13: 0.006 | O13: 0.05 | P13: 8 | T13: 2 | U13: 四舍五入 | W13: 0 | X13: 四舍五入
A14: 济南 | T14: 2 | U14: 四舍五入 | W14: 0 | X14: 四舍五入
A15: 嘉兴 | T15: 2 | U15: 四舍五入 | W15: 0 | X15: 四舍五入
A16: 金华 | T16: 2 | U16: 四舍五入 | W16: 0 | X16: 四舍五入
A17: 昆山 | T17: 2 | U17: 四舍五入 | W17: 0 | X17: 四舍五入
A18: 柳州 | C18: 0.08 | D18: 0.02 | E18: 0.01 | F18: 0.08 | J18: 0.2 | K18: 0.075 | L18: 0.02 | M18: 0.009 | N18: 0.005 | O18: 0.08 | T18: 1 | U18: 四舍五入 | W18: 0 | X18: 四舍五入
A19: 南京 | T19: 2 | U19: 四舍五入 | W19: 0 | X19: 四舍五入
A20: 南通 | C20: 0.08 | D20: 0.02 | E20: 0.01 | F20: 0.08 | G20: 10 | J20: 0.2 | K20: 0.08 | L20: 0.02 | M20: 0.008 | N20: 0.005 | O20: 0.08 | T20: 1 | U20: 进位 | W20: 0 | X20: 四舍五入
A21: 青岛 | T21: 2 | U21: 四舍五入 | W21: 0 | X21: 四舍五入
A22: 泉州 | C22: 0.08 | D22: 0.02 | E22: 0.01 | F22: 0.12 | J22: 0.18 | K22: 0.075 | L22: 0.02 | M22: 0.007 | N22: 0.005 | O22: 0.12 | T22: 2 | U22: 四舍五入 | W22: 0 | X22: 四舍五入
A23: 瑞安 | T23: 2 | U23: 四舍五入 | W23: 0 | X23: 四舍五入
A24: 汕头 | C24: 0.08 | D24: 0.02 | E24: 0.01 | F24: 0.08 | J24: 0.15 | K24: 0.06 | L24: 0.01 | M24: 0.0045 | N24: 0.005 | O24: 0.08 | T24: 1 | U24: 进位 | W24: 0 | X24: 四舍五入
A25: 上海 | C25: 0.08 | D25: 0.02 | E25: 0.01 | F25: 0.07 | J25: 0.22 | K25: 0.12 | L25: 0.017 | M25: 0.008 | N25: 0.005 | O25: 0.07 | T25: 1 | U25: 进位 | W25: 0 | X25: 四舍五入 | Y25: 372168
A26: 上海过渡 | T26: 1 | U26: 进位 | W26: 0 | X26: 四舍五入
A27: 深圳 | T27: 2 | U27: 四舍五入 | W27: 2 | X27: 四舍五入
A28: 石家庄 | T28: 2 | U28: 四舍五入 | W28: 0 | X28: 四舍五入
A29: 顺德 | C29: 0.08 | D29: 0.02 | E29: 0.005 | F29: 0.12 | J29: 0.11 | K29: 0.056 | L29: 0.005 | M29: 0.009 | N29: 0.0045 | O29: 0.12 | T29: 2 | U29: 四舍五入 | W29: 0 | X29: 四舍五入
A30: 苏州 | T30: 2 | U30: 四舍五入 | W30: 0 | X30: 四舍五入
A31: 苏州工业园 | C31: 0.01 | D31: 0.0175 | E31: 0.0125 | F31: 0.18 | J31: 0.01 | K31: 0.01 | L31: 0.0125 | M31: 0.0075 | N31: 0.002 | O31: 0.18 | T31: 1 | U31: 进位 | W31: 0 | X31: 四舍五入
A32: 太仓 | T32: 2 | U32: 四舍五入 | W32: 0 | X32: 四舍五入
A33: 泰安 | T33: 2 | U33: 四舍五入 | W33: 0 | X33: 四舍五入
A34: 泰州 | C34: 0.08 | D34: 0.023 | E34: 0.01 | F34: 0.1 | J34: 0.21 | K34: 0.095 | L34: 0.02 | M34: 0.01 | N34: 0.008 | O34: 0.1 | Q34: 19.5 | T34: 2 | U34: 四舍五入 | W34: 0 | X34: 四舍五入
A35: 天津 | C35: 0.08 | D35: 0.02 | E35: 0.01 | F35: 0.11 | J35: 0.2 | K35: 0.1 | L35: 0.02 | M35: 0.008 | N35: 0.005 | O35: 0.11 | T35: 2 | U35: 四舍五入 | W35: 0 | X35: 四舍五入
A36: 潍坊
A37: 温州 | C37: 0.08 | D37: 0.02 | E37: 0.01 | F37: 0.12 | G37: 9 | J37: 0.14 | K37: 0.095 | L37: 0.02 | M37: 0.006 | N37: 0.004 | O37: 0.12 | T37: 2 | U37: 四舍五入 | W37: 0 | X37: 四舍五入
A38: 无锡 | C38: 0.08 | D38: 0.02 | E38: 0.01 | F38: 0.12 | J38: 0.2 | K38: 0.082 | L38: 0.02 | M38: 0.009 | N38: 0.008 | O38: 0.12 | T38: 2 | U38: 四舍五入 | W38: 0 | X38: 四舍五入
A39: 吴江
A40: 武汉 | T40: 2 | U40: 四舍五入 | W40: 0 | X40: 四舍五入
A41: 萧山 | C41: 0.08 | D41: 0.02 | E41: 0.01 | F41: 0.12 | G41: 4 | J41: 0.14 | K41: 0.115 | L41: 0.02 | M41: 0.012 | N41: 0.005 | O41: 0.12 | T41: 2 | U41: 四舍五入 | W41: 0 | X41: 四舍五入
A42: 扬州 | T42: 2 | U42: 四舍五入 | W42: 0 | X42: 四舍五入
A43: 义乌 | C43: 0.08 | D43: 0.02 | E43: 0.01 | F43: 0.12 | J43: 0.12 | K43: 0.07 | L43: 0.02 | M43: 0.008 | N43: 0.005 | O43: 0.12 | T43: 2 | U43: 进位 | W43: 0 | X43: 四舍五入
A44: 张家港 | T44: 2 | U44: 四舍五入 | W44: 0 | X44: 进位
A45: 长沙 | C45: 0.08 | D45: 0.02 | E45: 0.003 | F45: 0.1 | J45: 0.16 | K45: 0.07 | L45: 0.007 | M45: 0.007 | N45: 0.002 | O45: 0.1 | T45: 2 | U45: 四舍五入 | W45: 0 | X45: 进位
A46: 东莞 | C46: 0.08 | D46: 0.02 | E46: 0.01 | F46: 0.08 | J46: 0.2 | K46: 0.077 | L46: 0.02 | M46: 0.006 | N46: 0.006 | O46: 0.08 | T46: 2 | U46: 四舍五入 | W46: 0 | X46: 四舍五入
A47: 泉州 | C47: 0.08 | D47: 0.02 | E47: 0.005 | F47: 0.12 | J47: 0.18 | K47: 0.075 | L47: 0.005 | M47: 0.005 | N47: 0.009 | O47: 0.12 | T47: 2 | U47: 四舍五入 | W47: 0 | X47: 四舍五入
A48: 阜阳 | T48: 2 | U48: 四舍五入 | W48: 0 | X48: 四舍五入
A49: 宁波 | T49: 2 | U49: 四舍五入 | W49: 0 | X49: 四舍五入
A50: 福州 | T50: 2 | U50: 四舍五入 | W50: 0 | X50: 四舍五入
A51: 重庆 | C51: 0.08 | D51: 0.02 | E51: 0.005 | F51: 0.12 | G51: 5 | J51: 0.16 | K51: 0.1 | L51: 0.005 | N51: 0.006 | O51: 0.12 | T51: 2 | U51: 四舍五入 | W51: 0 | X51: 四舍五入
A121: 1 | B121: 2 | C121: 3 | D121: 4 | E121: 5 | F121: 6 | G121: 7 | H121: 8 | I121: 9 | J121: 10 | K121: 11 | L121: 12 | M121: 13 | N121: 14 | O121: 15 | P121: 16 | Q121: 17 | R121: 18 | S121: 19 | T121: 20 | U121: 21 | V121: 22 | W121: 23 | X121: 24

Sheet 批注
A1: 基本信息 | I1: 国家代码
I2: 阿富汗 | J2: 004
A3: 用工性质 | B3: 1-中国大陆籍正式 | I3: 阿尔巴尼亚 | J3: 008
B4: 2-外籍及港澳台非居民 | I4: 南极洲 | J4: 010
B5: 3-实习、退休、临时 | I5: 阿尔及利亚 | J5: 012
B6: 4-实习学生（全日制学历教育） | I6: 美属萨摩亚 | J6: 016
I7: 安道尔 | J7: 020
A8: 税前/税后 | B8: 1-税前 | I8: 安哥拉 | J8: 024
B9: 2-税后 | I9: 安提瓜和巴布达 | J9: 028
I10: 阿塞拜疆 | J10: 031
A11: 独生子女津贴基数 | B11: 不享受，不输入 | I11: 阿根廷 | J11: 032
I12: 澳大利亚 | J12: 036
A13: 证件类型 | B13: 1-居民身份证 | I13: 奥地利 | J13: 040
B14: 2-外国护照 | I14: 巴哈马 | J14: 044
B15: 3-港澳居民居住证 | I15: 巴林 | J15: 048
B16: 4-台湾居民居住证 | I16: 孟加拉国 | J16: 050
B17: 5-台湾居民来往大陆通行证 | I17: 亚美尼亚 | J17: 051
B18: 6-港澳居民来往内地通行证 | I18: 巴巴多斯 | J18: 052
B19: 7-中国护照 | I19: 比利时 | J19: 056
B20: 8-外国人永久居留身份证 | I20: 百慕大 | J20: 060
B21: 9-外国人工作许可证（A类） | I21: 不丹 | J21: 064
B22: 10-外国人工作许可证（B类） | I22: 玻利维亚 | J22: 068
B23: 11-外国人工作许可证（C类） | I23: 波斯尼亚和黑塞哥维那 | J23: 070
B24: 12-其他个人证件 | I24: 博茨瓦纳 | J24: 072
I25: 布维岛 | J25: 074
I26: 巴西 | J26: 076
I27: 伯利兹 | J27: 084
I28: 英属印度洋领土 | J28: 086
I29: 所罗门群岛 | J29: 090
I30: 英属维尔京群岛 | J30: 092
I31: 文莱 | J31: 096
I32: 保加利亚 | J32: 100
I33: 缅甸 | J33: 104
I34: 布隆迪 | J34: 108
I35: 白俄罗斯 | J35: 112
I36: 柬埔寨 | J36: 116
... I71: Malvinas | J71: 238
I72: 南乔治亚岛和南桑德韦奇岛 | J72: 239
I73: 斐济 | J73: 242
I74: 芬兰 | J74: 246
I75: 法国 | J75: 250
I76: 法属圭亚那 | J76: 254
I77: 法属波利尼西亚 | J77: 258
I78: 法属南部领土 | J78: 260
I79: 吉布提 | J79: 262
I80: 加蓬 | J80: 266
I81: 格鲁吉亚 | J81: 268
I82: 冈比亚 | J82: 270
I83: 德国 | J83: 276
I84: 加纳 | J84: 288
... I164: 北马里亚纳 | J164: 580
I165: 美属太平洋各群岛(包括:中途岛、约翰斯顿岛、豪兰岛、贝克岛和威克岛等) | J165: 581
I166: 密克罗尼西亚 | J166: 583
I167: 马绍尔群岛 | J167: 584
I168: 贝劳 | J168: 585
I169: 巴基斯坦 | J169: 586
I170: 巴拿马 | J170: 591
I171: 巴布亚新几内亚 | J171: 598
I172: 巴拉圭 | J172: 600
I173: 秘鲁 | J173: 604
I174: 菲律宾 | J174: 608
I175: 皮特凯恩群岛 | J175: 612
I176: 波兰 | J176: 616
I177: 葡萄牙 | J177: 620
... I190: 圣皮埃尔和密克隆 | J190: 666
I191: 圣文森特和格林纳丁斯 | J191: 670
I192: 圣马力诺 | J192: 674
I193: 圣多美和普林西比 | J193: 678
I194: 沙竺阿拉伯 | J194: 682
I195: 塞内加尔 | J195: 686
I196: 塞舌尔 | J196: 690
I197: 塞拉利昂 | J197: 694
I198: 新加坡 | J198: 702
I199: 斯洛伐克 | J199: 703
I200: 越南 | J200: 704
I201: 斯洛文尼亚 | J201: 705
I202: 索马里 | J202: 706
I203: 南非 | J203: 710
I204: 津巴布韦 | J204: 716
I205: 西班牙 | J205: 724
... I240: 赞比亚 | J240: 894
