Workbook

Sheet PN
B1: NNRoad – Employer of Record, Payroll Worldwide
B2: 333 W San Carlos St., Suite 600, San Jose, CA 95113, USA
B3: USA: +1 (669) 377-5080 | www.NNRoad.com
A5: INVOICE
A7: Bill to:
A8: Company name: | B8: ERI | D8: Currency | F8: USD
A9: Client ID: | B9: CUS1510 | D9: Invoice number | F9: PN-CUS1510-060520262
A10: Address: | B10: 1579 Desert Island Drive, Fresno, CA 93720 | D10: Invoice date | F10: =TODAY() -> 46233
D11: Due date | F11: 46190
A14: Description | E14: ="Amount "&UK!C6 -> Amount (GBP) | F14: Approx. In USD*
A15: EOR/PEO Cost | E15: =SUM(E16:E19) -> 0 | F15: =SUM(F16:F19) -> #DIV/0!
A16: ="- Labor cost for "&UK!B9&" - "&MONTH(UK!B2)&"-"&YEAR(UK!B2) -> - Labor cost for {Employee Name} - 7-2026 | E16: =UK!J9+UK!N9+UK!Q9 -> 0 | F16: =E16/$B$29 -> #DIV/0!
A21: Service Fee | E21: =SUM(E22:E23) -> 450 | F21: =SUM(F22:F23) -> #DIV/0!
A22: ="- "&+"Management Fee - "&MONTH(UK!B2)&"-"&YEAR(UK!B2) -> - Management Fee - 7-2026 | E22: =UK!G6 -> 450 | F22: =E22/$B$29 -> #DIV/0!
A26: EOR/PEO Service Cost | E26: =E15+E21 -> 450 | F26: =F15+F21 -> #DIV/0!
A29: ="*FX rate USD: "&UK!C6 -> *FX rate USD: (GBP) | B29: =1/'UK-L'!D24 -> #DIV/0! | D29: EOR/PEO Service Cost | F29: =F26 -> #DIV/0!
D30: Outstanding payment | F30: =UK!E22 -> 0
D31: FX difference | F31: =UK!E23 -> 0
D32: Interests of delay | F32: =UK!E24 -> 0
D33: Bank Charges | F33: =UK!E25 -> 10
D34: Sub Total (Excluding Tax) | F34: =SUM(F29:F33) -> #DIV/0!
D35: Tax | F35: =UK!F6/B29 -> #DIV/0!
D36: Total | F36: =SUM(F34:F35) -> #DIV/0!
A40: Please pay the Invoice in FULL AMOUNT
A41: Beneficiary: NNROAD, INC. Bank Name: Chase Bank Bank Account: 132827913 Bank Add.: 690 River Oaks Parkway Ste A, San Jose, CA 95134, USA | D41: SWIFT BIC (international transfer): CHASUS33XXX Routing Number (domestic wire transfer): 021000021 Routing Number (domestic ACH and direct deposit): 322271627
A42: Notes:
A43: 1. Please ensure that you include the Invoice Number when making your payment. This will help us accurately process and allocate your payment .
A44: 2. This document becomes a Tax Invoice/Receipt upon payment. Please retain a copy for your records.
A45: 3. This is a computer generated document. No Signature required.

Sheet UK
A1: UK
A2: Pay Period | B2: =EOMONTH('UK-L'!B3,-1)+1 -> 46204 | C2: =EOMONTH('UK-L'!B3,0) -> 46234 | E2: ER
E3: Sum | F3: Business Tax | G3: Management Fee Fee | J3: Gross Salary | N3: Mandatory Contribution | Q3: Other Pay For EE | S3: Expense Claim
G4: Subtotal | H4: Recurring Fee | I4: Expense Fee | J4: Subtotal | K4: Basic Salary | L4: Holiday Pay | M4: Car Allowance | N4: Subtotal | O4: ER' NIC | P4: ER' Pension (Auto Enrolment) | Q4: Subtotal | R4: App Levy | S4: Subtotal | T4: Expense Claim
B6: Sum | C6: (GBP) | E6: =SUM(E9:E18) -> 450 | F6: =SUM(F9:F18) -> 0 | G6: =SUM(G9:G18) -> 450 | H6: =SUM(H9:H18) -> 450 | I6: =SUM(I9:I18) -> 0 | J6: =SUM(J9:J18) -> 0 | K6: =SUM(K9:K18) -> 0 | L6: =SUM(L9:L18) -> 0 | ... T6: =SUM(T9:T18) -> 0
B9: {Employee Name} | E9: =+S9+Q9+N9+J9+G9+F9 -> 450 | F9: 0 | G9: =SUM(H9:I9) -> 450 | H9: 450 | I9: =IF(S9=0,0,15) -> 0 | J9: =SUM(K9:M9) -> 0 | K9: ='UK-L'!B7 -> 0 | L9: ='UK-L'!B8 -> 0 | M9: ='UK-L'!B9 -> 0 | N9: =SUM(O9:P9) -> 0 | O9: ='UK-L'!B10 -> 0 | P9: ='UK-L'!B11 -> 0 | Q9: =SUM(R9:R9) -> 0 | R9: ='UK-L'!B22 -> 0 | S9: =SUM(T9:T9) -> 0 | T9: 0
A21: Other Fee | E21: =SUM(E22:E26) -> 10 | F21: 0
B22: Outstanding payment
B23: FX difference | F23: 0
B24: Interests of delay | F24: 0
B25: Bank Charges | E25: =10 -> 10
B26: Invoice adjustment | E26: 0

Sheet UK EE
A1: UK EE
H2: EE
B3: Client Code | C3: Client Name | D3: EE Code | E3: EE Name | F3: Pay Period | H3: Net Income | I3: Gross Salary | M3: Expense Claim | O3: Mandatory Contribution
F4: From | G4: To | I4: Subtotal | J4: Basic Salary | K4: Holiday Pay | L4: Car Allowance | M4: Subtotal | N4: Expense Claim | O4: Subtotal | P4: PAYE (Estimated) | Q4: EE'NIC | R4: EE' Pension (Auto Enrolment)
A6: EOR/PEO(GBP)
B9: CUS1510 | C9: =PN!$B$8 -> ERI | E9: =UK!B9 -> {Employee Name} | F9: =UK!B2 -> 46204 | G9: =UK!C2 -> 46234 | H9: =I9+M9-O9 -> 0 | I9: =SUM(J9:L9) -> 0 | J9: ='UK-L'!B7 -> 0 | K9: ='UK-L'!B8 -> 0 | L9: ='UK-L'!B9 -> 0 | M9: =SUM(N9:N9) -> 0 | N9: =UK!T9 -> 0 | O9: =SUM(P9:R9) -> 0 | P9: ='UK-L'!B14 -> 0 | Q9: ='UK-L'!B15 -> 0 | R9: ='UK-L'!B16 -> 0

Sheet UK-L
A3: {Employee Name}- Salary Calculation for FY {FY} | B3: =TODAY() -> 46233
A5: Details | B5: Amount in GBP
A6: Days Paid | B6: Full Month
A7: Gross Salary | B7: 0
A8: Holiday Pay | B8: 0
A9: Car Allowance | B9: 0
A10: ER' NIC | B10: 0
A11: ER' Pension (Auto Enrolment) | B11: 0
A12: Gross Salary + Er NIC | B12: =+B7+B9+B10+B11+B8 -> 0
A14: PAYE (Estimated) | B14: 0
A15: EE'NIC | B15: 0
A16: EE' Pension (Auto Enrolment) | B16: 0
A18: Net Salary | B18: =(B7+B9+B8)-(B14+B15+B16) -> 0
A20: Total Cost | B20: =B12 -> 0
A22: App Levy | B22: 0
C23: Amount in USD | D23: Exchange Rate
A24: Depsoit Invoice Amount | B24: =+B20+B22 -> 0 | C24: =B24*D24 -> 0
A25: Setup Fees | C25: =B25*D24 -> 0
A26: Payment Fees | B26: 0 | C26: =B26*D24 -> 0
A27: Regular Monthly Invoice Amount | B27: =SUM(B24:B26) -> 0 | C27: =SUM(C24:C26) -> 0
