Workbook

Sheet PN
B1: NNRoad – Employer of Record, Payroll Worldwide
B2: 333 W San Carlos St., Suite 600, San Jose, CA 95113, USA
B3: USA: +1 (669) 377-5080 | www.NNRoad.com
A5: INVOICE
A7: Bill to:
A8: Company name: | B8: Animal Equality | D8: Currency | F8: USD
A9: Client ID: | B9: CUS1513 | D9: Invoice number | F9: PN-CUS1513-031620261
A10: Address: | B10: 8581 Santa Monica Blvd. Ste. 350 Los Angeles, CA 90069 | D10: Invoice date | F10: =TODAY() -> 46097
D11: Due date | F11: 46104
A14: Description | E14: ="Amount "&Italy!C6 -> Amount EUR | F14: Approx. In USD*
A15: EOR/PEO Cost | E15: =SUM(E16:E17) -> 10743.51 | F15: =SUM(F16:F17) -> 12681.737
A16: ="- Labor cost for "&Italy!B9&" - "&MONTH(Italy!B2) &"-"& YEAR(Italy!B2) -> - Labor cost for CUPIMATTEO - 3-2026 | E16: =Italy!I9+Italy!Q9 -> 10743.51 | F16: =E16/$B$28 -> 12681.737
A17: ="- "&+"Expense claim for "&Italy!B9 -> - Expense claim for CUPIMATTEO | E17: =Italy!W9 -> 0 | F17: =E17/$B$28 -> 0
A20: Service Fee | E20: =SUM(E21:E22) -> 1128.0685 | F20: =SUM(F21:F22) -> 1331.5823
A21: ="- "&+"Management Fee - "&MONTH(Italy!B2) &"-"& YEAR(Italy!B2) -> - Management Fee - 3-2026 | E21: =Italy!H9 -> 1128.0685 | F21: =E21/$B$28 -> 1331.5823
A25: EOR/PEO Service Cost | E25: =E15+E20 -> 11871.579 | F25: =F15+F20 -> 14013.319
A28: ="*FX rate USD: "&Italy!C6 -> *FX rate USD: EUR | B28: =0.87336489*0.97 -> 0.84716394 | D28: EOR/PEO Service Cost | F28: =F25 -> 14013.319
D29: Outstanding payment | F29: =Italy!E22 -> 0
D30: FX difference | F30: =Italy!E23 -> 0
D31: Interests of delay | F31: =Italy!E24 -> 0
D32: Bank Charges | F32: =Italy!E25 -> 10
D33: Sub Total (Excluding Tax) | F33: =SUM(F28:F32) -> 14023.319
D34: Tax | F34: =Italy!F6/B28 -> 0
D35: Total | F35: =SUM(F33:F34) -> 14023.319
A39: Please pay the Invoice in FULL AMOUNT
A40: Beneficiary: NNROAD, INC. Bank Name: Chase Bank Bank Account: 132827913 Bank Add.: 690 River Oaks Parkway Ste A, San Jose, CA 95134, USA | D40: SWIFT BIC (international transfer): CHASUS33XXX Routing Number (domestic wire transfer): 021000021 Routing Number (domestic ACH and direct deposit): 322271627
A41: Notes:
A42: 1. Please ensure that you include the Invoice Number when making your payment. This will help us accurately process and allocate your payment .
A43: 2. This document becomes a Tax Invoice/Receipt upon payment. Please retain a copy for your records.
A44: 3. This is a computer generated document. No Signature required.

Sheet Italy
A1: =MID(CELL("filename",A1),FIND("]",CELL("filename",A1))+1,256) -> Italy
A2: Pay Period | B2: =EOMONTH(TODAY(),-1)+1 -> 46082 | C2: =EOMONTH(TODAY(),0) -> 46112 | E2: ER
E3: Sum | F3: Business Tax | G3: Management Fee | I3: Gross Salary | Q3: Mandatory Contribution | W3: Expense Claim
G4: Subtotal | H4: Recurring Fee | I4: Subtotal | J4: ='Italy-L'!K10 -> Jul 2025 Salary | K4: ='Italy-L'!N10 -> Vacation Leave | L4: Bonus | M4: ='Italy-L'!O10 -> 13th and 14th Accrual | N4: ='Italy-L'!P10 -> Vacation Accruals | O4: ='Italy-L'!Q10 -> Monthly Permitted Leave (Permessi Hours Ex-Fs) | P4: ='Italy-L'!R10 -> Monthly Permitted Leave ROL Accrual | Q4: Subtotal | R4: ='Italy-L'!L10 -> Social Cost | S4: ='Italy-L'!M10 -> Social contributions for accruals | T4: ='Italy-L'!S10 -> Unemployment Fund (TFR) Accrual | U4: ='Italy-L'!T10 -> Overheads | V4: ='Italy-L'!U10 -> Bilateral Trade Association | W4: Subtotal | X4: Expense Claim
B6: Sum | C6: EUR | E6: =SUM(E9:E17) -> 11871.579 | F6: =SUM(F9:F17) -> 0 | G6: =SUM(G9:G17) -> 1128.0685 | H6: =SUM(H9:H17) -> 1128.0685 | I6: =SUM(I9:I17) -> 7902.48 | J6: =SUM(J9:J17) -> 6071.42 | K6: =SUM(K9:K17) -> 505.96 | L6: =SUM(L9:L17) -> 0 | ... X6: =SUM(X9:X17) -> 0
B9: ='Italy-L'!B11 -> CUPIMATTEO | C9: ='Italy EE'!D10 -> CUS1513-0001 | E9: =F9+G9+I9+Q9+W9 -> 11871.579 | F9: 0 | G9: =SUM(H9:H9) -> 1128.0685 | H9: =MAX(750,(I9+Q9+X9)*10.5%) -> 1128.0685 | I9: =SUM(J9:P9) -> 7902.48 | J9: ='Italy-L'!K11 -> 6071.42 | K9: ='Italy-L'!N11 -> 505.96 | L9: ='Italy-L'!V11 -> 0 | M9: ='Italy-L'!O11 -> 1011.9 | N9: ='Italy-L'!P11 -> 0 | O9: ='Italy-L'!Q11 -> 96.37 | P9: ='Italy-L'!R11 -> 216.83 | Q9: =SUM(R9:V9) -> 2841.03 | R9: ='Italy-L'!L11 -> 1828.46 | S9: ='Italy-L'!M11 -> 570.31 | T9: ='Italy-L'!S11 -> 378.82 | U9: ='Italy-L'!T11 -> 60.71 | V9: ='Italy-L'!U11 -> 2.73 | W9: =SUM(X9:X9) -> 0 | X9: 0
A21: Other Fee | E21: =SUM(E22:E26) -> 10 | F21: 0
B22: Outstanding payment
B23: FX difference | F23: 0
B24: Interests of delay | F24: 0
B25: Bank Charges | E25: =10 -> 10
B26: Invoice adjustment | E26: 0

Sheet Italy EE
A1: =MID(CELL("filename",A1),FIND("]",CELL("filename",A1))+1,256) -> Italy EE
H2: EE
B3: Client Code | C3: Client Name | D3: EE Code | E3: EE Name | F3: Pay Period | H3: Net Income | I3: Gross Salary | M3: Expense Claim | O3: Mandatory Contribution | Q3: Deduction
F4: From | G4: To | I4: Subtotal | J4: ='Italy-L'!K10 -> Jul 2025 Salary | K4: ='Italy-L'!N10 -> Vacation Leave | L4: Bonus | M4: Subtotal | N4: Expense Claim | O4: Subtotal | P4: Other
A6: EOR/PEO(EUR)
B10: CUS1513 | C10: =PN!B8 -> Animal Equality | D10: CUS1513-0001 | E10: ='Italy-L'!B11 -> CUPIMATTEO | F10: =Italy!B2 -> 46082 | G10: =Italy!C2 -> 46112 | H10: =I10+M10-O10-Q10 -> 6577.38 | I10: =SUM(J10:L10) -> 6577.38 | J10: ='Italy-L'!K11 -> 6071.42 | K10: ='Italy-L'!N11 -> 505.96 | L10: ='Italy-L'!V11 -> 0 | M10: =SUM(N10:N10) -> 0 | N10: =0 -> 0 | O10: =SUM(P10:P10) -> 0 | P10: 0 | Q10: 0

Sheet Italy-L
B2: Customer | C2: Animal Equality
B3: Location | C3: Italy
B4: Workers | C4: =IF(COUNTA($B$11:$B$11)=0,"",COUNTA($B$11:$B$11)) -> 1
B5: Pay Period | C5: Mar'26
B6: SGWI VAT Code | C6: V9 | D6: ICE VAT Code | F6: V6
I8: SGWI Chargable | K8: Y | L8: Y | M8: Y | N8: N | O8: Y | P8: Y | Q8: Y | R8: Y | S8: Y | T8: Y | U8: Y
B10: Employee Name | C10: PO Number | D10: Fee %age Markup | E10: Fee Min | F10: Fee Minimum Currency | G10: Applied SGWI Min | H10: Applied SGWI Minimum Currency | I10: Currency | K10: Jul 2025 Salary | L10: Social Cost | M10: Social contributions for accruals | N10: Vacation Leave | O10: 13th and 14th Accrual | P10: Vacation Accruals | Q10: Monthly Permitted Leave (Permessi Hours Ex-Fs) | R10: Monthly Permitted Leave ROL Accrual | S10: Unemployment Fund (TFR) Accrual | T10: Overheads | U10: Bilateral Trade Association | V10: Legal Bonus (Una Tantum) | X10: Cost Basis | Z10: VAT | AA10: Invoice Total
B11: CUPIMATTEO | C11: - | D11: 0 | E11: 750 | F11: EUR | G11: =IFERROR(IF($B11="",0,IF($I11<>$F11,$E11/$G$8,$E11)),0) -> 750 | H11: =IF($B11="","",IF($F11="","",$I11)) -> EUR | I11: EUR | K11: 6071.42 | L11: 1828.46 | M11: 570.31 | N11: 505.96 | O11: 1011.9 | P11: 0 | Q11: 96.37 | R11: 216.83 | S11: 378.82 | T11: 60.71 | U11: 2.73 | V11: 0 | W11: 0 | X11: =ROUND(SUM($K11:$W11),2) -> 10743.51 | Y11: =ROUND(MAX(SUMPRODUCT(($K$8:$W$8="Y")*($K11:$W11))*$D11,$G11),2) -> 750 | Z11: =ROUND(IF($C$6="V2",SUM($X11:$Y11)*20%,0),2) -> 0 | AA11: =ROUND(SUM($X11:$Z11),2) -> 11493.51
B13: Fee Invoice Total | I13: =IF($I$11="","",$I$11) -> EUR | K13: =ROUND(SUM((K$11:K$11)),2) -> 6071.42 | L13: =ROUND(SUM((L$11:L$11)),2) -> 1828.46 | M13: =ROUND(SUM((M$11:M$11)),2) -> 570.31 | N13: =ROUND(SUM((N$11:N$11)),2) -> 505.96 | O13: =ROUND(SUM((O$11:O$11)),2) -> 1011.9 | P13: =ROUND(SUM((P$11:P$11)),2) -> 0 | Q13: =ROUND(SUM((Q$11:Q$11)),2) -> 96.37 | R13: =ROUND(SUM((R$11:R$11)),2) -> 216.83 | ... W13: =ROUND(SUM((W$11:W$11)),2) -> 0 | X13: =ROUND(SUM($K13:$W13),2) -> 10743.51 | Y13: =ROUND(SUM((Y$11:Y$11)),2) -> 750 | Z13: =ROUND(IF($C$6="V2",SUM($X13:$Y13)*20%,0),2) -> 0 | AA13: =ROUND(SUM($X13:$Z13),2) -> 11493.51

Sheet FI Report
A1: Direct Cost | B1: Business Tax | C1: Service Fee | D1: Bank Fee * | E1: Late Pay Fine | F1: Advance Payment | G1: Deposit | H1: Outstanding payment ** | I1: FX difference | J1: Invoice adjustment *** | K1: total
A2: =PN!F15 -> 12681.737 | B2: =PN!F34 -> 0 | C2: =PN!F20 -> 1331.5823 | D2: =PN!F32 -> 10 | E2: =PN!F31 -> 0 | F2: =0 -> 0 | G2: 0 | H2: =PN!F29 -> 0 | I2: =PN!F30 -> 0 | J2: 0 | K2: =SUM(A2:J2) -> 14023.319
A7: * NNRoad USD 10 + vendor bank in Vendor's invoice
A8: ** the differnece between NNRoad PN and the amount we actually received
A9: *** PN adjustment with pre-payment or PN revisal
