Workbook

Sheet PN
B1: NNRoad – Employer of Record, Payroll Worldwide
B2: 333 W San Carlos St., Suite 600, San Jose, CA 95113, USA
B3: USA: +1 (669) 377-5080 | www.NNRoad.com
A5: INVOICE
A7: Bill to:
A8: Company name: | D8: Currency
A9: Client ID: | D9: Invoice number
A10: Address: | D10: Invoice date
D11: Due date
A14: Description | E14: ="Amount "&TW!C6 -> Amount (NTD) | F14: Approx. In USD*
A15: EOR/PEO Cost | E15: =SUM(E16:E22) -> 0 | F15: =SUM(F16:F22) -> 0
A16: ="- Labor cost for "&TW!B9&" - "&MONTH(TW!$B$2)&"-"&YEAR(TW!$B$2) -> - Labor cost for 0 - 1-1900 | E16: =TW!J9+TW!Z9 -> 0 | F16: =E16/$B$31 -> 0
A17: ="- Labor cost for "&TW!B10&" - "&MONTH(TW!$B$2)&"-"&YEAR(TW!$B$2) -> - Labor cost for - 1-1900 | E17: =TW!J10+TW!Z10 -> 0 | F17: =E17/$B$31 -> 0
A18: ="- Labor cost for "&TW!B11&" - "&MONTH(TW!$B$2)&"-"&YEAR(TW!$B$2) -> - Labor cost for - 1-1900 | E18: =TW!J11+TW!Z11 -> 0 | F18: =E18/$B$31 -> 0
A19: ="- "&+"Expense claim for "&TW!B9 -> - Expense claim for 0 | E19: =TW!AB9 -> 0 | F19: =E19/$B$31 -> 0
A20: ="- "&+"Expense claim for "&TW!B10 -> - Expense claim for | E20: =TW!AB10 -> 0 | F20: =E20/$B$31 -> 0
A21: ="- "&+"Expense claim for "&TW!B11 -> - Expense claim for | E21: =TW!AB11 -> 0 | F21: =E21/$B$31 -> 0
A23: Service Fee | E23: =SUM(E24:E25) -> 4500 | F23: =SUM(F24:F25) -> 143.78053
A24: ="- "&+"Management Fee - "&MONTH(TW!B2)&"-"&YEAR(TW!B2) -> - Management Fee - 1-1900 | E24: =TW!G6 -> 4500 | F24: =E24/$B$31 -> 143.78053
A28: EOR/PEO Service Cost | E28: =E15+E23 -> 4500 | F28: =F15+F23 -> 143.78053
A31: ="*FX rate USD: "&TW!C6 -> *FX rate USD: (NTD) | B31: 31.2977 | D31: EOR/PEO Service Cost | F31: =F28 -> 143.78053
D32: Outstanding payment | F32: =TW!E22 -> 0
D33: FX difference | F33: =TW!E23 -> 0
D34: Interests of delay | F34: =TW!E24 -> 0
D35: Bank Charges | F35: =TW!E25 -> 10
D36: Sub Total (Excluding Tax) | F36: =SUM(F31:F35) -> 153.78053
D37: Tax | F37: =ROUNDUP(TW!F6/PN!B31,2)+0.01 -> 0.01
D38: Total | F38: =SUM(F36:F37) -> 153.79053
A42: Please pay the Invoice in FULL AMOUNT
A43: Beneficiary: NNROAD, INC. Bank Name: Chase Bank Bank Account: 132827913 Bank Add.: 690 River Oaks Parkway Ste A, San Jose, CA 95134, USA | D43: SWIFT BIC (international transfer): CHASUS33XXX Routing Number (domestic wire transfer): 021000021 Routing Number (domestic ACH and direct deposit): 322271627
A44: Notes:
A45: 1. Please ensure that you include the Invoice Number when making your payment. This will help us accurately process and allocate your payment .
A46: 2. This document becomes a Tax Invoice/Receipt upon payment. Please retain a copy for your records.
A47: 3. This is a computer generated document. No Signature required.

Sheet TW
A1: TW
A2: Pay Period | B2: ='TW-L'!C4 -> 0 | C2: ='TW-L'!C5 -> 0 | E2: ER
E3: Sum | F3: Business Tax | G3: Management Fee Fee | J3: Gross Salary | Z3: Mandatory Contribution | AB3: Expense Claim
G4: Subtotal | H4: Recurring Fee | I4: Expense Fee | J4: Subtotal | K4: Basic Salary | L4: Salary Adjustment | M4: OT | N4: Allw- Phone/ Communication | O4: Allw Transportation | P4: Back Pay | Q4: 伙食津貼Allw Meal | R4: Remote Stipend | S4: 病假扣薪 Sick Leave (half pay) | T4: NPL Hours | U4: No Pay Leave | V4: Bonus VB | W4: Incentives | X4: 特休結算 Untaken AL | Y4: 資遣費 Severance | Z4: Subtotal | AA4: ER insurance | AB4: Subtotal | AC4: Expense Claim
B6: Sum | C6: (NTD) | E6: =SUM(E9:E17) -> 4500 | F6: =SUM(F9:F17) -> 0 | G6: =SUM(G9:G17) -> 4500 | H6: =SUM(H9:H17) -> 4500 | I6: =SUM(I9:I17) -> 0 | J6: =SUM(J9:J17) -> 0 | K6: =SUM(K9:K17) -> 0 | L6: =SUM(L9:L17) -> 0 | ... AC6: =SUM(AC9:AC17) -> 0
B9: ='TW-L'!C9 -> 0 | C9: ='TW EE'!D10 -> 0 | E9: =SUM(F9:G9)+J9+Z9+AB9 -> 4500 | G9: =SUM(H9:I9) -> 4500 | H9: =MAX(4500,(J9+Z9)*12%) -> 4500 | I9: =IF(AB9>0,1500,0) -> 0 | J9: =SUM(K9:Y9) -> 0 | K9: ='TW-L'!N9 -> 0 | L9: 0 | M9: ='TW-L'!AC9 -> 0 | N9: ='TW-L'!O9 -> 0 | O9: ='TW-L'!P9 -> 0 | P9: ='TW-L'!Q9 -> 0 | Q9: ='TW-L'!R9 -> 0 | R9: ='TW-L'!R9 -> 0 | S9: ='TW-L'!U9 -> 0 | T9: ='TW-L'!V9 -> 0 | U9: ='TW-L'!W9 -> 0 | V9: ='TW-L'!X9 -> 0 | W9: ='TW-L'!Y9 -> 0 | X9: ='TW-L'!AA9 -> 0 | Y9: ='TW-L'!AB9 -> 0 | Z9: =SUM(AA9:AA9) -> 0 | AA9: ='TW-L'!BL9 -> 0 | AB9: =SUM(AC9:AC9) -> 0 | AC9: ='TW-L'!Z9 -> 0
A21: Other Fee | E21: =SUM(E22:E26) -> 10 | F21: 0
B22: Outstanding payment
B23: FX difference | F23: 0
B24: Interests of delay | F24: 0
B25: Bank Charges | E25: =10 -> 10
B26: Invoice adjustment | E26: 0

Sheet TW EE
A1: TW EE
H2: EE
B3: Client Code | C3: Client Name | D3: EE Code | E3: EE Name | F3: Pay Period | H3: Net Income | I3: Gross Salary | Y3: Expense Claim | AA3: Mandatory Contribution | AF3: Deduction | AG3: IIT
F4: From | G4: To | I4: Subtotal | J4: Basic Salary | K4: Salary Adjustment | L4: OT | M4: Allw- Phone/ Communication | N4: Allw Transportation | O4: Back Pay | P4: 伙食津貼 Allw Meal | Q4: Remote Stipend | R4: 病假扣薪 Sick Leave (half pay) | S4: NPL Hours | T4: No Pay Leave | U4: Bonus VB | V4: Incentives | W4: 特休結算 Untaken AL | X4: 資遣費 Severance | Y4: Subtotal | Z4: Expense Claim | AA4: Subtotal | AB4: LI | AC4: Pension | AD4: HI | AE4: 2G HI
A6: EOR/PEO(NTD)
B10: =PN!$B$9 -> 0 | C10: =PN!$B$8 -> 0 | E10: ='TW-L'!C9 -> 0 | F10: ='TW-L'!$C$4 -> 0 | G10: ='TW-L'!$C$5 -> 0 | H10: =I10+Y10+AA10+AF10+AG10 -> 0 | I10: =SUM(J10:X10) -> 0 | J10: ='TW-L'!N9 -> 0 | K10: 0 | L10: ='TW-L'!AC9 -> 0 | M10: ='TW-L'!O9 -> 0 | N10: ='TW-L'!P9 -> 0 | O10: ='TW-L'!Q9 -> 0 | P10: ='TW-L'!R9 -> 0 | Q10: ='TW-L'!X9+'TW-L'!Y9 -> 0 | R10: ='TW-L'!U9 -> 0 | S10: ='TW-L'!V9 -> 0 | T10: ='TW-L'!W9 -> 0 | U10: ='TW-L'!X9 -> 0 | V10: ='TW-L'!Y9 -> 0 | W10: ='TW-L'!AA9 -> 0 | X10: ='TW-L'!AB9 -> 0 | Y10: =SUM(Z10:Z10) -> 0 | Z10: ='TW-L'!Z9 -> 0 | AA10: =SUM(AB10:AE10) -> 0 | AB10: ='TW-L'!AR9+'TW-L'!AS9 -> 0 | AC10: ='TW-L'!AT9+'TW-L'!AU9 -> 0 | AD10: ='TW-L'!AV9+'TW-L'!AW9 -> 0 | AE10: ='TW-L'!AY9 -> 0 | AF10: 0 | AG10: ='TW-L'!AQ9 -> 0

Sheet TW-L
A2: NNRoad
A3: Payroll for the month of | AD3: Overtime Payment
B4: Start Date>
B5: End Date>
M6: Pay Items | AD6: Overtime Details | AL6: Social Insurance Grading | AQ6: EE Dedution | BB6: ER Insurance contribution
A7: BU | B7: CN Name | C7: EN Name | D7: Position | E7: Start Date | F7: End Date | G7: FT/PT | H7: Full Pay/Hourly Rate | I7: Monthly Basic Salary | J7: Allw- Phone/ Communication | K7: Allw Transportation | L7: Allw Meal | M7: Employment day/Hours Worked | N7: 薪資 Basic Salary | O7: Allw- Phone/ Communication | P7: Allw Transportation | Q7: Back Pay | R7: 伙食津貼Allw Meal | S7: Remote Stipend | T7: 病假時數 Sick Leave Hours | U7: 病假扣薪 Sick Leave (half pay) | V7: NPL Hours | W7: No Pay Leave | X7: Bonus VB | Y7: Incentives | Z7: 報帳 Reimb Claim | AA7: 特休結算 Untaken AL | AB7: 資遣費 Severance | AC7: 加班費 Overtime Payment | AD7: Hr (1.34x) | AE7: OT Payment (1.34x) | AF7: Hr (1.67x) | AG7: OT Payment (1.67x) | AH7: Hr (1x) | AI7: OT Payment (1x) | AJ7: Hr (2.67x) | AK7: OT Payment (2.67x) | AL7: 勞保級距 Insured Salary Grading - LI | AM7: 勞退級距 Pension Salary Grading | AN7: 健保投保級距Insured Salary Grading - HI | AO7: 健保眷屬 HI Dependent (person) | AP7: 勞保投保天數 LI Days | AQ7: 所得稅代扣 Withholding Tax | AR7: 勞保自付 LI EE | AS7: 勞保自付(調整) LI EE 1T | AT7: 勞退自提 Pension EE | AU7: 勞退自提 (調整) Pension EE 1T | AV7: 健保自付 HI EE | AW7: 健保自付(調整) HI EE 1T | AX7: 健保眷屬 HI Dep | AY7: 二代健保 自付 2G HI EE | AZ7: Gross Taxable Income | BA7: Net Salary | BB7: 勞保雇主 LI ER | BC7: 勞保雇主 LI ER 1T | BD7: 勞退雇主 Pension ER 6% | BE7: 勞退雇主 Pension ER 1T | BF7: 健保雇主 HI ER | BG7: 健保雇主 HI ER 1T | BH7: 二代健保 雇主 2G HI ER | BI7: 二代健保 雇主 2G HI ER 1T | BJ7: 團保 GI | BK7: Gross Salary (payable) | BL7: ER Insurance | BM7: Service Fee | BN7: Operation Fee | BO7: Total
H8: =SUM(H9:H14) -> 0 | I8: =SUM(I9:I14) -> 0 | J8: =SUM(J9:J14) -> 0 | K8: =SUM(K9:K14) -> 0 | L8: =SUM(L9:L14) -> 0 | M8: =SUM(M9:M14) -> 0 | N8: =SUM(N9:N14) -> 0 | O8: =SUM(O9:O14) -> 0 | ... BO8: =SUM(BO9:BO14) -> 0
