Workbook

Sheet PN
B1: NNRoad – Employer of Record, Payroll Worldwide
B2: 333 W San Carlos St., Suite 600, San Jose, CA 95113, USA
B3: USA: +1 (669) 377-5080 | www.NNRoad.com
A5: INVOICE
A7: Bill to:
A8: Company name: | B8: Danfoss Fzco | D8: Currency | F8: USD
A9: Client ID: | B9: CUS1677 | D9: Invoice number | F9: PN-CUS1677-031820261
A10: Address: | B10: Plot No. EWTA96 Opp. Belhasa Driving School Jebel Ali | D10: Invoice date | F10: =TODAY() -> 46099
D11: Due date | F11: 46127
A14: Description | E14: ="Amount "&Pakistan!C6 -> Amount PKR | F14: Approx. In USD*
A15: EOR/PEO Cost | E15: =SUM(E16:E23) -> 4500000 | F15: =SUM(F16:F23) -> 16623.145
A16: ="- Labor cost for "&Pakistan!B9&" - "&MONTH(Pakistan!$B$2) &"-"& YEAR(Pakistan!$B$2) -> - Labor cost for Muhammad Ismail Ghazi - 4-2026 | E16: =Pakistan!I9+Pakistan!Q9 -> 700000 | F16: =E16/$B$33 -> 2585.8225
A17: ="- Labor cost for "&Pakistan!B10&" - "&MONTH(Pakistan!$B$2)+1 &"-"& YEAR(Pakistan!$B$2) -> - Labor cost for Muhammad Ismail Ghazi - 5-2026 | E17: =Pakistan!I10+Pakistan!Q10 -> 700000 | F17: =E17/$B$33 -> 2585.8225
A18: ="- Labor cost for "&Pakistan!B11&" - "&MONTH(Pakistan!$B$2) +2&"-"& YEAR(Pakistan!$B$2) -> - Labor cost for Muhammad Ismail Ghazi - 6-2026 | E18: =Pakistan!I11+Pakistan!Q11 -> 700000 | F18: =E18/$B$33 -> 2585.8225
A19: ="- Labor cost for "&Pakistan!B12&" - "&MONTH(Pakistan!$B$2)&"-"& YEAR(Pakistan!$B$2) -> - Labor cost for Muhammad Jawad Raza - 4-2026 | E19: =Pakistan!I12+Pakistan!Q12 -> 800000 | F19: =E19/$B$33 -> 2955.2257
A20: ="- Labor cost for "&Pakistan!B13&" - "&MONTH(Pakistan!$B$2)+1&"-"& YEAR(Pakistan!$B$2) -> - Labor cost for Muhammad Jawad Raza - 5-2026 | E20: =Pakistan!I13+Pakistan!Q13 -> 800000 | F20: =E20/$B$33 -> 2955.2257
A21: ="- Labor cost for "&Pakistan!B14&" - "&MONTH(Pakistan!$B$2)+2&"-"& YEAR(Pakistan!$B$2) -> - Labor cost for Muhammad Jawad Raza - 6-2026 | E21: =Pakistan!I14+Pakistan!Q14 -> 800000 | F21: =E21/$B$33 -> 2955.2257
A22: ="- "&+"Expense claim for "&Pakistan!B9 -> - Expense claim for Muhammad Ismail Ghazi | E22: =Pakistan!T9 -> 0 | F22: =E22/$B$33 -> 0
A23: ="- "&+"Expense claim for "&Pakistan!B12 -> - Expense claim for Muhammad Jawad Raza | E23: =Pakistan!T12 -> 0 | F23: =E23/$B$33 -> 0
A25: Service Fee | E25: =SUM(E26:E28) -> 243636.21 | F25: =SUM(F26:F28) -> 900
A26: ="- "&+"Management Fee - "&MONTH(Pakistan!$B$2) &"-"& YEAR(Pakistan!$B$2) -> - Management Fee - 4-2026 | E26: =Pakistan!H9+Pakistan!H12 -> 81212.07 | F26: =E26/$B$33 -> 300
A27: ="- "&+"Management Fee - "&MONTH(Pakistan!$B$2) +1&"-"& YEAR(Pakistan!$B$2) -> - Management Fee - 5-2026 | E27: =Pakistan!H10+Pakistan!H13 -> 81212.07 | F27: =E27/$B$33 -> 300
A28: ="- "&+"Management Fee - "&MONTH(Pakistan!$B$2) +2&"-"& YEAR(Pakistan!$B$2) -> - Management Fee - 6-2026 | E28: =Pakistan!H11+Pakistan!H14 -> 81212.07 | F28: =E28/$B$33 -> 300
A30: EOR/PEO Service Cost | E30: =E15+E25 -> 4743636.2 | F30: =F15+F25 -> 17523.145
A33: ="*FX rate USD: "&Pakistan!C6 -> *FX rate USD: PKR | B33: =270.7069 -> 270.7069 | D33: EOR/PEO Service Cost | F33: =F30 -> 17523.145
D34: Outstanding payment | F34: =Pakistan!E22 -> 6.3
D35: FX difference | F35: =Pakistan!E23 -> 0
D36: Interests of delay | F36: =Pakistan!E24 -> 0
D37: Bank Charges | F37: =Pakistan!E25 -> 90
D38: Sub Total (Excluding Tax) | F38: =SUM(F33:F37) -> 17619.445
D39: Tax | F39: =Pakistan!F6/B33 -> 112.5
D40: Total | F40: =SUM(F38:F39) -> 17731.945
A44: Please pay the Invoice in FULL AMOUNT
A45: Beneficiary: NNROAD, INC. Bank Name: Chase Bank Bank Account: 132827913 Bank Add.: 690 River Oaks Parkway Ste A, San Jose, CA 95134, USA | D45: SWIFT BIC (international transfer): CHASUS33XXX Routing Number (domestic wire transfer): 021000021 Routing Number (domestic ACH and direct deposit): 322271627
A46: Notes:
A47: 1. Please ensure that you include the Invoice Number when making your payment. This will help us accurately process and allocate your payment .
A48: 2. This document becomes a Tax Invoice/Receipt upon payment. Please retain a copy for your records.
A49: 3. This is a computer generated document. No Signature required.

Sheet Pakistan
A1: =MID(CELL("filename",A1),FIND("]",CELL("filename",A1))+1,256) -> Pakistan
A2: Pay Period | B2: ='Pakistan-L'!C2 -> 2026/4/1 | C2: ='Pakistan-L'!E2 -> 2026/6/30 | E2: ER
E3: Sum | F3: Business Tax | G3: Management Fee | I3: Gross Salary | Q3: Mandatory Contribution | T3: Expense Claim
G4: Subtotal | H4: Recurring Fee | I4: Subtotal | J4: ='Pakistan-L'!C7 -> Base Salary | K4: ='Pakistan-L'!D7 -> Salary Adjusment | L4: ='Pakistan-L'!E7 -> OT | M4: ='Pakistan-L'!F7 -> Monthly Bonus | N4: ='Pakistan-L'!G7 -> Other Bonus | O4: ='Pakistan-L'!H7 -> Leave Payment | P4: ='Pakistan-L'!I7 -> Other | Q4: Subtotal | R4: ='Pakistan-L'!O7 -> Social Benefit | S4: ='Pakistan-L'!P7 -> Medical Insurance | T4: Subtotal | U4: Expense Claim
B6: Sum | C6: PKR | E6: =SUM(E9:E17) -> 4774090.7 | F6: =SUM(F9:F17) -> 30454.526 | G6: =SUM(G9:G17) -> 243636.21 | H6: =SUM(H9:H17) -> 243636.21 | I6: =SUM(I9:I17) -> 4500000 | J6: =SUM(J9:J17) -> 4500000 | K6: =SUM(K9:K17) -> 0 | L6: =SUM(L9:L17) -> 0 | ... U6: =SUM(U9:U17) -> 0
B9: ='Pakistan-L'!B8 -> Muhammad Ismail Ghazi | C9: ='Pakistan EE'!D10 -> CUS1677 - 1 | E9: =F9+G9+I9+Q9+T9 -> 745681.79 | F9: =18.75*PN!$B$33 -> 5075.7544 | G9: =SUM(H9:H9) -> 40606.035 | H9: =(150*PN!$B$33) -> 40606.035 | I9: =SUM(J9:P9) -> 700000 | J9: ='Pakistan-L'!C8 -> 700000 | K9: ='Pakistan-L'!D8 -> 0 | L9: ='Pakistan-L'!E8 -> 0 | M9: ='Pakistan-L'!F8 -> 0 | N9: ='Pakistan-L'!G8 -> 0 | O9: ='Pakistan-L'!H8 -> 0 | P9: ='Pakistan-L'!I8 -> 0 | Q9: =SUM(R9:S9) -> 0 | R9: ='Pakistan-L'!O8 -> 0 | S9: ='Pakistan-L'!P8 -> 0 | T9: =SUM(U9:U9) -> 0 | U9: ='Pakistan-L'!K8 -> 0
B10: ='Pakistan-L'!B9 -> Muhammad Ismail Ghazi | C10: ='Pakistan EE'!D11 -> CUS1677 - 1 | E10: =F10+G10+I10+Q10+T10 -> 745681.79 | F10: =18.75*PN!$B$33 -> 5075.7544 | G10: =SUM(H10:H10) -> 40606.035 | H10: =(150*PN!$B$33) -> 40606.035 | I10: =SUM(J10:P10) -> 700000 | J10: ='Pakistan-L'!C9 -> 700000 | K10: ='Pakistan-L'!D9 -> 0 | L10: ='Pakistan-L'!E9 -> 0 | M10: ='Pakistan-L'!F9 -> 0 | N10: ='Pakistan-L'!G9 -> 0 | O10: ='Pakistan-L'!H9 -> 0 | P10: ='Pakistan-L'!I9 -> 0 | Q10: =SUM(R10:S10) -> 0 | R10: ='Pakistan-L'!O9 -> 0 | S10: ='Pakistan-L'!P9 -> 0 | T10: =SUM(U10:U10) -> 0 | U10: ='Pakistan-L'!K9 -> 0
B11: ='Pakistan-L'!B10 -> Muhammad Ismail Ghazi | C11: ='Pakistan EE'!D12 -> CUS1677 - 1 | E11: =F11+G11+I11+Q11+T11 -> 745681.79 | F11: =18.75*PN!$B$33 -> 5075.7544 | G11: =SUM(H11:H11) -> 40606.035 | H11: =(150*PN!$B$33) -> 40606.035 | I11: =SUM(J11:P11) -> 700000 | J11: ='Pakistan-L'!C10 -> 700000 | K11: ='Pakistan-L'!D10 -> 0 | L11: ='Pakistan-L'!E10 -> 0 | M11: ='Pakistan-L'!F10 -> 0 | N11: ='Pakistan-L'!G10 -> 0 | O11: ='Pakistan-L'!H10 -> 0 | P11: ='Pakistan-L'!I10 -> 0 | Q11: =SUM(R11:S11) -> 0 | R11: ='Pakistan-L'!O10 -> 0 | S11: ='Pakistan-L'!P10 -> 0 | T11: =SUM(U11:U11) -> 0 | U11: ='Pakistan-L'!K10 -> 0
B12: ='Pakistan-L'!B11 -> Muhammad Jawad Raza | C12: ='Pakistan EE'!D13 -> CUS1677 - 2 | E12: =F12+G12+I12+Q12+T12 -> 845681.79 | F12: =18.75*PN!$B$33 -> 5075.7544 | G12: =SUM(H12:H12) -> 40606.035 | H12: =(150*PN!$B$33) -> 40606.035 | I12: =SUM(J12:P12) -> 800000 | J12: ='Pakistan-L'!C11 -> 800000 | K12: ='Pakistan-L'!D11 -> 0 | L12: ='Pakistan-L'!E11 -> 0 | M12: ='Pakistan-L'!F11 -> 0 | N12: ='Pakistan-L'!G11 -> 0 | O12: ='Pakistan-L'!H11 -> 0 | P12: ='Pakistan-L'!I11 -> 0 | Q12: =SUM(R12:S12) -> 0 | R12: ='Pakistan-L'!O11 -> 0 | S12: ='Pakistan-L'!P11 -> 0 | T12: =SUM(U12:U12) -> 0 | U12: ='Pakistan-L'!K11 -> 0
B13: ='Pakistan-L'!B12 -> Muhammad Jawad Raza | C13: ='Pakistan EE'!D14 -> CUS1677 - 2 | E13: =F13+G13+I13+Q13+T13 -> 845681.79 | F13: =18.75*PN!$B$33 -> 5075.7544 | G13: =SUM(H13:H13) -> 40606.035 | H13: =(150*PN!$B$33) -> 40606.035 | I13: =SUM(J13:P13) -> 800000 | J13: ='Pakistan-L'!C12 -> 800000 | K13: ='Pakistan-L'!D12 -> 0 | L13: ='Pakistan-L'!E12 -> 0 | M13: ='Pakistan-L'!F12 -> 0 | N13: ='Pakistan-L'!G12 -> 0 | O13: ='Pakistan-L'!H12 -> 0 | P13: ='Pakistan-L'!I12 -> 0 | Q13: =SUM(R13:S13) -> 0 | R13: ='Pakistan-L'!O12 -> 0 | S13: ='Pakistan-L'!P12 -> 0 | T13: =SUM(U13:U13) -> 0 | U13: ='Pakistan-L'!K12 -> 0
B14: ='Pakistan-L'!B13 -> Muhammad Jawad Raza | C14: ='Pakistan EE'!D15 -> CUS1677 - 2 | E14: =F14+G14+I14+Q14+T14 -> 845681.79 | F14: =18.75*PN!$B$33 -> 5075.7544 | G14: =SUM(H14:H14) -> 40606.035 | H14: =(150*PN!$B$33) -> 40606.035 | I14: =SUM(J14:P14) -> 800000 | J14: ='Pakistan-L'!C13 -> 800000 | K14: ='Pakistan-L'!D13 -> 0 | L14: ='Pakistan-L'!E13 -> 0 | M14: ='Pakistan-L'!F13 -> 0 | N14: ='Pakistan-L'!G13 -> 0 | O14: ='Pakistan-L'!H13 -> 0 | P14: ='Pakistan-L'!I13 -> 0 | Q14: =SUM(R14:S14) -> 0 | R14: ='Pakistan-L'!O13 -> 0 | S14: ='Pakistan-L'!P13 -> 0 | T14: =SUM(U14:U14) -> 0 | U14: ='Pakistan-L'!K13 -> 0
A21: Other Fee | E21: =SUM(E22:E26) -> 96.3 | F21: 0
B22: Outstanding payment | E22: 6.3
B23: FX difference | F23: 0
B24: Interests of delay | F24: 0
B25: Bank Charges | E25: =35+35+10+10 -> 90
B26: Invoice adjustment | E26: 0

Sheet Pakistan EE
A1: =MID(CELL("filename",A1),FIND("]",CELL("filename",A1))+1,256) -> Pakistan EE
H2: EE
B3: Client Code | C3: Client Name | D3: EE Code | E3: EE Name | F3: Pay Period | H3: Net Income | I3: Gross Salary | Q3: Expense Claim | S3: Mandatory Contribution
F4: From | G4: To | I4: Subtotal | J4: ='Pakistan-L'!C7 -> Base Salary | K4: ='Pakistan-L'!D7 -> Salary Adjusment | L4: ='Pakistan-L'!E7 -> OT | M4: ='Pakistan-L'!F7 -> Monthly Bonus | N4: ='Pakistan-L'!G7 -> Other Bonus | O4: ='Pakistan-L'!H7 -> Leave Payment | P4: ='Pakistan-L'!I7 -> Other | Q4: Subtotal | R4: Expense Claim | S4: Subtotal | T4: ='Pakistan-L'!L7 -> E.O.B.I | U4: ='Pakistan-L'!M7 -> IT
A6: EOR/PEO(PKR)
B10: =PN!$B$9 -> CUS1677 | C10: ='Pakistan-L'!$C$1 -> Danfoss Fzco | D10: =PN!$B$9&" - "&1 -> CUS1677 - 1 | E10: ='Pakistan-L'!B8 -> Muhammad Ismail Ghazi | F10: ='Pakistan-L'!$C$2 -> 2026/4/1 | G10: ='Pakistan-L'!$E$2 -> 2026/6/30 | H10: =I10+Q10-S10 -> 532845 | I10: =SUM(J10:P10) -> 700000 | J10: ='Pakistan-L'!C8 -> 700000 | K10: ='Pakistan-L'!D8 -> 0 | L10: ='Pakistan-L'!E8 -> 0 | M10: ='Pakistan-L'!F8 -> 0 | N10: ='Pakistan-L'!G8 -> 0 | O10: ='Pakistan-L'!H8 -> 0 | P10: ='Pakistan-L'!I8 -> 0 | Q10: =SUM(R10:R10) -> 0 | R10: ='Pakistan-L'!K8 -> 0 | S10: =SUM(T10:U10) -> 167155 | T10: ='Pakistan-L'!L8 -> 370 | U10: ='Pakistan-L'!M8 -> 166785
B11: =PN!$B$9 -> CUS1677 | C11: ='Pakistan-L'!$C$1 -> Danfoss Fzco | D11: =PN!$B$9&" - "&1 -> CUS1677 - 1 | E11: ='Pakistan-L'!B9 -> Muhammad Ismail Ghazi | F11: ='Pakistan-L'!$C$2 -> 2026/4/1 | G11: ='Pakistan-L'!$E$2 -> 2026/6/30 | H11: =I11+Q11-S11 -> 532845 | I11: =SUM(J11:P11) -> 700000 | J11: ='Pakistan-L'!C9 -> 700000 | K11: ='Pakistan-L'!D9 -> 0 | L11: ='Pakistan-L'!E9 -> 0 | M11: ='Pakistan-L'!F9 -> 0 | N11: ='Pakistan-L'!G9 -> 0 | O11: ='Pakistan-L'!H9 -> 0 | P11: ='Pakistan-L'!I9 -> 0 | Q11: =SUM(R11:R11) -> 0 | R11: ='Pakistan-L'!K9 -> 0 | S11: =SUM(T11:U11) -> 167155 | T11: ='Pakistan-L'!L9 -> 370 | U11: ='Pakistan-L'!M9 -> 166785
B12: =PN!$B$9 -> CUS1677 | C12: ='Pakistan-L'!$C$1 -> Danfoss Fzco | D12: =PN!$B$9&" - "&1 -> CUS1677 - 1 | E12: ='Pakistan-L'!B10 -> Muhammad Ismail Ghazi | F12: ='Pakistan-L'!$C$2 -> 2026/4/1 | G12: ='Pakistan-L'!$E$2 -> 2026/6/30 | H12: =I12+Q12-S12 -> 532845 | I12: =SUM(J12:P12) -> 700000 | J12: ='Pakistan-L'!C10 -> 700000 | K12: ='Pakistan-L'!D10 -> 0 | L12: ='Pakistan-L'!E10 -> 0 | M12: ='Pakistan-L'!F10 -> 0 | N12: ='Pakistan-L'!G10 -> 0 | O12: ='Pakistan-L'!H10 -> 0 | P12: ='Pakistan-L'!I10 -> 0 | Q12: =SUM(R12:R12) -> 0 | R12: ='Pakistan-L'!K10 -> 0 | S12: =SUM(T12:U12) -> 167155 | T12: ='Pakistan-L'!L10 -> 370 | U12: ='Pakistan-L'!M10 -> 166785
B13: =PN!$B$9 -> CUS1677 | C13: ='Pakistan-L'!$C$1 -> Danfoss Fzco | D13: =PN!$B$9&" - "&2 -> CUS1677 - 2 | E13: ='Pakistan-L'!B11 -> Muhammad Jawad Raza | F13: ='Pakistan-L'!$C$2 -> 2026/4/1 | G13: ='Pakistan-L'!$E$2 -> 2026/6/30 | H13: =I13+Q13-S13 -> 656130 | I13: =SUM(J13:P13) -> 800000 | J13: ='Pakistan-L'!C11 -> 800000 | K13: ='Pakistan-L'!D11 -> 0 | L13: ='Pakistan-L'!E11 -> 0 | M13: ='Pakistan-L'!F11 -> 0 | N13: ='Pakistan-L'!G11 -> 0 | O13: ='Pakistan-L'!H11 -> 0 | P13: ='Pakistan-L'!I11 -> 0 | Q13: =SUM(R13:R13) -> 0 | R13: ='Pakistan-L'!K11 -> 0 | S13: =SUM(T13:U13) -> 143870 | T13: ='Pakistan-L'!L11 -> 370 | U13: ='Pakistan-L'!M11 -> 143500
B14: =PN!$B$9 -> CUS1677 | C14: ='Pakistan-L'!$C$1 -> Danfoss Fzco | D14: =PN!$B$9&" - "&2 -> CUS1677 - 2 | E14: ='Pakistan-L'!B12 -> Muhammad Jawad Raza | F14: ='Pakistan-L'!$C$2 -> 2026/4/1 | G14: ='Pakistan-L'!$E$2 -> 2026/6/30 | H14: =I14+Q14-S14 -> 656130 | I14: =SUM(J14:P14) -> 800000 | J14: ='Pakistan-L'!C12 -> 800000 | K14: ='Pakistan-L'!D12 -> 0 | L14: ='Pakistan-L'!E12 -> 0 | M14: ='Pakistan-L'!F12 -> 0 | N14: ='Pakistan-L'!G12 -> 0 | O14: ='Pakistan-L'!H12 -> 0 | P14: ='Pakistan-L'!I12 -> 0 | Q14: =SUM(R14:R14) -> 0 | R14: ='Pakistan-L'!K12 -> 0 | S14: =SUM(T14:U14) -> 143870 | T14: ='Pakistan-L'!L12 -> 370 | U14: ='Pakistan-L'!M12 -> 143500
B15: =PN!$B$9 -> CUS1677 | C15: ='Pakistan-L'!$C$1 -> Danfoss Fzco | D15: =PN!$B$9&" - "&2 -> CUS1677 - 2 | E15: ='Pakistan-L'!B13 -> Muhammad Jawad Raza | F15: ='Pakistan-L'!$C$2 -> 2026/4/1 | G15: ='Pakistan-L'!$E$2 -> 2026/6/30 | H15: =I15+Q15-S15 -> 656130 | I15: =SUM(J15:P15) -> 800000 | J15: ='Pakistan-L'!C13 -> 800000 | K15: ='Pakistan-L'!D13 -> 0 | L15: ='Pakistan-L'!E13 -> 0 | M15: ='Pakistan-L'!F13 -> 0 | N15: ='Pakistan-L'!G13 -> 0 | O15: ='Pakistan-L'!H13 -> 0 | P15: ='Pakistan-L'!I13 -> 0 | Q15: =SUM(R15:R15) -> 0 | R15: ='Pakistan-L'!K13 -> 0 | S15: =SUM(T15:U15) -> 143870 | T15: ='Pakistan-L'!L13 -> 370 | U15: ='Pakistan-L'!M13 -> 143500

Sheet Pakistan-L
A1: Company name: | C1: =PN!B8 -> Danfoss Fzco
A2: Payroll period: | C2: 2026/4/1 | D2: to | E2: 2026/6/30
A3: Currency: | C3: PKR
A7: No. of EE | B7: Name of Employee | C7: Base Salary | D7: Salary Adjusment | E7: OT | F7: Monthly Bonus | G7: Other Bonus | H7: Leave Payment | I7: Other | J7: Gross Salary | K7: Expense Reimbursment | L7: E.O.B.I | M7: IT | N7: Net Salary | O7: Social Benefit | P7: Medical Insurance | Q7: Bank Charges | R7: Total Cost
A8: 1 | B8: Muhammad Ismail Ghazi | C8: 700000 | J8: =SUM(C8:I8) -> 700000 | L8: 370 | M8: 166785 | N8: =J8+K8-L8-M8 -> 532845 | R8: =J8+K8+O8+P8+Q8 -> 700000
A9: 1 | B9: Muhammad Ismail Ghazi | C9: 700000 | J9: =SUM(C9:I9) -> 700000 | L9: 370 | M9: 166785 | N9: =J9+K9-L9-M9 -> 532845 | R9: =J9+K9+O9+P9+Q9 -> 700000
A10: 1 | B10: Muhammad Ismail Ghazi | C10: 700000 | J10: =SUM(C10:I10) -> 700000 | L10: 370 | M10: 166785 | N10: =J10+K10-L10-M10 -> 532845 | R10: =J10+K10+O10+P10+Q10 -> 700000
A11: 2 | B11: Muhammad Jawad Raza | C11: 800000 | J11: =SUM(C11:I11) -> 800000 | L11: 370 | M11: 143500 | N11: =J11+K11-L11-M11 -> 656130 | R11: =J11+K11+O11+P11+Q11 -> 800000
A12: 2 | B12: Muhammad Jawad Raza | C12: 800000 | J12: =SUM(C12:I12) -> 800000 | L12: 370 | M12: 143500 | N12: =J12+K12-L12-M12 -> 656130 | R12: =J12+K12+O12+P12+Q12 -> 800000
A13: 2 | B13: Muhammad Jawad Raza | C13: 800000 | J13: =SUM(C13:I13) -> 800000 | L13: 370 | M13: 143500 | N13: =J13+K13-L13-M13 -> 656130 | R13: =J13+K13+O13+P13+Q13 -> 800000

Sheet FI Report
A1: Direct Cost | B1: Business Tax | C1: Service Fee | D1: Bank Fee * | E1: Late Pay Fine | F1: Advance Payment | G1: Deposit | H1: Outstanding payment ** | I1: FX difference | J1: Invoice adjustment *** | K1: total
A2: =PN!F15 -> 16623.145 | B2: =PN!F39 -> 112.5 | C2: =PN!F25 -> 900 | D2: =PN!F37 -> 90 | E2: =PN!F36 -> 0 | F2: =0 -> 0 | G2: 0 | H2: =PN!F34 -> 6.3 | I2: =PN!F35 -> 0 | J2: 0 | K2: =SUM(A2:J2) -> 17731.945
A7: * NNRoad USD 10 + vendor bank in Vendor's invoice
A8: ** the differnece between NNRoad PN and the amount we actually received
A9: *** PN adjustment with pre-payment or PN revisal
