Workbook

Sheet PN
B1: NNRoad – Employer of Record, Payroll Worldwide
B2: 333 W San Carlos St., Suite 600, San Jose, CA 95113, USA
B3: USA: +1 (669) 377-5080 | www.NNRoad.com
A5: INVOICE
A7: Bill to:
A8: Company name: | B8: Coral Sea | D8: Currency | F8: USD
A9: Client ID: | B9: CUS1516 | D9: Invoice number | F9: PN-CUS1516-031120261
A10: Address: | B10: 4205/41 Williams Esplanade, PALM COVE, QLD, Australia | D10: Invoice date | F10: =TODAY()
D11: Due date | F11: 46099
A14: Description | E14: ="Amount "&TW!C6 | F14: Approx. In USD*
A15: EOR/PEO Cost | E15: =SUM(E16:E22) | F15: =SUM(F16:F22)
A16: ="- Labor cost for "&TW!B9&" - "&MONTH(TW!$B$2)&"-"&YEAR(TW!$B$2) | E16: =TW!J9+TW!Z9 | F16: =E16/$B$31
A17: ="- Labor cost for "&TW!B10&" - "&MONTH(TW!$B$2)&"-"&YEAR(TW!$B$2) | E17: =TW!J10+TW!Z10 | F17: =E17/$B$31
A18: ="- Labor cost for "&TW!B11&" - "&MONTH(TW!$B$2)&"-"&YEAR(TW!$B$2) | E18: =TW!J11+TW!Z11 | F18: =E18/$B$31
A19: ="- Expense claim for "&TW!B9 | E19: =TW!AB9 | F19: =E19/$B$31
A20: ="- Expense claim for "&TW!B10 | E20: =TW!AB10 | F20: =E20/$B$31
A21: ="- Expense claim for "&TW!B11 | E21: =TW!AB11 | F21: =E21/$B$31
A23: Service Fee | E23: =SUM(E24:E25) | F23: =SUM(F24:F25)
A24: ="- Management Fee - "&MONTH(TW!B2)&"-"&YEAR(TW!B2) | E24: =TW!G6 | F24: =E24/$B$31
A28: EOR/PEO Service Cost | E28: =E15+E23 | F28: =F15+F23
A31: ="*FX rate USD: "&TW!C6 | B31: 31.2977 | D31: EOR/PEO Service Cost | F31: =F28
D32: Outstanding payment | F32: =TW!E22
D33: FX difference | F33: =TW!E23
D34: Interests of delay | F34: =TW!E24
D35: Bank Charges | F35: =TW!E25
D36: Sub Total (Excluding Tax) | F36: =SUM(F31:F35)
D37: Tax | F37: =ROUNDUP(TW!F6/PN!B31,2)+0.01
D38: Total | F38: =SUM(F36:F37)
A42: Please pay the Invoice in FULL AMOUNT
A43: Beneficiary: NNROAD, INC. Bank Name: Chase Bank Bank Account: 132827913 Bank Add.: 690 River Oaks Parkway Ste A, San Jose, CA 95134, USA | D43: SWIFT BIC (international transfer): CHASUS33XXX Routing Number (domestic wire transfer): 021000021 Routing Number (domestic ACH and direct deposit): 322271627
A44: Notes:
A45: 1. Please ensure that you include the Invoice Number when making your payment. This will help us accurately process and allocate your payment .
A46: 2. This document becomes a Tax Invoice/Receipt upon payment. Please retain a copy for your records.
A47: 3. This is a computer generated document. No Signature required.

Sheet TW
A1: =MID(CELL("filename",A1),FIND("]",CELL("filename",A1))+1,256)
A2: Pay Period | B2: ='TW-L'!C4 | C2: ='TW-L'!C5 | E2: ER
E3: Sum | F3: Business Tax | G3: Management Fee Fee | J3: Gross Salary | Z3: Mandatory Contribution | AB3: Expense Claim
G4: Subtotal | H4: Recurring Fee | I4: Expense Fee | J4: Subtotal | K4: Basic Salary | L4: Salary Adjustment | M4: OT | N4: Allw- Phone/ Communication | O4: Allw Transportation | P4: Back Pay | Q4: 伙食津貼Allw Meal | R4: Remote Stipend | S4: 病假扣薪 Sick Leave (half pay) | T4: NPL Hours | U4: No Pay Leave | V4: Bonus VB | W4: Incentives | X4: 特休結算 Untaken AL | Y4: 資遣費 Severance | Z4: Subtotal | AA4: ER insurance | AB4: Subtotal | AC4: Expense Claim
B6: Sum | C6: (NTD) | E6: =SUM(E9:E17) | F6: =SUM(F9:F17) | G6: =SUM(G9:G17) | H6: =SUM(H9:H17) | I6: =SUM(I9:I17) | J6: =SUM(J9:J17) | K6: =SUM(K9:K17) | L6: =SUM(L9:L17) | ... AC6: =SUM(AC9:AC17)
B9: ='TW-L'!C9 | C9: ='TW EE'!D10 | E9: =SUM(F9:G9)+J9+Z9+AB9 | G9: =SUM(H9:I9) | H9: =MAX(4500,(J9+Z9)*12%) | I9: =IF(AB9>0,1500,0) | J9: =SUM(K9:Y9) | K9: ='TW-L'!N9 | L9: 0 | M9: ='TW-L'!AC9 | N9: ='TW-L'!O9 | O9: ='TW-L'!P9 | P9: ='TW-L'!Q9 | Q9: ='TW-L'!R9 | R9: ='TW-L'!R9 | S9: ='TW-L'!U9 | T9: ='TW-L'!V9 | U9: ='TW-L'!W9 | V9: ='TW-L'!X9 | W9: ='TW-L'!Y9 | X9: ='TW-L'!AA9 | Y9: ='TW-L'!AB9 | Z9: =SUM(AA9:AA9) | AA9: ='TW-L'!BL9 | AB9: =SUM(AC9:AC9) | AC9: ='TW-L'!Z9
B10: ='TW-L'!C10 | C10: ='TW EE'!D11 | E10: =SUM(F10:G10)+J10+Z10+AB10 | G10: =SUM(H10:I10) | H10: =MAX(4500,(J10+Z10)*12%) | I10: =IF(AB10>0,1500,0) | J10: =SUM(K10:Y10) | K10: ='TW-L'!N10 | L10: 0 | M10: ='TW-L'!AC10 | N10: ='TW-L'!O10 | O10: ='TW-L'!P10 | P10: ='TW-L'!Q10 | Q10: ='TW-L'!R10 | R10: ='TW-L'!R10 | S10: ='TW-L'!U10 | T10: ='TW-L'!V10 | U10: ='TW-L'!W10 | V10: ='TW-L'!X10 | W10: ='TW-L'!Y10 | X10: ='TW-L'!AA10 | Y10: ='TW-L'!AB10 | Z10: =SUM(AA10:AA10) | AA10: ='TW-L'!BL10 | AB10: =SUM(AC10:AC10) | AC10: ='TW-L'!Z10
B11: ='TW-L'!C11 | C11: ='TW EE'!D12 | E11: =SUM(F11:G11)+J11+Z11+AB11 | G11: =SUM(H11:I11) | H11: =MAX(4500,(J11+Z11)*12%) | I11: =IF(AB11>0,1500,0) | J11: =SUM(K11:Y11) | K11: ='TW-L'!N11 | L11: 0 | M11: ='TW-L'!AC11 | N11: ='TW-L'!O11 | O11: ='TW-L'!P11 | P11: ='TW-L'!Q11 | Q11: ='TW-L'!R11 | R11: ='TW-L'!R11 | S11: ='TW-L'!U11 | T11: ='TW-L'!V11 | U11: ='TW-L'!W11 | V11: ='TW-L'!X11 | W11: ='TW-L'!Y11 | X11: ='TW-L'!AA11 | Y11: ='TW-L'!AB11 | Z11: =SUM(AA11:AA11) | AA11: ='TW-L'!BL11 | AB11: =SUM(AC11:AC11) | AC11: ='TW-L'!Z11
A21: Other Fee | E21: =SUM(E22:E26) | F21: 0
B22: Outstanding payment
B23: FX difference | F23: 0
B24: Interests of delay | F24: 0
B25: Bank Charges | E25: =10
B26: Invoice adjustment | E26: 0

Sheet TW EE
A1: =MID(CELL("filename",A1),FIND("]",CELL("filename",A1))+1,256)
H2: EE
B3: Client Code | C3: Client Name | D3: EE Code | E3: EE Name | F3: Pay Period | H3: Net Income | I3: Gross Salary | Y3: Expense Claim | AA3: Mandatory Contribution | AF3: Deduction | AG3: IIT
F4: From | G4: To | I4: Subtotal | J4: Basic Salary | K4: Salary Adjustment | L4: OT | M4: Allw- Phone/ Communication | N4: Allw Transportation | O4: Back Pay | P4: 伙食津貼 Allw Meal | Q4: Remote Stipend | R4: 病假扣薪 Sick Leave (half pay) | S4: NPL Hours | T4: No Pay Leave | U4: Bonus VB | V4: Incentives | W4: 特休結算 Untaken AL | X4: 資遣費 Severance | Y4: Subtotal | Z4: Expense Claim | AA4: Subtotal | AB4: LI | AC4: Pension | AD4: HI | AE4: 2G HI
A6: EOR/PEO(NTD)
B10: =PN!$B$9 | C10: =PN!$B$8 | D10: CUS1516-0001 | E10: ='TW-L'!C9 | F10: ='TW-L'!$C$4 | G10: ='TW-L'!$C$5 | H10: =I10+Y10+AA10+AF10+AG10 | I10: =SUM(J10:X10) | J10: ='TW-L'!N9 | K10: 0 | L10: ='TW-L'!AC9 | M10: ='TW-L'!O9 | N10: ='TW-L'!P9 | O10: ='TW-L'!Q9 | P10: ='TW-L'!R9 | Q10: ='TW-L'!X9+'TW-L'!Y9 | R10: ='TW-L'!U9 | S10: ='TW-L'!V9 | T10: ='TW-L'!W9 | U10: ='TW-L'!X9 | V10: ='TW-L'!Y9 | W10: ='TW-L'!AA9 | X10: ='TW-L'!AB9 | Y10: =SUM(Z10:Z10) | Z10: ='TW-L'!Z9 | AA10: =SUM(AB10:AE10) | AB10: ='TW-L'!AR9+'TW-L'!AS9 | AC10: ='TW-L'!AT9+'TW-L'!AU9 | AD10: ='TW-L'!AV9+'TW-L'!AW9 | AE10: ='TW-L'!AY9 | AF10: 0 | AG10: ='TW-L'!AQ9
B11: =PN!$B$9 | C11: =PN!B8 | D11: CUS1516-0002 | E11: ='TW-L'!C10 | F11: ='TW-L'!$C$4 | G11: ='TW-L'!$C$5 | H11: =I11+Y11+AA11+AF11+AG11 | I11: =SUM(J11:X11) | J11: ='TW-L'!N10 | K11: 0 | L11: ='TW-L'!AC10 | M11: ='TW-L'!O10 | N11: ='TW-L'!P10 | O11: ='TW-L'!Q10 | P11: ='TW-L'!R10 | Q11: ='TW-L'!X10+'TW-L'!Y10 | R11: ='TW-L'!U10 | S11: ='TW-L'!V10 | T11: ='TW-L'!W10 | U11: ='TW-L'!X10 | V11: ='TW-L'!Y10 | W11: ='TW-L'!AA10 | X11: ='TW-L'!AB10 | Y11: =SUM(Z11:Z11) | Z11: ='TW-L'!Z10 | AA11: =SUM(AB11:AE11) | AB11: ='TW-L'!AR10+'TW-L'!AS10 | AC11: ='TW-L'!AT10+'TW-L'!AU10 | AD11: ='TW-L'!AV10+'TW-L'!AW10 | AE11: ='TW-L'!AY10 | AF11: 0 | AG11: ='TW-L'!AQ10
B12: =PN!$B$9 | C12: =PN!B9 | D12: CUS1516-0003 | E12: ='TW-L'!C11 | F12: ='TW-L'!$C$4 | G12: ='TW-L'!$C$5 | H12: =I12+Y12+AA12+AF12+AG12 | I12: =SUM(J12:X12) | J12: ='TW-L'!N11 | K12: 0 | L12: ='TW-L'!AC11 | M12: ='TW-L'!O11 | N12: ='TW-L'!P11 | O12: ='TW-L'!Q11 | P12: ='TW-L'!R11 | Q12: ='TW-L'!X11+'TW-L'!Y11 | R12: ='TW-L'!U11 | S12: ='TW-L'!V11 | T12: ='TW-L'!W11 | U12: ='TW-L'!X11 | V12: ='TW-L'!Y11 | W12: ='TW-L'!AA11 | X12: ='TW-L'!AB11 | Y12: =SUM(Z12:Z12) | Z12: ='TW-L'!Z11 | AA12: =SUM(AB12:AE12) | AB12: ='TW-L'!AR11+'TW-L'!AS11 | AC12: ='TW-L'!AT11+'TW-L'!AU11 | AD12: ='TW-L'!AV11+'TW-L'!AW11 | AE12: ='TW-L'!AY11 | AF12: 0 | AG12: ='TW-L'!AQ11

Sheet TW-L
A2: NNRoad
A3: Payroll for the month of | AD3: Overtime Payment
B4: Start Date>
B5: End Date>
M6: Pay Items | AD6: Overtime Details | AL6: Social Insurance Grading | AQ6: EE Dedution | BB6: ER Insurance contribution
A7: BU | B7: CN Name | C7: EN Name | D7: Position | E7: Start Date | F7: End Date | G7: FT/PT | H7: Full Pay/Hourly Rate | I7: Monthly Basic Salary | J7: Allw- Phone/ Communication | K7: Allw Transportation | L7: Allw Meal | M7: Employment day/Hours Worked | N7: 薪資 Basic Salary | O7: Allw- Phone/ Communication | P7: Allw Transportation | Q7: Back Pay | R7: 伙食津貼Allw Meal | S7: Remote Stipend | T7: 病假時數 Sick Leave Hours | U7: 病假扣薪 Sick Leave (half pay) | V7: NPL Hours | W7: No Pay Leave | X7: Bonus VB | Y7: Incentives | Z7: 報帳 Reimb Claim | AA7: 特休結算 Untaken AL | AB7: 資遣費 Severance | AC7: 加班費 Overtime Payment | AD7: Hr (1.34x) | AE7: OT Payment (1.34x) | AF7: Hr (1.67x) | AG7: OT Payment (1.67x) | AH7: Hr (1x) | AI7: OT Payment (1x) | AJ7: Hr (2.67x) | AK7: OT Payment (2.67x) | AL7: 勞保級距 Insured Salary Grading - LI | AM7: 勞退級距 Pension Salary Grading | AN7: 健保投保級距Insured Salary Grading - HI | AO7: 健保眷屬 HI Dependent (person) | AP7: 勞保投保天數 LI Days | AQ7: 所得稅代扣 Withholding Tax | AR7: 勞保自付 LI EE | AS7: 勞保自付(調整) LI EE 1T | AT7: 勞退自提 Pension EE | AU7: 勞退自提 (調整) Pension EE 1T | AV7: 健保自付 HI EE | AW7: 健保自付(調整) HI EE 1T | AX7: 健保眷屬 HI Dep | AY7: 二代健保 自付 2G HI EE | AZ7: Gross Taxable Income | BA7: Net Salary | BB7: 勞保雇主 LI ER | BC7: 勞保雇主 LI ER 1T | BD7: 勞退雇主 Pension ER 6% | BE7: 勞退雇主 Pension ER 1T | BF7: 健保雇主 HI ER | BG7: 健保雇主 HI ER 1T | BH7: 二代健保 雇主 2G HI ER | BI7: 二代健保 雇主 2G HI ER 1T | BJ7: 團保 GI | BK7: Gross Salary (payable) | BL7: ER Insurance | BM7: Service Fee | BN7: Operation Fee | BO7: Total
H8: =SUM(H9:H14) | I8: =SUM(I9:I14) | J8: =SUM(J9:J14) | K8: =SUM(K9:K14) | L8: =SUM(L9:L14) | M8: =SUM(M9:M14) | N8: =SUM(N9:N14) | O8: =SUM(O9:O14) | ... BO8: =SUM(BO9:BO14)
