Workbook

Sheet PN
B1: NNRoad – Employer of Record, Payroll Worldwide
B2: 333 W San Carlos St., Suite 600, San Jose, CA 95113, USA
B3: USA: +1 (669) 377-5080 | www.NNRoad.com
A5: INVOICE
A7: Bill to:
A8: Company name: | B8: Danfoss Fzco | D8: Currency | F8: USD
A9: Client ID: | B9: CUS1677 | D9: Invoice number | F9: PN-CUS1677-060320261
A10: Address: | B10: Plot No. EWTA96 Opp. Belhasa Driving School Jebel Ali | D10: Invoice date | F10: =TODAY()
D11: Due date | F11: 46218
A14: Description | E14: ="Amount "&Pakistan!C6 | F14: Approx. In USD*
A15: EOR/PEO Cost | E15: =SUM(E16:E23) | F15: =SUM(F16:F23)
A16: ="- Labor cost for "&Pakistan!B9&" - "&MONTH(Pakistan!$B$2) &"-"& YEAR(Pakistan!$B$2) | E16: =Pakistan!I9+Pakistan!Q9 | F16: =E16/$B$33
A17: ="- Labor cost for "&Pakistan!B10&" - "&MONTH(Pakistan!$B$2)+1 &"-"& YEAR(Pakistan!$B$2) | E17: =Pakistan!I10+Pakistan!Q10 | F17: =E17/$B$33
A18: ="- Labor cost for "&Pakistan!B11&" - "&MONTH(Pakistan!$B$2) +2&"-"& YEAR(Pakistan!$B$2) | E18: =Pakistan!I11+Pakistan!Q11 | F18: =E18/$B$33
A19: ="- Labor cost for "&Pakistan!B12&" - "&MONTH(Pakistan!$B$2)&"-"& YEAR(Pakistan!$B$2) | E19: =Pakistan!I12+Pakistan!Q12 | F19: =E19/$B$33
A20: ="- Labor cost for "&Pakistan!B13&" - "&MONTH(Pakistan!$B$2)+1&"-"& YEAR(Pakistan!$B$2) | E20: =Pakistan!I13+Pakistan!Q13 | F20: =E20/$B$33
A21: ="- Labor cost for "&Pakistan!B14&" - "&MONTH(Pakistan!$B$2)+2&"-"& YEAR(Pakistan!$B$2) | E21: =Pakistan!I14+Pakistan!Q14 | F21: =E21/$B$33
A22: ="- "&+"Expense claim for "&Pakistan!B9 | E22: =Pakistan!T9 | F22: =E22/$B$33
A23: ="- "&+"Expense claim for "&Pakistan!B12 | E23: =Pakistan!T12 | F23: =E23/$B$33
A25: Service Fee | E25: =SUM(E26:E28) | F25: =SUM(F26:F28)
A26: ="- "&+"Management Fee - "&MONTH(Pakistan!$B$2) &"-"& YEAR(Pakistan!$B$2) | E26: =Pakistan!H9+Pakistan!H12 | F26: =E26/$B$33
A27: ="- "&+"Management Fee - "&MONTH(Pakistan!$B$2) +1&"-"& YEAR(Pakistan!$B$2) | E27: =Pakistan!H10+Pakistan!H13 | F27: =E27/$B$33
A28: ="- "&+"Management Fee - "&MONTH(Pakistan!$B$2) +2&"-"& YEAR(Pakistan!$B$2) | E28: =Pakistan!H11+Pakistan!H14 | F28: =E28/$B$33
A30: EOR/PEO Service Cost | E30: =E15+E25 | F30: =F15+F25
A33: ="*FX rate USD: "&Pakistan!C6 | B33: =270.0317 | D33: EOR/PEO Service Cost | F33: =F30
D34: Outstanding payment | F34: =Pakistan!E22
D35: FX difference | F35: =Pakistan!E23
D36: Interests of delay | F36: =Pakistan!E24
D37: Bank Charges | F37: =Pakistan!E25
D38: Sub Total (Excluding Tax) | F38: =SUM(F33:F37)
D39: Tax | F39: =Pakistan!F6/B33
D40: Total | F40: =SUM(F38:F39)
A44: Please pay the Invoice in FULL AMOUNT
A45: Beneficiary: NNROAD, INC. Bank Name: Chase Bank Bank Account: 132827913 Bank Add.: 690 River Oaks Parkway Ste A, San Jose, CA 95134, USA | D45: SWIFT BIC (international transfer): CHASUS33XXX Routing Number (domestic wire transfer): 021000021 Routing Number (domestic ACH and direct deposit): 322271627
A46: Notes:
A47: 1. Please ensure that you include the Invoice Number when making your payment. This will help us accurately process and allocate your payment .
A48: 2. This document becomes a Tax Invoice/Receipt upon payment. Please retain a copy for your records.
A49: 3. This is a computer generated document. No Signature required.

Sheet Pakistan
A1: =MID(CELL("filename",A1),FIND("]",CELL("filename",A1))+1,256)
A2: Pay Period | B2: ='Pakistan-L'!C2 | C2: ='Pakistan-L'!E2 | E2: ER
E3: Sum | F3: Business Tax | G3: Management Fee | I3: Gross Salary | Q3: Mandatory Contribution | T3: Expense Claim
G4: Subtotal | H4: Recurring Fee | I4: Subtotal | J4: ='Pakistan-L'!C7 | K4: ='Pakistan-L'!D7 | L4: ='Pakistan-L'!E7 | M4: ='Pakistan-L'!F7 | N4: ='Pakistan-L'!G7 | O4: ='Pakistan-L'!H7 | P4: ='Pakistan-L'!I7 | Q4: Subtotal | R4: ='Pakistan-L'!O7 | S4: ='Pakistan-L'!P7 | T4: Subtotal | U4: Expense Claim
B6: Sum | C6: PKR | E6: =SUM(E9:E17) | F6: =SUM(F9:F17) | G6: =SUM(G9:G17) | H6: =SUM(H9:H17) | I6: =SUM(I9:I17) | J6: =SUM(J9:J17) | K6: =SUM(K9:K17) | L6: =SUM(L9:L17) | ... U6: =SUM(U9:U17)
B9: ='Pakistan-L'!B8 | C9: ='Pakistan EE'!D10 | E9: =F9+G9+I9+Q9+T9 | F9: =18.75*PN!$B$33+6.7933*PN!$B$33 | G9: =SUM(H9:H9) | H9: =(150*PN!$B$33) | I9: =SUM(J9:P9) | J9: ='Pakistan-L'!C8 | K9: ='Pakistan-L'!D8 | L9: ='Pakistan-L'!E8 | M9: ='Pakistan-L'!F8 | N9: ='Pakistan-L'!G8 | O9: ='Pakistan-L'!H8 | P9: ='Pakistan-L'!I8 | Q9: =SUM(R9:S9) | R9: ='Pakistan-L'!O8 | S9: ='Pakistan-L'!P8 | T9: =SUM(U9:U9) | U9: ='Pakistan-L'!K8
B10: ='Pakistan-L'!B9 | C10: ='Pakistan EE'!D11 | E10: =F10+G10+I10+Q10+T10 | F10: =18.75*PN!$B$33+6.7933*PN!$B$33 | G10: =SUM(H10:H10) | H10: =(150*PN!$B$33) | I10: =SUM(J10:P10) | J10: ='Pakistan-L'!C9 | K10: ='Pakistan-L'!D9 | L10: ='Pakistan-L'!E9 | M10: ='Pakistan-L'!F9 | N10: ='Pakistan-L'!G9 | O10: ='Pakistan-L'!H9 | P10: ='Pakistan-L'!I9 | Q10: =SUM(R10:S10) | R10: ='Pakistan-L'!O9 | S10: ='Pakistan-L'!P9 | T10: =SUM(U10:U10) | U10: ='Pakistan-L'!K9
B11: ='Pakistan-L'!B10 | C11: ='Pakistan EE'!D12 | E11: =F11+G11+I11+Q11+T11 | F11: =18.75*PN!$B$33+6.7933*PN!$B$33 | G11: =SUM(H11:H11) | H11: =(150*PN!$B$33) | I11: =SUM(J11:P11) | J11: ='Pakistan-L'!C10 | K11: ='Pakistan-L'!D10 | L11: ='Pakistan-L'!E10 | M11: ='Pakistan-L'!F10 | N11: ='Pakistan-L'!G10 | O11: ='Pakistan-L'!H10 | P11: ='Pakistan-L'!I10 | Q11: =SUM(R11:S11) | R11: ='Pakistan-L'!O10 | S11: ='Pakistan-L'!P10 | T11: =SUM(U11:U11) | U11: ='Pakistan-L'!K10
B12: ='Pakistan-L'!B11 | C12: ='Pakistan EE'!D13 | E12: =F12+G12+I12+Q12+T12 | F12: =18.75*PN!$B$33+7.72*PN!$B$33 | G12: =SUM(H12:H12) | H12: =(150*PN!$B$33) | I12: =SUM(J12:P12) | J12: ='Pakistan-L'!C11 | K12: ='Pakistan-L'!D11 | L12: ='Pakistan-L'!E11 | M12: ='Pakistan-L'!F11 | N12: ='Pakistan-L'!G11 | O12: ='Pakistan-L'!H11 | P12: ='Pakistan-L'!I11 | Q12: =SUM(R12:S12) | R12: ='Pakistan-L'!O11 | S12: ='Pakistan-L'!P11 | T12: =SUM(U12:U12) | U12: ='Pakistan-L'!K11
B13: ='Pakistan-L'!B12 | C13: ='Pakistan EE'!D14 | E13: =F13+G13+I13+Q13+T13 | F13: =18.75*PN!$B$33+7.72*PN!$B$33 | G13: =SUM(H13:H13) | H13: =(150*PN!$B$33) | I13: =SUM(J13:P13) | J13: ='Pakistan-L'!C12 | K13: ='Pakistan-L'!D12 | L13: ='Pakistan-L'!E12 | M13: ='Pakistan-L'!F12 | N13: ='Pakistan-L'!G12 | O13: ='Pakistan-L'!H12 | P13: ='Pakistan-L'!I12 | Q13: =SUM(R13:S13) | R13: ='Pakistan-L'!O12 | S13: ='Pakistan-L'!P12 | T13: =SUM(U13:U13) | U13: ='Pakistan-L'!K12
B14: ='Pakistan-L'!B13 | C14: ='Pakistan EE'!D15 | E14: =F14+G14+I14+Q14+T14 | F14: =18.75*PN!$B$33+7.72*PN!$B$33 | G14: =SUM(H14:H14) | H14: =(150*PN!$B$33) | I14: =SUM(J14:P14) | J14: ='Pakistan-L'!C13 | K14: ='Pakistan-L'!D13 | L14: ='Pakistan-L'!E13 | M14: ='Pakistan-L'!F13 | N14: ='Pakistan-L'!G13 | O14: ='Pakistan-L'!H13 | P14: ='Pakistan-L'!I13 | Q14: =SUM(R14:S14) | R14: ='Pakistan-L'!O13 | S14: ='Pakistan-L'!P13 | T14: =SUM(U14:U14) | U14: ='Pakistan-L'!K13
A21: Other Fee | E21: =SUM(E22:E26) | F21: 0
B22: Outstanding payment | E22: 0
B23: FX difference | F23: 0
B24: Interests of delay | F24: 0
B25: Bank Charges | E25: =35+35+10+10
B26: Invoice adjustment | E26: 0

Sheet Pakistan EE
A1: =MID(CELL("filename",A1),FIND("]",CELL("filename",A1))+1,256)
H2: EE
B3: Client Code | C3: Client Name | D3: EE Code | E3: EE Name | F3: Pay Period | H3: Net Income | I3: Gross Salary | Q3: Expense Claim | S3: Mandatory Contribution
F4: From | G4: To | I4: Subtotal | J4: ='Pakistan-L'!C7 | K4: ='Pakistan-L'!D7 | L4: ='Pakistan-L'!E7 | M4: ='Pakistan-L'!F7 | N4: ='Pakistan-L'!G7 | O4: ='Pakistan-L'!H7 | P4: ='Pakistan-L'!I7 | Q4: Subtotal | R4: Expense Claim | S4: Subtotal | T4: ='Pakistan-L'!L7 | U4: ='Pakistan-L'!M7
A6: EOR/PEO(PKR)
B10: =PN!$B$9 | C10: ='Pakistan-L'!$C$1 | D10: =PN!$B$9&" - "&1 | E10: ='Pakistan-L'!B8 | F10: ='Pakistan-L'!$C$2 | G10: ='Pakistan-L'!$E$2 | H10: =I10+Q10-S10 | I10: =SUM(J10:P10) | J10: ='Pakistan-L'!C8 | K10: ='Pakistan-L'!D8 | L10: ='Pakistan-L'!E8 | M10: ='Pakistan-L'!F8 | N10: ='Pakistan-L'!G8 | O10: ='Pakistan-L'!H8 | P10: ='Pakistan-L'!I8 | Q10: =SUM(R10:R10) | R10: ='Pakistan-L'!K8 | S10: =SUM(T10:U10) | T10: ='Pakistan-L'!L8 | U10: ='Pakistan-L'!M8
B11: =PN!$B$9 | C11: ='Pakistan-L'!$C$1 | D11: =PN!$B$9&" - "&1 | E11: ='Pakistan-L'!B9 | F11: ='Pakistan-L'!$C$2 | G11: ='Pakistan-L'!$E$2 | H11: =I11+Q11-S11 | I11: =SUM(J11:P11) | J11: ='Pakistan-L'!C9 | K11: ='Pakistan-L'!D9 | L11: ='Pakistan-L'!E9 | M11: ='Pakistan-L'!F9 | N11: ='Pakistan-L'!G9 | O11: ='Pakistan-L'!H9 | P11: ='Pakistan-L'!I9 | Q11: =SUM(R11:R11) | R11: ='Pakistan-L'!K9 | S11: =SUM(T11:U11) | T11: ='Pakistan-L'!L9 | U11: ='Pakistan-L'!M9
B12: =PN!$B$9 | C12: ='Pakistan-L'!$C$1 | D12: =PN!$B$9&" - "&1 | E12: ='Pakistan-L'!B10 | F12: ='Pakistan-L'!$C$2 | G12: ='Pakistan-L'!$E$2 | H12: =I12+Q12-S12 | I12: =SUM(J12:P12) | J12: ='Pakistan-L'!C10 | K12: ='Pakistan-L'!D10 | L12: ='Pakistan-L'!E10 | M12: ='Pakistan-L'!F10 | N12: ='Pakistan-L'!G10 | O12: ='Pakistan-L'!H10 | P12: ='Pakistan-L'!I10 | Q12: =SUM(R12:R12) | R12: ='Pakistan-L'!K10 | S12: =SUM(T12:U12) | T12: ='Pakistan-L'!L10 | U12: ='Pakistan-L'!M10
B13: =PN!$B$9 | C13: ='Pakistan-L'!$C$1 | D13: =PN!$B$9&" - "&2 | E13: ='Pakistan-L'!B11 | F13: ='Pakistan-L'!$C$2 | G13: ='Pakistan-L'!$E$2 | H13: =I13+Q13-S13 | I13: =SUM(J13:P13) | J13: ='Pakistan-L'!C11 | K13: ='Pakistan-L'!D11 | L13: ='Pakistan-L'!E11 | M13: ='Pakistan-L'!F11 | N13: ='Pakistan-L'!G11 | O13: ='Pakistan-L'!H11 | P13: ='Pakistan-L'!I11 | Q13: =SUM(R13:R13) | R13: ='Pakistan-L'!K11 | S13: =SUM(T13:U13) | T13: ='Pakistan-L'!L11 | U13: ='Pakistan-L'!M11
B14: =PN!$B$9 | C14: ='Pakistan-L'!$C$1 | D14: =PN!$B$9&" - "&2 | E14: ='Pakistan-L'!B12 | F14: ='Pakistan-L'!$C$2 | G14: ='Pakistan-L'!$E$2 | H14: =I14+Q14-S14 | I14: =SUM(J14:P14) | J14: ='Pakistan-L'!C12 | K14: ='Pakistan-L'!D12 | L14: ='Pakistan-L'!E12 | M14: ='Pakistan-L'!F12 | N14: ='Pakistan-L'!G12 | O14: ='Pakistan-L'!H12 | P14: ='Pakistan-L'!I12 | Q14: =SUM(R14:R14) | R14: ='Pakistan-L'!K12 | S14: =SUM(T14:U14) | T14: ='Pakistan-L'!L12 | U14: ='Pakistan-L'!M12
B15: =PN!$B$9 | C15: ='Pakistan-L'!$C$1 | D15: =PN!$B$9&" - "&2 | E15: ='Pakistan-L'!B13 | F15: ='Pakistan-L'!$C$2 | G15: ='Pakistan-L'!$E$2 | H15: =I15+Q15-S15 | I15: =SUM(J15:P15) | J15: ='Pakistan-L'!C13 | K15: ='Pakistan-L'!D13 | L15: ='Pakistan-L'!E13 | M15: ='Pakistan-L'!F13 | N15: ='Pakistan-L'!G13 | O15: ='Pakistan-L'!H13 | P15: ='Pakistan-L'!I13 | Q15: =SUM(R15:R15) | R15: ='Pakistan-L'!K13 | S15: =SUM(T15:U15) | T15: ='Pakistan-L'!L13 | U15: ='Pakistan-L'!M13

Sheet Pakistan-L
A1: Company name:
A2: Payroll period: | D2: to
A3: Currency: | C3: PKR
A7: No. of EE | B7: Name of Employee | C7: Base Salary | D7: Salary Adjusment | E7: OT | F7: Monthly Bonus | G7: Other Bonus | H7: Leave Payment | I7: Other | J7: Gross Salary | K7: Expense Reimbursment | L7: E.O.B.I | M7: IT | N7: Net Salary | O7: Social Benefit | P7: Medical Insurance | Q7: Bank Charges | R7: Total Cost
J8: =SUM(C8:I8) | N8: =J8+K8-L8-M8 | R8: =J8+K8+O8+P8+Q8
