Workbook

Sheet PN
B1: NNRoad – Employer of Record, Payroll Worldwide
B2: 333 W San Carlos St., Suite 600, San Jose, CA 95113, USA
B3: USA: +1 (669) 377-5080 | www.NNRoad.com
A5: INVOICE
A7: Bill to:
A8: Company name: | B8: Omal Spa SB | D8: Currency | F8: USD
A9: Client ID: | B9: CNUS2025001 | D9: Invoice number | F9: PN-CNUS2025001-030520261
A10: Address: | B10: Ponte Nuovo 11/1, Rodengo Saiano (BS) Italy | D10: Invoice date | F10: =TODAY() -> 46086
D11: Due date | F11: 46098
A12: VAT number | B12: IT00645720988
A14: Description | E14: ="Amount "&UAE!C6 -> Amount AED | F14: Approx. In USD*
A15: EOR/PEO Cost | E15: =SUM(E16:E17) -> 43273.67 | F15: =SUM(F16:F17) -> 12147.592
A16: ="- Labor cost for "&UAE!B9&" - "&MONTH(UAE!B2) &"-"& YEAR(UAE!B2) -> - Labor cost for KUTAY SAMIM GOKSU - 3-2026 | E16: =UAE!I9+UAE!S9 -> 37518 | F16: =E16/$B$28 -> 10531.886
A17: ="- "&+"Expense claim for "&UAE!B9 -> - Expense claim for KUTAY SAMIM GOKSU | E17: =UAE!AE9 -> 5755.67 | F17: =E17/$B$28 -> 1615.706
A20: Service Fee | E20: =SUM(E21:E22) -> 1875 | F20: =SUM(F21:F22) -> 526.34164
A21: ="- "&+"Management Fee - "&MONTH(UAE!B2) &"-"& YEAR(UAE!B2) -> - Management Fee - 3-2026 | E21: =UAE!H9 -> 1875 | F21: =E21/$B$28 -> 526.34164
A25: EOR/PEO Service Cost | E25: =E15+E20 -> 45148.67 | F25: =F15+F20 -> 12673.933
A28: ="*FX rate USD: "&UAE!C6 -> *FX rate USD: AED | B28: =3.6725*0.97 -> 3.562325 | D28: EOR/PEO Service Cost | F28: =F25 -> 12673.933
D29: Outstanding payment | F29: =UAE!E22 -> 0
D30: FX difference | F30: =UAE!E23 -> 0
D31: Interests of delay | F31: =UAE!E24 -> 0
D32: Bank Charges | F32: =UAE!E25 -> 24.035777
D33: Sub Total (Excluding Tax) | F33: =SUM(F28:F32) -> 12697.969
D34: Tax | F34: =UAE!F6/PN!B28 -> 24.56261
D35: Total | F35: =SUM(F33:F34) -> 12722.532
A39: Please pay the Invoice in FULL AMOUNT
A40: Beneficiary: NNROAD, INC. Bank Name: Chase Bank Bank Account: 132827913 Bank Add.: 690 River Oaks Parkway Ste A, San Jose, CA 95134, USA | D40: SWIFT BIC (international transfer): CHASUS33XXX Routing Number (domestic wire transfer): 021000021 Routing Number (domestic ACH and direct deposit): 322271627
A41: Notes:
A42: 1. Please ensure that you include the Invoice Number when making your payment. This will help us accurately process and allocate your payment .
A43: 2. This document becomes a Tax Invoice/Receipt upon payment. Please retain a copy for your records.
A44: 3. This is a computer generated document. No Signature required.

Sheet UAE
A1: =MID(CELL("filename",A1),FIND("]",CELL("filename",A1))+1,256) -> UAE
A2: Pay Period | B2: {=Table1[From]} -> 46082 | C2: {=Table1[To]} -> 46112 | E2: ER
E3: Sum | F3: Business Tax | G3: Management Fee | I3: Gross Salary | S3: Mandatory Contribution | AE3: Expense Claim
G4: Subtotal | H4: Recurring Fee | I4: Subtotal | J4: EC - Basic Salary | K4: EC - Housing Allowance | L4: EC - Transport Allowance | M4: EC - School Allowance | N4: EC - Other allowance | O4: EC - Mobile Allowance | P4: EC - Food Allowance | Q4: EC - OT1 | R4: EC - OT2 | S4: Subtotal | T4: =Table1[[#Headers],[Gratuity]] -> Gratuity | U4: =Table1[[#Headers],[Airfare]] -> Airfare | V4: =Table1[[#Headers],[Annual Leave]] -> Annual Leave | W4: =Table1[[#Headers],[Other Accruals]] -> Other Accruals | X4: =Table1[[#Headers],[Ajeer]] -> Ajeer | Y4: =Table1[[#Headers],[LMRA]] -> LMRA | Z4: =Table1[[#Headers],[Localization]] -> Localization | AA4: =Table1[[#Headers],[GOSI]] -> GOSI | AB4: =Table1[[#Headers],[Workmen Comp]] -> Workmen Comp | AC4: =Table1[[#Headers],[Zakat]] -> Zakat | AD4: =Table1[[#Headers],[Family Visa Levy]] -> Family Visa Levy | AE4: Subtotal | AF4: Expense Claim
B6: Sum | C6: AED | E6: =SUM(E9:E17) -> 45236.17 | F6: =SUM(F9:F17) -> 87.5 | G6: =SUM(G9:G17) -> 1875 | H6: =SUM(H9:H17) -> 1875 | I6: =SUM(I9:I17) -> 35638 | J6: =SUM(J9:J17) -> 19635 | K6: =SUM(K9:K17) -> 9817.5 | L6: =SUM(L9:L17) -> 3272.5 | ... AF6: =SUM(AF9:AF17) -> 5755.67
B9: {=Table1[Employee Name]} -> KUTAY SAMIM GOKSU | C9: ='UAE EE'!D10 -> CNUS2025001-0001 | E9: =F9+G9+I9+S9+AE9 -> 45236.17 | F9: 87.5 | G9: =SUM(H9:H9) -> 1875 | H9: =1875 -> 1875 | I9: =SUM(J9:R9) -> 35638 | J9: {=Table1[EC - Basic Salary]} -> 19635 | K9: {=Table1[EC - Housing Allowance]} -> 9817.5 | L9: {=Table1[EC - Transport Allowance]} -> 3272.5 | M9: {=Table1[EC - School Allowance]} -> 0 | N9: {=Table1[EC - Other allowance]} -> 2913 | O9: {=Table1[EC - Mobile Allowance]} -> 0 | P9: {=Table1[EC - Food Allowance]} -> 0 | Q9: {=Table1[EC - OT1]} -> 0 | R9: {=Table1[EC - OT2]} -> 0 | S9: =SUM(T9:AD9) -> 1880 | T9: {=Table1[Gratuity]} -> 1130 | U9: {=Table1[Airfare]} -> 0 | V9: {=Table1[Annual Leave]} -> 0 | W9: {=Table1[Other Accruals]} -> 0 | X9: {=Table1[Ajeer]} -> 0 | Y9: {=Table1[LMRA]} -> 0 | Z9: {=Table1[Localization]*1.5} -> 750 | AA9: {=Table1[GOSI]} -> 0 | AB9: {=Table1[Workmen Comp]} -> 0 | AC9: {=Table1[Zakat]} -> 0 | AD9: {=Table1[Family Visa Levy]} -> 0 | AE9: =SUM(AF9:AF9) -> 5755.67 | AF9: {=Table1[Other Adjustments]} -> 5755.67
A21: Other Fee | E21: =SUM(E22:E26) -> 24.035777 | F21: 0
B22: Outstanding payment | E22: 0
B23: FX difference | F23: 0
B24: Interests of delay | F24: 0
B25: Bank Charges | E25: =10+50/PN!B28 -> 24.035777
B26: Invoice adjustment | E26: 0

Sheet UAE EE
A1: =MID(CELL("filename",A1),FIND("]",CELL("filename",A1))+1,256) -> UAE EE
H2: EE
B3: Client Code | C3: Client Name | D3: EE Code | E3: EE Name | F3: Pay Period | H3: Net Income | I3: Gross Salary | T3: Expense Claim | V3: Mandatory Contribution | X3: Deduction
F4: From | G4: To | I4: Subtotal | J4: Basic Salary | K4: Housing Allowance | L4: Transport Allowance | M4: School Allowance | N4: Mobile Allowance | O4: Food Allowance | P4: Other Allowance | Q4: OT1 | R4: OT2 | S4: Other Adjustments | T4: Subtotal | U4: Expense Claim | V4: Subtotal | W4: Other
A6: EOR/PEO(AED)
B10: CNUS2025001 | C10: =PN!B8 -> Omal Spa SB | D10: CNUS2025001-0001 | E10: {=Table1[Employee Name]} -> KUTAY SAMIM GOKSU | F10: {=Table1[From]} -> 46082 | G10: {=Table1[To]} -> 46112 | H10: =I10+T10-V10-X10 -> 41393.67 | I10: =SUM(J10:S10) -> 35638 | J10: {=Table1[Basic Salary]} -> 19635 | K10: {=Table1[Housing Allowance]} -> 9817.5 | L10: {=Table1[Transport Allowance]} -> 3272.5 | M10: {=Table1[School Allowance]} -> 0 | N10: {=Table1[Mobile Allowance]} -> 0 | O10: {=Table1[Food Allowance]} -> 0 | P10: {=Table1[Other Allowance]} -> 2913 | Q10: {=Table1[OT1]} -> 0 | R10: {=Table1[OT2]} -> 0 | S10: 0 | T10: =SUM(U10:U10) -> 5755.67 | U10: {=Table1[Other Adjustments]} -> 5755.67 | V10: =SUM(W10:W10) -> 0 | W10: 0 | X10: {=Table1[Deduction]} -> 0

Sheet UAE-L
A1: c | I1: Standard Salary Rates | Z1: HOURS AND DAYS WORKING | AD1: SALARIES | AP1: Installments | AS1: Accruals | AX1: Government Fees | BF1: INVOICE VALUES | BM1: OVERTIME 1
A2: Emp ID | B2: Employee Name | C2: Designation | D2: Payroll Currency | E2: Month Days | F2: From | G2: To | H2: Payroll Days | I2: EC - Basic Salary | J2: EC - Housing Allowance | K2: EC - Transport Allowance | L2: EC - School Allowance | M2: EC - Other allowance | N2: EC - Mobile Allowance | O2: EC - Food Allowance | P2: OT Eligible | Q2: EC - Gross Salary | R2: EC - OT1 | S2: EC - OT2 | T2: EC - Workmen Comp | U2: EC - Localization | V2: EC - Gratuity Accrual | W2: EC - Health Insurance Installment | X2: EC - GOSI | Y2: EC - Admin Fees | Z2: Absence Days | AA2: Days w/o Absence | AB2: Overtime 1 | AC2: Overtime 2 | AD2: Basic Salary | AE2: Housing Allowance | AF2: Transport Allowance | AG2: School Allowance | AH2: Mobile Allowance | AI2: Food Allowance | AJ2: Other Allowance | AK2: OT1 | AL2: OT2 | AM2: Other Adjustments | AN2: Deduction | AO2: Total Payout | AP2: Visa | AQ2: Medical Insurance | AR2: Total Installments | AS2: Gratuity | AT2: Airfare | AU2: Annual Leave | AV2: Other Accruals | AW2: Total Accruals | AX2: Ajeer | AY2: LMRA | AZ2: Localization | BA2: GOSI | BB2: Workmen Comp | BC2: Zakat | BD2: Family Visa Levy | BE2: Total Government Fees | BF2: Employee payout | BG2: Installments | BH2: Accruals | BI2: Government Fees | BJ2: Admin Fees | BK2: Invoice total | BM2: =+BL2+1 -> 1 | BN2: =+BM2+1 -> 2 | BO2: =+BN2+1 -> 3 | BP2: =+BO2+1 -> 4 | BQ2: =+BP2+1 -> 5 | BR2: =+BQ2+1 -> 6 | BS2: =+BR2+1 -> 7 | BT2: =+BS2+1 -> 8 | ... CQ2: =+CP2+1 -> 31 | CR2: Total
A3: AX01669 | B3: KUTAY SAMIM GOKSU | C3: Sales Manager | D3: AED | E3: 31 | F3: 46082 | G3: 46112 | H3: 22 | I3: 19635 | J3: 9817.5 | K3: 3272.5 | L3: 0 | M3: 2913 | N3: 0 | O3: 0 | P3: No | Q3: 32725 | T3: 0 | U3: 500 | V3: 1130 | W3: 0 | X3: 0 | Y3: 1250 | Z3: 0 | AA3: 22 | AB3: 0 | AC3: 0 | AD3: 19635 | AE3: 9817.5 | AF3: 3272.5 | AJ3: 2913 | AM3: 5755.67 | AN3: 0 | AO3: 41393.67 | AR3: 0 | AS3: 1130 | AW3: 1130 | AZ3: 500 | BE3: 500 | BF3: 41393.67 | BG3: 0 | BH3: 1130 | BI3: 500 | BJ3: 1250 | BK3: 44273.67 | BM3: =IFERROR(IF(#REF!<8,0,#REF!-8),0) -> 0 | BN3: =IFERROR(IF(#REF!<8,0,#REF!-8),0) -> 0 | BO3: =IFERROR(IF(#REF!<8,0,#REF!-8),0) -> 0 | BR3: =IFERROR(IF(#REF!<8,0,#REF!-8),0) -> 0 | BS3: =IFERROR(IF(#REF!<8,0,#REF!-8),0) -> 0 | BT3: =IFERROR(IF(#REF!<8,0,#REF!-8),0) -> 0 | BU3: =IFERROR(IF(#REF!<8,0,#REF!-8),0) -> 0 | BV3: =IFERROR(IF(#REF!<8,0,#REF!-8),0) -> 0 | BY3: =IFERROR(IF(#REF!<8,0,#REF!-8),0) -> 0 | BZ3: =IFERROR(IF(#REF!<8,0,#REF!-8),0) -> 0 | CA3: =IFERROR(IF(#REF!<8,0,#REF!-8),0) -> 0 | CB3: =IFERROR(IF(#REF!<8,0,#REF!-8),0) -> 0 | CC3: =IFERROR(IF(#REF!<8,0,#REF!-8),0) -> 0 | CF3: =IFERROR(IF(#REF!<8,0,#REF!-8),0) -> 0 | CG3: =IFERROR(IF(#REF!<8,0,#REF!-8),0) -> 0 | CH3: =IFERROR(IF(#REF!<8,0,#REF!-8),0) -> 0 | CI3: =IFERROR(IF(#REF!<8,0,#REF!-8),0) -> 0 | CJ3: =IFERROR(IF(#REF!<8,0,#REF!-8),0) -> 0 | CM3: =IFERROR(IF(#REF!<8,0,#REF!-8),0) -> 0 | CN3: =IFERROR(IF(#REF!<8,0,#REF!-8),0) -> 0 | CO3: =IFERROR(IF(#REF!<8,0,#REF!-8),0) -> 0 | CP3: =IFERROR(IF(#REF!<8,0,#REF!-8),0) -> 0 | CR3: =SUM(BM3:CQ3) -> 0
A4: Total | AO4: =SUBTOTAL(109,Table1[Total Payout]) -> 41393.67 | AR4: =SUBTOTAL(109,Table1[Total Installments]) -> 0 | AW4: =SUBTOTAL(109,Table1[Total Accruals]) -> 1130 | BE4: =SUBTOTAL(109,Table1[Total Government Fees]) -> 500 | BF4: =SUBTOTAL(109,Table1[Employee payout]) -> 41393.67 | BG4: =SUBTOTAL(109,Table1[Installments]) -> 0 | BH4: =SUBTOTAL(109,Table1[Accruals]) -> 1130 | BI4: =SUBTOTAL(109,Table1[Government Fees]) -> 500 | BJ4: =SUBTOTAL(109,Table1[Admin Fees]) -> 1250 | BK4: =SUBTOTAL(109,Table1[Invoice total]) -> 44273.67 | BM4: =SUM(BM3:BM3) -> 0 | BN4: =SUM(BN3:BN3) -> 0 | BO4: =SUM(BO3:BO3) -> 0 | BP4: =SUM(BP3:BP3) -> 0 | BQ4: =SUM(BQ3:BQ3) -> 0 | BR4: =SUM(BR3:BR3) -> 0 | BS4: =SUM(BS3:BS3) -> 0 | BT4: =SUM(BT3:BT3) -> 0 | ... CR4: =SUM(CR3:CR3) -> 0

Sheet FI Report
A1: Direct Cost | B1: Business Tax | C1: Service Fee | D1: Bank Fee * | E1: Late Pay Fine | F1: Advance Payment | G1: Deposit | H1: Outstanding payment ** | I1: FX difference | J1: Invoice adjustment *** | K1: total
A2: =PN!F15 -> 12147.592 | B2: =PN!F34 -> 24.56261 | C2: =PN!F20 -> 526.34164 | D2: =PN!F32 -> 24.035777 | E2: =PN!F31 -> 0 | F2: =0 -> 0 | G2: 0 | H2: =PN!F29 -> 0 | I2: =PN!F30 -> 0 | J2: 0 | K2: =SUM(A2:J2) -> 12722.532
A7: * NNRoad USD 10 + vendor bank in Vendor's invoice
A8: ** the differnece between NNRoad PN and the amount we actually received
A9: *** PN adjustment with pre-payment or PN revisal
