Workbook

Sheet PN
B1: NNRoad – Employer of Record, Payroll Worldwide
B2: 333 W San Carlos St., Suite 600, San Jose, CA 95113, USA
B3: USA: +1 (669) 377-5080 | www.NNRoad.com
A5: INVOICE
A7: Bill to:
A8: Company name: | B8: Mia Solano | D8: Currency | F8: USD
A9: Client ID: | B9: CNUS2026003 | D9: Invoice number | F9: PN-CNUS2026003-052220261
A10: Address: | B10: 885 S Auto Mall Dr Unit C American Fork, UT 84003, USA | D10: Invoice date | F10: =TODAY() -> 46183
D11: Due date | F11: 46161
A14: Description | E14: ="Amount "&China!C6 -> Amount (RMB) | F14: Approx. In USD*
A15: EOR/PEO Cost | E15: =SUM(E16:E17) -> 15410.95 | F15: =SUM(F16:F17) -> 2331.4599
A16: ="- Labor cost for "&China!B9&" - "&MONTH(China!B2) &"-"& YEAR(China!B2) -> - Labor cost for 徐桂亮 Leon Xu - 6-2026 | E16: =China!K9+China!V9+China!AL9 -> 15410.95 | F16: =E16/$B$27 -> 2331.4599
A17: ="- "&+"Expense claim for "&China!B9 -> - Expense claim for 徐桂亮 Leon Xu | E17: =China!AO9 -> 0 | F17: =E17/$B$27 -> 0
A20: Service Fee | E20: =SUM(E21:E22) -> 2180.1855 | F20: =SUM(F21:F22) -> 329.83139
A21: ="- "&+"Management Fee - "&MONTH(China!$B$2) &"-"& YEAR(China!$B$2) -> - Management Fee - 6-2026 | E21: =China!G9 -> 2180.1855 | F21: =E21/$B$27 -> 329.83139
A24: EOR/PEO Service Cost | E24: =E15+E20 -> 17591.136 | F24: =F15+F20 -> 2661.2913
A27: ="*FX rate USD: "&China!C6 -> *FX rate USD: (RMB) | B27: 6.61 | D27: EOR/PEO Service Cost | F27: =F24 -> 2661.2913
D28: Outstanding payment | F28: =China!E22 -> 0
D29: FX difference | F29: =China!E23 -> 0
D30: Interests of delay | F30: =China!E24 -> 0
D31: Bank Charges | F31: =China!E25 -> 10
D32: Sub Total (Excluding Tax) | F32: =SUM(F27:F31) -> 2671.2913
D33: Tax | F33: =China!F6/$B$27 -> 180.16942
D34: Total | F34: =SUM(F32:F33) -> 2851.4607
A38: Please pay the Invoice in FULL AMOUNT
A39: Beneficiary: NNROAD, INC. Bank Name: Chase Bank Bank Account: 132827913 Bank Add.: 690 River Oaks Parkway Ste A, San Jose, CA 95134, USA | D39: SWIFT BIC (international transfer): CHASUS33XXX Routing Number (domestic wire transfer): 021000021 Routing Number (domestic ACH and direct deposit): 322271627
A40: Notes:
A41: 1. Please ensure that you include the Invoice Number when making your payment. This will help us accurately process and allocate your payment .
A42: 2. This document becomes a Tax Invoice/Receipt upon payment. Please retain a copy for your records.
A43: 3. This is a computer generated document. No Signature required.

Sheet China
A1: =MID(CELL("filename",A1),FIND("]",CELL("filename",A1))+1,256) -> #VALUE!
A2: Pay Period | B2: =EOMONTH(TODAY(),-1)+1 -> 46174 | C2: =EOMONTH(TODAY(),0) -> 46203 | E2: ER
E3: Sum | F3: Business Tax | G3: Management Fee | K3: Gross Salary | W3: Mandatory Contribution | AL3: Other Payment For EE | AO3: Expense Claim | AR3: Refundable Deposit
G4: Subtotal | H4: For Recurring | I4: For Expense | J4: Set-up Fee(One time) | K4: Subtotal | L4: {='China-L (2)'!F3:F4} -> Net Income 员工实得 | M4: ='China-L (2)'!I4 -> Pension 养老-个人 | N4: ='China-L (2)'!J4 -> Medical 医疗-个人 | O4: ='China-L (2)'!K4 -> Unemployment 失业-个人 | P4: ='China-L (2)'!L4 -> Housing Fund 公积金-个人 | Q4: ='China-L (2)'!M4 -> Annuity 年金-个人 | R4: ='China-L (2)'!N4 -> SB Adj-EE 社保补差-个人 | S4: ='China-L (2)'!O4 -> PHF Adj-EE 公积金补差-个人 | T4: ='China-L (2)'!P4 -> Union Fee 工会费-个人 | U4: ='China-L (2)'!Q4 -> IIT Total 个税合计 | V4: Subtotal | W4: ='China-L (2)'!R4 -> Pension 养老-公司 | X4: ='China-L (2)'!S4 -> Medical 医疗-公司 | Y4: ='China-L (2)'!T4 -> Unemployment 失业-公司 | Z4: ='China-L (2)'!U4 -> Maternity 生育-公司 | AA4: ='China-L (2)'!V4 -> Work-Related-Injury 工伤 | AB4: ='China-L (2)'!W4 -> Disability 残保金 | AC4: ='China-L (2)'!X4 -> Housing Fund 公积金-公司 | AD4: ='China-L (2)'!Y4 -> Heating Fee 取暖费 | ... AJ4: ='China-L (2)'!AE4 -> Commercial Insurance 商业保险 | AK4: ='China-L (2)'!AH4 -> Employer Liability Insurance 雇主责任险 | AL4: Subtotal | AM4: 计税不发 | AN4: 当月个税（公司） | AO4: Subtotal | AP4: {='China-L'!AC3:AC4} -> Expense 报销款 | AQ4: ='China-L (2)'!AF4 -> Business Tax for Expense 报销款税额
L5: 0 | AP5: 0
B6: Sum | C6: (RMB) | E6: =SUM(E9:E18) -> 18782.055 | F6: =SUM(F9:F18) -> 1190.9199 | G6: =SUM(G9:G18) -> 2180.1855 | H6: =SUM(H9:H18) -> 1386.9855 | I6: =SUM(I9:I18) -> 0 | J6: =SUM(J9:J18) -> 793.2 | K6: =SUM(K9:K18) -> 10344.83 | L6: =SUM(L9:L18) -> 7672.59 | ... AR6: =SUM(AR9:AR18) -> 0
B9: ='China EE'!E10 -> 徐桂亮 Leon Xu | C9: CNUS2026003-0002 | E9: =F9+G9+K9+V9+AL9+AO9 -> 18782.055 | F9: =(K9+V9+AL9+AO9+G9)*6.77% -> 1190.9199 | G9: =SUM(H9:J9) -> 2180.1855 | H9: =MIN(MAX(150*PN!B27,9%*(K9+V9+AL9+AO9)),1000*PN!B27) -> 1386.9855 | I9: =50*PN!$B$27*0 -> 0 | J9: =120*PN!B27 -> 793.2 | K9: =SUM(L9:U9) -> 10344.83 | L9: ='China-L (2)'!F5 -> 7672.59 | M9: ='China-L (2)'!I5 -> 1200 | N9: ='China-L (2)'!J5 -> 300 | O9: ='China-L (2)'!K5 -> 30 | P9: ='China-L (2)'!L5 -> 1050 | Q9: ='China-L (2)'!M5 -> 0 | R9: ='China-L (2)'!N5 -> 0 | S9: ='China-L (2)'!O5 -> 0 | T9: ='China-L (2)'!P5 -> 0 | U9: ='China-L (2)'!Q5 -> 92.24 | V9: =SUM(W9:AK9) -> 5066.12 | W9: ='China-L (2)'!R5 -> 2400 | X9: ='China-L (2)'!S5 -> 1027.5 | Y9: ='China-L (2)'!T5 -> 120 | Z9: ='China-L (2)'!U5 -> 0 | AA9: ='China-L (2)'!V5 -> 60 | AB9: ='China-L (2)'!W5 -> 98.62 | AC9: ='China-L (2)'!X5 -> 1050 | AD9: ='China-L (2)'!Y5 -> 0 | ... AJ9: ='China-L (2)'!AE5 -> 310 | AK9: ='China-L (2)'!AH5 -> 0 | AL9: =SUM(AM9:AN9) -> 0 | AM9: 0 | AN9: ='China-L (2)'!Q5-'China-L'!AA5 -> 0 | AO9: =SUM(AP9:AQ9) -> 0 | AP9: ='China-L'!AC5 -> 0 | AQ9: ='China-L (2)'!AF5 -> 0 | AR9: 0
A21: Other Fee | E21: =SUM(E22:E26) -> 10 | F21: 0
B22: Outstanding payment | E22: 0
B23: FX difference | F23: 0
B24: Interests of delay | F24: 0
B25: Bank Charges | E25: =10 -> 10
B26: Invoice adjustment | E26: 0

Sheet China EE
A1: =MID(CELL("filename",A1),FIND("]",CELL("filename",A1))+1,256) -> #VALUE!
H2: EE
B3: Client Code | C3: Client Name | D3: EE Code | E3: EE Name | F3: Pay Period | H3: Net Income | I3: Salary | T3: Expense Claim | V3: EE Mandatory Contribution | AC3: IIT
F4: From | G4: To | I4: Subtotal | J4: ='China-L'!E4 -> Basic Salary 基本工资 | K4: ='China-L'!G4 -> Bonus 奖金 | L4: ='China-L'!H4 -> Annual Bonus/13th Salary 年终奖/13薪 | M4: ='China-L'!I4 -> Allowance/Subsidy 津贴/补贴 | N4: ='China-L'!J4 -> OT Payment 加班费 | O4: ='China-L'!K4 -> Other Adjustment Before Tax 税前其他调整 | P4: ='China-L'!L4 -> Income Employer Afford Tax 公司负税项 | Q4: ='China-L'!W4 -> Deduction for Personal Affair/Absenteeism Leave 扣事假/旷工 | R4: ='China-L'!X4 -> Deduction for Sick and Maternity Leave 扣病假/产假 | S4: {='China-L'!AB3:AB4} -> Adjustment After Tax 税后工资调整 | T4: Subtotal | U4: {='China-L'!AC3:AC4} -> Expense 报销款 | V4: Subtotal | W4: ='China-L'!Q4 -> Pension 缴养老 | X4: ='China-L'!R4 -> Medical 缴医疗 | Y4: ='China-L'!S4 -> Unemployment 缴失业 | Z4: ='China-L'!T4 -> Housing Fund 缴公积金 | AA4: ='China-L'!U4 -> SB Adj-EE 社保补差-个人 | AB4: ='China-L'!V4 -> PHF Adj-EE 公积金补差-个人
S5: 0 | U5: 0
A6: EOR/PEO(CNY)
B10: =PN!B9 -> CNUS2026003 | C10: =PN!B8 -> Mia Solano | D10: =China!C9 -> CNUS2026003-0002 | E10: ='China-L'!D5 -> 徐桂亮 Leon Xu | F10: =China!B2 -> 46174 | G10: =China!C2 -> 46203 | H10: =I10+T10-V10-AC10 -> 7672.59 | I10: =SUM(J10:S10) -> 10344.83 | J10: ='China-L'!E5 -> 15000 | K10: ='China-L'!G5 -> 0 | L10: ='China-L'!H5 -> 0 | M10: ='China-L'!I5 -> 0 | N10: ='China-L'!J5 -> 0 | O10: ='China-L'!K5 -> -4655.17 | P10: ='China-L'!L5 -> 0 | Q10: ='China-L'!W5 -> 0 | R10: ='China-L'!X5 -> 0 | S10: ='China-L'!AB5 -> 0 | T10: =SUM(U10:U10) -> 0 | U10: ='China-L'!AC5 -> 0 | V10: =SUM(W10:AB10) -> 2580 | W10: ='China-L'!Q5 -> 1200 | X10: ='China-L'!R5 -> 300 | Y10: ='China-L'!S5 -> 30 | Z10: ='China-L'!T5 -> 1050 | AA10: ='China-L'!U5 -> 0 | AB10: ='China-L'!V5 -> 0 | AC10: ='China-L'!AA5 -> 92.24

Sheet China-L
A1: Duration 发薪月 | D1: 202605 | E1: Employer 雇主 | F1: NNRoad-Madilane
A3: No. 序号 | B3: Dept./cost code 部门/成本中心 | C3: ID No. 工号 | D3: Name 姓名 | E3: Plus Item 加项 | O3: Basis for Social Benefits Calculation 社保基数 | P3: Basis for Housing Fund Calculation 公积金基数 | Q3: Minus Item 减项 | AA3: IIT 个税 | AB3: Adjustment After Tax 税后工资调整 | AC3: Expense 报销款 | AD3: Subsistence Allowance for Foreigners 外籍生活津贴 | AE3: Net Income 实发
E4: Basic Salary 基本工资 | F4: Actual Base Salary 实际基本工资 | G4: Bonus 奖金 | H4: Annual Bonus/13th Salary 年终奖/13薪 | I4: Allowance/Subsidy 津贴/补贴 | J4: OT Payment 加班费 | K4: Other Adjustment Before Tax 税前其他调整 | L4: Income Employer Afford Tax 公司负税项 | M4: Stock option incentive/股权激励 | N4: Compensation离职补偿金/赔偿金 | O4: Basis for Social Benefits Calculation 社保基数 | P4: Basis for Housing Fund Calculation 公积金基数 | Q4: Pension 缴养老 | R4: Medical 缴医疗 | S4: Unemployment 缴失业 | T4: Housing Fund 缴公积金 | U4: SB Adj-EE 社保补差-个人 | V4: PHF Adj-EE 公积金补差-个人 | W4: Deduction for Personal Affair/Absenteeism Leave 扣事假/旷工 | X4: Deduction for Sick and Maternity Leave 扣病假/产假 | Y4: Annuity 缴年金 | Z4: Union Fee 工会费
A5: 1 | C5: CHHK037-0001 | D5: 徐桂亮 Leon Xu | E5: 15000 | F5: 15000 | G5: 0 | H5: 0 | I5: 0 | J5: 0 | K5: -4655.17 | L5: 0 | M5: 0 | N5: 0 | O5: 15000 | P5: 15000 | Q5: 1200 | R5: 300 | S5: 30 | T5: 1050 | U5: 0 | V5: 0 | W5: 0 | X5: 0 | Y5: 0 | Z5: 0 | AA5: 92.24 | AB5: 0 | AC5: 0 | AD5: 0 | AE5: 7672.59
A8: Sum 合计 | E8: =SUM($E$1:E7) -> 15000 | F8: =SUM($F$1:F7) -> 15000 | G8: =SUM($G$1:G7) -> 0 | H8: =SUM($H$1:H7) -> 0 | I8: =SUM($I$1:I7) -> 0 | J8: =SUM($J$1:J7) -> 0 | K8: =SUM($K$1:K7) -> -4655.17 | L8: =SUM($L$1:L7) -> 0 | M8: =SUM($M$1:M7) -> 0 | N8: =SUM($N$1:N7) -> 0 | Q8: =SUM($Q$1:Q7) -> 1200 | R8: =SUM($R$1:R7) -> 300 | S8: =SUM($S$1:S7) -> 30 | T8: =SUM($T$1:T7) -> 1050 | U8: =SUM($U$1:U7) -> 0 | V8: =SUM($V$1:V7) -> 0 | W8: =SUM($W$1:W7) -> 0 | X8: =SUM($X$1:X7) -> 0 | Y8: =SUM($Y$1:Y7) -> 0 | Z8: =SUM($Z$1:Z7) -> 0 | AA8: =SUM($AA$1:AA7) -> 92.24 | AB8: =SUM($AB$1:AB7) -> 0 | AC8: =SUM($AC$1:AC7) -> 0 | AD8: =SUM($AD$1:AD7) -> 0 | AE8: =SUM($AE$1:AE7) -> 7672.59

Sheet China-L (2)
A1: Duration 发薪月 | D1: 202605 | E1: Client 客户 | F1: NNRoad-Madilane
A3: No. 序号 | B3: Dept./cost code 部门/成本中心 | C3: Employee ID 客户员工号 | D3: ID No. 工号 | E3: Name 姓名 | F3: Net Income 员工实得 | G3: Expense 报销款 | H3: Subsistence Allowance for Foreigners 外籍生活津贴 | I3: Individual Portion 个人部分 | R3: Employer Portion 雇主部分 | AJ3: Service Fee 服务费 | AK3: SFT 服务费税 | AL3: Value Added Tax 增值税 | AM3: Total Cost 总成本 | AN3: Remark 备注
I4: Pension 养老-个人 | J4: Medical 医疗-个人 | K4: Unemployment 失业-个人 | L4: Housing Fund 公积金-个人 | M4: Annuity 年金-个人 | N4: SB Adj-EE 社保补差-个人 | O4: PHF Adj-EE 公积金补差-个人 | P4: Union Fee 工会费-个人 | Q4: IIT Total 个税合计 | R4: Pension 养老-公司 | S4: Medical 医疗-公司 | T4: Unemployment 失业-公司 | U4: Maternity 生育-公司 | V4: Work-Related-Injury 工伤 | W4: Disability 残保金 | X4: Housing Fund 公积金-公司 | Y4: Heating Fee 取暖费 | Z4: SB Adj-Com 社保补差-公司 | AA4: PHF Adj-Com 公积金补差-公司 | AB4: CD Adj-Com 残保金补差-公司 | AC4: Annuity 年金-公司 | AD4: Union Fee 工会费-公司 | AE4: Commercial Insurance 商业保险 | AF4: Business Tax for Expense 报销款税额 | AG4: Deposit 押金 | AH4: Employer Liability Insurance 雇主责任险 | AI4: Office Seat 其他
A5: 1 | D5: CHHK037-0001 | E5: 徐桂亮 Leon Xu | F5: 7672.59 | G5: 0 | H5: 0 | I5: 1200 | J5: 300 | K5: 30 | L5: 1050 | M5: 0 | N5: 0 | O5: 0 | P5: 0 | Q5: 92.24 | R5: 2400 | S5: 1027.5 | T5: 120 | U5: 0 | V5: 60 | W5: 98.62 | X5: 1050 | Y5: 0 | Z5: 0 | AA5: 0 | AB5: 0 | AC5: 0 | AD5: 0 | AE5: 310 | AF5: 0 | AG5: 0 | AH5: 0 | AI5: 0 | AM5: 16934.74
A8: Sum 合计 | F8: =SUM($F$1:F7) -> 7672.59 | G8: =SUM($G$1:G7) -> 0 | H8: =SUM($H$1:H7) -> 0 | I8: =SUM($I$1:I7) -> 1200 | J8: =SUM($J$1:J7) -> 300 | K8: =SUM($K$1:K7) -> 30 | L8: =SUM($L$1:L7) -> 1050 | M8: =SUM($M$1:M7) -> 0 | N8: =SUM($N$1:N7) -> 0 | O8: =SUM($O$1:O7) -> 0 | P8: =SUM($P$1:P7) -> 0 | Q8: =SUM($Q$1:Q7) -> 92.24 | R8: =SUM($R$1:R7) -> 2400 | S8: =SUM($S$1:S7) -> 1027.5 | T8: =SUM($T$1:T7) -> 120 | U8: =SUM($U$1:U7) -> 0 | V8: =SUM($V$1:V7) -> 60 | W8: =SUM($W$1:W7) -> 98.62 | X8: =SUM($X$1:X7) -> 1050 | Y8: =SUM($Y$1:Y7) -> 0 | Z8: =SUM($Z$1:Z7) -> 0 | AA8: =SUM($AA$1:AA7) -> 0 | AB8: =SUM($AB$1:AB7) -> 0 | AC8: =SUM($AC$1:AC7) -> 0 | AD8: =SUM($AD$1:AD7) -> 0 | AE8: =SUM($AE$1:AE7) -> 310 | AF8: =SUM($AF$1:AF7) -> 0 | AG8: =SUM($AG$1:AG7) -> 0 | AH8: =SUM($AH$1:AH7) -> 0 | AI8: =SUM($AI$1:AI7) -> 0 | AJ8: =SUM($AJ$1:AJ7) -> 0 | AK8: =SUM($AK$1:AK7) -> 0 | AL8: =SUM($AL$1:AL7) -> 0 | AM8: =SUM($AM$1:AM7) -> 16934.74
