Workbook

Sheet PN
B1: NNRoad – Employer of Record, Payroll Worldwide
B2: 333 W San Carlos St., Suite 600, San Jose, CA 95113, USA
B3: USA: +1 (669) 377-5080 | www.NNRoad.com
A5: INVOICE
A7: Bill to:
A8: Company name: | D8: Currency | F8: USD
A9: Client ID: | D9: Invoice number
A10: Address: | D10: Invoice date | F10: =TODAY()
D11: Due date
A14: Description | E14: ="Amount "&Kyrgyzstan!C6 | F14: Approx. In USD*
A15: EOR/PEO Cost | E15: =SUM(E16:E18) | F15: =SUM(F16:F18)
A16: ="- Labor cost for "&Kyrgyzstan!B9&" - "&MONTH(Kyrgyzstan!B2) &"-"& YEAR(Kyrgyzstan!C2) | E16: =Kyrgyzstan!J9+Kyrgyzstan!P9-Kyrgyzstan!O9 | F16: =E16/$B$28
A17: ="- "&+"Expense claim for "&Kyrgyzstan!B9&" - "&MONTH(Kyrgyzstan!B2) &"-"& YEAR(Kyrgyzstan!C2) | E17: =Kyrgyzstan!T9 | F17: =E17/$B$28
A20: Service Fee | E20: =SUM(E21:E22) | F20: =SUM(F21:F22)
A21: ="- "&+"Management Fee - "&MONTH(Kyrgyzstan!B2) &"-"& YEAR(Kyrgyzstan!B2) | E21: =Kyrgyzstan!G9 | F21: =E21/$B$28
A25: EOR/PEO Service Cost | E25: =E15+E20 | F25: =F15+F20
A28: *FX rate USD/KGS: | D28: EOR/PEO Service Cost | F28: =F25
A29: *FX rate EUR/KGS | D29: Outstanding payment | F29: =Kyrgyzstan!E22
A30: *FX rate EUR/USD | B30: =ROUND(B29/B28,2) | D30: FX difference | F30: =Kyrgyzstan!E23
D31: Interests of delay | F31: =Kyrgyzstan!E24
D32: Bank Charges | F32: =Kyrgyzstan!E25
D33: Sub Total (Excluding Tax) | F33: =SUM(F28:F32)
D34: Tax | F34: =ROUND(Kyrgyzstan!F6/PN!B28,0)
D35: Total | F35: =SUM(F33:F34)
A39: Please pay the Invoice in FULL AMOUNT
A40: Beneficiary: NNROAD, INC. Bank Name: Chase Bank Bank Account: 132827913 Bank Add.: 690 River Oaks Parkway Ste A, San Jose, CA 95134, USA | D40: SWIFT BIC (international transfer): CHASUS33XXX Routing Number (domestic wire transfer): 021000021 Routing Number (domestic ACH and direct deposit): 322271627
A41: Notes:
A42: 1. Please ensure that you include the Invoice Number when making your payment. This will help us accurately process and allocate your payment .
A43: 2. This document becomes a Tax Invoice/Receipt upon payment. Please retain a copy for your records.
A44: 3. This is a computer generated document. No Signature required.

Sheet Kyrgyzstan
A1: =MID(CELL("filename",A1),FIND("]",CELL("filename",A1))+1,256)
A2: Pay Period | B2: ='Kyrgyzstan-L'!C2 | C2: ='Kyrgyzstan-L'!E2 | E2: ER
E3: Sum | F3: Business Tax | G3: Management Fee | J3: Gross Salary | P3: Mandatory Contribution | T3: Expense Claim
G4: Subtotal | H4: Recurring Fee | I4: Set-up Fee | J4: Subtotal | K4: Base Salary | L4: OT | M4: Salary Adjusment | N4: Bonus | O4: Other | P4: Subtotal | Q4: ='Kyrgyzstan-L'!N7 | R4: ='Kyrgyzstan-L'!O7 | S4: ='Kyrgyzstan-L'!P7 | T4: Subtotal | U4: Expense Claim
B6: Sum | C6: (KGS) | E6: =SUM(E9:E17) | F6: =SUM(F9:F17) | G6: =SUM(G9:G17) | H6: =SUM(H9:H17) | I6: =SUM(I9:I17) | J6: =SUM(J9:J17) | K6: =SUM(K9:K17) | L6: =SUM(L9:L17) | ... U6: =SUM(U9:U17)
B9: ='Kyrgyzstan-L'!B8 | C9: ='Kyrgyzstan EE'!D10 | E9: =F9+G9+J9+P9+T9 | F9: =(J9+P9+T9+200*PN!B29)*6% | G9: =SUM(H9:I9) | H9: =300*PN!B29 | I9: =100*PN!B29 | J9: =SUM(K9:O9) | K9: ='Kyrgyzstan-L'!C8 | L9: ='Kyrgyzstan-L'!D8 | M9: ='Kyrgyzstan-L'!E8 | N9: ='Kyrgyzstan-L'!F8 | O9: ='Kyrgyzstan-L'!G8 | P9: =SUM(Q9:S9) | Q9: ='Kyrgyzstan-L'!N8 | R9: ='Kyrgyzstan-L'!O8 | S9: ='Kyrgyzstan-L'!P8 | T9: =SUM(U9:U9) | U9: ='Kyrgyzstan-L'!H8
A21: Other Fee | E21: =SUM(E22:E26) | F21: 0
B22: Outstanding payment | E22: 0
B23: FX difference | F23: 0
B24: Interests of delay | F24: 0
B25: Bank Charges | E25: =10*PN!B30
B26: Invoice adjustment | E26: 0

Sheet Kyrgyzstan EE
A1: =MID(CELL("filename",A1),FIND("]",CELL("filename",A1))+1,256)
H2: EE
B3: Client Code | C3: Client Name | D3: EE Code | E3: EE Name | F3: Pay Period | H3: Net Income | I3: Gross Salary | O3: Expense Claim | Q3: Mandatory Contribution | T3: IIT
F4: From | G4: To | I4: Subtotal | J4: Base Salary | K4: OT | L4: Salary Adjusment | M4: Bonus | N4: Other | O4: Subtotal | P4: Expense Claim | Q4: Subtotal | R4: ='Kyrgyzstan-L'!K7 | S4: ='Kyrgyzstan-L'!L7 | T4: Subtotal | U4: ='Kyrgyzstan-L'!J7
A6: EOR/PEO(KGS)
B10: =PN!B9 | C10: =PN!B8 | D10: ='Kyrgyzstan-L'!A8 | E10: ='Kyrgyzstan-L'!B8 | F10: ='Kyrgyzstan-L'!C2 | G10: ='Kyrgyzstan-L'!E2 | H10: =I10+O10-Q10-T10 | I10: =SUM(J10:N10) | J10: ='Kyrgyzstan-L'!C8 | K10: ='Kyrgyzstan-L'!D8 | L10: ='Kyrgyzstan-L'!E8 | M10: ='Kyrgyzstan-L'!F8 | N10: ='Kyrgyzstan-L'!G8 | O10: =SUM(P10:P10) | P10: ='Kyrgyzstan-L'!H8 | Q10: =SUM(R10:S10) | R10: ='Kyrgyzstan-L'!K8 | S10: ='Kyrgyzstan-L'!L8 | T10: =U10 | U10: ='Kyrgyzstan-L'!J8

Sheet Kyrgyzstan-L
A1: Company name: | C1: =PN!B8
A2: Payroll period: | D2: to
A3: Currency: | C3: KGS
A7: No. of EE | B7: Name of Employee | C7: Base Salary | D7: OT | E7: Salary Adjusment | F7: Bonus | G7: Other | H7: Expense Reimbursment | I7: Gross Salary | J7: Personal Income Tax | K7: Pension fund | L7: Accumulative pension fund | M7: Net Salary | N7: Medical insurance fund | O7: Workers' Health Fund | P7: Workmen Compensation Insurance | Q7: Other | R7: Total Cost
I8: =SUM(C8:G8) | J8: =ROUND((C8-L8-K8-650)*10%,0) | K8: =ROUND(C8*8%,0) | L8: =ROUND(C8*2%,0) | M8: =I8-K8-L8-J8 | N8: =ROUND(C8*2%,0) | O8: =ROUND(C8*0.25%,0) | P8: =ROUND(C8*0.03%,0) | R8: =I8+N8+O8+P8+Q8
