Workbook

Sheet PN
B1: NNRoad – Employer of Record, Payroll Worldwide
B2: 333 W San Carlos St., Suite 600, San Jose, CA 95113, USA
B3: USA: +1 (669) 377-5080 | www.NNRoad.com
A5: INVOICE
A7: Bill to:
A8: Company name: | B8: Coral Sea | D8: Currency | F8: USD
A9: Client ID: | B9: CUS1516 | D9: Invoice number | F9: PN-CUS1516-031120261
A10: Address: | B10: 4205/41 Williams Esplanade, PALM COVE, QLD, Australia | D10: Invoice date | F10: =TODAY() -> 46092
D11: Due date | F11: 46099
A14: Description | E14: ="Amount "&TW!C6 -> Amount (NTD) | F14: Approx. In USD*
A15: EOR/PEO Cost | E15: =SUM(E16:E22) -> 60267.5 | F15: =SUM(F16:F22) -> 1925.6207
A16: ="- Labor cost for "&TW!B9&" - "&MONTH(TW!$B$2) &"-"& YEAR(TW!$B$2) -> - Labor cost for Pin Han - 3-2026 | E16: =TW!J9+TW!Z9 -> 40035.5 | F16: =E16/$B$31 -> 1279.1835
A17: ="- Labor cost for "&TW!B10&" - "&MONTH(TW!$B$2) &"-"& YEAR(TW!$B$2) -> - Labor cost for Min Han - 3-2026 | E17: =TW!J10+TW!Z10 -> 9789 | F17: =E17/$B$31 -> 312.77059
A18: ="- Labor cost for "&TW!B11&" - "&MONTH(TW!$B$2) &"-"& YEAR(TW!$B$2) -> - Labor cost for Wen kai - 3-2026 | E18: =TW!J11+TW!Z11 -> 10443 | F18: =E18/$B$31 -> 333.66669
A19: ="- "&+"Expense claim for "&TW!B9 -> - Expense claim for Pin Han | E19: =TW!AB9 -> 0 | F19: =E19/$B$31 -> 0
A20: ="- "&+"Expense claim for "&TW!B10 -> - Expense claim for Min Han | E20: =TW!AB10 -> 0 | F20: =E20/$B$31 -> 0
A21: ="- "&+"Expense claim for "&TW!B11 -> - Expense claim for Wen kai | E21: =TW!AB11 -> 0 | F21: =E21/$B$31 -> 0
A23: Service Fee | E23: =SUM(E24:E25) -> 13804.26 | F23: =SUM(F24:F25) -> 441.06308
A24: ="- "&+"Management Fee - "&MONTH(TW!B2) &"-"& YEAR(TW!B2) -> - Management Fee - 3-2026 | E24: =TW!G6 -> 13804.26 | F24: =E24/$B$31 -> 441.06308
A28: EOR/PEO Service Cost | E28: =E15+E23 -> 74071.76 | F28: =F15+F23 -> 2366.6838
A31: ="*FX rate USD: "&TW!C6 -> *FX rate USD: (NTD) | B31: 31.2977 | D31: EOR/PEO Service Cost | F31: =F28 -> 2366.6838
D32: Outstanding payment | F32: =TW!E22 -> 0
D33: FX difference | F33: =TW!E23 -> 0
D34: Interests of delay | F34: =TW!E24 -> 0
D35: Bank Charges | F35: =TW!E25 -> 10
D36: Sub Total (Excluding Tax) | F36: =SUM(F31:F35) -> 2376.6838
D37: Tax | F37: =ROUNDUP(TW!F6/PN!B31,2)+0.01 -> 110.66
D38: Total | F38: =SUM(F36:F37) -> 2487.3438
A42: Please pay the Invoice in FULL AMOUNT
A43: Beneficiary: NNROAD, INC. Bank Name: Chase Bank Bank Account: 132827913 Bank Add.: 690 River Oaks Parkway Ste A, San Jose, CA 95134, USA | D43: SWIFT BIC (international transfer): CHASUS33XXX Routing Number (domestic wire transfer): 021000021 Routing Number (domestic ACH and direct deposit): 322271627
A44: Notes:
A45: 1. Please ensure that you include the Invoice Number when making your payment. This will help us accurately process and allocate your payment .
A46: 2. This document becomes a Tax Invoice/Receipt upon payment. Please retain a copy for your records.
A47: 3. This is a computer generated document. No Signature required.

Sheet TW
A1: =MID(CELL("filename",A1),FIND("]",CELL("filename",A1))+1,256) -> TW
A2: Pay Period | B2: ='TW-L'!C4 -> 2026/3/1 | C2: ='TW-L'!C5 -> 2026/3/31 | E2: ER
E3: Sum | F3: Business Tax | G3: Management Fee Fee | J3: Gross Salary | Z3: Mandatory Contribution | AB3: Expense Claim
G4: Subtotal | H4: Recurring Fee | I4: Expense Fee | J4: Subtotal | K4: Basic Salary | L4: Salary Adjustment | M4: OT | N4: Allw- Phone/ Communication | O4: Allw Transportation | P4: Back Pay | Q4: 伙食津貼Allw Meal | R4: Remote Stipend | S4: 病假扣薪 Sick Leave (half pay) | T4: NPL Hours | U4: No Pay Leave | V4: Bonus VB | W4: Incentives | X4: 特休結算 Untaken AL | Y4: 資遣費 Severance | Z4: Subtotal | AA4: ER insurance | AB4: Subtotal | AC4: Expense Claim
B6: Sum | C6: (NTD) | E6: =SUM(E9:E17) -> 77534.76 | F6: =SUM(F9:F17) -> 3463 | G6: =SUM(G9:G17) -> 13804.26 | H6: =SUM(H9:H17) -> 13804.26 | I6: =SUM(I9:I17) -> 0 | J6: =SUM(J9:J17) -> 50222.5 | K6: =SUM(K9:K17) -> 38155 | L6: =SUM(L9:L17) -> 0 | ... AC6: =SUM(AC9:AC17) -> 0
B9: ='TW-L'!C9 -> Pin Han | C9: ='TW EE'!D10 -> CUS1516-0001 | E9: =SUM(F9:G9)+J9+Z9+AB9 -> 46991.76 | F9: 2152 | G9: =SUM(H9:I9) -> 4804.26 | H9: =MAX(4500,(J9+Z9)*12%) -> 4804.26 | I9: =IF(AB9>0,1500,0) -> 0 | J9: =SUM(K9:Y9) -> 33422.5 | K9: ='TW-L'!N9 -> 25355 | L9: 0 | M9: ='TW-L'!AC9 -> 9220 | N9: ='TW-L'!O9 -> 0 | O9: ='TW-L'!P9 -> 0 | P9: ='TW-L'!Q9 -> 0 | Q9: ='TW-L'!R9 -> 0 | R9: ='TW-L'!R9 -> 0 | S9: ='TW-L'!U9 -> -1152.5 | T9: ='TW-L'!V9 -> 0 | U9: ='TW-L'!W9 -> 0 | V9: ='TW-L'!X9 -> 0 | W9: ='TW-L'!Y9 -> 0 | X9: ='TW-L'!AA9 -> 0 | Y9: ='TW-L'!AB9 -> 0 | Z9: =SUM(AA9:AA9) -> 6613 | AA9: ='TW-L'!BL9 -> 6613 | AB9: =SUM(AC9:AC9) -> 0 | AC9: ='TW-L'!Z9 -> 0
B10: ='TW-L'!C10 -> Min Han | C10: ='TW EE'!D11 -> CUS1516-0002 | E10: =SUM(F10:G10)+J10+Z10+AB10 -> 14928 | F10: 639 | G10: =SUM(H10:I10) -> 4500 | H10: =MAX(4500,(J10+Z10)*12%) -> 4500 | I10: =IF(AB10>0,1500,0) -> 0 | J10: =SUM(K10:Y10) -> 8000 | K10: ='TW-L'!N10 -> 6000 | L10: 0 | M10: ='TW-L'!AC10 -> 2000 | N10: ='TW-L'!O10 -> 0 | O10: ='TW-L'!P10 -> 0 | P10: ='TW-L'!Q10 -> 0 | Q10: ='TW-L'!R10 -> 0 | R10: ='TW-L'!R10 -> 0 | S10: ='TW-L'!U10 -> 0 | T10: ='TW-L'!V10 -> 0 | U10: ='TW-L'!W10 -> 0 | V10: ='TW-L'!X10 -> 0 | W10: ='TW-L'!Y10 -> 0 | X10: ='TW-L'!AA10 -> 0 | Y10: ='TW-L'!AB10 -> 0 | Z10: =SUM(AA10:AA10) -> 1789 | AA10: ='TW-L'!BL10 -> 1789 | AB10: =SUM(AC10:AC10) -> 0 | AC10: ='TW-L'!Z10 -> 0
B11: ='TW-L'!C11 -> Wen kai | C11: ='TW EE'!D12 -> CUS1516-0003 | E11: =SUM(F11:G11)+J11+Z11+AB11 -> 15615 | F11: 672 | G11: =SUM(H11:I11) -> 4500 | H11: =MAX(4500,(J11+Z11)*12%) -> 4500 | I11: =IF(AB11>0,1500,0) -> 0 | J11: =SUM(K11:Y11) -> 8800 | K11: ='TW-L'!N11 -> 6800 | L11: 0 | M11: ='TW-L'!AC11 -> 2000 | N11: ='TW-L'!O11 -> 0 | O11: ='TW-L'!P11 -> 0 | P11: ='TW-L'!Q11 -> 0 | Q11: ='TW-L'!R11 -> 0 | R11: ='TW-L'!R11 -> 0 | S11: ='TW-L'!U11 -> 0 | T11: ='TW-L'!V11 -> 0 | U11: ='TW-L'!W11 -> 0 | V11: ='TW-L'!X11 -> 0 | W11: ='TW-L'!Y11 -> 0 | X11: ='TW-L'!AA11 -> 0 | Y11: ='TW-L'!AB11 -> 0 | Z11: =SUM(AA11:AA11) -> 1643 | AA11: ='TW-L'!BL11 -> 1643 | AB11: =SUM(AC11:AC11) -> 0 | AC11: ='TW-L'!Z11 -> 0
A21: Other Fee | E21: =SUM(E22:E26) -> 10 | F21: 0
B22: Outstanding payment
B23: FX difference | F23: 0
B24: Interests of delay | F24: 0
B25: Bank Charges | E25: =10 -> 10
B26: Invoice adjustment | E26: 0

Sheet TW EE
A1: =MID(CELL("filename",A1),FIND("]",CELL("filename",A1))+1,256) -> TW EE
H2: EE
B3: Client Code | C3: Client Name | D3: EE Code | E3: EE Name | F3: Pay Period | H3: Net Income | I3: Gross Salary | Y3: Expense Claim | AA3: Mandatory Contribution | AF3: Deduction | AG3: IIT
F4: From | G4: To | I4: Subtotal | J4: Basic Salary | K4: Salary Adjustment | L4: OT | M4: Allw- Phone/ Communication | N4: Allw Transportation | O4: Back Pay | P4: 伙食津貼 Allw Meal | Q4: Remote Stipend | R4: 病假扣薪 Sick Leave (half pay) | S4: NPL Hours | T4: No Pay Leave | U4: Bonus VB | V4: Incentives | W4: 特休結算 Untaken AL | X4: 資遣費 Severance | Y4: Subtotal | Z4: Expense Claim | AA4: Subtotal | AB4: LI | AC4: Pension | AD4: HI | AE4: 2G HI
A6: EOR/PEO(NTD)
B10: =PN!$B$9 -> CUS1516 | C10: =PN!$B$8 -> Coral Sea | D10: CUS1516-0001 | E10: ='TW-L'!C9 -> Pin Han | F10: ='TW-L'!$C$4 -> 2026/3/1 | G10: ='TW-L'!$C$5 -> 2026/3/31 | H10: =I10+Y10+AA10+AF10+AG10 -> 32420.5 | I10: =SUM(J10:X10) -> 33422.5 | J10: ='TW-L'!N9 -> 25355 | K10: 0 | L10: ='TW-L'!AC9 -> 9220 | M10: ='TW-L'!O9 -> 0 | N10: ='TW-L'!P9 -> 0 | O10: ='TW-L'!Q9 -> 0 | P10: ='TW-L'!R9 -> 0 | Q10: ='TW-L'!X9+'TW-L'!Y9 -> 0 | R10: ='TW-L'!U9 -> -1152.5 | S10: ='TW-L'!V9 -> 0 | T10: ='TW-L'!W9 -> 0 | U10: ='TW-L'!X9 -> 0 | V10: ='TW-L'!Y9 -> 0 | W10: ='TW-L'!AA9 -> 0 | X10: ='TW-L'!AB9 -> 0 | Y10: =SUM(Z10:Z10) -> 0 | Z10: ='TW-L'!Z9 -> 0 | AA10: =SUM(AB10:AE10) -> -1002 | AB10: ='TW-L'!AR9+'TW-L'!AS9 -> -1002 | AC10: ='TW-L'!AT9+'TW-L'!AU9 -> 0 | AD10: ='TW-L'!AV9+'TW-L'!AW9 -> 0 | AE10: ='TW-L'!AY9 -> 0 | AF10: 0 | AG10: ='TW-L'!AQ9 -> 0
B11: =PN!$B$9 -> CUS1516 | C11: =PN!B8 -> Coral Sea | D11: CUS1516-0002 | E11: ='TW-L'!C10 -> Min Han | F11: ='TW-L'!$C$4 -> 2026/3/1 | G11: ='TW-L'!$C$5 -> 2026/3/31 | H11: =I11+Y11+AA11+AF11+AG11 -> 7723 | I11: =SUM(J11:X11) -> 8000 | J11: ='TW-L'!N10 -> 6000 | K11: 0 | L11: ='TW-L'!AC10 -> 2000 | M11: ='TW-L'!O10 -> 0 | N11: ='TW-L'!P10 -> 0 | O11: ='TW-L'!Q10 -> 0 | P11: ='TW-L'!R10 -> 0 | Q11: ='TW-L'!X10+'TW-L'!Y10 -> 0 | R11: ='TW-L'!U10 -> 0 | S11: ='TW-L'!V10 -> 0 | T11: ='TW-L'!W10 -> 0 | U11: ='TW-L'!X10 -> 0 | V11: ='TW-L'!Y10 -> 0 | W11: ='TW-L'!AA10 -> 0 | X11: ='TW-L'!AB10 -> 0 | Y11: =SUM(Z11:Z11) -> 0 | Z11: ='TW-L'!Z10 -> 0 | AA11: =SUM(AB11:AE11) -> -277 | AB11: ='TW-L'!AR10+'TW-L'!AS10 -> -277 | AC11: ='TW-L'!AT10+'TW-L'!AU10 -> 0 | AD11: ='TW-L'!AV10+'TW-L'!AW10 -> 0 | AE11: ='TW-L'!AY10 -> 0 | AF11: 0 | AG11: ='TW-L'!AQ10 -> 0
B12: =PN!$B$9 -> CUS1516 | C12: =PN!B9 -> CUS1516 | D12: CUS1516-0003 | E12: ='TW-L'!C11 -> Wen kai | F12: ='TW-L'!$C$4 -> 2026/3/1 | G12: ='TW-L'!$C$5 -> 2026/3/31 | H12: =I12+Y12+AA12+AF12+AG12 -> 8523 | I12: =SUM(J12:X12) -> 8800 | J12: ='TW-L'!N11 -> 6800 | K12: 0 | L12: ='TW-L'!AC11 -> 2000 | M12: ='TW-L'!O11 -> 0 | N12: ='TW-L'!P11 -> 0 | O12: ='TW-L'!Q11 -> 0 | P12: ='TW-L'!R11 -> 0 | Q12: ='TW-L'!X11+'TW-L'!Y11 -> 0 | R12: ='TW-L'!U11 -> 0 | S12: ='TW-L'!V11 -> 0 | T12: ='TW-L'!W11 -> 0 | U12: ='TW-L'!X11 -> 0 | V12: ='TW-L'!Y11 -> 0 | W12: ='TW-L'!AA11 -> 0 | X12: ='TW-L'!AB11 -> 0 | Y12: =SUM(Z12:Z12) -> 0 | Z12: ='TW-L'!Z11 -> 0 | AA12: =SUM(AB12:AE12) -> -277 | AB12: ='TW-L'!AR11+'TW-L'!AS11 -> -277 | AC12: ='TW-L'!AT11+'TW-L'!AU11 -> 0 | AD12: ='TW-L'!AV11+'TW-L'!AW11 -> 0 | AE12: ='TW-L'!AY11 -> 0 | AF12: 0 | AG12: ='TW-L'!AQ11 -> 0

Sheet TW-L
A2: NNRoad
A3: Payroll for the month of | C3: 46082 | AD3: Overtime Payment
B4: Start Date> | C4: 2026/3/1
B5: End Date> | C5: 2026/3/31
M6: Pay Items | AD6: Overtime Details | AL6: Social Insurance Grading | AQ6: EE Dedution | BB6: ER Insurance contribution
A7: BU | B7: CN Name | C7: EN Name | D7: Position | E7: Start Date | F7: End Date | G7: FT/PT | H7: Full Pay/Hourly Rate | I7: Monthly Basic Salary | J7: Allw- Phone/ Communication | K7: Allw Transportation | L7: Allw Meal | M7: Employment day/Hours Worked | N7: 薪資 Basic Salary | O7: Allw- Phone/ Communication | P7: Allw Transportation | Q7: Back Pay | R7: 伙食津貼Allw Meal | S7: Remote Stipend | T7: 病假時數 Sick Leave Hours | U7: 病假扣薪 Sick Leave (half pay) | V7: NPL Hours | W7: No Pay Leave | X7: Bonus VB | Y7: Incentives | Z7: 報帳 Reimb Claim | AA7: 特休結算 Untaken AL | AB7: 資遣費 Severance | AC7: 加班費 Overtime Payment | AD7: Hr (1.34x) | AE7: OT Payment (1.34x) | AF7: Hr (1.67x) | AG7: OT Payment (1.67x) | AH7: Hr (1x) | AI7: OT Payment (1x) | AJ7: Hr (2.67x) | AK7: OT Payment (2.67x) | AL7: 勞保級距 Insured Salary Grading - LI | AM7: 勞退級距 Pension Salary Grading | AN7: 健保投保級距Insured Salary Grading - HI | AO7: 健保眷屬 HI Dependent (person) | AP7: 勞保投保天數 LI Days | AQ7: 所得稅代扣 Withholding Tax | AR7: 勞保自付 LI EE | AS7: 勞保自付(調整) LI EE 1T | AT7: 勞退自提 Pension EE | AU7: 勞退自提 (調整) Pension EE 1T | AV7: 健保自付 HI EE | AW7: 健保自付(調整) HI EE 1T | AX7: 健保眷屬 HI Dep | AY7: 二代健保 自付 2G HI EE | AZ7: Gross Taxable Income | BA7: Net Salary | BB7: 勞保雇主 LI ER | BC7: 勞保雇主 LI ER 1T | BD7: 勞退雇主 Pension ER 6% | BE7: 勞退雇主 Pension ER 1T | BF7: 健保雇主 HI ER | BG7: 健保雇主 HI ER 1T | BH7: 二代健保 雇主 2G HI ER | BI7: 二代健保 雇主 2G HI ER 1T | BJ7: 團保 GI | BK7: Gross Salary (payable) | BL7: ER Insurance | BM7: Service Fee | BN7: Operation Fee | BO7: Total
H8: =SUM(H9:H14) -> 1261 | I8: =SUM(I9:I14) -> 0 | J8: =SUM(J9:J14) -> 0 | K8: =SUM(K9:K14) -> 0 | L8: =SUM(L9:L14) -> 0 | M8: =SUM(M9:M14) -> 87 | N8: =SUM(N9:N14) -> 38155 | O8: =SUM(O9:O14) -> 0 | ... BO8: =SUM(BO9:BO14) -> 69267
A9: Coral Sea | B9: 王品涵 | C9: Pin Han | D9: Aquarist | E9: 44137 | G9: PT | H9: 461 | M9: 55 | N9: 25355 | O9: 0 | P9: 0 | Q9: 0 | R9: 0 | T9: 5 | U9: =-H9*5/2 -> -1152.5 | X9: 0 | Y9: 0 | Z9: 0 | AA9: 0 | AB9: 0 | AC9: 9220 | AD9: 0 | AE9: 0 | AF9: 0 | AG9: 0 | AH9: 0 | AI9: 0 | AJ9: 0 | AK9: 0 | AL9: 40100 | AM9: 40100 | AN9: 0 | AO9: 0 | AP9: 30 | AQ9: 0 | AR9: -1002 | AS9: 0 | AT9: 0 | AU9: 0 | AV9: 0 | AW9: 0 | AX9: 0 | AY9: 0 | AZ9: 24202 | BA9: 32420 | BB9: 3563 | BC9: 0 | BD9: 2406 | BE9: 0 | BF9: 0 | BG9: 0 | BH9: 511 | BI9: 0 | BJ9: 133 | BK9: 33422 | BL9: 6613 | BN9: 0 | BO9: 43035
A10: Coral Sea | B10: 洪民翰 | C10: Min Han | D10: Diver | E10: 45871 | G10: PT | H10: 400 | M10: 15 | N10: 6000 | O10: 0 | P10: 0 | Q10: 0 | R10: 0 | T10: 0 | U10: 0 | X10: 0 | Y10: 0 | Z10: 0 | AA10: 0 | AB10: 0 | AC10: 2000 | AD10: 0 | AE10: 0 | AF10: 0 | AG10: 0 | AH10: 0 | AI10: 0 | AJ10: 0 | AK10: 0 | AL10: 11100 | AM10: 8700 | AN10: 0 | AO10: 0 | AP10: 30 | AQ10: 0 | AR10: -277 | AS10: 0 | AT10: 0 | AU10: 0 | AV10: 0 | AW10: 0 | AX10: 0 | AY10: 0 | AZ10: 6000 | BA10: 7723 | BB10: 1007 | BC10: 0 | BD10: 522 | BE10: 0 | BF10: 0 | BG10: 0 | BH10: 127 | BI10: 0 | BJ10: 133 | BK10: 8000 | BL10: 1789 | BN10: 0 | BO10: 12789
A11: Coral Sea | B11: 楊文凱 | C11: Wen kai | D11: Diver | E11: 45962 | G11: PT | H11: 400 | M11: 17 | N11: 6800 | T11: 0 | AC11: 2000 | AL11: 11100 | AM11: 6000 | AP11: 30 | AR11: -277 | AY11: 0 | AZ11: 6800 | BA11: 8523 | BB11: 1007 | BC11: 0 | BD11: 360 | BE11: 0 | BF11: 0 | BG11: 0 | BH11: 143 | BI11: 0 | BJ11: 133 | BK11: 8800 | BL11: 1643 | BO11: 13443

Sheet FI Report
A1: Direct Cost | B1: Business Tax | C1: Service Fee | D1: Bank Fee * | E1: Late Pay Fine | F1: Advance Payment | G1: Deposit | H1: Outstanding payment ** | I1: FX difference | J1: Invoice adjustment *** | K1: total
A2: =PN!F15 -> 1925.6207 | B2: =PN!F37 -> 110.66 | C2: =PN!F23 -> 441.06308 | D2: =PN!F35 -> 10 | E2: =PN!F34 -> 0 | F2: 0 | G2: 0 | H2: =PN!F32 -> 0 | I2: =PN!F33 -> 0 | J2: 0 | K2: =SUM(A2:J2) -> 2487.3438
A7: * NNRoad USD 10 + vendor bank in Vendor's invoice
A8: ** the differnece between NNRoad PN and the amount we actually received
A9: *** PN adjustment with pre-payment or PN revisal
