Workbook

Sheet PN
B1: NNRoad – Employer of Record, Payroll Worldwide
B2: 333 W San Carlos St., Suite 600, San Jose, CA 95113, USA
B3: USA: +1 (669) 377-5080 | www.NNRoad.com
A5: INVOICE
A7: Bill to:
A8: Company name: | B8: ERI | D8: Currency | F8: USD
A9: Client ID: | B9: CUS1510 | D9: Invoice number | F9: PN-CUS1510-030920261
A10: Address: | B10: 1579 Desert Island Drive, Fresno, CA 93720 | D10: Invoice date | F10: =TODAY() -> 46090
D11: Due date | F11: 46098
A14: Description | E14: ="Amount "&UK!C6 -> Amount (GBP) | F14: Approx. In USD*
A15: EOR/PEO Cost | E15: =SUM(E16:E19) -> 17613.71 | F15: =SUM(F16:F19) -> 24597.546
A16: ="- Labor cost for "&UK!B9&" - "&MONTH(UK!B2) &"-"& YEAR(UK!B2) -> - Labor cost for Adrian Grace - 3-2026 | E16: =UK!J9+UK!N9+UK!Q9 -> 11444.19 | F16: =E16/$B$29 -> 15981.811
A17: ="- Labor cost for "&UK!B10&" - "&MONTH(UK!$B$2) &"-"& YEAR(UK!$B$2) -> - Labor cost for Darren Staples - 3-2026 | E17: =UK!J10+UK!N10+UK!Q10 -> 6169.52 | F17: =E17/$B$29 -> 8615.7347
A18: ="- "&+"Expense claim for "&UK!B9 -> - Expense claim for Adrian Grace | E18: =UK!S9 -> 0 | F18: =E18/$B$29 -> 0
A19: ="- "&+"Expense claim for "&UK!B10 -> - Expense claim for Darren Staples | E19: =UK!S10 -> 0 | F19: =E19/$B$29 -> 0
A21: Service Fee | E21: =SUM(E22:E23) -> 1301.0933 | F21: =SUM(F22:F23) -> 1816.9768
A22: ="- "&+"Management Fee - "&MONTH(UK!B2)&"-"&YEAR(UK!B2) -> - Management Fee - 3-2026 | E22: =UK!G6 -> 1301.0933 | F22: =E22/$B$29 -> 1816.9768
A26: EOR/PEO Service Cost | E26: =E15+E21 -> 18914.803 | F26: =F15+F21 -> 26414.523
A29: ="*FX rate USD: "&UK!C6 -> *FX rate USD: (GBP) | B29: =1/'UK-L'!D24 -> 0.7160759 | D29: EOR/PEO Service Cost | F29: =F26 -> 26414.523
D30: Outstanding payment | F30: =UK!E22 -> 0
D31: FX difference | F31: =UK!E23 -> 0
D32: Interests of delay | F32: =UK!E24 -> 0
D33: Bank Charges | F33: =UK!E25 -> 23.965
D34: Sub Total (Excluding Tax) | F34: =SUM(F29:F33) -> 26438.488
D35: Tax | F35: =UK!F6/B29 -> 0
D36: Total | F36: =SUM(F34:F35) -> 26438.488
A40: Please pay the Invoice in FULL AMOUNT
A41: Beneficiary: NNROAD, INC. Bank Name: Chase Bank Bank Account: 132827913 Bank Add.: 690 River Oaks Parkway Ste A, San Jose, CA 95134, USA | D41: SWIFT BIC (international transfer): CHASUS33XXX Routing Number (domestic wire transfer): 021000021 Routing Number (domestic ACH and direct deposit): 322271627
A42: Notes:
A43: 1. Please ensure that you include the Invoice Number when making your payment. This will help us accurately process and allocate your payment .
A44: 2. This document becomes a Tax Invoice/Receipt upon payment. Please retain a copy for your records.
A45: 3. This is a computer generated document. No Signature required.

Sheet UK
A1: =MID(CELL("filename",A1),FIND("]",CELL("filename",A1))+1,256) -> UK
A2: Pay Period | B2: =EOMONTH('UK-L'!B3,-1)+1 -> 46082 | C2: =EOMONTH('UK-L'!B3,0) -> 46112 | E2: ER
E3: Sum | F3: Business Tax | G3: Management Fee Fee | J3: Gross Salary | N3: Mandatory Contribution | Q3: Other Pay For EE | S3: Expense Claim
G4: Subtotal | H4: Recurring Fee | I4: Expense Fee | J4: Subtotal | K4: Basic Salary | L4: Holiday Pay | M4: Car Allowance | N4: Subtotal | O4: ER' NIC | P4: ER' Pension (Auto Enrolment) | Q4: Subtotal | R4: App Levy | S4: Subtotal | T4: Expense Claim
B6: Sum | C6: (GBP) | E6: =SUM(E9:E18) -> 18914.803 | F6: =SUM(F9:F18) -> 0 | G6: =SUM(G9:G18) -> 1301.0933 | H6: =SUM(H9:H18) -> 1301.0933 | I6: =SUM(I9:I18) -> 0 | J6: =SUM(J9:J18) -> 15166.67 | K6: =SUM(K9:K18) -> 14466.67 | L6: =SUM(L9:L18) -> 0 | ... T6: =SUM(T9:T18) -> 0
B9: Adrian Grace | E9: =+S9+Q9+N9+J9+G9+F9 -> 12245.283 | F9: 0 | G9: =SUM(H9:I9) -> 801.0933 | H9: =MAX(500, (J9+N9+Q9)*7%) -> 801.0933 | I9: =IF(S9=0,0,15) -> 0 | J9: =SUM(K9:M9) -> 9866.67 | K9: ='UK-L'!B7 -> 9166.67 | L9: ='UK-L'!B8 -> 0 | M9: ='UK-L'!B9 -> 700 | N9: =SUM(O9:P9) -> 1527.52 | O9: ='UK-L'!B10 -> 1417.45 | P9: ='UK-L'!B11 -> 110.07 | Q9: =SUM(R9:R9) -> 50 | R9: ='UK-L'!B22 -> 50 | S9: =SUM(T9:T9) -> 0 | T9: 0
B10: Darren Staples | E10: =+S10+Q10+N10+J10+G10+F10 -> 6669.52 | F10: 0 | G10: =SUM(H10:I10) -> 500 | H10: =MAX(500, (J10+N10+Q10)*7%) -> 500 | I10: =IF(S10=0,0,15) -> 0 | J10: =SUM(K10:M10) -> 5300 | K10: ='UK-L (2)'!B7 -> 5300 | L10: ='UK-L (2)'!B8 -> 0 | M10: ='UK-L (2)'!B9 -> 0 | N10: =SUM(O10:P10) -> 842.52 | O10: ='UK-L (2)'!B10 -> 732.45 | P10: ='UK-L (2)'!B11 -> 110.07 | Q10: =SUM(R10:R10) -> 27 | R10: ='UK-L (2)'!B22 -> 27 | S10: =SUM(T10:T10) -> 0 | T10: 0
A21: Other Fee | E21: =SUM(E22:E26) -> 23.965 | F21: 0
B22: Outstanding payment
B23: FX difference | F23: 0
B24: Interests of delay | F24: 0
B25: Bank Charges | E25: =10+10/PN!B29 -> 23.965
B26: Invoice adjustment | E26: 0

Sheet UK EE
A1: =MID(CELL("filename",A1),FIND("]",CELL("filename",A1))+1,256) -> UK EE
H2: EE
B3: Client Code | C3: Client Name | D3: EE Code | E3: EE Name | F3: Pay Period | H3: Net Income | I3: Gross Salary | M3: Expense Claim | O3: Mandatory Contribution
F4: From | G4: To | I4: Subtotal | J4: Basic Salary | K4: Holiday Pay | L4: Car Allowance | M4: Subtotal | N4: Expense Claim | O4: Subtotal | P4: PAYE (Estimated) | Q4: EE'NIC | R4: EE' Pension (Auto Enrolment)
A6: EOR/PEO(GBP)
B9: CUS1510 | C9: =PN!$B$8 -> ERI | E9: =UK!B9 -> Adrian Grace | F9: =UK!$B$7 -> 0 | G9: =UK!$C$7 -> 0 | H9: =I9+M9-O9 -> 6929.15 | I9: =SUM(J9:L9) -> 9866.67 | J9: ='UK-L'!B7 -> 9166.67 | K9: ='UK-L'!B8 -> 0 | L9: ='UK-L'!B9 -> 700 | M9: =SUM(N9:N9) -> 0 | N9: =UK!T9 -> 0 | O9: =SUM(P9:R9) -> 2937.52 | P9: ='UK-L'!B14 -> 2754.07 | Q9: ='UK-L'!B15 -> 0 | R9: ='UK-L'!B16 -> 183.45
B10: CUS1510 | C10: =PN!$B$8 -> ERI | E10: =UK!B10 -> Darren Staples | F10: =UK!$B$7 -> 0 | G10: =UK!$C$7 -> 0 | H10: =I10+M10-O10 -> 3844.18 | I10: =SUM(J10:L10) -> 5300 | J10: ='UK-L (2)'!B7 -> 5300 | K10: ='UK-L (2)'!B8 -> 0 | L10: ='UK-L (2)'!B9 -> 0 | M10: =SUM(N10:N10) -> 0 | N10: =UK!T10 -> 0 | O10: =SUM(P10:R10) -> 1455.82 | P10: ='UK-L (2)'!B14 -> 998.87 | Q10: ='UK-L (2)'!B15 -> 273.5 | R10: ='UK-L (2)'!B16 -> 183.45

Sheet UK-L
A3: Adrian Grace Salary Calculation for FY 26-27 | B3: =TODAY() -> 46090
A5: Details | B5: Amount in GBP
A6: Days Paid | B6: Full Month
A7: Gross Salary | B7: 9166.67
A8: Holiday Pay | B8: 0
A9: Car Allowance | B9: 700
A10: ER' NIC | B10: 1417.45
A11: ER' Pension (Auto Enrolment) | B11: 110.07
A12: Gross Salary + Er NIC | B12: =+B7+B9+B10+B11+B8 -> 11394.19
A14: PAYE (Estimated) | B14: 2754.07
A15: EE'NIC | B15: 0
A16: EE' Pension (Auto Enrolment) | B16: 183.45
A18: Net Salary | B18: =(B7+B9+B8)-(B14+B15+B16) -> 6929.15
A20: Total Cost | B20: =B12 -> 11394.19
A22: App Levy | B22: 50
C23: Amount in USD | D23: Exchange Rate
A24: Depsoit Invoice Amount | B24: =+B20+B22 -> 11444.19 | C24: =B24*D24 -> 15981.811 | D24: 1.3965
A25: Setup Fees | C25: =B25*D24 -> 0
A26: Payment Fees | B26: 5 | C26: =B26*D24 -> 6.9825
A27: Regular Monthly Invoice Amount | B27: =SUM(B24:B26) -> 11449.19 | C27: =SUM(C24:C26) -> 15988.794

Sheet UK-L (2)
A3: Darren Staples Salary Calculation for FY 26-25 | B3: =TODAY() -> 46090
A5: Details | B5: Amount in GBP
A6: Days Paid | B6: Full Month
A7: Gross Salary | B7: 5300
A8: Holiday | B8: 0
A9: Car Allowance | B9: 0
A10: ER' NIC | B10: 732.45
A11: ER' Pension (Auto Enrolment) | B11: 110.07
A12: Gross Salary + Er NIC | B12: =SUM(B7:B11) -> 6142.52
A14: PAYE (Estimated) | B14: 998.87
A15: EE'NIC | B15: 273.5
A16: EE' Pension (Auto Enrolment) | B16: 183.45
A18: Net Salary | B18: =(B8+B7)-(B14+B15+B16) -> 3844.18
A20: Total Cost | B20: =B12 -> 6142.52
A22: App Levy | B22: 27
C23: Amount in USD | D23: Exchange Rate
A24: Depsoit Invoice Amount | B24: =+B20+B22 -> 6169.52 | C24: =B24*D24 -> 8615.7347 | D24: 1.3965
A25: Setup Fees | C25: =B25*D24 -> 0
A26: Payment Fees | B26: 5 | C26: =B26*D24 -> 6.9825
A27: Regular Monthly Invoice Amount | B27: =SUM(B24:B26) -> 6174.52 | C27: =SUM(C24:C26) -> 8622.7172

Sheet FI Report
A1: Direct Cost | B1: Business Tax | C1: Service Fee | D1: Bank Fee * | E1: Late Pay Fine | F1: Advance Payment | G1: Deposit | H1: Outstanding payment ** | I1: FX difference | J1: Invoice adjustment *** | K1: total
A2: =PN!F15 -> 24597.546 | B2: =PN!F35 -> 0 | C2: =PN!F21 -> 1816.9768 | D2: =PN!F33 -> 23.965 | E2: =PN!F32 -> 0 | F2: 0 | G2: 0 | H2: =PN!F30 -> 0 | I2: =PN!F31 -> 0 | J2: 0 | K2: =SUM(A2:J2) -> 26438.488
A7: * NNRoad USD 10 + vendor bank in Vendor's invoice
A8: ** the differnece between NNRoad PN and the amount we actually received
A9: *** PN adjustment with pre-payment or PN revisal
