Workbook

Sheet PN
B1: NNRoad – Employer of Record, Payroll Worldwide
B2: 333 W San Carlos St., Suite 600, San Jose, CA 95113, USA
B3: USA: +1 (669) 377-5080 | www.NNRoad.com
A5: INVOICE
A7: Bill to:
A8: Company name: | B8: Animal Equality | D8: Currency | F8: USD
A9: Client ID: | B9: CUS1513 | D9: Invoice number | F9: PN-CUS1513-052120261
A10: Address: | B10: 8581 Santa Monica Blvd. Ste. 350 Los Angeles, CA 90069 | D10: Invoice date | F10: =TODAY()
D11: Due date | F11: 46164
A14: Description | E14: ="Amount "&Italy!C6 | F14: Approx. In USD*
A15: EOR/PEO Cost | E15: =SUM(E16:E17) | F15: =SUM(F16:F17)
A16: ="- Labor cost for "&Italy!B9&" - "&MONTH(Italy!B2) &"-"& YEAR(Italy!B2) | E16: =Italy!I9+Italy!Q9 | F16: =E16/$B$28
A17: ="- "&+"Expense claim for "&Italy!B9 | E17: =Italy!W9 | F17: =E17/$B$28
A20: Service Fee | E20: =SUM(E21:E22) | F20: =SUM(F21:F22)
A21: ="- "&+"Management Fee - "&MONTH(Italy!B2) &"-"& YEAR(Italy!B2) | E21: =Italy!H9 | F21: =E21/$B$28
A25: EOR/PEO Service Cost | E25: =E15+E20 | F25: =F15+F20
A28: ="*FX rate USD: "&Italy!C6 | B28: =0.86051971*0.97 | D28: EOR/PEO Service Cost | F28: =F25
D29: Outstanding payment | F29: =Italy!E22
D30: FX difference | F30: =Italy!E23
D31: Interests of delay | F31: =Italy!E24
D32: Bank Charges | F32: =Italy!E25
D33: Sub Total (Excluding Tax) | F33: =SUM(F28:F32)
D34: Tax | F34: =Italy!F6/B28
D35: Total | F35: =SUM(F33:F34)
A39: Please pay the Invoice in FULL AMOUNT
A40: Beneficiary: NNROAD, INC. Bank Name: Chase Bank Bank Account: 132827913 Bank Add.: 690 River Oaks Parkway Ste A, San Jose, CA 95134, USA | D40: SWIFT BIC (international transfer): CHASUS33XXX Routing Number (domestic wire transfer): 021000021 Routing Number (domestic ACH and direct deposit): 322271627
A41: Notes:
A42: 1. Please ensure that you include the Invoice Number when making your payment. This will help us accurately process and allocate your payment .
A43: 2. This document becomes a Tax Invoice/Receipt upon payment. Please retain a copy for your records.
A44: 3. This is a computer generated document. No Signature required.

Sheet Italy
A1: =MID(CELL("filename",A1),FIND("]",CELL("filename",A1))+1,256)
A2: Pay Period | B2: =EOMONTH(TODAY(),-1)+1 | C2: =EOMONTH(TODAY(),0) | E2: ER
E3: Sum | F3: Business Tax | G3: Management Fee | I3: Gross Salary | Q3: Mandatory Contribution | W3: Expense Claim
G4: Subtotal | H4: Recurring Fee | I4: Subtotal | J4: ='Italy-L'!K10 | K4: ='Italy-L'!N10 | L4: Bonus | M4: ='Italy-L'!O10 | N4: ='Italy-L'!P10 | O4: ='Italy-L'!Q10 | P4: ='Italy-L'!R10 | Q4: Subtotal | R4: ='Italy-L'!L10 | S4: ='Italy-L'!M10 | T4: ='Italy-L'!S10 | U4: ='Italy-L'!T10 | V4: ='Italy-L'!U10 | W4: Subtotal | X4: Expense Claim
B6: Sum | C6: EUR | E6: =SUM(E9:E17) | F6: =SUM(F9:F17) | G6: =SUM(G9:G17) | H6: =SUM(H9:H17) | I6: =SUM(I9:I17) | J6: =SUM(J9:J17) | K6: =SUM(K9:K17) | L6: =SUM(L9:L17) | ... X6: =SUM(X9:X17)
B9: ='Italy-L'!B11 | C9: ='Italy EE'!D10 | E9: =F9+G9+I9+Q9+W9 | F9: 0 | G9: =SUM(H9:H9) | H9: =MAX(750,(I9+Q9+X9)*10.5%) | I9: =SUM(J9:P9) | J9: ='Italy-L'!K11 | K9: ='Italy-L'!N11 | L9: =0 | M9: ='Italy-L'!O11 | N9: ='Italy-L'!P11 | O9: ='Italy-L'!Q11 | P9: ='Italy-L'!R11 | Q9: =SUM(R9:V9) | R9: ='Italy-L'!L11 | S9: ='Italy-L'!M11+'Italy-L'!V11 | T9: ='Italy-L'!S11+'Italy-L'!W11 | U9: ='Italy-L'!T11 | V9: ='Italy-L'!U11 | W9: =SUM(X9:X9) | X9: 0
A21: Other Fee | E21: =SUM(E22:E26) | F21: 0
B22: Outstanding payment
B23: FX difference | F23: 0
B24: Interests of delay | F24: 0
B25: Bank Charges | E25: =10
B26: Invoice adjustment | E26: 0

Sheet Italy EE
A1: =MID(CELL("filename",A1),FIND("]",CELL("filename",A1))+1,256)
H2: EE
B3: Client Code | C3: Client Name | D3: EE Code | E3: EE Name | F3: Pay Period | H3: Net Income | I3: Gross Salary | M3: Expense Claim | O3: Mandatory Contribution | Q3: Deduction
F4: From | G4: To | I4: Subtotal | J4: ='Italy-L'!K10 | K4: ='Italy-L'!N10 | L4: Bonus | M4: Subtotal | N4: Expense Claim | O4: Subtotal | P4: Other
A6: EOR/PEO(EUR)
B10: CUS1513 | C10: =PN!B8 | D10: CUS1513-0001 | E10: ='Italy-L'!B11 | F10: =Italy!B2 | G10: =Italy!C2 | H10: =I10+M10-O10-Q10 | I10: =SUM(J10:L10) | J10: ='Italy-L'!K11 | K10: ='Italy-L'!N11 | L10: =0 | M10: =SUM(N10:N10) | N10: =0 | O10: =SUM(P10:P10) | P10: 0 | Q10: 0

Sheet Italy-L
B2: Customer | C2: Animal Equality
B3: Location | C3: Italy
B4: Workers | C4: =IF(COUNTA($B$11:$B$11)=0,"",COUNTA($B$11:$B$11))
B5: Pay Period | C5: May'26
B6: SGWI VAT Code | C6: V9 | D6: ICE VAT Code | F6: V6
I8: SGWI Chargable | K8: Y | L8: Y | M8: Y | N8: N | O8: Y | P8: Y | Q8: Y | R8: Y | S8: Y | T8: Y | U8: Y
B10: Employee Name | C10: PO Number | D10: Fee %age Markup | E10: Fee Min | F10: Fee Minimum Currency | G10: Applied SGWI Min | H10: Applied SGWI Minimum Currency | I10: Currency | K10: May 2026 Salary | L10: Social Cost | M10: Social contributions for accruals | N10: Vacation Leave | O10: 13th and 14th Accrual | P10: Vacation Accruals | Q10: Monthly Permitted Leave (Permessi Hours Ex-Fs) | R10: Monthly Permitted Leave ROL Accrual | S10: Unemployment Fund (TFR) Accrual | T10: Overheads | U10: Bilateral Trade Association | V10: Social Contributions Employer (INPS) April | W10: Unemployment Fund (TFR) Accrual April | X10: Cost Basis | Z10: VAT | AA10: Invoice Total
B11: CUPIMATTEO | C11: - | D11: 0 | E11: 750 | F11: EUR | G11: =IFERROR(IF($B11="",0,IF($I11<>$F11,$E11/$G$8,$E11)),0) | H11: =IF($B11="","",IF($F11="","",$I11)) | I11: EUR | K11: 6071.42 | L11: 2218.7 | M11: 560.92 | N11: 505.95 | O11: 1011.9 | P11: 0 | Q11: 96.37 | R11: 216.84 | S11: 293.39 | T11: 60.71 | U11: 2.73 | V11: -116.56 | W11: 1690.39 | X11: =ROUND(SUM($K11:$W11),2) | Y11: =ROUND(MAX(SUMIF($K$8:$W$8,"Y",$K11:$W11)*$D11,$G11),2) | Z11: =ROUND(IF($C$6="V2",SUM($X11:$Y11)*20%,0),2) | AA11: =ROUND(SUM($X11:$Z11),2)
B13: Fee Invoice Total | I13: =IF($I$11="","",$I$11) | K13: =ROUND(SUM((K$11:K$11)),2) | L13: =ROUND(SUM((L$11:L$11)),2) | M13: =ROUND(SUM((M$11:M$11)),2) | N13: =ROUND(SUM((N$11:N$11)),2) | O13: =ROUND(SUM((O$11:O$11)),2) | P13: =ROUND(SUM((P$11:P$11)),2) | Q13: =ROUND(SUM((Q$11:Q$11)),2) | R13: =ROUND(SUM((R$11:R$11)),2) | ... W13: =ROUND(SUM((W$11:W$11)),2) | X13: =ROUND(SUM($K13:$W13),2) | Y13: =ROUND(SUM((Y$11:Y$11)),2) | Z13: =ROUND(IF($C$6="V2",SUM($X13:$Y13)*20%,0),2) | AA13: =ROUND(SUM($X13:$Z13),2)
