Workbook

Sheet PN
B1: NNRoad – Employer of Record, Payroll Worldwide
B2: 333 W San Carlos St., Suite 600, San Jose, CA 95113, USA
B3: USA: +1 (669) 377-5080 | www.NNRoad.com
A5: INVOICE
A7: Bill to:
A8: Company name: | B8: Cityzen Property London Ltd | D8: Currency | F8: USD
A9: Client ID: | B9: CUS1628 | D9: Invoice number | F9: PN-CUS1628-030620261
A10: Address: | B10: 73 Cornhill，London, UK, EC3V 3QQ | D10: Invoice date | F10: =TODAY() -> 46087
D11: Due date | F11: 46094
A14: Description | E14: ="Amount "&UAE!C6 -> Amount AED | F14: Approx. In USD*
A15: EOR/PEO Cost | E15: =SUM(E16:E19) -> 72564.57 | F15: =SUM(F16:F19) -> 20370.003
A16: ="- Labor cost for "&UAE!B9&" - "&MONTH(UAE!$B$2) &"-"& YEAR(UAE!$B$2) -> - Labor cost for Kevin Wilmaser - 3-2026 | E16: =UAE!I9+UAE!P9 -> 52930.79 | F16: =E16/$B$29 -> 14858.496
A17: ="- Labor cost for "&UAE!B10&" - "&MONTH(UAE!$B$2) &"-"& YEAR(UAE!$B$2) -> - Labor cost for Zineb Messaoud - 3-2026 | E17: =UAE!I10+UAE!P10 -> 10626.78 | F17: =E17/$B$29 -> 2983.1023
A18: ="- "&+"Expense claim for "&UAE!B9 -> - Expense claim for Kevin Wilmaser | E18: =UAE!S9 -> 9007 | F18: =E18/$B$29 -> 2528.4049
A19: ="- "&+"Expense claim for "&UAE!B10 -> - Expense claim for Zineb Messaoud | E19: =UAE!S10 -> 0 | F19: =E19/$B$29 -> 0
A21: Service Fee | E21: =SUM(E22:E23) -> 8003.468 | F21: =SUM(F22:F23) -> 2246.6979
A22: ="- "&+"Management Fee - "&MONTH(UAE!B2) &"-"& YEAR(UAE!B2) -> - Management Fee - 3-2026 | E22: =UAE!H6 -> 8003.468 | F22: =E22/$B$29 -> 2246.6979
A26: EOR/PEO Service Cost | E26: =E15+E21 -> 80568.038 | F26: =F15+F21 -> 22616.701
A29: ="*FX rate USD: "&UAE!C6 -> *FX rate USD: AED | B29: =3.6725*0.97 -> 3.562325 | D29: EOR/PEO Service Cost | F29: =F26 -> 22616.701
D30: Outstanding payment | F30: =UAE!E22 -> 40.36
D31: FX difference | F31: =UAE!E23 -> 0
D32: Interests of delay | F32: =UAE!E24 -> 0
D33: Bank Charges | F33: =UAE!E25 -> 24.03297
D34: Sub Total (Excluding Tax) | F34: =SUM(F29:F33) -> 22681.094
D35: Tax | F35: =UAE!F6/B29 -> 0
D36: Total | F36: =SUM(F34:F35) -> 22681.094
A40: Please pay the Invoice in FULL AMOUNT
A41: Beneficiary: NNROAD, INC. Bank Name: Chase Bank Bank Account: 132827913 Bank Add.: 690 River Oaks Parkway Ste A, San Jose, CA 95134, USA | D41: SWIFT BIC (international transfer): CHASUS33XXX Routing Number (domestic wire transfer): 021000021 Routing Number (domestic ACH and direct deposit): 322271627
A42: Notes:
A43: 1. Please ensure that you include the Invoice Number when making your payment. This will help us accurately process and allocate your payment .
A44: 2. This document becomes a Tax Invoice/Receipt upon payment. Please retain a copy for your records.
A45: 3. This is a computer generated document. No Signature required.

Sheet UAE
A1: =MID(CELL("filename",A1),FIND("]",CELL("filename",A1))+1,256) -> UAE
A2: Pay Period | B2: ='UAE-L'!C2 -> 2026/3/1 | C2: ='UAE-L'!E2 -> 2026/3/31 | E2: ER
E3: Sum | F3: Business Tax | G3: Management Fee | I3: Gross Salary | P3: Mandatory Contribution | S3: Expense Claim
G4: Subtotal | H4: Recurring Fee | I4: Subtotal | J4: ='UAE-L'!G7 -> Basic Salary | K4: ='UAE-L'!H7 -> Housing Allowance | L4: ='UAE-L'!I7 -> Transport | M4: ='UAE-L'!J7 -> Other allowances | N4: ='UAE-L'!K7 -> Project Allowance | O4: ='UAE-L'!L7 -> Commission /bonus | P4: Subtotal | Q4: EOSB Accrual | R4: Emiratization fee | S4: Subtotal | T4: Expense Claim
B6: Sum | C6: AED | E6: =SUM(E9:E17) -> 80568.038 | F6: =SUM(F9:F17) -> 0 | G6: =SUM(G9:G17) -> 8003.468 | H6: =SUM(H9:H17) -> 8003.468 | I6: =SUM(I9:I17) -> 59107.83 | J6: =SUM(J9:J17) -> 25918 | K6: =SUM(K9:K17) -> 0 | L6: =SUM(L9:L17) -> 0 | ... T6: =SUM(T9:T17) -> 9007
B9: ='UAE-L'!B8 -> Kevin Wilmaser | C9: ='UAE EE'!D10 -> CUS1628-0001 | E9: =F9+G9+I9+P9+S9 -> 68441.258 | F9: 0 | G9: =SUM(H9:H9) -> 6503.468 | H9: =MAX(1500,(I9+P9+T9)*10.5%) -> 6503.468 | I9: =SUM(J9:O9) -> 51607.83 | J9: ='UAE-L'!G8 -> 18418 | K9: ='UAE-L'!H8 -> 0 | L9: ='UAE-L'!I8 -> 0 | M9: ='UAE-L'!J8 -> 0 | N9: ='UAE-L'!K8 -> 0 | O9: ='UAE-L'!L8 -> 33189.83 | P9: =SUM(Q9:R9) -> 1322.96 | Q9: ='UAE-L'!Q8 -> 662.96 | R9: ='UAE-L'!R8 -> 660 | S9: =SUM(T9:T9) -> 9007 | T9: ='UAE-L'!M8 -> 9007
B10: ='UAE-L'!B9 -> Zineb Messaoud | C10: ='UAE EE'!D11 -> CUS1628-0002 | E10: =F10+G10+I10+P10+S10 -> 12126.78 | F10: 0 | G10: =SUM(H10:H10) -> 1500 | H10: =MAX(1500,(I10+P10+T10)*10.5%) -> 1500 | I10: =SUM(J10:O10) -> 7500 | J10: ='UAE-L'!G9 -> 7500 | K10: ='UAE-L'!H9 -> 0 | L10: ='UAE-L'!I9 -> 0 | M10: ='UAE-L'!J9 -> 0 | N10: ='UAE-L'!K9 -> 0 | O10: ='UAE-L'!L9 -> 0 | P10: =SUM(Q10:R10) -> 3126.78 | Q10: ='UAE-L'!Q9 -> 2466.78 | R10: ='UAE-L'!R9 -> 660 | S10: =SUM(T10:T10) -> 0 | T10: ='UAE-L'!M9 -> 0
A21: Other Fee | E21: =SUM(E22:E26) -> 64.39297 | F21: 0
B22: Outstanding payment | E22: 40.36
B23: FX difference | F23: 0
B24: Interests of delay | F24: 0
B25: Bank Charges | E25: =10+49.99/PN!B29 -> 24.03297
B26: Invoice adjustment | E26: 0

Sheet UAE EE
A1: =MID(CELL("filename",A1),FIND("]",CELL("filename",A1))+1,256) -> UAE EE
H2: EE
B3: Client Code | C3: Client Name | D3: EE Code | E3: EE Name | F3: Pay Period | H3: Net Income | I3: Gross Salary | P3: Expense Claim | R3: Mandatory Contribution | T3: Deduction
F4: From | G4: To | I4: Subtotal | J4: ='UAE-L'!G7 -> Basic Salary | K4: ='UAE-L'!H7 -> Housing Allowance | L4: ='UAE-L'!I7 -> Transport | M4: ='UAE-L'!J7 -> Other allowances | N4: ='UAE-L'!K7 -> Project Allowance | O4: ='UAE-L'!L7 -> Commission /bonus | P4: Subtotal | Q4: Expense Claim | R4: Subtotal | S4: Other
A6: EOR/PEO(AED)
B10: CUS1628 | C10: ='UAE-L'!$C$1 -> Cityzen | D10: CUS1628-0001 | E10: ='UAE-L'!B8 -> Kevin Wilmaser | F10: ='UAE-L'!$C$2 -> 2026/3/1 | G10: ='UAE-L'!$E$2 -> 2026/3/31 | H10: =I10+P10-R10-T10 -> 60614.83 | I10: =SUM(J10:O10) -> 51607.83 | J10: ='UAE-L'!G8 -> 18418 | K10: ='UAE-L'!H8 -> 0 | L10: ='UAE-L'!I8 -> 0 | M10: ='UAE-L'!J8 -> 0 | N10: ='UAE-L'!K8 -> 0 | O10: ='UAE-L'!L8 -> 33189.83 | P10: =SUM(Q10:Q10) -> 9007 | Q10: ='UAE-L'!M8 -> 9007 | R10: =SUM(S10:S10) -> 0 | S10: 0 | T10: ='UAE-L'!N8 -> 0
B11: CUS1628 | C11: ='UAE-L'!$C$1 -> Cityzen | D11: CUS1628-0002 | E11: ='UAE-L'!B9 -> Zineb Messaoud | F11: ='UAE-L'!$C$2 -> 2026/3/1 | G11: ='UAE-L'!$E$2 -> 2026/3/31 | H11: =I11+P11-R11-T11 -> 7500 | I11: =SUM(J11:O11) -> 7500 | J11: ='UAE-L'!G9 -> 7500 | K11: ='UAE-L'!H9 -> 0 | L11: ='UAE-L'!I9 -> 0 | M11: ='UAE-L'!J9 -> 0 | N11: ='UAE-L'!K9 -> 0 | O11: ='UAE-L'!L9 -> 0 | P11: =SUM(Q11:Q11) -> 0 | Q11: ='UAE-L'!M9 -> 0 | R11: =SUM(S11:S11) -> 0 | S11: 0 | T11: ='UAE-L'!N9 -> 0

Sheet UAE-L
A1: Company name: | C1: Cityzen
A2: Payroll period: | C2: 2026/3/1 | D2: to | E2: 2026/3/31
A3: Currency: | C3: AED
A7: S.No | B7: English Name | C7: Client | D7: From | E7: To | F7: No of days | G7: Basic Salary | H7: Housing Allowance | I7: Transport | J7: Other allowances | K7: Project Allowance | L7: Commission /bonus | M7: Additional Expenses | N7: Deduction | O7: Net salary | P7: Sevice Fees | Q7: EOSB Accrual | R7: Emiratization fee | S7: Invoice Before VAT | T7: Total Invoice Value in AED
A8: 2 | B8: Kevin Wilmaser | C8: Cityzen | D8: =C2 -> 2026/3/1 | E8: =E2 -> 2026/3/31 | F8: =E8-D8+1 -> 31 | G8: 18418 | H8: 0 | I8: 0 | K8: 0 | L8: 33189.83 | M8: 9007 | O8: =SUM(G8:M8) -> 60614.83 | Q8: 662.96 | R8: 660 | S8: =SUM(O8:R8) -> 61937.79 | T8: =O8+P8+R8+Q8 -> 61937.79
B9: Zineb Messaoud | D9: =C2 -> 2026/3/1 | E9: =E2 -> 2026/3/31 | F9: =E9-D9+1 -> 31 | G9: =7500 -> 7500 | H9: 0 | I9: 0 | K9: 0 | M9: 0 | O9: =SUM(G9:M9) -> 7500 | Q9: 2466.78 | R9: 660 | S9: =SUM(O9:R9) -> 10626.78 | T9: =O9+P9+R9+Q9 -> 10626.78

Sheet FI Report
A1: Direct Cost | B1: Business Tax | C1: Service Fee | D1: Bank Fee * | E1: Late Pay Fine | F1: Advance Payment | G1: Deposit | H1: Outstanding payment ** | I1: FX difference | J1: Invoice adjustment *** | K1: total
A2: =PN!F15 -> 20370.003 | B2: =PN!F35 -> 0 | C2: =PN!F21 -> 2246.6979 | D2: =PN!F33 -> 24.03297 | E2: =PN!F31 -> 0 | F2: =0 -> 0 | G2: 0 | H2: =PN!F30 -> 40.36 | I2: =PN!F31 -> 0 | J2: 0 | K2: =SUM(A2:J2) -> 22681.094
A6: * NNRoad USD 10 + vendor bank in Vendor's invoice
A7: ** the differnece between NNRoad PN and the amount we actually received
A8: *** PN adjustment with pre-payment or PN revisal
