Workbook

Sheet PN
B1: NNRoad – Employer of Record, Payroll Worldwide
B2: 333 W San Carlos St., Suite 600, San Jose, CA 95113, USA
B3: USA: +1 (669) 377-5080 | www.NNRoad.com
A5: INVOICE
A7: Bill to:
A8: Company name: | B8: Atlant International Group Ltd | D8: Currency | F8: EUR
A9: Client ID: | B9: CNUS2026002 | D9: Invoice number | F9: PN-CNUS2026002-031020261
A10: Address: | B10: 20 Wenlock Road, London N1 7GU, United Kingdom | D10: Invoice date | F10: =TODAY() -> 46091
D11: Due date | F11: 46104
A14: Description | F14: ="Amount "&Cyprus!C6 -> Amount (EUR)
A15: EOR/PEO Cost | F15: =SUM(F16:F17) -> 4280.1
A16: ="- Labor cost for "&Cyprus!B9&" - "&MONTH(Cyprus!B2) &"-"& YEAR(Cyprus!C2) -> - Labor cost for Anatoly Sidorov - 3-2026 | F16: =Cyprus!J9+Cyprus!R9 -> 4280.1
A17: ="- "&+"Expense claim for "&Cyprus!B9 -> - Expense claim for Anatoly Sidorov | F17: =Cyprus!V9 -> 0
A20: Service Fee | F20: =SUM(F21:F22) -> 500
A21: ="- "&+"Management Fee - "&MONTH(Cyprus!B2) &"-"& YEAR(Cyprus!B2) -> - Management Fee - 3-2026 | F21: =Cyprus!G9 -> 500
A25: EOR/PEO Service Cost | F25: =F15+F20 -> 4780.1
D28: EOR/PEO Service Cost | F28: =F25 -> 4780.1
D29: Outstanding payment | F29: =Cyprus!E22 -> 0
D30: FX difference | F30: =Cyprus!E23 -> 0
D31: Interests of delay | F31: =Cyprus!E24 -> 0
D32: Bank Charges | F32: =Cyprus!E25 -> 0
D33: Sub Total (Excluding Tax) | F33: =SUM(F28:F32) -> 4780.1
D34: Tax | F34: =Cyprus!F6 -> 0
D35: Total | F35: =SUM(F33:F34) -> 4780.1
A39: Please pay the Invoice in FULL AMOUNT
A40: Beneficiary: NNROAD, INC. Bank Name: Wise Bank Account: 9364559 Bank Add.: Rue du Trône 100, 3rd floor, Brussels,1050, Belgium | D40: SWIFT BIC (international transfer): TRWIBEB1XXX IBAN: BE11 9679 3645 5948
A41: Notes:
A42: 1. Please ensure that you include the Invoice Number when making your payment. This will help us accurately process and allocate your payment .
A43: 2. This document becomes a Tax Invoice/Receipt upon payment. Please retain a copy for your records.
A44: 3. This is a computer generated document. No Signature required.

Sheet Cyprus
A1: =MID(CELL("filename",A1),FIND("]",CELL("filename",A1))+1,256) -> Cyprus
A2: Pay Period | B2: ='Cyprus-L'!C2 -> 2026/3/1 | C2: ='Cyprus-L'!E2 -> 2026/3/31 | E2: ER
E3: Sum | F3: Business Tax | G3: Management Fee | J3: Gross Salary | R3: Mandatory Contribution | V3: Expense Claim
G4: Subtotal | H4: One-Time Set-up Fee | I4: Recurring Fee | J4: Subtotal | K4: Base Salary | L4: OT | M4: Salary Adjusment | N4: Bonus | O4: Leave Payment | P4: Backpay | Q4: Other | R4: Subtotal | S4: ='Cyprus-L'!L7 -> Employer's contributions | T4: ='Cyprus-L'!M7 -> Employer's & Public Liabilit | U4: ='Cyprus-L'!O7 -> Medical Insurance | V4: Subtotal | W4: Expense Claim
B6: Sum | C6: (EUR) | E6: =SUM(E9:E17) -> 4780.1 | F6: =SUM(F9:F17) -> 0 | G6: =SUM(G9:G17) -> 500 | H6: =SUM(H9:H17) -> 0 | I6: =SUM(I9:I17) -> 500 | J6: =SUM(J9:J17) -> 3695.92 | K6: =SUM(K9:K17) -> 3695.92 | L6: =SUM(L9:L17) -> 0 | ... W6: =SUM(W9:W17) -> 0
B9: ='Cyprus-L'!B8 -> Anatoly Sidorov | C9: ='Cyprus EE'!D10 -> CNUS2026002-0002 | E9: =F9+G9+J9+R9+V9 -> 4780.1 | F9: 0 | G9: =SUM(H9:I9) -> 500 | H9: 0 | I9: 500 | J9: =SUM(K9:Q9) -> 3695.92 | K9: ='Cyprus-L'!C8 -> 3695.92 | L9: ='Cyprus-L'!D8 -> 0 | M9: ='Cyprus-L'!E8 -> 0 | N9: ='Cyprus-L'!F8 -> 0 | O9: ='Cyprus-L'!G8 -> 0 | P9: ='Cyprus-L'!H8 -> 0 | Q9: ='Cyprus-L'!I8 -> 0 | R9: =SUM(S9:U9) -> 584.18 | S9: ='Cyprus-L'!L8 -> 569.18 | T9: ='Cyprus-L'!M8 -> 15 | U9: ='Cyprus-L'!O8 -> 0 | V9: =SUM(W9:W9) -> 0 | W9: ='Cyprus-L'!J8 -> 0
A21: Other Fee | E21: =SUM(E22:E26) -> 0 | F21: 0
B22: Outstanding payment
B23: FX difference | F23: 0
B24: Interests of delay | F24: 0
B25: Bank Charges
B26: Invoice adjustment | E26: 0

Sheet Cyprus EE
A1: =MID(CELL("filename",A1),FIND("]",CELL("filename",A1))+1,256) -> Cyprus EE
H2: EE
B3: Client Code | C3: Client Name | D3: EE Code | E3: EE Name | F3: Pay Period | H3: Net Income | I3: Gross Salary | Q3: Expense Claim | S3: Mandatory Contribution
F4: From | G4: To | I4: Subtotal | J4: Base Salary | K4: OT | L4: Salary Adjusment | M4: Bonus | N4: Leave Payment | O4: Backpay | P4: Other | Q4: Subtotal | R4: Expense Claim | S4: Subtotal | T4: EE
A6: EOR/PEO(HKD)
B10: =PN!B9 -> CNUS2026002 | C10: =PN!B8 -> Atlant International Group Ltd | D10: ='Cyprus-L'!A8 -> CNUS2026002-0002 | E10: ='Cyprus-L'!B8 -> Anatoly Sidorov | F10: ='Cyprus-L'!C2 -> 2026/3/1 | G10: ='Cyprus-L'!E2 -> 2026/3/31 | H10: =I10+Q10+S10 -> 3000 | I10: =SUM(J10:P10) -> 3695.92 | J10: ='Cyprus-L'!C8 -> 3695.92 | K10: ='Cyprus-L'!D8 -> 0 | L10: ='Cyprus-L'!E8 -> 0 | M10: ='Cyprus-L'!F8 -> 0 | N10: ='Cyprus-L'!G8 -> 0 | O10: ='Cyprus-L'!H8 -> 0 | P10: ='Cyprus-L'!I8 -> 0 | Q10: =SUM(R10:R10) -> 0 | R10: ='Cyprus-L'!J8 -> 0 | S10: =SUM(T10:T10) -> -695.92 | T10: ='Cyprus-L'!N8 -> -695.92

Sheet Cyprus-L
A1: Company name: | C1: =PN!B8 -> Atlant International Group Ltd
A2: Payroll period: | C2: 2026/3/1 | D2: to | E2: 2026/3/31
A3: Currency: | C3: EUR
A7: No. of EE | B7: Name of Employee | C7: Base salary | D7: OT | E7: Salary Adjusment | F7: Bonus | G7: Leave Payment | H7: Backpay | I7: Other | J7: Expense Reimbursment | K7: Gross Salary | L7: Employer's contributions | M7: Employer's & Public Liabilit | N7: Employee's deduction | O7: Medical Insurance | P7: Net Adjustment | Q7: Net Pay | R7: Total Cost
A8: CNUS2026002-0002 | B8: Anatoly Sidorov | C8: 3695.92 | K8: =SUM(C8:I8) -> 3695.92 | L8: 569.18 | M8: 15 | N8: -695.92 | Q8: =K8+J8+N8 -> 3000 | R8: =J8+K8+L8+M8+O8+P8 -> 4280.1

Sheet FI Report
A1: Direct Cost | B1: Business Tax | C1: Service Fee | D1: Bank Fee * | E1: Late Pay Fine | F1: Advance Payment | G1: Deposit | H1: Outstanding payment ** | I1: FX difference | J1: Invoice adjustment *** | K1: total
A2: =PN!F15 -> 4280.1 | B2: =PN!F34 -> 0 | C2: =PN!F20 -> 500 | D2: =PN!F32 -> 0 | E2: =PN!F31 -> 0 | F2: 0 | G2: 0 | H2: =PN!F29 -> 0 | I2: =PN!F30 -> 0 | J2: 0 | K2: =SUM(A2:J2) -> 4780.1
A7: * NNRoad USD 10 + vendor bank in Vendor's invoice
A8: ** the differnece between NNRoad PN and the amount we actually received
A9: *** PN adjustment with pre-payment or PN revisal
