Workbook

Sheet PN
B1: NNRoad – Employer of Record, Payroll Worldwide
B2: 333 W San Carlos St., Suite 600, San Jose, CA 95113, USA
B3: USA: +1 (669) 377-5080 | www.NNRoad.com
A5: INVOICE
A7: Bill to:
A8: Company name: | B8: UE Corp | D8: Currency | F8: USD
A9: Client ID: | B9: CUS1503 | D9: Invoice number | F9: PN-CUS1503-031820261
A10: Address: | B10: 168 Georgetown Rd., Canonsburg, Pennsylvanis, USA | D10: Invoice date | F10: =TODAY()
D11: Due date | F11: 46104
A14: Description | E14: ="Amount "&'Hong Kong'!C6 | F14: Approx. In USD*
A15: EOR/PEO Cost | E15: =SUM(E16:E18) | F15: =SUM(F16:F18)
A16: ="- Labor cost for "&'Hong Kong'!B9&" - "&MONTH('Hong Kong'!B2) &"-"& YEAR('Hong Kong'!C2) | E16: ='Hong Kong'!I9+'Hong Kong'!R9-'Hong Kong'!P9 | F16: =E16/$B$28
A17: ="- "&+"Expense claim for "&'Hong Kong'!B9&" - "&MONTH('Hong Kong'!B2) &"-"& YEAR('Hong Kong'!C2) | E17: ='Hong Kong'!V9 | F17: =E17/$B$28
A18: ="- Office Rental" | E18: ='Hong Kong'!P6 | F18: =E18/$B$28
A20: Service Fee | E20: =SUM(E21:E22) | F20: =SUM(F21:F22)
A21: ="- "&+"Management Fee - "&MONTH('Hong Kong'!B2) &"-"& YEAR('Hong Kong'!B2) | E21: ='Hong Kong'!G9 | F21: =E21/$B$28
A25: EOR/PEO Service Cost | E25: =E15+E20 | F25: =F15+F20
A28: ="*FX rate USD: "&'Hong Kong'!C6 | B28: =7.81039098*0.97 | D28: EOR/PEO Service Cost | F28: =F25
D29: Outstanding payment | F29: ='Hong Kong'!E22
D30: FX difference | F30: ='Hong Kong'!E23
D31: Interests of delay | F31: ='Hong Kong'!E24
D32: Bank Charges | F32: ='Hong Kong'!E25
D33: Sub Total (Excluding Tax) | F33: =SUM(F28:F32)
D34: Tax | F34: ='Hong Kong'!F6
D35: Total | F35: =SUM(F33:F34)
A39: Please pay the Invoice in FULL AMOUNT
A40: Beneficiary: NNROAD, INC. Bank Name: Chase Bank Bank Account: 132827913 Bank Add.: 690 River Oaks Parkway Ste A, San Jose, CA 95134, USA | D40: SWIFT BIC (international transfer): CHASUS33XXX Routing Number (domestic wire transfer): 021000021 Routing Number (domestic ACH and direct deposit): 322271627
A41: Notes:
A42: 1. Please ensure that you include the Invoice Number when making your payment. This will help us accurately process and allocate your payment .
A43: 2. This document becomes a Tax Invoice/Receipt upon payment. Please retain a copy for your records.
A44: 3. This is a computer generated document. No Signature required.

Sheet Hong Kong
A1: =MID(CELL("filename",A1),FIND("]",CELL("filename",A1))+1,256)
A2: Pay Period | B2: ='Hong Kong-L'!C2 | C2: ='Hong Kong-L'!E2 | E2: ER
E3: Sum | F3: Business Tax | G3: Management Fee | I3: Gross Salary | R3: Mandatory Contribution | V3: Expense Claim
G4: Subtotal | H4: Recurring Fee | I4: Subtotal | J4: Base Salary | K4: OT | L4: Salary Adjusment | M4: Bonus | N4: Leave Payment | O4: Backpay | P4: Other | Q4: Net Adjustment | R4: Subtotal | S4: Employees' Compensation Insurance | T4: MPF ER | U4: Others | V4: Subtotal | W4: Expense Claim
B6: Sum | C6: (HKD) | E6: =SUM(E9:E17) | F6: =SUM(F9:F17) | G6: =SUM(G9:G17) | H6: =SUM(H9:H17) | I6: =SUM(I9:I17) | J6: =SUM(J9:J17) | K6: =SUM(K9:K17) | L6: =SUM(L9:L17) | ... W6: =SUM(W9:W17)
B9: ='Hong Kong-L'!B8 | C9: ='Hong Kong EE'!D10 | E9: =F9+G9+I9+R9+V9 | F9: 0 | G9: =SUM(H9:H9) | H9: =MAX(600*PN!B28,(I9+R9+V9)*16%) | I9: =SUM(J9:Q9) | J9: ='Hong Kong-L'!C8 | K9: ='Hong Kong-L'!D8 | L9: ='Hong Kong-L'!E8 | M9: ='Hong Kong-L'!F8 | N9: ='Hong Kong-L'!G8 | O9: ='Hong Kong-L'!H8 | P9: ='Hong Kong-L'!I8 | Q9: ='Hong Kong-L'!P8 | R9: =SUM(S9:U9) | S9: ='Hong Kong-L'!L8 | T9: ='Hong Kong-L'!M8 | U9: ='Hong Kong-L'!O8 | V9: =SUM(W9:W9) | W9: ='Hong Kong-L'!J8
A21: Other Fee | E21: =SUM(E22:E26) | F21: 0
B22: Outstanding payment | E22: 18.33
B23: FX difference | F23: 0
B24: Interests of delay | F24: 0
B25: Bank Charges | E25: 10
B26: Invoice adjustment | E26: 0

Sheet Hong Kong EE
A1: =MID(CELL("filename",A1),FIND("]",CELL("filename",A1))+1,256)
H2: EE
B3: Client Code | C3: Client Name | D3: EE Code | E3: EE Name | F3: Pay Period | H3: Net Income | I3: Gross Salary | R3: Expense Claim | T3: Mandatory Contribution
F4: From | G4: To | I4: Subtotal | J4: Base Salary | K4: OT | L4: Salary Adjusment | M4: Bonus | N4: Leave Payment | O4: Backpay | P4: Other | Q4: Net Adjustment | R4: Subtotal | S4: Expense Claim | T4: Subtotal | U4: MPF EE
A6: EOR/PEO(HKD)
B10: =PN!B9 | C10: =PN!B8 | D10: ='Hong Kong-L'!A8 | E10: ='Hong Kong-L'!B8 | F10: ='Hong Kong-L'!C2 | G10: ='Hong Kong-L'!E2 | H10: =I10+R10+T10 | I10: =SUM(J10:Q10) | J10: ='Hong Kong-L'!C8 | K10: ='Hong Kong-L'!D8 | L10: ='Hong Kong-L'!E8 | M10: ='Hong Kong-L'!F8 | N10: ='Hong Kong-L'!G8 | O10: ='Hong Kong-L'!H8 | P10: ='Hong Kong-L'!I8 | Q10: ='Hong Kong-L'!P8 | R10: =SUM(S10:S10) | S10: ='Hong Kong-L'!J8 | T10: =SUM(U10:U10) | U10: ='Hong Kong-L'!N8

Sheet Hong Kong-L
A1: Company name: | C1: UE Corp
A2: Payroll period: | C2: 2026/3/1 | D2: to | E2: 2026/3/31
A3: Currency: | C3: HKD
A7: No. of EE | B7: Name of Employee | C7: Base Salary | D7: OT | E7: Salary Adjusment | F7: Bonus | G7: Leave Payment | H7: Backpay | I7: Other | J7: Expense Reimbursment | K7: Gross Salary | L7: Employees' Compensation Insurance | M7: MPF ER | N7: MPF EE | O7: Medical Insurance | P7: Net Adjustment | Q7: Net Pay | R7: Total Cost
A8: CUS1503-0001 | B8: Chan Kin Pong | C8: 62130.35 | E8: 0 | F8: 184496.47 | I8: 9000 | J8: 44146.88 | K8: 255626.82 | L8: 5112.5364 | M8: 1500 | N8: -1500 | Q8: 298273.7 | R8: 306386.24

Sheet FI Report
A1: Direct Cost | B1: Business Tax | C1: Service Fee | D1: Bank Fee * | E1: Late Pay Fine | F1: Advance Payment | G1: Deposit | H1: Outstanding payment ** | I1: FX difference | J1: Invoice adjustment *** | K1: total
A2: =PN!F15 | B2: =PN!F34 | C2: =PN!F20 | D2: =PN!F32 | E2: =PN!F31 | F2: 0 | G2: 0 | H2: =PN!F29 | I2: =PN!F30 | J2: 0 | K2: =SUM(A2:J2)
A7: * NNRoad USD 10 + vendor bank in Vendor's invoice
A8: ** the differnece between NNRoad PN and the amount we actually received
A9: *** PN adjustment with pre-payment or PN revisal
