Workbook

Sheet PN
A5: Client | B5: NNRoad (UE Corp)
A6: Client address | B6: 333 West San Carlos St, Suite 600, San Jose, CA 95110, USA
A7: Payment period | B7: ='Hong Kong'!B11&"-"&'Hong Kong'!C11 -> 6/1/2025-6/30/2025
A8: Issue date (mm/dd/yyyy) | B8: =TODAY() -> 45905
A9: Due date (mm/dd/yyyy) | B9: =B8+20 -> 45925
A10: PN number | B10: PN-NNR-CUS1503-060620251
B12: Sum Total | D12: Total (USD)
A14: Sum | B14: =B18+B29+B37 -> 14661.007 | D14: =D18+D29+D37 -> 14661.007
A16: Please remit payment to | B16: Beneficiary: TOP FDI COMPANY LIMITED Bank Name: HSBC Hong Kong Bank Account: 040-299273-838 SWIFT BIC (international transfer): HSBCHKHHHKH Routing Number (domestic wire transfer): 004 Routing Number (domestic ACH and direct deposit): Bank Add.: 1 Queen’s Road Central Hong Kong
A18: EOR/PEO | B18: =SUM(B19:B27) -> 14661.007 | D18: =SUM(D19:D27) -> 14661.007
A19: Business tax | B19: =D19 -> 0 | D19: ='Hong Kong'!F9 -> 0
A20: Management fee | B20: =D20 -> 119.81761 | D20: ='Hong Kong'!G9 -> 119.81761
A21: Salary | B21: =D21 -> 7773.9229 | D21: ='Hong Kong'!K9 -> 7773.9229
A22: Other payment to EE | B22: =D22 -> 1182.4106 | D22: ='Hong Kong'!R9 -> 1182.4106
A23: Mandatory contribution | B23: =D23 -> 376.19511 | D23: ='Hong Kong'!V9 -> 376.19511
A24: Other payment for EE | B24: =D24 -> 0 | D24: ='Hong Kong'!Z9 -> 0
A25: Expense claim | B25: =D25 -> 5208.6607 | D25: ='Hong Kong'!AC9 -> 5208.6607
A26: Advance Payment | B26: =D26 -> 0 | D26: ='Hong Kong'!AE9 -> 0
A27: Refundable Deposit | B27: =D27 -> 0 | D27: ='Hong Kong'!AF9 -> 0
A29: Other Service | B29: =SUM(B30:B35) -> 0 | D29: =SUM(D30:D35) -> 0
A30: Company Formation | B30: =D30 -> 0 | D30: ='Hong Kong'!E27 -> 0
A31: Office Rental | B31: =D31 -> 0 | D31: ='Hong Kong'!E28 -> 0
A32: Visa | B32: =D32 -> 0 | D32: ='Hong Kong'!E29 -> 0
A33: Accounting | B33: =D33 -> 0 | D33: ='Hong Kong'!E30 -> 0
A34: Template/Process Setup | B34: =D34 -> 0 | D34: ='Hong Kong'!E31 -> 0
A35: Other | B35: =D35 -> 0 | D35: ='Hong Kong'!E32 -> 0
A37: Other fee | B37: =SUM(B38:B42) -> 0 | D37: =SUM(D38:D42) -> 0
A38: Historical balance | B38: =D38 -> 0 | D38: ='Hong Kong'!E36 -> 0
A39: Interests of delay | B39: =D39 -> 0 | D39: ='Hong Kong'!E37 -> 0
A40: Bank Charge | B40: =D40 -> 0 | D40: ='Hong Kong'!E38 -> 0
A41: Other | B41: =D41 -> 0 | D41: ='Hong Kong'!E39 -> 0
A42: Business tax | B42: =D42 -> 0 | D42: ='Hong Kong'!E40 -> 0
A44: *This document becomes a Tax Invoice/Receipt upon payment. Please retain a copy for your records.
A46: Prepared by | B46: Wang, Jessie
A47: Signature
A50: Approved by | B50: Liu, Siyu
A51: Signature

Sheet Hong Kong
A1: =MID(CELL("filename",A1),FIND("]",CELL("filename",A1))+1,256) -> #VALUE!
A2: Exchange rate (USD per USD) | B2: 1
A3: Exchange rate (HKD per HKD) | B3: =7.8469783*0.97 -> 7.611569
E5: ER
E6: Sum | F6: Business Tax | G6: Management Fee | K6: Gross Salary | R6: Other Payment To EE | V6: Mandatory Contribution | Z6: Other Pay For EE | AC6: Expense Claim | AE6: Advance Payment | AF6: Refundable Deposit
G7: Subtotal | H7: OneTime Setup | I7: Recurring Fee | J7: Expense Fee | K7: Subtotal | L7: Base Salary | M7: OT | N7: Salary Adjusment | O7: Leave Payment | P7: Backpay | Q7: Other | R7: Subtotal | S7: Bonus | T7: Insurance Allowance | U7: Other | V7: Subtotal | W7: Employees' Compensation Insurance | X7: MPF ER | Y7: Others | Z7: Subtotal | AA7: Insurance | AB7: Others | AC7: Subtotal | AD7: Expense Claim
A9: EOR/PEO | B9: Sum | C9: (USD) | E9: =E10/$B$3 -> 14661.007 | F9: =F10/$B$3 -> 0 | G9: =G10/$B$3 -> 119.81761 | H9: =H10/$B$3 -> 0 | I9: =I10/$B$3 -> 119.81761 | J9: =J10/$B$3 -> 0 | K9: =K10/$B$3 -> 7773.9229 | L9: =L10/$B$3 -> 7773.9229 | ... AF9: =AF10/$B$3 -> 0
B10: Sum | C10: (HKD) | E10: =SUM(E13:E22) -> 111593.26 | F10: =SUM(F13:F22) -> 0 | G10: =SUM(G13:G22) -> 912 | H10: =SUM(H13:H22) -> 0 | I10: =SUM(I13:I22) -> 912 | J10: =SUM(J13:J22) -> 0 | K10: =SUM(K13:K22) -> 59171.75 | L10: =SUM(L13:L22) -> 59171.75 | ... AF10: =SUM(AF13:AF22) -> 0
A11: Pay Period | B11: ='Hong Kong-L'!C2 -> 6/1/2025 | C11: ='Hong Kong-L'!E2 -> 6/30/2025
B13: ='Hong Kong-L'!B8 -> Chan Kin Pong | C13: ='Hong Kong-L'!A8 -> CUS1503-0001 | E13: =F13+G13+K13+R13+V13+Z13+AC13+AE13+AF13 -> 111593.26 | F13: 0 | G13: =SUM(H13:J13) -> 912 | H13: 0 | I13: =ROUND(120*7.6,2) -> 912 | J13: 0 | K13: =SUM(L13:Q13) -> 59171.75 | L13: ='Hong Kong-L'!C8 -> 59171.75 | M13: ='Hong Kong-L'!D8 -> 0 | N13: ='Hong Kong-L'!E8 -> 0 | O13: ='Hong Kong-L'!G8 -> 0 | P13: ='Hong Kong-L'!H8 -> 0 | Q13: 0 | R13: =SUM(S13:U13) -> 9000 | S13: ='Hong Kong-L'!F8 -> 0 | T13: ='Hong Kong-L'!I8 -> 0 | U13: ='Hong Kong-L'!J8 -> 9000 | V13: =SUM(W13:Y13) -> 2863.435 | W13: ='Hong Kong-L'!M8 -> 1363.435 | X13: ='Hong Kong-L'!N8 -> 1500 | Y13: 0 | Z13: =SUM(AA13:AB13) -> 0 | AA13: =-'Hong Kong-L'!P8 -> 0 | AB13: ='Hong Kong-L'!Q8 -> 0 | AC13: =SUM(AD13:AD13) -> 39646.08 | AD13: ='Hong Kong-L'!K8 -> 39646.08 | AE13: 0 | AF13: 0
E25: (HKD) | F25: (HKD) | G25: 3rd Party Fee | H25: Service Fee | I25: Tax
A26: Other Service | B26: Total | E26: =F26/$B$3 -> 0 | F26: =SUM(F27:F32) -> 0 | G26: =SUM(G27:G32) -> 0 | H26: =SUM(H27:H32) -> 0 | I26: =SUM(I27:I32) -> 0
B27: Company Formation | E27: =F27/$B$3 -> 0 | F27: =SUM(G27:I27) -> 0
B28: Office Rental | E28: =F28/$B$3 -> 0 | F28: =SUM(G28:I28) -> 0
B29: Visa | E29: =F29/$B$3 -> 0 | F29: =SUM(G29:I29) -> 0
B30: Accounting | E30: =F30/$B$3 -> 0 | F30: =SUM(G30:I30) -> 0
B31: Template/Process Setup | E31: =F31/$B$3 -> 0 | F31: =SUM(G31:I31) -> 0
B32: Other | E32: =F32/$B$3 -> 0 | F32: =SUM(G32:I32) -> 0
E34: (USD) | F34: (HKD)
A35: Other Fee | B35: Total | E35: =SUM(E36:E40) -> 0
B36: Historical Balance | E36: 0
B37: Insterests of Delay | E37: =F37/$B$3 -> 0
B38: Bank Charge | E38: 0
B39: Other | E39: =F39/$B$3 -> 0
B40: Business Tax | E40: =F40/$B$3 -> 0

Sheet Hong Kong EE
A1: =MID(CELL("filename",A1),FIND("]",CELL("filename",A1))+1,256) -> #VALUE!
A2: Exchange rate (HKD per USD) | B2: ='Hong Kong'!B3 -> 7.611569 | H2: EE
B3: Client Code | C3: Client Name | D3: EE Code | E3: EE Name | F3: Pay Period | H3: Net Income | I3: Gross Salary | P3: Expense Claim | R3: Other Payment To EE | V3: Mandatory Contribution | Y3: Deduction
F4: From | G4: To | I4: Subtotal | J4: Base Salary | K4: OT | L4: Salary Adjusment | M4: Leave Payment | N4: Backpay | O4: Other | P4: Subtotal | Q4: Expense Claim | R4: Subtotal | S4: Monthly Bonus | T4: Insurance Allowance | U4: Other | V4: Subtotal | W4: MPF EE | X4: Other
A6: EOR/PEO(HKD)
B9: CUS1503 | C9: ='Hong Kong-L'!C1 -> NNRoad (UE Corp) | D9: ='Hong Kong-L'!A8 -> CUS1503-0001 | E9: ='Hong Kong-L'!B8 -> Chan Kin Pong | F9: ='Hong Kong-L'!C2 -> 6/1/2025 | G9: ='Hong Kong-L'!E2 -> 6/30/2025 | H9: =I9+P9+R9+V9+Y9 -> 106317.83 | I9: =SUM(J9:O9) -> 59171.75 | J9: ='Hong Kong-L'!C8 -> 59171.75 | K9: ='Hong Kong-L'!D8 -> 0 | L9: ='Hong Kong-L'!E8 -> 0 | M9: ='Hong Kong-L'!G8 -> 0 | N9: ='Hong Kong-L'!H8 -> 0 | O9: ='Hong Kong-L'!H8 -> 0 | P9: =SUM(Q9:Q9) -> 39646.08 | Q9: ='Hong Kong-L'!K8 -> 39646.08 | R9: =SUM(S9:U9) -> 9000 | S9: ='Hong Kong-L'!F8 -> 0 | T9: ='Hong Kong-L'!I8 -> 0 | U9: ='Hong Kong-L'!J8 -> 9000 | V9: =SUM(W9:X9) -> -1500 | W9: ='Hong Kong-L'!O8 -> -1500 | X9: 0 | Y9: =0 -> 0

Sheet Hong Kong-L
A1: Company name: | C1: =PN!B5 -> NNRoad (UE Corp)
A2: Payroll period: | C2: 6/1/2025 | D2: to | E2: 6/30/2025
A3: Currency: | C3: HKD
A7: No. of EE | B7: Name of Employee | C7: Base Salary | D7: OT | E7: Salary Adjusment | F7: Bonus | G7: Leave Payment | H7: Backpay | I7: Medical Insurance Allowance | J7: Other | K7: Expense Reimbursment | L7: Gross Salary | M7: Employees' Compensation Insurance | N7: MPF ER | O7: MPF EE | P7: Medical Insurance | Q7: Net Adjustment | R7: Net Pay | S7: Total Cost
A8: CUS1503-0001 | B8: Chan Kin Pong | C8: =ROUND(57448.3*1.03,2) -> 59171.75 | E8: 0 | J8: 9000 | K8: 39646.08 | L8: =SUM(C8:J8) -> 68171.75 | M8: =L8*2% -> 1363.435 | N8: =MIN(5%*SUM(C8:J8),1500) -> 1500 | O8: =-N8 -> -1500 | R8: =L8+O8+Q8+K8 -> 106317.83 | S8: =K8+L8+M8+N8+P8+Q8 -> 110681.26
