Workbook

Sheet PN
B1: NNRoad – Employer of Record, Payroll Worldwide
B2: 333 W San Carlos St., Suite 600, San Jose, CA 95113, USA
B3: USA: +1 (669) 377-5080 | www.NNRoad.com
A5: INVOICE
A7: Bill to:
A8: Company name: | D8: Currency | F8: USD
A9: Client ID: | D9: Invoice number
A10: Address: | D10: Invoice date
D11: Due date
A14: Description | E14: ="Amount "&China!C6 -> Amount (RMB) | F14: Approx. In USD*
A15: EOR/PEO Cost | E15: =SUM(E16:E17) -> 0 | F15: =SUM(F16:F17) -> 0
A16: ="- Labor cost for "&China!B9&" - "&MONTH(China!B2)&"-"&YEAR(China!B2) -> - Labor cost for - 7-2026 | E16: =China!K9+China!AQ9+China!BC9 -> 0 | F16: =E16/$B$29 -> 0
A17: ="- "&+"Expense claim for "&China!B9 -> - Expense claim for | E17: =China!BF9 -> 0 | F17: =E17/$B$29 -> 0
A20: Service Fee | E20: =SUM(E21:E22) -> 2349.4 | F20: =SUM(F21:F22) -> 340
A21: ="- "&+"Management Fee - "&MONTH(China!$B$2)&"-"&YEAR(China!$B$2) -> - Management Fee - 7-2026 | E21: =China!G9 -> 2349.4 | F21: =E21/$B$29 -> 340
A23: Recurring Deposit | E23: =SUM(E24) -> 0 | F23: =SUM(F24) -> 0
A24: ="- "&+"Deposit for "&China!B9&" - "&MONTH(China!B2)&"-"&YEAR(China!B2) -> - Deposit for - 7-2026 | E24: =China!BI9 -> 0 | F24: =E24/$B$29 -> 0
A26: EOR/PEO Service Cost | E26: =E15+E20+E23 -> 2349.4 | F26: =F15+F20+F23 -> 340
A29: ="*FX rate USD: "&China!C6 -> *FX rate USD: (RMB) | B29: 6.91 | D29: EOR/PEO Service Cost | F29: =F26 -> 340
D30: Outstanding payment | F30: =China!E22 -> 25
D31: FX difference | F31: =China!E23 -> 0
D32: Interests of delay | F32: =China!E24 -> 0
D33: Bank Charges | F33: =China!E25 -> 10
D34: Sub Total (Excluding Tax) | F34: =SUM(F29:F33) -> 375
D35: Tax | F35: =China!F6/$B$29 -> 0
D36: Total | F36: =SUM(F34:F35) -> 375
A40: Please pay the Invoice in FULL AMOUNT
A41: Beneficiary: NNROAD, INC. Bank Name: Chase Bank Bank Account: 132827913 Bank Add.: 690 River Oaks Parkway Ste A, San Jose, CA 95134, USA | D41: SWIFT BIC (international transfer): CHASUS33XXX Routing Number (domestic wire transfer): 021000021 Routing Number (domestic ACH and direct deposit): 322271627
A42: Notes:
A43: 1. Please ensure that you include the Invoice Number when making your payment. This will help us accurately process and allocate your payment .
A44: 2. This document becomes a Tax Invoice/Receipt upon payment. Please retain a copy for your records.
A45: 3. This is a computer generated document. No Signature required.

Sheet China
A1: China
A2: Pay Period | B2: =EOMONTH(TODAY(),-1)+1 -> 46204 | C2: =EOMONTH(TODAY(),0) -> 46234 | E2: ER
E3: Sum | F3: Business Tax | G3: Management Fee | K3: Gross Salary | AQ3: Mandatory Contribution | BC3: Other Payment For EE | BF3: Expense Claim | BI3: Refundable Deposit
G4: Subtotal | H4: For Recurring | I4: For Expense | J4: Other | K4: Subtotal | L4: 基本工资 | M4: 浮动工资 | N4: 月奖 | O4: 季奖 | P4: 其他奖金 | Q4: 加班工资150 | R4: 加班工资200 | S4: 加班工资300 | T4: 入离职缺勤扣 | U4: 扣事假 | V4: 扣旷工 | W4: 扣病假 | X4: 交通费 | Y4: 通讯费 | Z4: 其他津贴 | AA4: 中班费 | AB4: 夜班费 | AC4: 高温费 | AD4: 高温作业费 | AE4: 有毒有害作业费 | AF4: 补发 | AG4: 补扣 | AH4: 税前调整 | AI4: 公司负税项 | AJ4: 独生子女费 | AK4: 外籍生活津贴 | AL4: 税后补 | AM4: 税后扣 | AN4: 13薪/年终奖 | AO4: 离职补偿金/赔偿金 | AP4: 股权激励 | AQ4: Subtotal | AR4: 公司养老 | AS4: 公司医疗 | AT4: 公司失业 | AU4: 生育 | AV4: 工伤 | AW4: 残保金 | AX4: 公积金 | AY4: 补充公积金（免税） | AZ4: 工会费 | BA4: 雇主责任险 | BB4: 公司社保公积金调整 | BC4: Subtotal | BD4: 计税不发 | BE4: 当月个税（公司） | BF4: Subtotal | BG4: 报销款 | BH4: 报销款25%
B6: Sum | C6: (RMB) | E6: =SUM(E9:E18) -> 2349.4 | F6: =SUM(F9:F18) -> 0 | G6: =SUM(G9:G18) -> 2349.4 | H6: =SUM(H9:H18) -> 2073 | I6: =SUM(I9:I18) -> 276.4 | J6: =SUM(J9:J18) -> 0 | K6: =SUM(K9:K18) -> 0 | L6: =SUM(L9:L18) -> 0 | ... BI6: =SUM(BI9:BI18) -> 0
C9: ='China-L'!A2 -> 0 | E9: =SUM(F9:G9)+K9+AQ9+BC9+BF9+BI9 -> 2349.4 | F9: =(K9+AQ9+BC9+BF9)*6% -> 0 | G9: =SUM(H9:J9) -> 2349.4 | H9: =300*PN!$B$29+IF(AN9=0,0,300*PN!$B$29) -> 2073 | I9: =40*PN!$B$29*1 -> 276.4 | K9: =SUM(L9:AP9) -> 0 | L9: ='China-L'!C2 -> 0 | M9: ='China-L'!D2 -> 0 | N9: ='China-L'!E2 -> 0 | O9: ='China-L'!F2 -> 0 | P9: ='China-L'!G2 -> 0 | Q9: ='China-L'!H2 -> 0 | R9: ='China-L'!I2 -> 0 | S9: ='China-L'!J2 -> 0 | ... AH9: ='China-L'!Y2 -> 0 | AI9: ='China-L'!AY2 -> 0 | AJ9: ='China-L'!BF2 -> 0 | AK9: ='China-L'!BJ2 -> 0 | AL9: ='China-L'!BK2 -> 0 | AM9: ='China-L'!BL2 -> 0 | AN9: ='China-L'!BM2 -> 0 | AO9: ='China-L'!BO2 -> 0 | AP9: ='China-L'!BQ2 -> 0 | AQ9: =SUM(AR9:BB9) -> 0 | AR9: ='China-L'!BV2 -> 0 | AS9: ='China-L'!BW2 -> 0 | AT9: ='China-L'!BX2 -> 0 | AU9: ='China-L'!BY2 -> 0 | AV9: ='China-L'!BZ2 -> 0 | AW9: ='China-L'!CA2 -> 0 | AX9: ='China-L'!CB2 -> 0 | AY9: ='China-L'!CC2 -> 0 | AZ9: ='China-L'!CF2 -> 0 | BA9: ='China-L'!CG2 -> 0 | BB9: ='China-L'!CK2 -> 0 | BC9: =SUM(BD9:BE9) -> 0 | BD9: ='China-L'!AI2 -> 0 | BE9: ='China-L'!BE2 -> 0 | BF9: =SUM(BG9:BH9) -> 0 | BG9: ='China-L'!BH2 -> 0 | BH9: =+'China-L'!BI2 -> 0 | BI9: =(K9+AQ9+BC9)*20% -> 0
E19: =E9-F9-G9-BI9 -> 0
A21: Other Fee | E21: =SUM(E22:E26) -> 35 | F21: 0
B22: Outstanding payment | E22: 25
B23: FX difference | F23: 0
B24: Interests of delay | F24: 0
B25: Bank Charges | E25: =10 -> 10
B26: Invoice adjustment | E26: 0

Sheet China EE
A1: China EE
H2: EE
B3: Client Code | C3: Client Name | D3: EE Code | E3: EE Name | F3: Pay Period | H3: Net Income | I3: Salary | AO3: Expense Claim | AR3: EE Mandatory Contribution | BB3: Deduction | BC3: IIT
F4: From | G4: To | I4: Subtotal | J4: 基本工资 | K4: 浮动工资 | L4: 月奖 | M4: 季奖 | N4: 其他奖金 | O4: 加班工资150 | P4: 加班工资200 | Q4: 加班工资300 | R4: 入离职缺勤扣 | S4: 扣事假 | T4: 扣旷工 | U4: 扣病假 | V4: 交通费 | W4: 通讯费 | X4: 其他津贴 | Y4: 中班费 | Z4: 夜班费 | AA4: 高温费 | AB4: 高温作业费 | AC4: 有毒有害作业费 | AD4: 补发 | AE4: 补扣 | AF4: 税前调整 | AG4: 公司负税项 | AH4: 独生子女费 | AI4: 外籍生活津贴 | AJ4: 税后补 | AK4: 税后扣 | AL4: 13薪/年终奖 | AM4: 离职补偿金/赔偿金 | AN4: 股权激励 | AO4: Subtotal | AP4: 报销款 | AQ4: 报销款25% | AR4: Subtotal | AS4: 缴养老 | AT4: 缴医疗 | AU4: 缴失业 | AV4: 缴公积金 | AW4: 缴补充公积金（免税） | AX4: 社保调整 | AY4: 公积金调整 | AZ4: 年金 | BA4: 工会费
A6: EOR/PEO(CNY)
C10: =PN!B8 -> 0 | D10: =China!C9 | E10: =China!B9 -> 0 | F10: =China!B2 -> 46204 | G10: =China!C2 -> 46234 | H10: =I10+AO10-AR10-BB10-BC10 -> 0 | I10: =SUM(J10:AN10) -> 0 | J10: ='China-L'!C2 -> 0 | K10: ='China-L'!D2 -> 0 | L10: ='China-L'!E2 -> 0 | M10: ='China-L'!F2 -> 0 | N10: ='China-L'!G2 -> 0 | O10: ='China-L'!H2 -> 0 | P10: ='China-L'!I2 -> 0 | Q10: ='China-L'!J2 -> 0 | ... AF10: ='China-L'!Y2 -> 0 | AG10: ='China-L'!AY2 -> 0 | AH10: ='China-L'!BF2 -> 0 | AI10: ='China-L'!BJ2 -> 0 | AJ10: ='China-L'!BK2 -> 0 | AK10: ='China-L'!BL2 -> 0 | AL10: ='China-L'!BM2 -> 0 | AM10: ='China-L'!BO2 -> 0 | AN10: ='China-L'!BQ2 -> 0 | AO10: =SUM(AP10:AQ10) -> 0 | AP10: ='China-L'!BH2 -> 0 | AQ10: ='China-L'!BI2 -> 0 | AR10: =SUM(AS10:BA10) -> 0 | AS10: ='China-L'!Z2 -> 0 | AT10: ='China-L'!AA2 -> 0 | AU10: ='China-L'!AB2 -> 0 | AV10: ='China-L'!AC2 -> 0 | AW10: ='China-L'!AD2 -> 0 | AX10: ='China-L'!AE2 -> 0 | AY10: ='China-L'!AF2 -> 0 | AZ10: ='China-L'!AG2 -> 0 | BA10: ='China-L'!AH2 -> 0 | BC10: ='China-L'!AX2+'China-L'!BN2+'China-L'!BP2+'China-L'!BR2 -> 0

Sheet China-L
A1: 工号 | B1: 姓名 | C1: 基本工资 | D1: 浮动工资 | E1: 月奖 | F1: 季奖 | G1: 其他奖金 | H1: 加班工资150 | I1: 加班工资200 | J1: 加班工资300 | K1: 入离职缺勤扣 | L1: 扣事假 | M1: 扣旷工 | N1: 扣病假 | O1: 交通费 | P1: 通讯费 | Q1: 其他津贴 | R1: 中班费 | S1: 夜班费 | T1: 高温费 | U1: 高温作业费 | V1: 有毒有害作业费 | W1: 补发 | X1: 补扣 | Y1: 税前调整 | Z1: 缴养老 | AA1: 缴医疗 | AB1: 缴失业 | AC1: 缴公积金 | AD1: 缴补充公积金（免税） | AE1: 社保调整 | AF1: 公积金调整 | AG1: 年金 | AH1: 工会费 | AI1: 计税不发 | AJ1: 当月税前收入额 | AK1: 当月基本扣除 | AL1: 累计税前收入-员工 | AM1: 累计个人社保公积金 | AN1: 累计基本扣除 | AO1: 累计子女教育 | AP1: 累计继续教育 | AQ1: 累计住房贷款利息 | AR1: 累计住房租金 | AS1: 累计赡养老人 | AT1: 累计其他税前扣除 | AU1: 累计免税扣除合计(不含社保公积金） | AV1: 累计应税总额 | AW1: 累计个税（个人） | AX1: 当月个税（个人） | AY1: 公司负税项 | AZ1: 当月公司负税合计 | BA1: 累计税后计税收入 | BB1: 累计税前收入 | BC1: 导算当月应发工资 | BD1: 累计个税（公司+个人） | BE1: 当月个税（公司） | BF1: 独生子女费 | BG1: 缴补充公积金（不免税） | BH1: 报销款 | BI1: 报销款25% | BJ1: 外籍生活津贴 | BK1: 税后补 | BL1: 税后扣 | BM1: 13薪/年终奖 | BN1: 13薪/年终奖税 | BO1: 离职补偿金/赔偿金 | BP1: 离职补偿金税/赔偿金税 | BQ1: 股权激励 | BR1: 股权激励税 | BS1: 应发 | BT1: 应扣 | BU1: 实发 | BV1: 公司养老 | BW1: 公司医疗 | BX1: 公司失业 | BY1: 生育 | BZ1: 工伤 | CA1: 残保金 | CB1: 公积金 | CC1: 补充公积金（免税） | CD1: 累计已扣工资税 | CE1: 累计婴幼儿照护费用 | CF1: 工会费 | CG1: 雇主责任险 | CK1: 公司社保公积金调整
